Workbook

Sheet BASE
B19: CLIENTE: | C19: ='CUSTO NOVA'!H2 -> BRASCOLA LTDA -
B20: CNPJ:
B21: LOCAL REMETENTE:
B22: TIPO DE FRETE:

Sheet RESULTADO DIRETO
B3: COMPETENCIA | D3: TOTAL GERAL | L3: CUSTOS | P3: PESO 2024 | S3: 70449976
B4: FRETE | G4: CUSTOS | L4: Desp. Operacional | N4: 10313790 | P4: DESPESA ADMINISTRATIVA 2024 | S4: 15734290
B5: VALOR | D5: =VLOOKUP('RESULTADO DIRETO'!D3,FONTES!B5:I15,5,) -> 33465.1 | G5: Custo Operacional | I5: =VLOOKUP(D3,FONTES!B5:I15,8,) -> 22859.03 | L5: Carga e Descarga | N5: 4671731 | P5: RATEIO | S5: =S4/S3 -> 0.22333989
B6: Receita por kg | D6: =D5/D24 -> 2.4317564 | G6: Focal (agendamento) | L6: Motorista | N6: -2454302.6
B7: Tem Subst.Trib.? | G7: Seguro Acidente (0,014%) com iof | I7: =($D$25*0.01%)*7.38%+($D$25*0.01%) -> 36.439142 | L7: TOTAL | N7: =SUM(N4:N6) -> 12531218 | P7: FATURAMENTO | S7: 85634757
B8: Aliq. | C8: 0.12 | D8: =VLOOKUP('RESULTADO DIRETO'!D3,FONTES!B5:I15,3,) -> 4015.812 | E8: =IF(D7=$A$2,D5*C8,$A$11) -> 4015.812 | G8: Seguro Roubo (0,014%) com iof | I8: =($D$25*0.01%)*7.38%+($D$25*0.01%) -> 36.439142 | L8: Desp. Frota | N8: 1301293 | P8: Avarias S/ | S8: 600078
G9: Custo Indenizações | L9: Diárias | N9: -306752 | P9: FATURAMENTO | S9: =S8/S7 -> 0.0070074117
B10: IMPOSTOS | G10: Custo Ajudantes extras/entregas | L10: Lavação | N10: -54194
B11: TRIBUTO | C11: ALÍQUOTA | D11: VALOR | G11: Comissão Comercial/Freelancer | L11: Sinistro | N11: -37032
B12: ICMS | D12: =VLOOKUP(D3,FONTES!B5:I15,3,) -> 4015.812 | F12: =N27 -> 0.20906161 | G12: RATEIO DESP. ADMINIST./apoio op | I12: ='CUSTO NOVA'!X83 -> 1793.2052 | J12: =I12/D5 -> 0.053584336 | L12: Reboque | N12: -16900
B13: INSS DESON. 1,2 | F13: =N15 -> 0.19042701 | G13: RATEIO DESP. CLT operacional | I13: ='CUSTO NOVA'!Z83 -> 1633.3687 | J13: =I13/D5 -> 0.048808124 | L13: Gerenciamento de Risco | N13: -2055
B14: ISS | C14: 0 | D14: =IF(D5="","",(D5*C14)) -> 0 | G14: TOTAL CUSTOS | I14: =SUM(I5:I13) -> 26358.482 | J14: =SUM(J12:J13) -> 0.10239246 | L14: TOTAL | N14: =SUM(N8:N13) -> 884360
B15: PIS | C15: 0.052 | D15: =D5*C15 -> 1740.1852 | L15: RATEIO | N15: =(N7+N14)/S3 -> 0.19042701
B16: COFINS | G16: APURAÇÃO DO RESULTADO
B17: IRPJ | G17: VALOR BRUTO | I17: =D5 -> 33465.1
B18: CSLL | G18: ( - ) IMPOSTOS | I18: =D19*-1 -> -5755.9972
B19: TOTAL TRIBITOS | D19: =SUM(D12:D18) -> 5755.9972 | G19: ( - ) CUSTOS | I19: =I14*-1 -> -26358.482
L20: CUSTOS
B21: VALOR RECEITA LIQUIDA: | D21: =D5-D19 -> 27709.103 | L21: Despesa Adminstrativa | N21: 15734290
G22: VALOR LIQUIDO | I22: =SUM(I17:I21) -> 1350.6203 | L22: Boletos | N22: 76586
B23: INFORMAÇÕES EXTRAS | G23: % | I23: =I22*100%/I17 -> 0.04035907 | L23: Target | N23: 12917
B24: Tonelada | D24: =VLOOKUP(D3,FONTES!B5:I15,4,) -> 13761.699 | L24: Multa Processo RJ | N24: -306546.52
B25: Valor de NF | D25: =VLOOKUP(D3,FONTES!B5:I15,7,) -> 339347.57 | G25: QTD CTRC | H25: 82 | I25: =SUM(I26:I27) -> 1 | L25: Manutenções/Instalações Predial/Balanço Patrimonial | N25: -788861
B26: Redespacho | D26: =VLOOKUP(D3,FONTES!B5:I15,6,) -> 8055.45 | E26: =D26/D5 -> 0.24071197 | G26: Bases | H26: 16 | I26: =H26/H25 -> 0.19512195 | L26: TOTAL | N26: =SUM(N21:N25) -> 14728385
G27: Redespachos | H27: 66 | I27: =H27/H25 -> 0.80487805 | L27: RATEIO | N27: =N26/S3 -> 0.20906161
B28: Fat. cte Redespacho | D28: 21962.954 | E28: =D26/D28 -> 0.36677443
B29: Excluído por estar inclusa no Rateio Desp. ADM/OP
B30: Tonelada

Sheet FONTES
B5: COMPETENCIA | C5: TOTAL CTRC | D5: IMPOSTOS | E5: TONELADA | F5: FRETE | G5: REDESPACHO | H5: VALOR MERCADORIA | I5: TOTAL
B6: jan | C6: ='CUSTO NOVA'!I83 -> 82 | D6: ='CUSTO NOVA'!AF83 -> 4015.812 | E6: ='CUSTO NOVA'!L83 -> 13761.699 | F6: ='CUSTO NOVA'!M83 -> 33465.1 | G6: ='CUSTO NOVA'!T83 -> 8055.45 | H6: ='CUSTO NOVA'!J83 -> 339347.57 | I6: ='CUSTO NOVA'!V83 -> 22859.03
B7: feb
B8: mar
B9: apr
B10: may
B11: jun
B12: jul
B13: aug
B14: sep
B15: Total Geral | C15: =SUM(C6:C14) -> 82 | D15: =SUM(D6:D14) -> 4015.812 | E15: =SUM(E6:E14) -> 13761.699 | F15: =SUM(F6:F14) -> 33465.1 | G15: =SUM(G6:G14) -> 8055.45 | H15: =SUM(H6:H14) -> 339347.57 | I15: =SUM(I6:I14) -> 22859.03

Sheet RESULTADO REDESPACHO

Sheet BASE DADOS
A1: 1 | B1: Serie/Numero CTRC | C1: Tipo do Documento | D1: Praca Expedidora | E1: Unidade Emissora | F1: Data de Emissao | G1: Placa de Coleta | H1: Chave CT-e | I1: CNPJ Remetente | J1: Cliente Remetente | K1: Endereco do Remetente | L1: Bairro do Remetente | M1: Setor de Coleta | N1: Cidade do Remetente | O1: UF do Remetente | P1: CEP do Remetente | Q1: CNPJ Expedidor | R1: Cliente Expedidor | S1: Cidade do Expedidor | T1: UF do Expedidor | U1: CNPJ Pagador | V1: Cliente Pagador | W1: Endereco do Pagador | X1: Bairro do Pagador | Y1: Cidade do Pagador | Z1: UF do Pagador | AA1: Fone do Pagador | AB1: Segmento do Pagador | AC1: CNPJ Destinatario | AD1: Cliente Destinatario | AE1: Setor de Destino | AF1: Praca de Destino | AG1: Cidade do Destinatario | AH1: UF do Destinatario | AI1: CNPJ Recebedor | AJ1: Cliente Recebedor | AK1: Cidade de Entrega | AL1: UF de Entrega | AM1: Unidade Receptora | AN1: Numero da Nota Fiscal | AO1: Peso Real em Kg | AP1: Cubagem em m3 | AQ1: Quantidade de Volumes | AR1: Quantidade de Pares | AS1: Tipo do Frete | AT1: Tipo de Baixa | AU1: Data da Liquidacao | AV1: Valor Liquidado | AW1: Mercadoria | AX1: Especie | AY1: Valor da Mercadoria | AZ1: Tipo de Calculo | BA1: Tabela de Calculo | BB1: Valor do Frete | BC1: Valor do Frete sem ICMS | BD1: Base Calculo ICMS/ISS | BE1: Valor do ICMS | BF1: Aliquota | BG1: Valor do ISS | BH1: Peso Calculado em Kg | BI1: Frete Peso | BJ1: Frete Valor | BK1: Despacho | BL1: CAT | BM1: ITR | BN1: GRIS | BO1: Pedagio | BP1: TAS | BQ1: TDA | BR1: Suframa | BS1: Dev Canhoto NF | BT1: Reembolso | BU1: Outros | BV1: Coleta | BW1: TDC | BX1: TDE | BY1: TAR | BZ1: TRT | CA1: POS | CB1: Praca Comercial Origem | CC1: Praca Comercial Destino | CD1: Frete NTC | CE1: Frete Entrega | CF1: Separacao | CG1: Capatazia | CH1: Veiculo Dedicado | CI1: Paletizacao | CJ1: CO2 | CK1: RDC | CL1: CTRC Origem | CM1: CTe Origem | CN1: Valor do Frete do CTRC Origem | CO1: TDC CTRC Origem | CP1: TDE CTRC Origem | CQ1: TAR CTRC Origem | CR1: TRT CTRC Origem | CS1: TDA CTRC Origem | CT1: Valor do ICMS origem | CU1: Valor da Comissao de Expedicao | CV1: Rel de Comissao de Expedicao | CW1: Valor da Comissao Exp Creditada | CX1: Fatura do Subcon Exp Conferida Opcao 607 | CY1: Valor da Comissao de Recepcao | CZ1: Rel de Comissao de Recepcao | DA1: Valor da Comissao Rec Creditada | DB1: Fatura do Subcon Rec Conferida Opcao 607 | DE1: Adicional de Frete | DF1: ABC Pagador | DG1: UF origem da prestacao | DH1: Cidade origem da prestacao | DI1: IE cliente remetente | DJ1: Fone Remetente | DK1: Agendamento | DL1: Unidade Responsavel Pagador | DM1: Imposto Repassado
A2: 2 | B2: JOI025273-5 | C2: NORMAL | D2: JOIR | E2: JOI | F2: 46237 | G2: MMM1H28 | H2: 42260803098929000789570010000251101003655624 | I2: 61105060000163 | J2: BRASCOLA LTDA - | K2: RUA DONA FRANCISCA 8300 BLOCO D | L2: ZONA INDUSTRIAL | M2: 892 | N2: JOINVILLE | O2: SC | P2: 89219-600 | Q2: 61105060000163 | R2: BRASCOLA LTDA - | S2: JOINVILLE | T2: SC | U2: 61105060000163 | V2: BRASCOLA LTDA - | W2: RUA DONA FRANCISCA 8300 BLOCO D | X2: ZONA INDUSTRIAL | Y2: JOINVILLE | Z2: SC | AA2: (47 ) 32052727 | AC2: 18245738000184 | AD2: CACIFE TINTAS LTDA | AE2: 4 ROTA POUSO ALEGRE | AF2: DCCR | AG2: POUSO ALEGRE | AH2: MG | AI2: 18245738000184 | AJ2: CACIFE TINTAS LTDA | AK2: POUSO ALEGRE | AL2: MG | AM2: DCC | AN2: 000330234 | AO2: 55.36 | AP2: 0.0001 | AQ2: 10 | AR2: 0 | AS2: CP | AT2: LIQUIDADO | AU2: 46262 | AV2: 247.68 | AW2: 001-DIVERSOS | AX2: 001-DIVERSOS | AY2: 1536.74 | AZ2: COMBINADA | BA2: CO3809046 | BB2: 247.68 | BC2: 217.96 | BD2: 247.68 | BE2: 29.72 | BF2: 0.12 | BG2: 0 | BH2: 55.36 | BI2: 181.6 | BJ2: 0 | BK2: 18 | BL2: 0 | BM2: 0 | BN2: 3.25 | BO2: 5.5 | BP2: 4.23 | BQ2: 0 | BR2: 0 | BS2: 0 | BT2: 0 | BU2: 0 | BV2: 0 | BW2: 0 | BX2: 0 | BY2: 0 | BZ2: 0 | CA2: 5.38 | CB2: RSCP | CC2: ALTP | CD2: 373.35 | CE2: 0 | CF2: 0 | CG2: 0 | CH2: 0 | CI2: 0 | CJ2: 0 | CK2: 0 | CN2: 0 | CO2: 0 | CP2: 0 | CQ2: 0 | CR2: 0 | CS2: 0 | CT2: 0 | CU2: 49.54 | CV2: FATURA: 12310 | CW2: 49.54 | CX2: 012310 | CY2: 86.69 | CZ2: FATURA: 143 | DA2: 86.69 | DB2: 000143 | DE2: 0 | DF2: A. | DG2: SC | DH2: JOINVILLE | DI2: 252895738 | DJ2: (47 ) 32052727 | DK2: 0 | DL2: JOI | DM2: 29.72
A3: 2 | B3: JOI025274-3 | C3: NORMAL | D3: JOIR | E3: JOI | F3: 46237 | G3: MMM1H28 | H3: 42260803098929000789570010000251111003655630 | I3: 61105060000163 | J3: BRASCOLA LTDA - | K3: RUA DONA FRANCISCA 8300 BLOCO D | L3: ZONA INDUSTRIAL | M3: 892 | N3: JOINVILLE | O3: SC | P3: 89219-600 | Q3: 61105060000163 | R3: BRASCOLA LTDA - | S3: JOINVILLE | T3: SC | U3: 61105060000163 | V3: BRASCOLA LTDA - | W3: RUA DONA FRANCISCA 8300 BLOCO D | X3: ZONA INDUSTRIAL | Y3: JOINVILLE | Z3: SC | AA3: (47 ) 32052727 | AC3: 22429872000102 | AD3: LUMINOSOS E TOLDOS ITAJUBA LTDA ME | AE3: 3 ROTA ITAJUBA | AF3: DCCR | AG3: ITAJUBA | AH3: MG | AI3: 22429872000102 | AJ3: LUMINOSOS E TOLDOS ITAJUBA LTDA ME | AK3: ITAJUBA | AL3: MG | AM3: DCC | AN3: 000330250 | AO3: 44.036 | AP3: 0.0001 | AQ3: 13 | AR3: 0 | AS3: CP | AT3: LIQUIDADO | AU3: 46262 | AV3: 204.4 | AW3: 001-DIVERSOS | AX3: 001-DIVERSOS | AY3: 1596.25 | AZ3: COMBINADA | BA3: CO3809036 | BB3: 204.4 | BC3: 179.87 | BD3: 204.4 | BE3: 24.53 | BF3: 0.12 | BG3: 0 | BH3: 44.036 | BI3: 143.3 | BJ3: 0 | BK3: 18 | BL3: 0 | BM3: 0 | BN3: 3.25 | BO3: 5.5 | BP3: 4.23 | BQ3: 0 | BR3: 0 | BS3: 0 | BT3: 0 | BU3: 0 | BV3: 0 | BW3: 0 | BX3: 0 | BY3: 0 | BZ3: 0 | CA3: 5.59 | CB3: RSCP | CC3: ALTR | CD3: 373.95 | CE3: 0 | CF3: 0 | CG3: 0 | CH3: 0 | CI3: 0 | CJ3: 0 | CK3: 0 | CN3: 0 | CO3: 0 | CP3: 0 | CQ3: 0 | CR3: 0 | CS3: 0 | CT3: 0 | CU3: 40.88 | CV3: FATURA: 12310 | CW3: 40.88 | CX3: 012310 | CY3: 71.54 | CZ3: FATURA: 143 | DA3: 71.54 | DB3: 000143 | DE3: 0 | DF3: A. | DG3: SC | DH3: JOINVILLE | DI3: 252895738 | DJ3: (47 ) 32052727 | DK3: 0 | DL3: JOI | DM3: 24.53
A4: 2 | B4: JOI025275-1 | C4: NORMAL | D4: JOIR | E4: JOI | F4: 46237 | G4: MMM1H28 | H4: 42260803098929000789570010000251121003655645 | I4: 61105060000163 | J4: BRASCOLA LTDA - | K4: RUA DONA FRANCISCA 8300 BLOCO D | L4: ZONA INDUSTRIAL | M4: 892 | N4: JOINVILLE | O4: SC | P4: 89219-600 | Q4: 61105060000163 | R4: BRASCOLA LTDA - | S4: JOINVILLE | T4: SC | U4: 61105060000163 | V4: BRASCOLA LTDA - | W4: RUA DONA FRANCISCA 8300 BLOCO D | X4: ZONA INDUSTRIAL | Y4: JOINVILLE | Z4: SC | AA4: (47 ) 32052727 | AC4: 27743915000143 | AD4: ADILIA FERNANDA PINTO | AE4: 386 | AF4: STJP | AG4: PARACATU | AH4: MG | AI4: 27743915000143 | AJ4: ADILIA FERNANDA PINTO | AK4: PARACATU | AL4: MG | AM4: STJ | AN4: 000330273 | AO4: 64.212 | AP4: 0.0001 | AQ4: 18 | AR4: 0 | AS4: CP | AT4: LIQUIDADO | AU4: 46262 | AV4: 251.33 | AW4: 001-DIVERSOS | AX4: 001-DIVERSOS | AY4: 2369.18 | AZ4: COMBINADA | BA4: CO3809048 | BB4: 251.33 | BC4: 221.17 | BD4: 251.33 | BE4: 30.16 | BF4: 0.12 | BG4: 0 | BH4: 64.212 | BI4: 181.6 | BJ4: 0 | BK4: 18 | BL4: 0 | BM4: 0 | BN4: 3.55 | BO4: 5.5 | BP4: 4.23 | BQ4: 0 | BR4: 0 | BS4: 0 | BT4: 0 | BU4: 0 | BV4: 0 | BW4: 0 | BX4: 0 | BY4: 0 | BZ4: 0 | CA4: 8.29 | CB4: RSCP | CC4: PANI | CD4: 381.67 | CE4: 0 | CF4: 0 | CG4: 0 | CH4: 0 | CI4: 0 | CJ4: 0 | CK4: 0 | CN4: 0 | CO4: 0 | CP4: 0 | CQ4: 0 | CR4: 0 | CS4: 0 | CT4: 0 | CU4: 50.27 | CV4: FATURA: 12310 | CW4: 50.27 | CX4: 012310 | CY4: 51 | CZ4: FATURA: 64592 | DA4: 51 | DB4: 064592 | DE4: 0 | DF4: A. | DG4: SC | DH4: JOINVILLE | DI4: 252895738 | DJ4: (47 ) 32052727 | DK4: 0 | DL4: JOI | DM4: 30.16
A5: 2 | B5: JOI025276-0 | C5: NORMAL | D5: JOIR | E5: JOI | F5: 46237 | G5: MMM1H28 | H5: 42260803098929000789570010000251131003655650 | I5: 61105060000163 | J5: BRASCOLA LTDA - | K5: RUA DONA FRANCISCA 8300 BLOCO D | L5: ZONA INDUSTRIAL | M5: 892 | N5: JOINVILLE | O5: SC | P5: 89219-600 | Q5: 61105060000163 | R5: BRASCOLA LTDA - | S5: JOINVILLE | T5: SC | U5: 61105060000163 | V5: BRASCOLA LTDA - | W5: RUA DONA FRANCISCA 8300 BLOCO D | X5: ZONA INDUSTRIAL | Y5: JOINVILLE | Z5: SC | AA5: (47 ) 32052727 | AC5: 17732396000164 | AD5: DAVI ARRUDA DAS DORES ME | AE5: 010 RIBEIRAO DAS NEVES | AF5: BHZP | AG5: RIBEIRAO DAS NEVES | AH5: MG | AI5: 17732396000164 | AJ5: DAVI ARRUDA DAS DORES ME | AK5: RIBEIRAO DAS NEVES | AL5: MG | AM5: BHZ | AN5: 000330178 | AO5: 205.52 | AP5: 0.0001 | AQ5: 28 | AR5: 0 | AS5: CP | AT5: LIQUIDADO | AU5: 46262 | AV5: 394 | AW5: 001-DIVERSOS | AX5: 001-DIVERSOS | AY5: 4577.16 | AZ5: COMBINADA | BA5: CO3809017 | BB5: 394 | BC5: 346.72 | BD5: 394 | BE5: 47.28 | BF5: 0.12 | BG5: 0 | BH5: 205.52 | BI5: 285.1 | BJ5: 0 | BK5: 18 | BL5: 0 | BM5: 0 | BN5: 6.87 | BO5: 16.5 | BP5: 4.23 | BQ5: 0 | BR5: 0 | BS5: 0 | BT5: 0 | BU5: 0 | BV5: 0 | BW5: 0 | BX5: 0 | BY5: 0 | BZ5: 0 | CA5: 16.02 | CB5: RSCP | CC5: BHZP | CD5: 423.29 | CE5: 0 | CF5: 0 | CG5: 0 | CH5: 0 | CI5: 0 | CJ5: 0 | CK5: 0 | CN5: 0 | CO5: 0 | CP5: 0 | CQ5: 0 | CR5: 0 | CS5: 0 | CT5: 0 | CU5: 78.8 | CV5: FATURA: 12310 | CW5: 78.8 | CX5: 012310 | CY5: 28.77 | CZ5: MAPA: 161 | DA5: 0 | DE5: 0 | DF5: A. | DG5: SC | DH5: JOINVILLE | DI5: 252895738 | DJ5: (47 ) 32052727 | DK5: 0 | DL5: JOI | DM5: 47.28
A6: 2 | B6: JOI025277-8 | C6: NORMAL | D6: JOIR | E6: JOI | F6: 46237 | G6: MMM1H28 | H6: 42260803098929000789570010000251061003655575 | I6: 61105060000163 | J6: BRASCOLA LTDA - | K6: RUA DONA FRANCISCA 8300 BLOCO D | L6: ZONA INDUSTRIAL | M6: 892 | N6: JOINVILLE | O6: SC | P6: 89219-600 | Q6: 61105060000163 | R6: BRASCOLA LTDA - | S6: JOINVILLE | T6: SC | U6: 61105060000163 | V6: BRASCOLA LTDA - | W6: RUA DONA FRANCISCA 8300 BLOCO D | X6: ZONA INDUSTRIAL | Y6: JOINVILLE | Z6: SC | AA6: (47 ) 32052727 | AC6: 21980768000149 | AD6: AUTOLATAS ACESSORIOS LTDA EIRE | AE6: 001 SETE LAGOAS | AF6: SETP | AG6: SETE LAGOAS | AH6: MG | AI6: 21980768000149 | AJ6: AUTOLATAS ACESSORIOS LTDA EIRE | AK6: SETE LAGOAS | AL6: MG | AM6: SET | AN6: 000330177 | AO6: 65.852 | AP6: 0.0001 | AQ6: 9 | AR6: 0 | AS6: CP | AT6: LIQUIDADO | AU6: 46262 | AV6: 192.06 | AW6: 001-DIVERSOS | AX6: 001-DIVERSOS | AY6: 1699.8 | AZ6: 1700.8 | BA6: CO3809016 | BB6: 192.06 | BC6: 169.01 | BD6: 192.06 | BE6: 23.05 | BF6: 0.12 | BG6: 0 | BH6: 65.852 | BI6: 132.08 | BJ6: 0 | BK6: 18 | BL6: 0 | BM6: 0 | BN6: 3.25 | BO6: 5.5 | BP6: 4.23 | BQ6: 0 | BR6: 0 | BS6: 0 | BT6: 0 | BU6: 0 | BV6: 0 | BW6: 0 | BX6: 0 | BY6: 0 | BZ6: 0 | CA6: 5.95 | CB6: RSCP | CC6: SETP | CD6: 374.97 | CE6: 0 | CF6: 0 | CG6: 0 | CH6: 0 | CI6: 0 | CJ6: 0 | CK6: 0 | CN6: 0 | CO6: 0 | CP6: 0 | CQ6: 0 | CR6: 0 | CS6: 0 | CT6: 0 | CU6: 38.41 | CV6: FATURA: 12310 | CW6: 38.41 | CX6: 012310 | CY6: 12 | CZ6: MAPA: 161 | DA6: 0 | DE6: 0 | DF6: A. | DG6: SC | DH6: JOINVILLE | DI6: 252895738 | DJ6: (47 ) 32052727 | DK6: 0 | DL6: JOI | DM6: 23.05
A7: 2 | B7: JOI025278-6 | C7: NORMAL | D7: JOIR | E7: JOI | F7: 46237 | G7: MMM1H28 | H7: 42260803098929000789570010000251041003655538 | I7: 61105060000163 | J7: BRASCOLA LTDA - | K7: RUA DONA FRANCISCA 8300 BLOCO D | L7: ZONA INDUSTRIAL | M7: 892 | N7: JOINVILLE | O7: SC | P7: 89219-600 | Q7: 61105060000163 | R7: BRASCOLA LTDA - | S7: JOINVILLE | T7: SC | U7: 61105060000163 | V7: BRASCOLA LTDA - | W7: RUA DONA FRANCISCA 8300 BLOCO D | X7: ZONA INDUSTRIAL | Y7: JOINVILLE | Z7: SC | AA7: (47 ) 32052727 | AC7: 64220981000165 | AD7: MUNDIAL TINTAS E FERRAMENTAS LTDA | AE7: 12 ROTA CAMPOS GERAIS | AF7: DCCR | AG7: TRES PONTAS | AH7: MG | AI7: 64220981000165 | AJ7: MUNDIAL TINTAS E FERRAMENTAS LTDA | AK7: TRES PONTAS | AL7: MG | AM7: DCC | AN7: 000330175 | AO7: 107.628 | AP7: 0.0001 | AQ7: 21 | AR7: 0 | AS7: CP | AT7: LIQUIDADO | AU7: 46262 | AV7: 288.84 | AW7: 001-DIVERSOS | AX7: 001-DIVERSOS | AY7: 2951.4 | AZ7: COMBINADA | BA7: CO3809037 | BB7: 288.84 | BC7: 254.18 | BD7: 288.84 | BE7: 34.66 | BF7: 0.12 | BG7: 0 | BH7: 107.628 | BI7: 206.19 | BJ7: 0 | BK7: 18 | BL7: 0 | BM7: 0 | BN7: 4.43 | BO7: 11 | BP7: 4.23 | BQ7: 0 | BR7: 0 | BS7: 0 | BT7: 0 | BU7: 0 | BV7: 0 | BW7: 0 | BX7: 0 | BY7: 0 | BZ7: 0 | CA7: 10.33 | CB7: RSCP | CC7: ALTI | CD7: 388.38 | CE7: 0 | CF7: 0 | CG7: 0 | CH7: 0 | CI7: 0 | CJ7: 0 | CK7: 0 | CN7: 0 | CO7: 0 | CP7: 0 | CQ7: 0 | CR7: 0 | CS7: 0 | CT7: 0 | CU7: 57.77 | CV7: FATURA: 12310 | CW7: 57.77 | CX7: 012310 | CY7: 101.09 | CZ7: FATURA: 143 | DA7: 101.09 | DB7: 000143 | DE7: 0 | DF7: A. | DG7: SC | DH7: JOINVILLE | DI7: 252895738 | DJ7: (47 ) 32052727 | DK7: 0 | DL7: JOI | DM7: 34.66
A8: 2 | B8: JOI025279-4 | C8: NORMAL | D8: JOIR | E8: JOI | F8: 46237 | G8: MMM1H28 | H8: 42260803098929000789570010000251071003655599 | I8: 61105060000163 | J8: BRASCOLA LTDA - | K8: RUA DONA FRANCISCA 8300 BLOCO D | L8: ZONA INDUSTRIAL | M8: 892 | N8: JOINVILLE | O8: SC | P8: 89219-600 | Q8: 61105060000163 | R8: BRASCOLA LTDA - | S8: JOINVILLE | T8: SC | U8: 61105060000163 | V8: BRASCOLA LTDA - | W8: RUA DONA FRANCISCA 8300 BLOCO D | X8: ZONA INDUSTRIAL | Y8: JOINVILLE | Z8: SC | AA8: (47 ) 32052727 | AC8: 26600777000180 | AD8: PAULO ROBERTO REZENDE | AE8: 1 ROTA VARGINHA | AF8: DCCR | AG8: VARGINHA | AH8: MG | AI8: 26600777000180 | AJ8: PAULO ROBERTO REZENDE | AK8: VARGINHA | AL8: MG | AM8: DCC | AN8: 000330170 | AO8: 327.948 | AP8: 0.0001 | AQ8: 48 | AR8: 0 | AS8: CP | AT8: LIQUIDADO | AU8: 46262 | AV8: 632.51 | AW8: 001-DIVERSOS | AX8: 001-DIVERSOS | AY8: 7938.11 | AZ8: COMBINADA | BA8: CO3809036 | BB8: 632.51 | BC8: 556.61 | BD8: 632.51 | BE8: 75.9 | BF8: 0.12 | BG8: 0 | BH8: 327.948 | BI8: 472.69 | BJ8: 0 | BK8: 18 | BL8: 0 | BM8: 0 | BN8: 11.91 | BO8: 22 | BP8: 4.23 | BQ8: 0 | BR8: 0 | BS8: 0 | BT8: 0 | BU8: 0 | BV8: 0 | BW8: 0 | BX8: 0 | BY8: 0 | BZ8: 0 | CA8: 27.78 | CB8: RSCP | CC8: ALTR | CD8: 773.05 | CE8: 0 | CF8: 0 | CG8: 0 | CH8: 0 | CI8: 0 | CJ8: 0 | CK8: 0 | CN8: 0 | CO8: 0 | CP8: 0 | CQ8: 0 | CR8: 0 | CS8: 0 | CT8: 0 | CU8: 126.5 | CV8: FATURA: 12310 | CW8: 126.5 | CX8: 012310 | CY8: 221.38 | CZ8: FATURA: 143 | DA8: 221.38 | DB8: 000143 | DE8: 0 | DF8: A. | DG8: SC | DH8: JOINVILLE | DI8: 252895738 | DJ8: (47 ) 32052727 | DK8: 0 | DL8: JOI | DM8: 75.9
A9: 2 | B9: JOI025280-8 | C9: NORMAL | D9: JOIR | E9: JOI | F9: 46237 | G9: MMM1H28 | H9: 42260803098929000789570010000251051003655551 | I9: 61105060000163 | J9: BRASCOLA LTDA - | K9: RUA DONA FRANCISCA 8300 BLOCO D | L9: ZONA INDUSTRIAL | M9: 892 | N9: JOINVILLE | O9: SC | P9: 89219-600 | Q9: 61105060000163 | R9: BRASCOLA LTDA - | S9: JOINVILLE | T9: SC | U9: 61105060000163 | V9: BRASCOLA LTDA - | W9: RUA DONA FRANCISCA 8300 BLOCO D | X9: ZONA INDUSTRIAL | Y9: JOINVILLE | Z9: SC | AA9: (47 ) 32052727 | AC9: 07695443000193 | AD9: PRATA FERRO E ACO LTDA | AE9: 355 | AF9: DDBP | AG9: DIVINOPOLIS | AH9: MG | AI9: 07695443000193 | AJ9: PRATA FERRO E ACO LTDA | AK9: DIVINOPOLIS | AL9: MG | AM9: DDB | AN9: 000330186 | AO9: 1 | AP9: 0.0001 | AQ9: 1 | AR9: 0 | AS9: CP | AT9: LIQUIDADO | AU9: 46262 | AV9: 178.75 | AW9: 001-DIVERSOS | AX9: 001-DIVERSOS | AY9: 59.58 | AZ9: COMBINADA | BA9: CO3809055 | BB9: 178.75 | BC9: 157.3 | BD9: 178.75 | BE9: 21.45 | BF9: 0.12 | BG9: 0 | BH9: 1 | BI9: 126.11 | BJ9: 0 | BK9: 18 | BL9: 0 | BM9: 0 | BN9: 3.25 | BO9: 5.5 | BP9: 4.23 | BQ9: 0 | BR9: 0 | BS9: 0 | BT9: 0 | BU9: 0 | BV9: 0 | BW9: 0 | BX9: 0 | BY9: 0 | BZ9: 0 | CA9: 0.21 | CB9: RSCP | CC9: RWNI | CD9: 358.58 | CE9: 0 | CF9: 0 | CG9: 0 | CH9: 0 | CI9: 0 | CJ9: 0 | CK9: 0 | CN9: 0 | CO9: 0 | CP9: 0 | CQ9: 0 | CR9: 0 | CS9: 0 | CT9: 0 | CU9: 35.75 | CV9: FATURA: 12310 | CW9: 35.75 | CX9: 012310 | CY9: 54 | CZ9: MAPA: 0 | DA9: =CY9 -> 54 | DE9: 0 | DF9: A. | DG9: SC | DH9: JOINVILLE | DI9: 252895738 | DJ9: (47 ) 32052727 | DK9: 0 | DL9: JOI | DM9: 21.45
A10: 2 | B10: JOI025281-6 | C10: NORMAL | D10: JOIR | E10: JOI | F10: 46237 | G10: MMM1H28 | H10: 42260803098929000789570010000251081003655600 | I10: 61105060000163 | J10: BRASCOLA LTDA - | K10: RUA DONA FRANCISCA 8300 BLOCO D | L10: ZONA INDUSTRIAL | M10: 892 | N10: JOINVILLE | O10: SC | P10: 89219-600 | Q10: 61105060000163 | R10: BRASCOLA LTDA - | S10: JOINVILLE | T10: SC | U10: 61105060000163 | V10: BRASCOLA LTDA - | W10: RUA DONA FRANCISCA 8300 BLOCO D | X10: ZONA INDUSTRIAL | Y10: JOINVILLE | Z10: SC | AA10: (47 ) 32052727 | AC10: 06249968000132 | AD10: WME INDUSTRIA E COMERCIO DE PERFILADOS LTDA | AE10: 351 | AF10: GVRP | AG10: TIMOTEO | AH10: MG | AI10: 06249968000132 | AJ10: WME INDUSTRIA E COMERCIO DE PERFILADOS LTDA | AK10: TIMOTEO | AL10: MG | AM10: GVR | AN10: 000330185 | AO10: 1 | AP10: 0.0001 | AQ10: 1 | AR10: 0 | AS10: CP | AT10: LIQUIDADO | AU10: 46262 | AV10: 178.75 | AW10: 001-DIVERSOS | AX10: 001-DIVERSOS | AY10: 59.58 | AZ10: COMBINADA | BA10: CO3809055 | BB10: 178.75 | BC10: 157.3 | BD10: 178.75 | BE10: 21.45 | BF10: 0.12 | BG10: 0 | BH10: 1 | BI10: 126.11 | BJ10: 0 | BK10: 18 | BL10: 0 | BM10: 0 | BN10: 3.25 | BO10: 5.5 | BP10: 4.23 | BQ10: 0 | BR10: 0 | BS10: 0 | BT10: 0 | BU10: 0 | BV10: 0 | BW10: 0 | BX10: 0 | BY10: 0 | BZ10: 0 | CA10: 0.21 | CB10: RSCP | CC10: RWNI | CD10: 358.58 | CE10: 0 | CF10: 0 | CG10: 0 | CH10: 0 | CI10: 0 | CJ10: 0 | CK10: 0 | CN10: 0 | CO10: 0 | CP10: 0 | CQ10: 0 | CR10: 0 | CS10: 0 | CT10: 0 | CU10: 35.75 | CV10: FATURA: 12310 | CW10: 35.75 | CX10: 012310 | CY10: 67.06 | CZ10: FATURA: 12223 | DA10: 67.06 | DB10: 012223 | DE10: 0 | DF10: A. | DG10: SC | DH10: JOINVILLE | DI10: 252895738 | DJ10: (47 ) 32052727 | DK10: 0 | DL10: JOI | DM10: 21.45
A11: 2 | B11: JOI025282-4 | C11: NORMAL | D11: JOIR | E11: JOI | F11: 46237 | G11: MMM1H28 | H11: 42260803098929000789570010000251091003655615 | I11: 61105060000163 | J11: BRASCOLA LTDA - | K11: RUA DONA FRANCISCA 8300 BLOCO D | L11: ZONA INDUSTRIAL | M11: 892 | N11: JOINVILLE | O11: SC | P11: 89219-600 | Q11: 61105060000163 | R11: BRASCOLA LTDA - | S11: JOINVILLE | T11: SC | U11: 61105060000163 | V11: BRASCOLA LTDA - | W11: RUA DONA FRANCISCA 8300 BLOCO D | X11: ZONA INDUSTRIAL | Y11: JOINVILLE | Z11: SC | AA11: (47 ) 32052727 | AC11: 05290889000102 | AD11: CENTER TINTAS DE PARACATU LTDA - EPP | AE11: 386 | AF11: STJP | AG11: PARACATU | AH11: MG | AI11: 05290889000102 | AJ11: CENTER TINTAS DE PARACATU LTDA - EPP | AK11: PARACATU | AL11: MG | AM11: STJ | AN11: 000330223 | AO11: 65.694 | AP11: 0.0001 | AQ11: 11 | AR11: 0 | AS11: CP | AT11: LIQUIDADO | AU11: 46262 | AV11: 248.9 | AW11: 001-DIVERSOS | AX11: 001-DIVERSOS | AY11: 1842.97 | AZ11: COMBINADA | BA11: CO3809048 | BB11: 248.9 | BC11: 219.03 | BD11: 248.9 | BE11: 29.87 | BF11: 0.12 | BG11: 0 | BH11: 65.694 | BI11: 181.6 | BJ11: 0 | BK11: 18 | BL11: 0 | BM11: 0 | BN11: 3.25 | BO11: 5.5 | BP11: 4.23 | BQ11: 0 | BR11: 0 | BS11: 0 | BT11: 0 | BU11: 0 | BV11: 0 | BW11: 0 | BX11: 0 | BY11: 0 | BZ11: 0 | CA11: 6.45 | CB11: RSCP | CC11: PANI | CD11: 376.44 | CE11: 0 | CF11: 0 | CG11: 0 | CH11: 0 | CI11: 0 | CJ11: 0 | CK11: 0 | CN11: 0 | CO11: 0 | CP11: 0 | CQ11: 0 | CR11: 0 | CS11: 0 | CT11: 0 | CU11: 49.78 | CV11: FATURA: 12310 | CW11: 49.78 | CX11: 012310 | CY11: 51 | CZ11: FATURA: 64592 | DA11: 51 | DB11: 064592 | DE11: 0 | DF11: A. | DG11: SC | DH11: JOINVILLE | DI11: 252895738 | DJ11: (47 ) 32052727 | DK11: 0 | DL11: JOI | DM11: 29.87
A12: 2 | B12: JOI025355-3 | C12: NORMAL | D12: JOIR | E12: JOI | F12: 46239 | G12: MMM1H28 | H12: 42260803098929000789570010000251851003666481 | I12: 61105060000163 | J12: BRASCOLA LTDA - | K12: RUA DONA FRANCISCA 8300 BLOCO D | L12: ZONA INDUSTRIAL | M12: 892 | N12: JOINVILLE | O12: SC | P12: 89219-600 | Q12: 61105060000163 | R12: BRASCOLA LTDA - | S12: JOINVILLE | T12: SC | U12: 61105060000163 | V12: BRASCOLA LTDA - | W12: RUA DONA FRANCISCA 8300 BLOCO D | X12: ZONA INDUSTRIAL | Y12: JOINVILLE | Z12: SC | AA12: (47 ) 32052727 | AC12: 08853127000165 | AD12: BR FERRAGENS LTDA ME | AE12: 353 | AF12: GVRI | AG12: RIO CASCA | AH12: MG | AI12: 08853127000165 | AJ12: BR FERRAGENS LTDA ME | AK12: RIO CASCA | AL12: MG | AM12: GVR | AN12: 000330285 | AO12: 146.24 | AP12: 0.0001 | AQ12: 30 | AR12: 0 | AS12: CP | AT12: LIQUIDADO | AU12: 46262 | AV12: 332.13 | AW12: 001-DIVERSOS | AX12: 001-DIVERSOS | AY12: 4515.09 | AZ12: COMBINADA | BA12: CO3809041 | BB12: 332.13 | BC12: 292.27 | BD12: 332.13 | BE12: 39.86 | BF12: 0.12 | BG12: 0 | BH12: 146.24 | BI12: 236.47 | BJ12: 0 | BK12: 18 | BL12: 0 | BM12: 0 | BN12: 6.77 | BO12: 11 | BP12: 4.23 | BQ12: 0 | BR12: 0 | BS12: 0 | BT12: 0 | BU12: 0 | BV12: 0 | BW12: 0 | BX12: 0 | BY12: 0 | BZ12: 0 | CA12: 15.8 | CB12: RSCP | CC12: TAMI | CD12: 408.67 | CE12: 0 | CF12: 0 | CG12: 0 | CH12: 0 | CI12: 0 | CJ12: 0 | CK12: 0 | CN12: 0 | CO12: 0 | CP12: 0 | CQ12: 0 | CR12: 0 | CS12: 0 | CT12: 0 | CU12: 66.43 | CV12: FATURA: 12310 | CW12: 66.43 | CX12: 012310 | CY12: 125.25 | CZ12: FATURA: 12378 | DA12: 125.25 | DB12: 012378 | DE12: 0 | DF12: A. | DG12: SC | DH12: JOINVILLE | DI12: 252895738 | DJ12: (47 ) 32052727 | DK12: 0 | DL12: JOI | DM12: 39.86
A13: 2 | B13: JOI025356-1 | C13: NORMAL | D13: JOIR | E13: JOI | F13: 46239 | G13: MMM1H28 | H13: 42260803098929000789570010000251861003666497 | I13: 61105060000163 | J13: BRASCOLA LTDA - | K13: RUA DONA FRANCISCA 8300 BLOCO D | L13: ZONA INDUSTRIAL | M13: 892 | N13: JOINVILLE | O13: SC | P13: 89219-600 | Q13: 61105060000163 | R13: BRASCOLA LTDA - | S13: JOINVILLE | T13: SC | U13: 61105060000163 | V13: BRASCOLA LTDA - | W13: RUA DONA FRANCISCA 8300 BLOCO D | X13: ZONA INDUSTRIAL | Y13: JOINVILLE | Z13: SC | AA13: (47 ) 32052727 | AC13: 16690770000143 | AD13: POCOS ACABAMENTOS LTDA | AE13: 6 ROTA POCOS DE CALDAS | AF13: DCCR | AG13: POCOS DE CALDAS | AH13: MG | AI13: 16690770000143 | AJ13: POCOS ACABAMENTOS LTDA | AK13: POCOS DE CALDAS | AL13: MG | AM13: DCC | AN13: 000330315 | AO13: 29.08 | AP13: 0.0001 | AQ13: 7 | AR13: 0 | AS13: CP | AT13: LIQUIDADO | AU13: 46262 | AV13: 171.94 | AW13: 001-DIVERSOS | AX13: 001-DIVERSOS | AY13: 1624.49 | AZ13: COMBINADA | BA13: CO3809036 | BB13: 171.94 | BC13: 151.31 | BD13: 171.94 | BE13: 20.63 | BF13: 0.12 | BG13: 0 | BH13: 29.08 | BI13: 114.64 | BJ13: 0 | BK13: 18 | BL13: 0 | BM13: 0 | BN13: 3.25 | BO13: 5.5 | BP13: 4.23 | BQ13: 0 | BR13: 0 | BS13: 0 | BT13: 0 | BU13: 0 | BV13: 0 | BW13: 0 | BX13: 0 | BY13: 0 | BZ13: 0 | CA13: 5.69 | CB13: RSCP | CC13: ALTR | CD13: 374.27 | CE13: 0 | CF13: 0 | CG13: 0 | CH13: 0 | CI13: 0 | CJ13: 0 | CK13: 0 | CN13: 0 | CO13: 0 | CP13: 0 | CQ13: 0 | CR13: 0 | CS13: 0 | CT13: 0 | CU13: 34.39 | CV13: FATURA: 12310 | CW13: 34.39 | CX13: 012310 | CY13: 60.18 | CZ13: FATURA: 143 | DA13: 60.18 | DB13: 000143 | DE13: 0 | DF13: A. | DG13: SC | DH13: JOINVILLE | DI13: 252895738 | DJ13: (47 ) 32052727 | DK13: 0 | DL13: JOI | DM13: 20.63
A14: 2 | B14: JOI025357-0 | C14: NORMAL | D14: JOIR | E14: JOI | F14: 46239 | G14: MMM1H28 | H14: 42260803098929000789570010000251871003666508 | I14: 61105060000163 | J14: BRASCOLA LTDA - | K14: RUA DONA FRANCISCA 8300 BLOCO D | L14: ZONA INDUSTRIAL | M14: 892 | N14: JOINVILLE | O14: SC | P14: 89219-600 | Q14: 61105060000163 | R14: BRASCOLA LTDA - | S14: JOINVILLE | T14: SC | U14: 61105060000163 | V14: BRASCOLA LTDA - | W14: RUA DONA FRANCISCA 8300 BLOCO D | X14: ZONA INDUSTRIAL | Y14: JOINVILLE | Z14: SC | AA14: (47 ) 32052727 | AC14: 64382120000183 | AD14: W01356-01- ANTONIO GILBERTO TEIXEIRA ALVES JUNIOR | AE14: 394 | AF14: VEAI | AG14: JANAUBA | AH14: MG | AI14: 64382120000183 | AJ14: W01356-01- ANTONIO GILBERTO TEIXEIRA ALVES JUNIOR | AK14: JANAUBA | AL14: MG | AM14: VEA | AN14: 000330246 | AO14: 146.8 | AP14: 0.0001 | AQ14: 20 | AR14: 0 | AS14: CP | AT14: LIQUIDADO | AU14: 46262 | AV14: 361.7 | AW14: 001-DIVERSOS | AX14: 001-DIVERSOS | AY14: 3238.98 | AZ14: COMBINADA | BA14: CO3809060 | BB14: 361.7 | BC14: 318.3 | BD14: 361.7 | BE14: 43.4 | BF14: 0.12 | BG14: 0 | BH14: 146.8 | BI14: 268.87 | BJ14: 0 | BK14: 18 | BL14: 0 | BM14: 0 | BN14: 4.86 | BO14: 11 | BP14: 4.23 | BQ14: 0 | BR14: 0 | BS14: 0 | BT14: 0 | BU14: 0 | BV14: 0 | BW14: 0 | BX14: 0 | BY14: 0 | BZ14: 0 | CA14: 11.34 | CB14: RSCP | CC14: VEAI | CD14: 392.09 | CE14: 0 | CF14: 0 | CG14: 0 | CH14: 0 | CI14: 0 | CJ14: 0 | CK14: 0 | CN14: 0 | CO14: 0 | CP14: 0 | CQ14: 0 | CR14: 0 | CS14: 0 | CT14: 0 | CU14: 72.34 | CV14: FATURA: 12310 | CW14: 72.34 | CX14: 012310 | CY14: 108.51 | CZ14: MAPA: 0 | DA14: =CY14 -> 108.51 | DE14: 0 | DF14: A. | DG14: SC | DH14: JOINVILLE | DI14: 252895738 | DJ14: (47 ) 32052727 | DK14: 0 | DL14: JOI | DM14: 43.4
A15: 2 | B15: JOI025358-8 | C15: NORMAL | D15: JOIR | E15: JOI | F15: 46239 | G15: MMM1H28 | H15: 42260803098929000789570010000251881003666513 | I15: 61105060000163 | J15: BRASCOLA LTDA - | K15: RUA DONA FRANCISCA 8300 BLOCO D | L15: ZONA INDUSTRIAL | M15: 892 | N15: JOINVILLE | O15: SC | P15: 89219-600 | Q15: 61105060000163 | R15: BRASCOLA LTDA - | S15: JOINVILLE | T15: SC | U15: 61105060000163 | V15: BRASCOLA LTDA - | W15: RUA DONA FRANCISCA 8300 BLOCO D | X15: ZONA INDUSTRIAL | Y15: JOINVILLE | Z15: SC | AA15: (47 ) 32052727 | AC15: 86502002000102 | AD15: JUPEMAR AUTO PECAS LTDA | AE15: 359 | AF15: EJMP | AG15: JOAO MONLEVADE | AH15: MG | AI15: 86502002000102 | AJ15: JUPEMAR AUTO PECAS LTDA | AK15: JOAO MONLEVADE | AL15: MG | AM15: EJM | AN15: 000330237 | AO15: 449.876 | AP15: 0.0001 | AQ15: 1 | AR15: 0 | AS15: CP | AT15: LIQUIDADO | AU15: 46262 | AV15: 967.19 | AW15: 001-DIVERSOS | AX15: 001-DIVERSOS | AY15: 9522.96 | AZ15: COMBINADA | BA15: CO3809055 | BB15: 967.19 | BC15: 851.13 | BD15: 967.19 | BE15: 116.06 | BF15: 0.12 | BG15: 0 | BH15: 449.876 | BI15: 753.79 | BJ15: 0 | BK15: 18 | BL15: 0 | BM15: 0 | BN15: 14.28 | BO15: 27.5 | BP15: 4.23 | BQ15: 0 | BR15: 0 | BS15: 0 | BT15: 0 | BU15: 0 | BV15: 0 | BW15: 0 | BX15: 0 | BY15: 0 | BZ15: 0 | CA15: 33.33 | CB15: RSCP | CC15: RWNI | CD15: 1098.46 | CE15: 0 | CF15: 0 | CG15: 0 | CH15: 0 | CI15: 0 | CJ15: 0 | CK15: 0 | CN15: 0 | CO15: 0 | CP15: 0 | CQ15: 0 | CR15: 0 | CS15: 0 | CT15: 0 | CU15: 193.44 | CV15: FATURA: 12310 | CW15: 193.44 | CX15: 012310 | CY15: 386.88 | CZ15: MAPA: 161 | DA15: =CY15 -> 386.88 | DE15: 0 | DF15: A. | DG15: SC | DH15: JOINVILLE | DI15: 252895738 | DJ15: (47 ) 32052727 | DK15: 0 | DL15: JOI | DM15: 116.06
A16: 2 | B16: JOI025398-7 | C16: NORMAL | D16: JOIR | E16: JOI | F16: 46240 | G16: MMM1H28 | H16: 42260803098929000789570010000252291003675045 | I16: 61105060000163 | J16: BRASCOLA LTDA - | K16: RUA DONA FRANCISCA 8300 BLOCO D | L16: ZONA INDUSTRIAL | M16: 892 | N16: JOINVILLE | O16: SC | P16: 89219-600 | Q16: 61105060000163 | R16: BRASCOLA LTDA - | S16: JOINVILLE | T16: SC | U16: 61105060000163 | V16: BRASCOLA LTDA - | W16: RUA DONA FRANCISCA 8300 BLOCO D | X16: ZONA INDUSTRIAL | Y16: JOINVILLE | Z16: SC | AA16: (47 ) 32052727 | AC16: 10801726000187 | AD16: AVILA DISTRIBUIDORA E COMERCIO | AE16: 9 ROTA ALFENAS | AF16: DCCI | AG16: ALFENAS | AH16: MG | AI16: 10801726000187 | AJ16: AVILA DISTRIBUIDORA E COMERCIO | AK16: ALFENAS | AL16: MG | AM16: DCC | AN16: 000330385 | AO16: 70.43 | AP16: 0.0001 | AQ16: 31 | AR16: 0 | AS16: CP | AT16: LIQUIDADO | AU16: 46262 | AV16: 249.45 | AW16: 001-DIVERSOS | AX16: 001-DIVERSOS | AY16: 3084.36 | AZ16: COMBINADA | BA16: CO3809036 | BB16: 249.45 | BC16: 219.52 | BD16: 249.45 | BE16: 29.93 | BF16: 0.12 | BG16: 0 | BH16: 70.43 | BI16: 176.36 | BJ16: 0 | BK16: 18 | BL16: 0 | BM16: 0 | BN16: 4.63 | BO16: 5.5 | BP16: 4.23 | BQ16: 0 | BR16: 0 | BS16: 0 | BT16: 0 | BU16: 0 | BV16: 0 | BW16: 0 | BX16: 0 | BY16: 0 | BZ16: 0 | CA16: 10.8 | CB16: RSCP | CC16: ALTR | CD16: 390.07 | CE16: 0 | CF16: 0 | CG16: 0 | CH16: 0 | CI16: 0 | CJ16: 0 | CK16: 0 | CN16: 0 | CO16: 0 | CP16: 0 | CQ16: 0 | CR16: 0 | CS16: 0 | CT16: 0 | CU16: 49.89 | CV16: FATURA: 12310 | CW16: 49.89 | CX16: 012310 | CY16: 87.31 | CZ16: FATURA: 143 | DA16: 87.31 | DB16: 000143 | DE16: 0 | DF16: A. | DG16: SC | DH16: JOINVILLE | DI16: 252895738 | DJ16: (47 ) 32052727 | DK16: 0 | DL16: JOI | DM16: 29.93
A17: 2 | B17: JOI025399-5 | C17: NORMAL | D17: JOIR | E17: JOI | F17: 46240 | G17: MMM1H28 | H17: 42260803098929000789570010000252301003675054 | I17: 61105060000163 | J17: BRASCOLA LTDA - | K17: RUA DONA FRANCISCA 8300 BLOCO D | L17: ZONA INDUSTRIAL | M17: 892 | N17: JOINVILLE | O17: SC | P17: 89219-600 | Q17: 61105060000163 | R17: BRASCOLA LTDA - | S17: JOINVILLE | T17: SC | U17: 61105060000163 | V17: BRASCOLA LTDA - | W17: RUA DONA FRANCISCA 8300 BLOCO D | X17: ZONA INDUSTRIAL | Y17: JOINVILLE | Z17: SC | AA17: (47 ) 32052727 | AC17: 57006983000433 | AD17: FANIA COM E IND DE PECAS LTDA | AE17: 3 ROTA ITAJUBA | AF17: DCCR | AG17: ITAJUBA | AH17: MG | AI17: 57006983000433 | AJ17: FANIA COM E IND DE PECAS LTDA | AK17: ITAJUBA | AL17: MG | AM17: DCC | AN17: 000330394 | AO17: 64 | AP17: 0.0001 | AQ17: 4 | AR17: 0 | AS17: CP | AT17: LIQUIDADO | AU17: 46262 | AV17: 230.4 | AW17: 001-DIVERSOS | AX17: 001-DIVERSOS | AY17: 1911.24 | AZ17: COMBINADA | BA17: CO3809036 | BB17: 230.4 | BC17: 202.75 | BD17: 230.4 | BE17: 27.65 | BF17: 0.12 | BG17: 0 | BH17: 64 | BI17: 165.08 | BJ17: 0 | BK17: 18 | BL17: 0 | BM17: 0 | BN17: 3.25 | BO17: 5.5 | BP17: 4.23 | BQ17: 0 | BR17: 0 | BS17: 0 | BT17: 0 | BU17: 0 | BV17: 0 | BW17: 0 | BX17: 0 | BY17: 0 | BZ17: 0 | CA17: 6.69 | CB17: RSCP | CC17: ALTR | CD17: 377.09 | CE17: 0 | CF17: 0 | CG17: 0 | CH17: 0 | CI17: 0 | CJ17: 0 | CK17: 0 | CN17: 0 | CO17: 0 | CP17: 0 | CQ17: 0 | CR17: 0 | CS17: 0 | CT17: 0 | CU17: 46.08 | CV17: FATURA: 12310 | CW17: 46.08 | CX17: 012310 | CY17: 80.64 | CZ17: FATURA: 143 | DA17: 80.64 | DB17: 000143 | DE17: 0 | DF17: A. | DG17: SC | DH17: JOINVILLE | DI17: 252895738 | DJ17: (47 ) 32052727 | DK17: 0 | DL17: JOI | DM17: 27.65
A18: 2 | B18: JOI025400-2 | C18: NORMAL | D18: JOIR | E18: JOI | F18: 46240 | G18: MMM1H28 | H18: 42260803098929000789570010000252311003675060 | I18: 61105060000163 | J18: BRASCOLA LTDA - | K18: RUA DONA FRANCISCA 8300 BLOCO D | L18: ZONA INDUSTRIAL | M18: 892 | N18: JOINVILLE | O18: SC | P18: 89219-600 | Q18: 61105060000163 | R18: BRASCOLA LTDA - | S18: JOINVILLE | T18: SC | U18: 61105060000163 | V18: BRASCOLA LTDA - | W18: RUA DONA FRANCISCA 8300 BLOCO D | X18: ZONA INDUSTRIAL | Y18: JOINVILLE | Z18: SC | AA18: (47 ) 32052727 | AC18: 14011822000182 | AD18: JM DE OLIVEIRA TINTAS ME | AE18: 360 | AF18: TAMP | AG18: JUIZ DE FORA | AH18: MG | AI18: 14011822000182 | AJ18: JM DE OLIVEIRA TINTAS ME | AK18: JUIZ DE FORA | AL18: MG | AM18: TAM | AN18: 000330404 | AO18: 73.4 | AP18: 0.0001 | AQ18: 10 | AR18: 0 | AS18: CP | AT18: LIQUIDADO | AU18: 46262 | AV18: 241.66 | AW18: 001-DIVERSOS | AX18: 001-DIVERSOS | AY18: 1520 | AZ18: COMBINADA | BA18: CO3809041 | BB18: 241.66 | BC18: 212.66 | BD18: 241.66 | BE18: 29 | BF18: 0.12 | BG18: 0 | BH18: 73.4 | BI18: 176.36 | BJ18: 0 | BK18: 18 | BL18: 0 | BM18: 0 | BN18: 3.25 | BO18: 5.5 | BP18: 4.23 | BQ18: 0 | BR18: 0 | BS18: 0 | BT18: 0 | BU18: 0 | BV18: 0 | BW18: 0 | BX18: 0 | BY18: 0 | BZ18: 0 | CA18: 5.32 | CB18: RSCP | CC18: TAMI | CD18: 373.22 | CE18: 0 | CF18: 0 | CG18: 0 | CH18: 0 | CI18: 0 | CJ18: 0 | CK18: 0 | CN18: 0 | CO18: 0 | CP18: 0 | CQ18: 0 | CR18: 0 | CS18: 0 | CT18: 0 | CU18: 48.33 | CV18: FATURA: 12310 | CW18: 48.33 | CX18: 012310 | CY18: 30.09 | CZ18: FATURA: 21534 | DA18: 30.09 | DB18: 021534 | DE18: 0 | DF18: A. | DG18: SC | DH18: JOINVILLE | DI18: 252895738 | DJ18: (47 ) 32052727 | DK18: 0 | DL18: JOI | DM18: 29
A19: 2 | B19: JOI025401-1 | C19: NORMAL | D19: JOIR | E19: JOI | F19: 46240 | G19: MMM1H28 | H19: 42260803098929000789570010000252281003675030 | I19: 61105060000163 | J19: BRASCOLA LTDA - | K19: RUA DONA FRANCISCA 8300 BLOCO D | L19: ZONA INDUSTRIAL | M19: 892 | N19: JOINVILLE | O19: SC | P19: 89219-600 | Q19: 61105060000163 | R19: BRASCOLA LTDA - | S19: JOINVILLE | T19: SC | U19: 61105060000163 | V19: BRASCOLA LTDA - | W19: RUA DONA FRANCISCA 8300 BLOCO D | X19: ZONA INDUSTRIAL | Y19: JOINVILLE | Z19: SC | AA19: (47 ) 32052727 | AC19: 13921752000137 | AD19: BOMDIPEL MATERIAIS DE CONSTRUCAO LTDA - ME | AE19: 356 | AF19: STJP | AG19: POMPEU | AH19: MG | AI19: 13921752000137 | AJ19: BOMDIPEL MATERIAIS DE CONSTRUCAO LTDA - ME | AK19: POMPEU | AL19: MG | AM19: STJ | AN19: 000330407 | AO19: 54.66 | AP19: 0.0001 | AQ19: 9 | AR19: 0 | AS19: CP | AT19: LIQUIDADO | AU19: 46262 | AV19: 248.25 | AW19: 001-DIVERSOS | AX19: 001-DIVERSOS | AY19: 1680.29 | AZ19: COMBINADA | BA19: CO3809055 | BB19: 248.25 | BC19: 218.46 | BD19: 248.25 | BE19: 29.79 | BF19: 0.12 | BG19: 0 | BH19: 54.66 | BI19: 181.6 | BJ19: 0 | BK19: 18 | BL19: 0 | BM19: 0 | BN19: 3.25 | BO19: 5.5 | BP19: 4.23 | BQ19: 0 | BR19: 0 | BS19: 0 | BT19: 0 | BU19: 0 | BV19: 0 | BW19: 0 | BX19: 0 | BY19: 0 | BZ19: 0 | CA19: 5.88 | CB19: RSCP | CC19: RWNI | CD19: 374.77 | CE19: 0 | CF19: 0 | CG19: 0 | CH19: 0 | CI19: 0 | CJ19: 0 | CK19: 0 | CN19: 0 | CO19: 0 | CP19: 0 | CQ19: 0 | CR19: 0 | CS19: 0 | CT19: 0 | CU19: 49.65 | CV19: FATURA: 12310 | CW19: 49.65 | CX19: 012310 | CY19: 51 | CZ19: FATURA: 64592 | DA19: 51 | DB19: 064592 | DE19: 0 | DF19: A. | DG19: SC | DH19: JOINVILLE | DI19: 252895738 | DJ19: (47 ) 32052727 | DK19: 0 | DL19: JOI | DM19: 29.79
A20: 2 | B20: JOI025402-9 | C20: NORMAL | D20: JOIR | E20: JOI | F20: 46240 | G20: MMM1H28 | H20: 42260803098929000789570010000252321003675075 | I20: 61105060000163 | J20: BRASCOLA LTDA - | K20: RUA DONA FRANCISCA 8300 BLOCO D | L20: ZONA INDUSTRIAL | M20: 892 | N20: JOINVILLE | O20: SC | P20: 89219-600 | Q20: 61105060000163 | R20: BRASCOLA LTDA - | S20: JOINVILLE | T20: SC | U20: 61105060000163 | V20: BRASCOLA LTDA - | W20: RUA DONA FRANCISCA 8300 BLOCO D | X20: ZONA INDUSTRIAL | Y20: JOINVILLE | Z20: SC | AA20: (47 ) 32052727 | AC20: 42858274000166 | AD20: PAIOL AGROGURGEL COMERCIO DE FERRAGENS L | AE20: 10 ROTA CIRCUITO DAS AGUAS | AF20: DCCR | AG20: SAO LOURENCO | AH20: MG | AI20: 42858274000166 | AJ20: PAIOL AGROGURGEL COMERCIO DE FERRAGENS L | AK20: SAO LOURENCO | AL20: MG | AM20: DCC | AN20: 000330443 | AO20: 161.47 | AP20: 0.0001 | AQ20: 52 | AR20: 0 | AS20: CP | AT20: LIQUIDADO | AU20: 46262 | AV20: 357.01 | AW20: 001-DIVERSOS | AX20: 001-DIVERSOS | AY20: 4935.52 | AZ20: COMBINADA | BA20: CO3809036 | BB20: 357.01 | BC20: 314.17 | BD20: 357.01 | BE20: 42.84 | BF20: 0.12 | BG20: 0 | BH20: 161.47 | BI20: 256.27 | BJ20: 0 | BK20: 18 | BL20: 0 | BM20: 0 | BN20: 7.4 | BO20: 11 | BP20: 4.23 | BQ20: 0 | BR20: 0 | BS20: 0 | BT20: 0 | BU20: 0 | BV20: 0 | BW20: 0 | BX20: 0 | BY20: 0 | BZ20: 0 | CA20: 17.27 | CB20: RSCP | CC20: ALTR | CD20: 414.16 | CE20: 0 | CF20: 0 | CG20: 0 | CH20: 0 | CI20: 0 | CJ20: 0 | CK20: 0 | CN20: 0 | CO20: 0 | CP20: 0 | CQ20: 0 | CR20: 0 | CS20: 0 | CT20: 0 | CU20: 71.4 | CV20: FATURA: 12310 | CW20: 71.4 | CX20: 012310 | CY20: 124.95 | CZ20: FATURA: 143 | DA20: 324.95 | DB20: 000143 | DE20: 0 | DF20: A. | DG20: SC | DH20: JOINVILLE | DI20: 252895738 | DJ20: (47 ) 32052727 | DK20: 0 | DL20: JOI | DM20: 42.84
A21: 2 | B21: JOI025454-1 | C21: NORMAL | D21: JOIR | E21: JOI | F21: 46241 | G21: MMM1H28 | H21: 42260803098929000789570010000252841003684062 | I21: 61105060000163 | J21: BRASCOLA LTDA - | K21: RUA DONA FRANCISCA 8300 BLOCO D | L21: ZONA INDUSTRIAL | M21: 892 | N21: JOINVILLE | O21: SC | P21: 89219-600 | Q21: 61105060000163 | R21: BRASCOLA LTDA - | S21: JOINVILLE | T21: SC | U21: 61105060000163 | V21: BRASCOLA LTDA - | W21: RUA DONA FRANCISCA 8300 BLOCO D | X21: ZONA INDUSTRIAL | Y21: JOINVILLE | Z21: SC | AA21: (47 ) 32052727 | AC21: 30373444000133 | AD21: GEANDERSON CESAR CAETANO ME | AE21: 359 | AF21: GVRP | AG21: ITABIRA | AH21: MG | AI21: 30373444000133 | AJ21: GEANDERSON CESAR CAETANO ME | AK21: ITABIRA | AL21: MG | AM21: GVR | AN21: 000330493 | AO21: 40.984 | AP21: 0.0001 | AQ21: 9 | AR21: 0 | AS21: CP | AT21: LIQUIDADO | AU21: 46262 | AV21: 220.82 | AW21: 001-DIVERSOS | AX21: 001-DIVERSOS | AY21: 1631.71 | AZ21: COMBINADA | BA21: CO3809055 | BB21: 220.82 | BC21: 194.32 | BD21: 220.82 | BE21: 26.5 | BF21: 0.12 | BG21: 0 | BH21: 40.984 | BI21: 157.63 | BJ21: 0 | BK21: 18 | BL21: 0 | BM21: 0 | BN21: 3.25 | BO21: 5.5 | BP21: 4.23 | BQ21: 0 | BR21: 0 | BS21: 0 | BT21: 0 | BU21: 0 | BV21: 0 | BW21: 0 | BX21: 0 | BY21: 0 | BZ21: 0 | CA21: 5.71 | CB21: RSCP | CC21: RWNI | CD21: 374.33 | CE21: 0 | CF21: 0 | CG21: 0 | CH21: 0 | CI21: 0 | CJ21: 0 | CK21: 0 | CN21: 0 | CO21: 0 | CP21: 0 | CQ21: 0 | CR21: 0 | CS21: 0 | CT21: 0 | CU21: 44.16 | CV21: FATURA: 12323 | CW21: 44.16 | CX21: 012323 | CY21: 81.79 | CZ21: FATURA: 12223 | DA21: 81.79 | DB21: 012223 | DE21: 0 | DF21: A. | DG21: SC | DH21: JOINVILLE | DI21: 252895738 | DJ21: (47 ) 32052727 | DK21: 0 | DL21: JOI | DM21: 26.5
A22: 2 | B22: JOI025455-0 | C22: NORMAL | D22: JOIR | E22: JOI | F22: 46241 | G22: MMM1H28 | H22: 42260803098929000789570010000252851003684078 | I22: 61105060000163 | J22: BRASCOLA LTDA - | K22: RUA DONA FRANCISCA 8300 BLOCO D | L22: ZONA INDUSTRIAL | M22: 892 | N22: JOINVILLE | O22: SC | P22: 89219-600 | Q22: 61105060000163 | R22: BRASCOLA LTDA - | S22: JOINVILLE | T22: SC | U22: 61105060000163 | V22: BRASCOLA LTDA - | W22: RUA DONA FRANCISCA 8300 BLOCO D | X22: ZONA INDUSTRIAL | Y22: JOINVILLE | Z22: SC | AA22: (47 ) 32052727 | AC22: 09342854000120 | AD22: CUNHA MATERIAL DE CONSTRUCAO LTDA ME | AE22: 397 | AF22: GRFI | AG22: DIVINOLANDIA DE MINAS | AH22: MG | AI22: 09342854000120 | AJ22: CUNHA MATERIAL DE CONSTRUCAO LTDA ME | AK22: DIVINOLANDIA DE MINAS | AL22: MG | AM22: GRF | AN22: 000330483 | AO22: 74.328 | AP22: 0.0001 | AQ22: 19 | AR22: 0 | AS22: CP | AT22: LIQUIDADO | AU22: 46262 | AV22: 269.3 | AW22: 001-DIVERSOS | AX22: 001-DIVERSOS | AY22: 3051.01 | AZ22: COMBINADA | BA22: CO3809063 | BB22: 269.3 | BC22: 236.98 | BD22: 269.3 | BE22: 32.32 | BF22: 0.12 | BG22: 0 | BH22: 74.328 | BI22: 193.99 | BJ22: 0 | BK22: 18 | BL22: 0 | BM22: 0 | BN22: 4.58 | BO22: 5.5 | BP22: 4.23 | BQ22: 0 | BR22: 0 | BS22: 0 | BT22: 0 | BU22: 0 | BV22: 0 | BW22: 0 | BX22: 0 | BY22: 0 | BZ22: 0 | CA22: 10.68 | CB22: RSCP | CC22: GRFI | CD22: 389.67 | CE22: 0 | CF22: 0 | CG22: 0 | CH22: 0 | CI22: 0 | CJ22: 0 | CK22: 0 | CN22: 0 | CO22: 0 | CP22: 0 | CQ22: 0 | CR22: 0 | CS22: 0 | CT22: 0 | CU22: 53.86 | CV22: FATURA: 12323 | CW22: 53.86 | CX22: 012323 | CY22: 123.78 | CZ22: FATURA: 130688 | DA22: 138.93 | DB22: 130688 | DE22: 0 | DF22: A. | DG22: SC | DH22: JOINVILLE | DI22: 252895738 | DJ22: (47 ) 32052727 | DK22: 0 | DL22: JOI | DM22: 32.32
A23: 2 | B23: JOI025456-8 | C23: NORMAL | D23: JOIR | E23: JOI | F23: 46241 | G23: MMM1H28 | H23: 42260803098929000789570010000252861003684083 | I23: 61105060000163 | J23: BRASCOLA LTDA - | K23: RUA DONA FRANCISCA 8300 BLOCO D | L23: ZONA INDUSTRIAL | M23: 892 | N23: JOINVILLE | O23: SC | P23: 89219-600 | Q23: 61105060000163 | R23: BRASCOLA LTDA - | S23: JOINVILLE | T23: SC | U23: 61105060000163 | V23: BRASCOLA LTDA - | W23: RUA DONA FRANCISCA 8300 BLOCO D | X23: ZONA INDUSTRIAL | Y23: JOINVILLE | Z23: SC | AA23: (47 ) 32052727 | AC23: 03078191000100 | AD23: COMERCIAL IRMAOS CIMINI LTDA | AE23: 350 | AF23: GVRP | AG23: GOVERNADOR VALADARES | AH23: MG | AI23: 03078191000100 | AJ23: COMERCIAL IRMAOS CIMINI LTDA | AK23: GOVERNADOR VALADARES | AL23: MG | AM23: GVR | AN23: 000330524 | AO23: 121.068 | AP23: 0 | AQ23: 25 | AR23: 0 | AS23: CP | AT23: LIQUIDADO | AU23: 46262 | AV23: 312.23 | AW23: 001-DIVERSOS | AX23: 001-DIVERSOS | AY23: 2766.4 | AZ23: COMBINADA | BA23: CO3809055 | BB23: 312.23 | BC23: 274.76 | BD23: 312.23 | BE23: 37.47 | BF23: 0.12 | BG23: 0 | BH23: 121.068 | BI23: 227.7 | BJ23: 0 | BK23: 18 | BL23: 0 | BM23: 0 | BN23: 4.15 | BO23: 11 | BP23: 4.23 | BQ23: 0 | BR23: 0 | BS23: 0 | BT23: 0 | BU23: 0 | BV23: 0 | BW23: 0 | BX23: 0 | BY23: 0 | BZ23: 0 | CA23: 9.68 | CB23: RSCP | CC23: RWNI | CD23: 385.95 | CE23: 0 | CF23: 0 | CG23: 0 | CH23: 0 | CI23: 0 | CJ23: 0 | CK23: 0 | CN23: 0 | CO23: 0 | CP23: 0 | CQ23: 0 | CR23: 0 | CS23: 0 | CT23: 0 | CU23: 62.45 | CV23: FATURA: 12323 | CW23: 62.45 | CX23: 012323 | CY23: 118.28 | CZ23: FATURA: 12223 | DA23: 118.28 | DB23: 012223 | DE23: 0 | DF23: A. | DG23: SC | DH23: JOINVILLE | DI23: 252895738 | DJ23: (47 ) 32052727 | DK23: 0 | DL23: JOI | DM23: 37.47
A24: 2 | B24: JOI025497-5 | C24: NORMAL | D24: JOIR | E24: JOI | F24: 46244 | G24: MMM1H28 | H24: 42260803098929000789570010000253231003692480 | I24: 61105060000163 | J24: BRASCOLA LTDA - | K24: RUA DONA FRANCISCA 8300 BLOCO D | L24: ZONA INDUSTRIAL | M24: 892 | N24: JOINVILLE | O24: SC | P24: 89219-600 | Q24: 61105060000163 | R24: BRASCOLA LTDA - | S24: JOINVILLE | T24: SC | U24: 61105060000163 | V24: BRASCOLA LTDA - | W24: RUA DONA FRANCISCA 8300 BLOCO D | X24: ZONA INDUSTRIAL | Y24: JOINVILLE | Z24: SC | AA24: (47 ) 32052727 | AC24: 02275530000178 | AD24: MINAS CHAPAS LTDA | AE24: 002 BELO HORIZONTE | AF24: BHZP | AG24: BELO HORIZONTE | AH24: MG | AI24: 02275530000178 | AJ24: MINAS CHAPAS LTDA | AK24: BELO HORIZONTE | AL24: MG | AM24: BHZ | AN24: 000330610 | AO24: 286 | AP24: 0.0001 | AQ24: 1 | AR24: 0 | AS24: CP | AT24: LIQUIDADO | AU24: 46269 | AV24: 506.6 | AW24: 001-DIVERSOS | AX24: 001-DIVERSOS | AY24: 5078.78 | AZ24: COMBINADA | BA24: CO3809017 | BB24: 506.6 | BC24: 445.81 | BD24: 506.6 | BE24: 60.79 | BF24: 0.12 | BG24: 0 | BH24: 286 | BI24: 381.68 | BJ24: 0 | BK24: 18 | BL24: 0 | BM24: 0 | BN24: 7.62 | BO24: 16.5 | BP24: 4.23 | BQ24: 0 | BR24: 0 | BS24: 0 | BT24: 0 | BU24: 0 | BV24: 0 | BW24: 0 | BX24: 0 | BY24: 0 | BZ24: 0 | CA24: 17.78 | CB24: RSCP | CC24: BHZP | CD24: 717.06 | CE24: 0 | CF24: 0 | CG24: 0 | CH24: 0 | CI24: 0 | CJ24: 0 | CK24: 0 | CN24: 0 | CO24: 0 | CP24: 0 | CQ24: 0 | CR24: 0 | CS24: 0 | CT24: 0 | CU24: 101.32 | CV24: FATURA: 12323 | CW24: 101.32 | CX24: 012323 | CY24: 40.04 | CZ24: MAPA: 161 | DA24: 0 | DE24: 0 | DF24: A. | DG24: SC | DH24: JOINVILLE | DI24: 252895738 | DJ24: (47 ) 32052727 | DK24: 0 | DL24: JOI | DM24: 60.79
A25: 2 | B25: JOI025498-3 | C25: NORMAL | D25: JOIR | E25: JOI | F25: 46244 | G25: MMM1H28 | H25: 42260803098929000789570010000253241003692496 | I25: 61105060000163 | J25: BRASCOLA LTDA - | K25: RUA DONA FRANCISCA 8300 BLOCO D | L25: ZONA INDUSTRIAL | M25: 892 | N25: JOINVILLE | O25: SC | P25: 89219-600 | Q25: 61105060000163 | R25: BRASCOLA LTDA - | S25: JOINVILLE | T25: SC | U25: 61105060000163 | V25: BRASCOLA LTDA - | W25: RUA DONA FRANCISCA 8300 BLOCO D | X25: ZONA INDUSTRIAL | Y25: JOINVILLE | Z25: SC | AA25: (47 ) 32052727 | AC25: 21765695000172 | AD25: CHAPADACO FERRAGENS LTDA EPP | AE25: 393 | AF25: STJI | AG25: CHAPADA GAUCHA | AH25: MG | AI25: 21765695000172 | AJ25: CHAPADACO FERRAGENS LTDA EPP | AK25: SAO FRANCISCO | AL25: MG | AM25: STJ | AN25: 000330540 | AO25: 39.12 | AP25: 0.0001 | AQ25: 10 | AR25: 0 | AS25: CP | AT25: LIQUIDADO | AU25: 46269 | AV25: 221.23 | AW25: 001-DIVERSOS | AX25: 001-DIVERSOS | AY25: 1734.34 | AZ25: COMBINADA | BA25: CO3809052 | BB25: 221.23 | BC25: 194.68 | BD25: 221.23 | BE25: 26.55 | BF25: 0.12 | BG25: 0 | BH25: 39.12 | BI25: 157.63 | BJ25: 0 | BK25: 18 | BL25: 0 | BM25: 0 | BN25: 3.25 | BO25: 5.5 | BP25: 4.23 | BQ25: 0 | BR25: 0 | BS25: 0 | BT25: 0 | BU25: 0 | BV25: 0 | BW25: 0 | BX25: 0 | BY25: 0 | BZ25: 0 | CA25: 6.07 | CB25: RSCP | CC25: RMCP | CD25: 375.35 | CE25: 0 | CF25: 0 | CG25: 0 | CH25: 0 | CI25: 0 | CJ25: 0 | CK25: 0 | CN25: 0 | CO25: 0 | CP25: 0 | CQ25: 0 | CR25: 0 | CS25: 0 | CT25: 0 | CU25: 44.25 | CV25: FATURA: 12323 | CW25: 44.25 | CX25: 012323 | CY25: 51 | CZ25: FATURA: 65166 | DA25: 51 | DB25: 065166 | DE25: 0 | DF25: A. | DG25: SC | DH25: JOINVILLE | DI25: 252895738 | DJ25: (47 ) 32052727 | DK25: 0 | DL25: JOI | DM25: 26.55
A26: 2 | B26: JOI025499-1 | C26: NORMAL | D26: JOIR | E26: JOI | F26: 46244 | G26: MMM1H28 | H26: 42260803098929000789570010000253251003692507 | I26: 61105060000163 | J26: BRASCOLA LTDA - | K26: RUA DONA FRANCISCA 8300 BLOCO D | L26: ZONA INDUSTRIAL | M26: 892 | N26: JOINVILLE | O26: SC | P26: 89219-600 | Q26: 61105060000163 | R26: BRASCOLA LTDA - | S26: JOINVILLE | T26: SC | U26: 61105060000163 | V26: BRASCOLA LTDA - | W26: RUA DONA FRANCISCA 8300 BLOCO D | X26: ZONA INDUSTRIAL | Y26: JOINVILLE | Z26: SC | AA26: (47 ) 32052727 | AC26: 04505326000121 | AD26: COMERCIAL FERRONORTE COMERCIO INDUSTRIA E SERVICOS LTDA | AE26: 394 | AF26: VEAI | AG26: MONTES CLAROS | AH26: MG | AI26: 04505326000121 | AJ26: COMERCIAL FERRONORTE COMERCIO INDUSTRIA E SERVICOS LTDA | AK26: MONTES CLAROS | AL26: MG | AM26: VEA | AN26: 000330541 | AO26: 90.212 | AP26: 0.0001 | AQ26: 19 | AR26: 0 | AS26: CP | AT26: LIQUIDADO | AU26: 46269 | AV26: 270.92 | AW26: 001-DIVERSOS | AX26: 001-DIVERSOS | AY26: 3337.82 | AZ26: COMBINADA | BA26: CO3809060 | BB26: 270.92 | BC26: 238.41 | BD26: 270.92 | BE26: 32.51 | BF26: 0.12 | BG26: 0 | BH26: 90.212 | BI26: 193.99 | BJ26: 0 | BK26: 18 | BL26: 0 | BM26: 0 | BN26: 5.01 | BO26: 5.5 | BP26: 4.23 | BQ26: 0 | BR26: 0 | BS26: 0 | BT26: 0 | BU26: 0 | BV26: 0 | BW26: 0 | BX26: 0 | BY26: 0 | BZ26: 0 | CA26: 11.68 | CB26: RSCP | CC26: VEAI | CD26: 393.38 | CE26: 0 | CF26: 0 | CG26: 0 | CH26: 0 | CI26: 0 | CJ26: 0 | CK26: 0 | CN26: 0 | CO26: 0 | CP26: 0 | CQ26: 0 | CR26: 0 | CS26: 0 | CT26: 0 | CU26: 54.18 | CV26: FATURA: 12323 | CW26: 54.18 | CX26: 012323 | CY26: 81.28 | CZ26: MAPA: 0 | DA26: =CY26 -> 81.28 | DE26: 0 | DF26: A. | DG26: SC | DH26: JOINVILLE | DI26: 252895738 | DJ26: (47 ) 32052727 | DK26: 0 | DL26: JOI | DM26: 32.51
A27: 2 | B27: JOI025500-9 | C27: NORMAL | D27: JOIR | E27: JOI | F27: 46244 | G27: MMM1H28 | H27: 42260803098929000789570010000253261003692512 | I27: 61105060000163 | J27: BRASCOLA LTDA - | K27: RUA DONA FRANCISCA 8300 BLOCO D | L27: ZONA INDUSTRIAL | M27: 892 | N27: JOINVILLE | O27: SC | P27: 89219-600 | Q27: 61105060000163 | R27: BRASCOLA LTDA - | S27: JOINVILLE | T27: SC | U27: 61105060000163 | V27: BRASCOLA LTDA - | W27: RUA DONA FRANCISCA 8300 BLOCO D | X27: ZONA INDUSTRIAL | Y27: JOINVILLE | Z27: SC | AA27: (47 ) 32052727 | AC27: 01177077000102 | AD27: LOJA PINHEIRO CONFECCOES E ARMARINHO LTDA | AE27: 398 | AF27: GRFP | AG27: TEOFILO OTONI | AH27: MG | AI27: 01177077000102 | AJ27: LOJA PINHEIRO CONFECCOES E ARMARINHO LTDA | AK27: TEOFILO OTONI | AL27: MG | AM27: GRF | AN27: 000330547 | AO27: 45 | AP27: 0.0001 | AQ27: 25 | AR27: 0 | AS27: CP | AT27: LIQUIDADO | AU27: 46269 | AV27: 221.92 | AW27: 001-DIVERSOS | AX27: 001-DIVERSOS | AY27: 1907.49 | AZ27: COMBINADA | BA27: CO3809065 | BB27: 221.92 | BC27: 195.29 | BD27: 221.92 | BE27: 26.63 | BF27: 0.12 | BG27: 0 | BH27: 45 | BI27: 157.63 | BJ27: 0 | BK27: 18 | BL27: 0 | BM27: 0 | BN27: 3.25 | BO27: 5.5 | BP27: 4.23 | BQ27: 0 | BR27: 0 | BS27: 0 | BT27: 0 | BU27: 0 | BV27: 0 | BW27: 0 | BX27: 0 | BY27: 0 | BZ27: 0 | CA27: 6.68 | CB27: RSCP | CC27: LTOI | CD27: 377.09 | CE27: 0 | CF27: 0 | CG27: 0 | CH27: 0 | CI27: 0 | CJ27: 0 | CK27: 0 | CN27: 0 | CO27: 0 | CP27: 0 | CQ27: 0 | CR27: 0 | CS27: 0 | CT27: 0 | CU27: 44.38 | CV27: FATURA: 12323 | CW27: 44.38 | CX27: 012323 | CY27: 103.05 | CZ27: FATURA: 130688 | DA27: 115.34 | DB27: 130688 | DE27: 0 | DF27: A. | DG27: SC | DH27: JOINVILLE | DI27: 252895738 | DJ27: (47 ) 32052727 | DK27: 0 | DL27: JOI | DM27: 26.63
A28: 2 | B28: JOI025501-7 | C28: NORMAL | D28: JOIR | E28: JOI | F28: 46244 | G28: MMM1H28 | H28: 42260803098929000789570010000253271003692528 | I28: 61105060000163 | J28: BRASCOLA LTDA - | K28: RUA DONA FRANCISCA 8300 BLOCO D | L28: ZONA INDUSTRIAL | M28: 892 | N28: JOINVILLE | O28: SC | P28: 89219-600 | Q28: 61105060000163 | R28: BRASCOLA LTDA - | S28: JOINVILLE | T28: SC | U28: 61105060000163 | V28: BRASCOLA LTDA - | W28: RUA DONA FRANCISCA 8300 BLOCO D | X28: ZONA INDUSTRIAL | Y28: JOINVILLE | Z28: SC | AA28: (47 ) 32052727 | AC28: 63792748000194 | AD28: 63.792.748 GABRIEL GUIMARAES DE MATOS | AE28: 332 | AF28: BHZP | AG28: LAGOA SANTA | AH28: MG | AI28: 63792748000194 | AJ28: 63.792.748 GABRIEL GUIMARAES DE MATOS | AK28: LAGOA SANTA | AL28: MG | AM28: BHZ | AN28: 000330550 | AO28: 69.12 | AP28: 0.0001 | AQ28: 39 | AR28: 0 | AS28: CP | AT28: LIQUIDADO | AU28: 46269 | AV28: 198.91 | AW28: 001-DIVERSOS | AX28: 001-DIVERSOS | AY28: 3046.21 | AZ28: COMBINADA | BA28: CO3809017 | BB28: 198.91 | BC28: 175.04 | BD28: 198.91 | BE28: 23.87 | BF28: 0.12 | BG28: 0 | BH28: 69.12 | BI28: 132.08 | BJ28: 0 | BK28: 18 | BL28: 0 | BM28: 0 | BN28: 4.57 | BO28: 5.5 | BP28: 4.23 | BQ28: 0 | BR28: 0 | BS28: 0 | BT28: 0 | BU28: 0 | BV28: 0 | BW28: 0 | BX28: 0 | BY28: 0 | BZ28: 0 | CA28: 10.66 | CB28: RSCP | CC28: BHZP | CD28: 389.56 | CE28: 0 | CF28: 0 | CG28: 0 | CH28: 0 | CI28: 0 | CJ28: 0 | CK28: 0 | CN28: 0 | CO28: 0 | CP28: 0 | CQ28: 0 | CR28: 0 | CS28: 0 | CT28: 0 | CU28: 39.78 | CV28: FATURA: 12323 | CW28: 39.78 | CX28: 012323 | CY28: 15 | CZ28: MAPA: 161 | DA28: 0 | DE28: 0 | DF28: A. | DG28: SC | DH28: JOINVILLE | DI28: 252895738 | DJ28: (47 ) 32052727 | DK28: 0 | DL28: JOI | DM28: 23.87
A29: 2 | B29: JOI025502-5 | C29: NORMAL | D29: JOIR | E29: JOI | F29: 46244 | G29: MMM1H28 | H29: 42260803098929000789570010000253281003692533 | I29: 61105060000163 | J29: BRASCOLA LTDA - | K29: RUA DONA FRANCISCA 8300 BLOCO D | L29: ZONA INDUSTRIAL | M29: 892 | N29: JOINVILLE | O29: SC | P29: 89219-600 | Q29: 61105060000163 | R29: BRASCOLA LTDA - | S29: JOINVILLE | T29: SC | U29: 61105060000163 | V29: BRASCOLA LTDA - | W29: RUA DONA FRANCISCA 8300 BLOCO D | X29: ZONA INDUSTRIAL | Y29: JOINVILLE | Z29: SC | AA29: (47 ) 32052727 | AC29: 21513577000177 | AD29: ELETRO BRAGA LTDA | AE29: 363 | AF29: TAMR | AG29: SAO JOAO DEL REI | AH29: MG | AI29: 21513577000177 | AJ29: ELETRO BRAGA LTDA | AK29: SAO JOAO DEL REI | AL29: MG | AM29: TAM | AN29: 000330554 | AO29: 103.632 | AP29: 0.0001 | AQ29: 23 | AR29: 0 | AS29: CP | AT29: LIQUIDADO | AU29: 46269 | AV29: 261.52 | AW29: 001-DIVERSOS | AX29: 001-DIVERSOS | AY29: 3165.42 | AZ29: COMBINADA | BA29: CO3809042 | BB29: 261.52 | BC29: 230.14 | BD29: 261.52 | BE29: 31.38 | BF29: 0.12 | BG29: 0 | BH29: 103.632 | BI29: 181.08 | BJ29: 0 | BK29: 18 | BL29: 0 | BM29: 0 | BN29: 4.75 | BO29: 11 | BP29: 4.23 | BQ29: 0 | BR29: 0 | BS29: 0 | BT29: 0 | BU29: 0 | BV29: 0 | BW29: 0 | BX29: 0 | BY29: 0 | BZ29: 0 | CA29: 11.08 | CB29: RSCP | CC29: TAMR | CD29: 391.15 | CE29: 0 | CF29: 0 | CG29: 0 | CH29: 0 | CI29: 0 | CJ29: 0 | CK29: 0 | CN29: 0 | CO29: 0 | CP29: 0 | CQ29: 0 | CR29: 0 | CS29: 0 | CT29: 0 | CU29: 52.3 | CV29: FATURA: 12323 | CW29: 52.3 | CX29: 012323 | CY29: 51.82 | CZ29: FATURA: 21744 | DA29: 51.82 | DB29: 021744 | DE29: 0 | DF29: A. | DG29: SC | DH29: JOINVILLE | DI29: 252895738 | DJ29: (47 ) 32052727 | DK29: 0 | DL29: JOI | DM29: 31.38
A30: 2 | B30: JOI025503-3 | C30: NORMAL | D30: JOIR | E30: JOI | F30: 46244 | G30: MMM1H28 | H30: 42260803098929000789570010000253291003692549 | I30: 61105060000163 | J30: BRASCOLA LTDA - | K30: RUA DONA FRANCISCA 8300 BLOCO D | L30: ZONA INDUSTRIAL | M30: 892 | N30: JOINVILLE | O30: SC | P30: 89219-600 | Q30: 61105060000163 | R30: BRASCOLA LTDA - | S30: JOINVILLE | T30: SC | U30: 61105060000163 | V30: BRASCOLA LTDA - | W30: RUA DONA FRANCISCA 8300 BLOCO D | X30: ZONA INDUSTRIAL | Y30: JOINVILLE | Z30: SC | AA30: (47 ) 32052727 | AC30: 55816370000193 | AD30: NOVA ALVORADA MATERIAIS PARA CONSTRUCAO LTDA | AE30: 6 ROTA POCOS DE CALDAS | AF30: DCCR | AG30: POCOS DE CALDAS | AH30: MG | AI30: 55816370000193 | AJ30: NOVA ALVORADA MATERIAIS PARA CONSTRUCAO LTDA | AK30: POCOS DE CALDAS | AL30: MG | AM30: DCC | AN30: 000330569 | AO30: 361.88 | AP30: 0.0001 | AQ30: 1 | AR30: 0 | AS30: CP | AT30: LIQUIDADO | AU30: 46269 | AV30: 683.1 | AW30: 001-DIVERSOS | AX30: 001-DIVERSOS | AY30: 8021.33 | AZ30: COMBINADA | BA30: CO3809036 | BB30: 683.1 | BC30: 601.13 | BD30: 683.1 | BE30: 81.97 | BF30: 0.12 | BG30: 0 | BH30: 361.88 | BI30: 516.8 | BJ30: 0 | BK30: 18 | BL30: 0 | BM30: 0 | BN30: 12.03 | BO30: 22 | BP30: 4.23 | BQ30: 0 | BR30: 0 | BS30: 0 | BT30: 0 | BU30: 0 | BV30: 0 | BW30: 0 | BX30: 0 | BY30: 0 | BZ30: 0 | CA30: 28.07 | CB30: RSCP | CC30: ALTR | CD30: 1020.92 | CE30: 0 | CF30: 0 | CG30: 0 | CH30: 0 | CI30: 0 | CJ30: 0 | CK30: 0 | CN30: 0 | CO30: 0 | CP30: 0 | CQ30: 0 | CR30: 0 | CS30: 0 | CT30: 0 | CU30: 136.62 | CV30: FATURA: 12323 | CW30: 136.62 | CX30: 012323 | CY30: 239.09 | CZ30: FATURA: 143 | DA30: 239.09 | DB30: 000143 | DE30: 0 | DF30: A. | DG30: SC | DH30: JOINVILLE | DI30: 252895738 | DJ30: (47 ) 32052727 | DK30: 0 | DL30: JOI | DM30: 81.97
A31: 2 | B31: JOI025504-1 | C31: NORMAL | D31: JOIR | E31: JOI | F31: 46244 | G31: MMM1H28 | H31: 42260803098929000789570010000253301003692558 | I31: 61105060000163 | J31: BRASCOLA LTDA - | K31: RUA DONA FRANCISCA 8300 BLOCO D | L31: ZONA INDUSTRIAL | M31: 892 | N31: JOINVILLE | O31: SC | P31: 89219-600 | Q31: 61105060000163 | R31: BRASCOLA LTDA - | S31: JOINVILLE | T31: SC | U31: 61105060000163 | V31: BRASCOLA LTDA - | W31: RUA DONA FRANCISCA 8300 BLOCO D | X31: ZONA INDUSTRIAL | Y31: JOINVILLE | Z31: SC | AA31: (47 ) 32052727 | AC31: 24178418000151 | AD31: EZEQUIAS SELMIEL DE CARVALHO | AE31: 3 ROTA ITAJUBA | AF31: DCCR | AG31: ITAJUBA | AH31: MG | AI31: 24178418000151 | AJ31: EZEQUIAS SELMIEL DE CARVALHO | AK31: ITAJUBA | AL31: MG | AM31: DCC | AN31: 000330578 | AO31: 55.376 | AP31: 0.0001 | AQ31: 8 | AR31: 0 | AS31: CP | AT31: LIQUIDADO | AU31: 46269 | AV31: 228.9 | AW31: 001-DIVERSOS | AX31: 001-DIVERSOS | AY31: 1534.86 | AZ31: COMBINADA | BA31: CO3809036 | BB31: 228.9 | BC31: 201.43 | BD31: 228.9 | BE31: 27.47 | BF31: 0.12 | BG31: 0 | BH31: 55.376 | BI31: 165.08 | BJ31: 0 | BK31: 18 | BL31: 0 | BM31: 0 | BN31: 3.25 | BO31: 5.5 | BP31: 4.23 | BQ31: 0 | BR31: 0 | BS31: 0 | BT31: 0 | BU31: 0 | BV31: 0 | BW31: 0 | BX31: 0 | BY31: 0 | BZ31: 0 | CA31: 5.37 | CB31: RSCP | CC31: ALTR | CD31: 373.35 | CE31: 0 | CF31: 0 | CG31: 0 | CH31: 0 | CI31: 0 | CJ31: 0 | CK31: 0 | CN31: 0 | CO31: 0 | CP31: 0 | CQ31: 0 | CR31: 0 | CS31: 0 | CT31: 0 | CU31: 45.78 | CV31: FATURA: 12323 | CW31: 45.78 | CX31: 012323 | CY31: 80.12 | CZ31: FATURA: 143 | DA31: 80.12 | DB31: 000143 | DE31: 0 | DF31: A. | DG31: SC | DH31: JOINVILLE | DI31: 252895738 | DJ31: (47 ) 32052727 | DK31: 0 | DL31: JOI | DM31: 27.47
A32: 2 | B32: JOI025505-0 | C32: NORMAL | D32: JOIR | E32: JOI | F32: 46244 | G32: MMM1H28 | H32: 42260803098929000789570010000253311003692563 | I32: 61105060000163 | J32: BRASCOLA LTDA - | K32: RUA DONA FRANCISCA 8300 BLOCO D | L32: ZONA INDUSTRIAL | M32: 892 | N32: JOINVILLE | O32: SC | P32: 89219-600 | Q32: 61105060000163 | R32: BRASCOLA LTDA - | S32: JOINVILLE | T32: SC | U32: 61105060000163 | V32: BRASCOLA LTDA - | W32: RUA DONA FRANCISCA 8300 BLOCO D | X32: ZONA INDUSTRIAL | Y32: JOINVILLE | Z32: SC | AA32: (47 ) 32052727 | AC32: 76639285004245 | AD32: FERRAGENS NEGRAO COMERCIAL LTDA | AE32: 010 RIBEIRAO DAS NEVES | AF32: BHZP | AG32: RIBEIRAO DAS NEVES | AH32: MG | AI32: 76639285004245 | AJ32: FERRAGENS NEGRAO COMERCIAL LTDA | AK32: RIBEIRAO DAS NEVES | AL32: MG | AM32: BHZ | AN32: 000330638 | AO32: 103.176 | AP32: 0.0001 | AQ32: 18 | AR32: 0 | AS32: CP | AT32: LIQUIDADO | AU32: 46269 | AV32: 234.68 | AW32: 001-DIVERSOS | AX32: 001-DIVERSOS | AY32: 2198.63 | AZ32: COMBINADA | BA32: CO3809017 | BB32: 234.68 | BC32: 206.52 | BD32: 234.68 | BE32: 28.16 | BF32: 0.12 | BG32: 0 | BH32: 103.176 | BI32: 162.29 | BJ32: 0 | BK32: 18 | BL32: 0 | BM32: 0 | BN32: 3.3 | BO32: 11 | BP32: 4.23 | BQ32: 0 | BR32: 0 | BS32: 0 | BT32: 0 | BU32: 0 | BV32: 0 | BW32: 0 | BX32: 0 | BY32: 0 | BZ32: 0 | CA32: 7.7 | CB32: RSCP | CC32: BHZP | CD32: 379.99 | CE32: 0 | CF32: 0 | CG32: 0 | CH32: 0 | CI32: 0 | CJ32: 0 | CK32: 0 | CN32: 0 | CO32: 0 | CP32: 0 | CQ32: 0 | CR32: 0 | CS32: 0 | CT32: 0 | CU32: 46.94 | CV32: FATURA: 12323 | CW32: 46.94 | CX32: 012323 | CY32: 15 | CZ32: MAPA: 161 | DA32: 0 | DE32: 0 | DF32: A. | DG32: SC | DH32: JOINVILLE | DI32: 252895738 | DJ32: (47 ) 32052727 | DK32: 0 | DL32: JOI | DM32: 28.16
A33: 2 | B33: JOI025557-2 | C33: NORMAL | D33: JOIR | E33: JOI | F33: 46245 | G33: MMM1H28 | H33: 42260803098929000789570010000253831003699084 | I33: 61105060000163 | J33: BRASCOLA LTDA - | K33: RUA DONA FRANCISCA 8300 BLOCO D | L33: ZONA INDUSTRIAL | M33: 892 | N33: JOINVILLE | O33: SC | P33: 89219-600 | Q33: 61105060000163 | R33: BRASCOLA LTDA - | S33: JOINVILLE | T33: SC | U33: 61105060000163 | V33: BRASCOLA LTDA - | W33: RUA DONA FRANCISCA 8300 BLOCO D | X33: ZONA INDUSTRIAL | Y33: JOINVILLE | Z33: SC | AA33: (47 ) 32052727 | AC33: 05244723000150 | AD33: AILTON OLIVEIRA BORBOREMA | AE33: 394 | AF33: VEAI | AG33: MONTES CLAROS | AH33: MG | AI33: 05244723000150 | AJ33: AILTON OLIVEIRA BORBOREMA | AK33: MONTES CLAROS | AL33: MG | AM33: VEA | AN33: 000330671 | AO33: 411.044 | AP33: 0.0001 | AQ33: 1 | AR33: 0 | AS33: CP | AT33: LIQUIDADO | AU33: 46269 | AV33: 889.57 | AW33: 001-DIVERSOS | AX33: 001-DIVERSOS | AY33: 8285.41 | AZ33: COMBINADA | BA33: CO3809060 | BB33: 889.57 | BC33: 782.82 | BD33: 889.57 | BE33: 106.75 | BF33: 0.12 | BG33: 0 | BH33: 411.044 | BI33: 691.66 | BJ33: 0 | BK33: 18 | BL33: 0 | BM33: 0 | BN33: 12.43 | BO33: 27.5 | BP33: 4.23 | BQ33: 0 | BR33: 0 | BS33: 0 | BT33: 0 | BU33: 0 | BV33: 0 | BW33: 0 | BX33: 0 | BY33: 0 | BZ33: 0 | CA33: 29 | CB33: RSCP | CC33: VEAI | CD33: 1196.3 | CE33: 0 | CF33: 0 | CG33: 0 | CH33: 0 | CI33: 0 | CJ33: 0 | CK33: 0 | CN33: 0 | CO33: 0 | CP33: 0 | CQ33: 0 | CR33: 0 | CS33: 0 | CT33: 0 | CU33: 177.91 | CV33: FATURA: 12323 | CW33: 177.91 | CX33: 012323 | CY33: 266.87 | CZ33: MAPA: 0 | DA33: =CY33 -> 266.87 | DE33: 0 | DF33: A. | DG33: SC | DH33: JOINVILLE | DI33: 252895738 | DJ33: (47 ) 32052727 | DK33: 0 | DL33: JOI | DM33: 106.75
A34: 2 | B34: JOI025558-1 | C34: NORMAL | D34: JOIR | E34: JOI | F34: 46245 | G34: MMM1H28 | H34: 42260803098929000789570010000253841003699090 | I34: 61105060000163 | J34: BRASCOLA LTDA - | K34: RUA DONA FRANCISCA 8300 BLOCO D | L34: ZONA INDUSTRIAL | M34: 892 | N34: JOINVILLE | O34: SC | P34: 89219-600 | Q34: 61105060000163 | R34: BRASCOLA LTDA - | S34: JOINVILLE | T34: SC | U34: 61105060000163 | V34: BRASCOLA LTDA - | W34: RUA DONA FRANCISCA 8300 BLOCO D | X34: ZONA INDUSTRIAL | Y34: JOINVILLE | Z34: SC | AA34: (47 ) 32052727 | AC34: 04259137000116 | AD34: FERROLAGOS COMERCIO DE ACO E D | AE34: 001 SETE LAGOAS | AF34: SETP | AG34: SETE LAGOAS | AH34: MG | AI34: 04259137000116 | AJ34: FERROLAGOS COMERCIO DE ACO E D | AK34: SETE LAGOAS | AL34: MG | AM34: SET | AN34: 000330687 | AO34: 829 | AP34: 0.0001 | AQ34: 2 | AR34: 0 | AS34: CP | AT34: LIQUIDADO | AU34: 46269 | AV34: 1345.16 | AW34: 001-DIVERSOS | AX34: 001-DIVERSOS | AY34: 15746.58 | AZ34: COMBINADA | BA34: CO3809016 | BB34: 1345.16 | BC34: 1183.74 | BD34: 1345.16 | BE34: 161.42 | BF34: 0.12 | BG34: 0 | BH34: 829 | BI34: 1033.28 | BJ34: 0 | BK34: 18 | BL34: 0 | BM34: 0 | BN34: 23.62 | BO34: 49.5 | BP34: 4.23 | BQ34: 0 | BR34: 0 | BS34: 0 | BT34: 0 | BU34: 0 | BV34: 0 | BW34: 0 | BX34: 0 | BY34: 0 | BZ34: 0 | CA34: 55.11 | CB34: RSCP | CC34: SETP | CD34: 2756.48 | CE34: 0 | CF34: 0 | CG34: 0 | CH34: 0 | CI34: 0 | CJ34: 0 | CK34: 0 | CN34: 0 | CO34: 0 | CP34: 0 | CQ34: 0 | CR34: 0 | CS34: 0 | CT34: 0 | CU34: 269.03 | CV34: FATURA: 12323 | CW34: 269.03 | CX34: 012323 | CY34: 66.32 | CZ34: MAPA: 161 | DA34: 0 | DE34: 0 | DF34: A. | DG34: SC | DH34: JOINVILLE | DI34: 252895738 | DJ34: (47 ) 32052727 | DK34: 0 | DL34: JOI | DM34: 161.42
A35: 2 | B35: JOI025559-9 | C35: NORMAL | D35: JOIR | E35: JOI | F35: 46245 | G35: MMM1H28 | H35: 42260803098929000789570010000253851003699100 | I35: 61105060000163 | J35: BRASCOLA LTDA - | K35: RUA DONA FRANCISCA 8300 BLOCO D | L35: ZONA INDUSTRIAL | M35: 892 | N35: JOINVILLE | O35: SC | P35: 89219-600 | Q35: 61105060000163 | R35: BRASCOLA LTDA - | S35: JOINVILLE | T35: SC | U35: 61105060000163 | V35: BRASCOLA LTDA - | W35: RUA DONA FRANCISCA 8300 BLOCO D | X35: ZONA INDUSTRIAL | Y35: JOINVILLE | Z35: SC | AA35: (47 ) 32052727 | AC35: 02235305000108 | AD35: GLOBAL COMPANY INDUSTRIA LTDA | AE35: 5 ROTA EXTREMA | AF35: DCCR | AG35: EXTREMA | AH35: MG | AI35: 02235305000108 | AJ35: GLOBAL COMPANY INDUSTRIA LTDA | AK35: EXTREMA | AL35: MG | AM35: DCC | AN35: 000330688 | AO35: 246 | AP35: 0.0001 | AQ35: 12 | AR35: 0 | AS35: CP | AT35: LIQUIDADO | AU35: 46269 | AV35: 479.19 | AW35: 001-DIVERSOS | AX35: 001-DIVERSOS | AY35: 3360 | AZ35: COMBINADA | BA35: CO3809036 | BB35: 479.19 | BC35: 421.69 | BD35: 479.19 | BE35: 57.5 | BF35: 0.12 | BG35: 0 | BH35: 246 | BI35: 366.16 | BJ35: 0 | BK35: 18 | BL35: 0 | BM35: 0 | BN35: 5.04 | BO35: 16.5 | BP35: 4.23 | BQ35: 0 | BR35: 0 | BS35: 0 | BT35: 0 | BU35: 0 | BV35: 0 | BW35: 0 | BX35: 0 | BY35: 0 | BZ35: 0 | CA35: 11.76 | CB35: RSCP | CC35: ALTR | CD35: 554.68 | CE35: 0 | CF35: 0 | CG35: 0 | CH35: 0 | CI35: 0 | CJ35: 0 | CK35: 0 | CN35: 0 | CO35: 0 | CP35: 0 | CQ35: 0 | CR35: 0 | CS35: 0 | CT35: 0 | CU35: 95.84 | CV35: FATURA: 12323 | CW35: 95.84 | CX35: 012323 | CY35: 167.72 | CZ35: FATURA: 143 | DA35: 167.72 | DB35: 000143 | DE35: 0 | DF35: A. | DG35: SC | DH35: JOINVILLE | DI35: 252895738 | DJ35: (47 ) 32052727 | DK35: 0 | DL35: JOI | DM35: 57.5
A36: 2 | B36: JOI025560-2 | C36: NORMAL | D36: JOIR | E36: JOI | F36: 46245 | G36: MMM1H28 | H36: 42260803098929000789570010000253861003699116 | I36: 61105060000163 | J36: BRASCOLA LTDA - | K36: RUA DONA FRANCISCA 8300 BLOCO D | L36: ZONA INDUSTRIAL | M36: 892 | N36: JOINVILLE | O36: SC | P36: 89219-600 | Q36: 61105060000163 | R36: BRASCOLA LTDA - | S36: JOINVILLE | T36: SC | U36: 61105060000163 | V36: BRASCOLA LTDA - | W36: RUA DONA FRANCISCA 8300 BLOCO D | X36: ZONA INDUSTRIAL | Y36: JOINVILLE | Z36: SC | AA36: (47 ) 32052727 | AC36: 06342548000104 | AD36: PATOS PLASTICOS E TECIDOS LTDA ME | AE36: 387 | AF36: TRUI | AG36: PATOS DE MINAS | AH36: MG | AI36: 06342548000104 | AJ36: PATOS PLASTICOS E TECIDOS LTDA ME | AK36: PATOS DE MINAS | AL36: MG | AM36: TRU | AN36: 000330709 | AO36: 43.3 | AP36: 0.0001 | AQ36: 15 | AR36: 0 | AS36: CP | AT36: LIQUIDADO | AU36: 46269 | AV36: 220.78 | AW36: 001-DIVERSOS | AX36: 001-DIVERSOS | AY36: 1624.13 | AZ36: COMBINADA | BA36: CO3809048 | BB36: 220.78 | BC36: 194.29 | BD36: 220.78 | BE36: 26.49 | BF36: 0.12 | BG36: 0 | BH36: 43.3 | BI36: 157.63 | BJ36: 0 | BK36: 18 | BL36: 0 | BM36: 0 | BN36: 3.25 | BO36: 5.5 | BP36: 4.23 | BQ36: 0 | BR36: 0 | BS36: 0 | BT36: 0 | BU36: 0 | BV36: 0 | BW36: 0 | BX36: 0 | BY36: 0 | BZ36: 0 | CA36: 5.68 | CB36: RSCP | CC36: PANI | CD36: 374.27 | CE36: 0 | CF36: 0 | CG36: 0 | CH36: 0 | CI36: 0 | CJ36: 0 | CK36: 0 | CN36: 0 | CO36: 0 | CP36: 0 | CQ36: 0 | CR36: 0 | CS36: 0 | CT36: 0 | CU36: 44.16 | CV36: FATURA: 12323 | CW36: 44.16 | CX36: 012323 | CY36: 99.35 | CZ36: FATURA: 232784 | DA36: 84.33 | DB36: 232784 | DE36: 0 | DF36: A. | DG36: SC | DH36: JOINVILLE | DI36: 252895738 | DJ36: (47 ) 32052727 | DK36: 0 | DL36: JOI | DM36: 26.49
A37: 2 | B37: JOI025563-7 | C37: NORMAL | D37: JOIR | E37: JOI | F37: 46245 | G37: MMM1H28 | H37: 42260803098929000789570010000253891003699339 | I37: 61105060000163 | J37: BRASCOLA LTDA - | K37: RUA DONA FRANCISCA 8300 BLOCO D | L37: ZONA INDUSTRIAL | M37: 892 | N37: JOINVILLE | O37: SC | P37: 89219-600 | Q37: 61105060000163 | R37: BRASCOLA LTDA - | S37: JOINVILLE | T37: SC | U37: 61105060000163 | V37: BRASCOLA LTDA - | W37: RUA DONA FRANCISCA 8300 BLOCO D | X37: ZONA INDUSTRIAL | Y37: JOINVILLE | Z37: SC | AA37: (47 ) 32052727 | AC37: 27945015000189 | AD37: MINAS COUROS LTDA | AE37: 002 BELO HORIZONTE | AF37: BHZP | AG37: BELO HORIZONTE | AH37: MG | AI37: 27945015000189 | AJ37: MINAS COUROS LTDA | AK37: BELO HORIZONTE | AL37: MG | AM37: BHZ | AN37: 000330713 | AO37: 72 | AP37: 0.0001 | AQ37: 40 | AR37: 0 | AS37: CP | AT37: LIQUIDADO | AU37: 46269 | AV37: 228.81 | AW37: 001-DIVERSOS | AX37: 001-DIVERSOS | AY37: 3029.58 | AZ37: COMBINADA | BA37: CO3809017 | BB37: 228.81 | BC37: 201.35 | BD37: 228.81 | BE37: 27.46 | BF37: 0.12 | BG37: 0 | BH37: 72 | BI37: 158.48 | BJ37: 0 | BK37: 18 | BL37: 0 | BM37: 0 | BN37: 4.54 | BO37: 5.5 | BP37: 4.23 | BQ37: 0 | BR37: 0 | BS37: 0 | BT37: 0 | BU37: 0 | BV37: 0 | BW37: 0 | BX37: 0 | BY37: 0 | BZ37: 0 | CA37: 10.6 | CB37: RSCP | CC37: BHZP | CD37: 389.4 | CE37: 0 | CF37: 0 | CG37: 0 | CH37: 0 | CI37: 0 | CJ37: 0 | CK37: 0 | CN37: 0 | CO37: 0 | CP37: 0 | CQ37: 0 | CR37: 0 | CS37: 0 | CT37: 0 | CU37: 45.76 | CV37: FATURA: 12323 | CW37: 45.76 | CX37: 012323 | CY37: 15 | CZ37: MAPA: 162 | DA37: 0 | DE37: 0 | DF37: A. | DG37: SC | DH37: JOINVILLE | DI37: 252895738 | DJ37: (47 ) 32052727 | DK37: 0 | DL37: JOI | DM37: 27.46
A38: 2 | B38: JOI025602-1 | C38: NORMAL | D38: JOIR | E38: JOI | F38: 46246 | G38: MMM1H28 | H38: 42260803098929000789570010000254281003707196 | I38: 61105060000163 | J38: BRASCOLA LTDA - | K38: RUA DONA FRANCISCA 8300 BLOCO D | L38: ZONA INDUSTRIAL | M38: 892 | N38: JOINVILLE | O38: SC | P38: 89219-600 | Q38: 61105060000163 | R38: BRASCOLA LTDA - | S38: JOINVILLE | T38: SC | U38: 61105060000163 | V38: BRASCOLA LTDA - | W38: RUA DONA FRANCISCA 8300 BLOCO D | X38: ZONA INDUSTRIAL | Y38: JOINVILLE | Z38: SC | AA38: (47 ) 32052727 | AC38: 43943637000124 | AD38: FERNANDES E ANDRADE LTDA | AE38: 352 | AF38: GRFI | AG38: CONSELHEIRO PENA | AH38: MG | AI38: 43943637000124 | AJ38: FERNANDES E ANDRADE LTDA | AK38: CONSELHEIRO PENA | AL38: MG | AM38: GRF | AN38: 000330841 | AO38: 90.28 | AP38: 0.0001 | AQ38: 20 | AR38: 0 | AS38: CP | AT38: LIQUIDADO | AU38: 46269 | AV38: 268.39 | AW38: 001-DIVERSOS | AX38: 001-DIVERSOS | AY38: 2891.44 | AZ38: COMBINADA | BA38: CO3809065 | BB38: 268.39 | BC38: 236.18 | BD38: 268.39 | BE38: 32.21 | BF38: 0.12 | BG38: 0 | BH38: 90.28 | BI38: 193.99 | BJ38: 0 | BK38: 18 | BL38: 0 | BM38: 0 | BN38: 4.34 | BO38: 5.5 | BP38: 4.23 | BQ38: 0 | BR38: 0 | BS38: 0 | BT38: 0 | BU38: 0 | BV38: 0 | BW38: 0 | BX38: 0 | BY38: 0 | BZ38: 0 | CA38: 10.12 | CB38: RSCP | CC38: LTOI | CD38: 387.57 | CE38: 0 | CF38: 0 | CG38: 0 | CH38: 0 | CI38: 0 | CJ38: 0 | CK38: 0 | CN38: 0 | CO38: 0 | CP38: 0 | CQ38: 0 | CR38: 0 | CS38: 0 | CT38: 0 | CU38: 53.68 | CV38: FATURA: 12346 | CW38: 53.68 | CX38: 012346 | CY38: 123.78 | CZ38: FATURA: 130688 | DA38: 138.93 | DB38: 130688 | DE38: 0 | DF38: A. | DG38: SC | DH38: JOINVILLE | DI38: 252895738 | DJ38: (47 ) 32052727 | DK38: 0 | DL38: JOI | DM38: 32.21
A39: 2 | B39: JOI025603-0 | C39: NORMAL | D39: JOIR | E39: JOI | F39: 46246 | G39: MMM1H28 | H39: 42260803098929000789570010000254291003707207 | I39: 61105060000163 | J39: BRASCOLA LTDA - | K39: RUA DONA FRANCISCA 8300 BLOCO D | L39: ZONA INDUSTRIAL | M39: 892 | N39: JOINVILLE | O39: SC | P39: 89219-600 | Q39: 61105060000163 | R39: BRASCOLA LTDA - | S39: JOINVILLE | T39: SC | U39: 61105060000163 | V39: BRASCOLA LTDA - | W39: RUA DONA FRANCISCA 8300 BLOCO D | X39: ZONA INDUSTRIAL | Y39: JOINVILLE | Z39: SC | AA39: (47 ) 32052727 | AC39: 40193950000102 | AD39: 40.193.950 BRENO DE ARAUJO LIMA | AE39: 002 BELO HORIZONTE | AF39: BHZP | AG39: BELO HORIZONTE | AH39: MG | AI39: 40193950000102 | AJ39: 40.193.950 BRENO DE ARAUJO LIMA | AK39: BELO HORIZONTE | AL39: MG | AM39: BHZ | AN39: 000330818 | AO39: 4.5 | AP39: 0.0001 | AQ39: 1 | AR39: 0 | AS39: CP | AT39: LIQUIDADO | AU39: 46269 | AV39: 128.5 | AW39: 001-DIVERSOS | AX39: 001-DIVERSOS | AY39: 165.44 | AZ39: COMBINADA | BA39: CO3809017 | BB39: 128.5 | BC39: 113.08 | BD39: 128.5 | BE39: 15.42 | BF39: 0.12 | BG39: 0 | BH39: 4.5 | BI39: 81.52 | BJ39: 0 | BK39: 18 | BL39: 0 | BM39: 0 | BN39: 3.25 | BO39: 5.5 | BP39: 4.23 | BQ39: 0 | BR39: 0 | BS39: 0 | BT39: 0 | BU39: 0 | BV39: 0 | BW39: 0 | BX39: 0 | BY39: 0 | BZ39: 0 | CA39: 0.58 | CB39: RSCP | CC39: BHZP | CD39: 359.64 | CE39: 0 | CF39: 0 | CG39: 0 | CH39: 0 | CI39: 0 | CJ39: 0 | CK39: 0 | CN39: 0 | CO39: 0 | CP39: 0 | CQ39: 0 | CR39: 0 | CS39: 0 | CT39: 0 | CU39: 25.7 | CV39: FATURA: 12346 | CW39: 25.7 | CX39: 012346 | CY39: 15 | CZ39: MAPA: 162 | DA39: 0 | DE39: 0 | DF39: A. | DG39: SC | DH39: JOINVILLE | DI39: 252895738 | DJ39: (47 ) 32052727 | DK39: 0 | DL39: JOI | DM39: 15.42
A40: 2 | B40: JOI025645-5 | C40: CORTESIA | D40: JOIP | E40: JOI | F40: 46247 | G40: ARMAZEM | H40: 42260803098929000789570010000254711003714711 | I40: 61105060000163 | J40: BRASCOLA LTDA - | K40: RUA DONA FRANCISCA 8300 BLOCO D | L40: ZONA INDUSTRIAL | M40: 892 | N40: JOINVILLE | O40: SC | P40: 89219-600 | Q40: 61105060000163 | R40: BRASCOLA LTDA - | S40: JOINVILLE | T40: SC | U40: 61105060000163 | V40: BRASCOLA LTDA - | W40: RUA DONA FRANCISCA 8300 BLOCO D | X40: ZONA INDUSTRIAL | Y40: JOINVILLE | Z40: SC | AA40: (47 ) 32052727 | AC40: 55511582000162 | AD40: CONSTRUFACIL LTDA | AE40: 352 | AF40: GRFP | AG40: DIVINO DAS LARANJEIRAS | AH40: MG | AI40: 55511582000162 | AJ40: CONSTRUFACIL LTDA | AK40: DIVINO DAS LARANJEIRAS | AL40: MG | AM40: GRF | AN40: 000329459 | AO40: 5 | AP40: 0 | AQ40: 1 | AR40: 0 | AS40: CP | AT40: LIQUIDADO | AU40: 46247 | AV40: 0 | AW40: 001-DIVERSOS | AX40: 001-DIVERSOS | AY40: 0.01 | AZ40: INFORMADO | BB40: 0.01 | BC40: 0.01 | BD40: 0.01 | BE40: 0 | BF40: 0.12 | BG40: 0 | BH40: 5 | BI40: 0.01 | BJ40: 0 | BK40: 0 | BL40: 0 | BM40: 0 | BN40: 0 | BO40: 0 | BP40: 0 | BQ40: 0 | BR40: 0 | BS40: 0 | BT40: 0 | BU40: 0 | BV40: 0 | BW40: 0 | BX40: 0 | BY40: 0 | BZ40: 0 | CA40: 0 | CB40: RSCP | CC40: GRFP | CD40: 0.01 | CE40: 0 | CF40: 0 | CG40: 0 | CH40: 0 | CI40: 0 | CJ40: 0 | CK40: 0 | CN40: 0 | CO40: 0 | CP40: 0 | CQ40: 0 | CR40: 0 | CS40: 0 | CT40: 0 | CU40: 0.01 | CV40: MAPA: 0 | CW40: =CU40 -> 0.01 | CY40: 0.01 | CZ40: FATURA: 12346 | DA40: 20 | DB40: 012346 | DE40: 0 | DF40: A. | DG40: SC | DH40: JOINVILLE | DI40: 252895738 | DJ40: (47 ) 32052727 | DK40: 0 | DL40: JOI | DM40: 0
A41: 2 | B41: JOI025657-9 | C41: NORMAL | D41: JOIR | E41: JOI | F41: 46247 | G41: MMM1H28 | H41: 42260803098929000789570010000254831003717517 | I41: 61105060000163 | J41: BRASCOLA LTDA - | K41: RUA DONA FRANCISCA 8300 BLOCO D | L41: ZONA INDUSTRIAL | M41: 892 | N41: JOINVILLE | O41: SC | P41: 89219-600 | Q41: 61105060000163 | R41: BRASCOLA LTDA - | S41: JOINVILLE | T41: SC | U41: 61105060000163 | V41: BRASCOLA LTDA - | W41: RUA DONA FRANCISCA 8300 BLOCO D | X41: ZONA INDUSTRIAL | Y41: JOINVILLE | Z41: SC | AA41: (47 ) 32052727 | AC41: 00543999000204 | AD41: ALBINO DECORACOES EIRELI | AE41: 350 | AF41: GVRP | AG41: GOVERNADOR VALADARES | AH41: MG | AI41: 00543999000204 | AJ41: ALBINO DECORACOES EIRELI | AK41: GOVERNADOR VALADARES | AL41: MG | AM41: GVR | AN41: 000330958 | AO41: 90 | AP41: 0.0001 | AQ41: 6 | AR41: 0 | AS41: CP | AT41: LIQUIDADO | AU41: 46269 | AV41: 582.7 | AW41: 001-DIVERSOS | AX41: 001-DIVERSOS | AY41: 2212.44 | AZ41: COMBINADA | BA41: CO3809055 | BB41: 582.7 | BC41: 512.78 | BD41: 582.7 | BE41: 69.92 | BF41: 0.12 | BG41: 0 | BH41: 90 | BI41: 193.99 | BJ41: 0 | BK41: 18 | BL41: 0 | BM41: 0 | BN41: 3.32 | BO41: 5.5 | BP41: 4.23 | BQ41: 0 | BR41: 0 | BS41: 0 | BT41: 0 | BU41: 0 | BV41: 0 | BW41: 0 | BX41: 280 | BY41: 0 | BZ41: 0 | CA41: 7.74 | CB41: RSCP | CC41: RWNI | CD41: 391.84 | CE41: 0 | CF41: 0 | CG41: 0 | CH41: 0 | CI41: 0 | CJ41: 0 | CK41: 0 | CN41: 0 | CO41: 0 | CP41: 0 | CQ41: 0 | CR41: 0 | CS41: 0 | CT41: 0 | CU41: 116.54 | CV41: FATURA: 12346 | CW41: 116.54 | CX41: 012346 | CY41: 508.45 | CZ41: FATURA: 12262 | DA41: 508.45 | DB41: 012262 | DE41: 0 | DF41: A. | DG41: SC | DH41: JOINVILLE | DI41: 252895738 | DJ41: (47 ) 32052727 | DK41: 0 | DL41: JOI | DM41: 69.92
A42: 2 | B42: JOI025738-9 | C42: NORMAL | D42: JOIR | E42: JOI | F42: 46251 | G42: MMM1H28 | H42: 42260803098929000789570010000255661003730844 | I42: 61105060000163 | J42: BRASCOLA LTDA - | K42: RUA DONA FRANCISCA 8300 BLOCO D | L42: ZONA INDUSTRIAL | M42: 892 | N42: JOINVILLE | O42: SC | P42: 89219-600 | Q42: 61105060000163 | R42: BRASCOLA LTDA - | S42: JOINVILLE | T42: SC | U42: 61105060000163 | V42: BRASCOLA LTDA - | W42: RUA DONA FRANCISCA 8300 BLOCO D | X42: ZONA INDUSTRIAL | Y42: JOINVILLE | Z42: SC | AA42: (47 ) 32052727 | AC42: 59541591000157 | AD42: COMERCIAL BARBOSA E-COMMERCE LTDA | AE42: 6 ROTA POCOS DE CALDAS | AF42: DCCR | AG42: POCOS DE CALDAS | AH42: MG | AI42: 59541591000157 | AJ42: COMERCIAL BARBOSA E-COMMERCE LTDA | AK42: POCOS DE CALDAS | AL42: MG | AM42: DCC | AN42: 000331060 | AO42: 207.77 | AP42: 0.0001 | AQ42: 1 | AR42: 0 | AS42: CP | AT42: LIQUIDADO | AU42: 46276 | AV42: 437.1 | AW42: 001-DIVERSOS | AX42: 001-DIVERSOS | AY42: 5891.09 | AZ42: COMBINADA | BA42: CO3809036 | BB42: 437.1 | BC42: 384.65 | BD42: 437.1 | BE42: 52.45 | BF42: 0.12 | BG42: 0 | BH42: 207.77 | BI42: 316.46 | BJ42: 0 | BK42: 18 | BL42: 0 | BM42: 0 | BN42: 8.84 | BO42: 16.5 | BP42: 4.23 | BQ42: 0 | BR42: 0 | BS42: 0 | BT42: 0 | BU42: 0 | BV42: 0 | BW42: 0 | BX42: 0 | BY42: 0 | BZ42: 0 | CA42: 20.62 | CB42: RSCP | CC42: ALTR | CD42: 472.39 | CE42: 0 | CF42: 0 | CG42: 0 | CH42: 0 | CI42: 0 | CJ42: 0 | CK42: 0 | CN42: 0 | CO42: 0 | CP42: 0 | CQ42: 0 | CR42: 0 | CS42: 0 | CT42: 0 | CU42: 87.42 | CV42: FATURA: 12346 | CW42: 87.42 | CX42: 012346 | CY42: 152.99 | CZ42: FATURA: 149 | DA42: 152.99 | DB42: 000149 | DE42: 0 | DF42: A. | DG42: SC | DH42: JOINVILLE | DI42: 252895738 | DJ42: (47 ) 32052727 | DK42: 0 | DL42: JOI | DM42: 52.45
A43: 2 | B43: JOI025739-7 | C43: NORMAL | D43: JOIR | E43: JOI | F43: 46251 | G43: MMM1H28 | H43: 42260803098929000789570010000255671003730850 | I43: 61105060000163 | J43: BRASCOLA LTDA - | K43: RUA DONA FRANCISCA 8300 BLOCO D | L43: ZONA INDUSTRIAL | M43: 892 | N43: JOINVILLE | O43: SC | P43: 89219-600 | Q43: 61105060000163 | R43: BRASCOLA LTDA - | S43: JOINVILLE | T43: SC | U43: 61105060000163 | V43: BRASCOLA LTDA - | W43: RUA DONA FRANCISCA 8300 BLOCO D | X43: ZONA INDUSTRIAL | Y43: JOINVILLE | Z43: SC | AA43: (47 ) 32052727 | AC43: 08678892000196 | AD43: CONSTRUMAIA S/A | AE43: 394 | AF43: VEAI | AG43: MONTES CLAROS | AH43: MG | AI43: 08678892000196 | AJ43: CONSTRUMAIA S/A | AK43: MONTES CLAROS | AL43: MG | AM43: VEA | AN43: 000331042 | AO43: 64.202 | AP43: 0.0001 | AQ43: 18 | AR43: 0 | AS43: CP | AT43: LIQUIDADO | AU43: 46276 | AV43: 249.74 | AW43: 001-DIVERSOS | AX43: 001-DIVERSOS | AY43: 2053.74 | AZ43: COMBINADA | BA43: CO3809060 | BB43: 249.74 | BC43: 219.77 | BD43: 249.74 | BE43: 29.97 | BF43: 0.12 | BG43: 0 | BH43: 64.202 | BI43: 181.6 | BJ43: 0 | BK43: 18 | BL43: 0 | BM43: 0 | BN43: 3.25 | BO43: 5.5 | BP43: 4.23 | BQ43: 0 | BR43: 0 | BS43: 0 | BT43: 0 | BU43: 0 | BV43: 0 | BW43: 0 | BX43: 0 | BY43: 0 | BZ43: 0 | CA43: 7.19 | CB43: RSCP | CC43: VEAI | CD43: 389.55 | CE43: 0 | CF43: 0 | CG43: 0 | CH43: 0 | CI43: 0 | CJ43: 0 | CK43: 0 | CN43: 0 | CO43: 0 | CP43: 0 | CQ43: 0 | CR43: 0 | CS43: 0 | CT43: 0 | CU43: 49.95 | CV43: FATURA: 12346 | CW43: 49.95 | CX43: 012346 | CY43: 74.92 | CZ43: MAPA: 0 | DA43: =CY43 -> 74.92 | DE43: 0 | DF43: A. | DG43: SC | DH43: JOINVILLE | DI43: 252895738 | DJ43: (47 ) 32052727 | DK43: 0 | DL43: JOI | DM43: 29.97
A44: 2 | B44: JOI025740-1 | C44: NORMAL | D44: JOIR | E44: JOI | F44: 46251 | G44: MMM1H28 | H44: 42260803098929000789570010000255681003730865 | I44: 61105060000163 | J44: BRASCOLA LTDA - | K44: RUA DONA FRANCISCA 8300 BLOCO D | L44: ZONA INDUSTRIAL | M44: 892 | N44: JOINVILLE | O44: SC | P44: 89219-600 | Q44: 61105060000163 | R44: BRASCOLA LTDA - | S44: JOINVILLE | T44: SC | U44: 61105060000163 | V44: BRASCOLA LTDA - | W44: RUA DONA FRANCISCA 8300 BLOCO D | X44: ZONA INDUSTRIAL | Y44: JOINVILLE | Z44: SC | AA44: (47 ) 32052727 | AC44: 02631261000135 | AD44: MADEIREIRA SANTA LUZIA LTDA EPP | AE44: 350 | AF44: GVRP | AG44: GOVERNADOR VALADARES | AH44: MG | AI44: 02631261000135 | AJ44: MADEIREIRA SANTA LUZIA LTDA EPP | AK44: GOVERNADOR VALADARES | AL44: MG | AM44: GVR | AN44: 000331000 | AO44: 78.454 | AP44: 0.0001 | AQ44: 21 | AR44: 0 | AS44: CP | AT44: LIQUIDADO | AU44: 46276 | AV44: 264.83 | AW44: 001-DIVERSOS | AX44: 001-DIVERSOS | AY44: 2266.61 | AZ44: COMBINADA | BA44: CO3809055 | BB44: 264.83 | BC44: 233.05 | BD44: 264.83 | BE44: 31.78 | BF44: 0.12 | BG44: 0 | BH44: 78.454 | BI44: 193.99 | BJ44: 0 | BK44: 18 | BL44: 0 | BM44: 0 | BN44: 3.4 | BO44: 5.5 | BP44: 4.23 | BQ44: 0 | BR44: 0 | BS44: 0 | BT44: 0 | BU44: 0 | BV44: 0 | BW44: 0 | BX44: 0 | BY44: 0 | BZ44: 0 | CA44: 7.93 | CB44: RSCP | CC44: RWNI | CD44: 392.63 | CE44: 0 | CF44: 0 | CG44: 0 | CH44: 0 | CI44: 0 | CJ44: 0 | CK44: 0 | CN44: 0 | CO44: 0 | CP44: 0 | CQ44: 0 | CR44: 0 | CS44: 0 | CT44: 0 | CU44: 52.97 | CV44: FATURA: 12346 | CW44: 52.97 | CX44: 012346 | CY44: 97.19 | CZ44: FATURA: 12262 | DA44: 97.19 | DB44: 012262 | DE44: 0 | DF44: A. | DG44: SC | DH44: JOINVILLE | DI44: 252895738 | DJ44: (47 ) 32052727 | DK44: 0 | DL44: JOI | DM44: 31.78
A45: 2 | B45: JOI025741-9 | C45: NORMAL | D45: JOIR | E45: JOI | F45: 46251 | G45: MMM1H28 | H45: 42260803098929000789570010000255691003730870 | I45: 61105060000163 | J45: BRASCOLA LTDA - | K45: RUA DONA FRANCISCA 8300 BLOCO D | L45: ZONA INDUSTRIAL | M45: 892 | N45: JOINVILLE | O45: SC | P45: 89219-600 | Q45: 61105060000163 | R45: BRASCOLA LTDA - | S45: JOINVILLE | T45: SC | U45: 61105060000163 | V45: BRASCOLA LTDA - | W45: RUA DONA FRANCISCA 8300 BLOCO D | X45: ZONA INDUSTRIAL | Y45: JOINVILLE | Z45: SC | AA45: (47 ) 32052727 | AC45: 32236320000131 | AD45: NTC COOLING INDUSTRIAL EIRELI | AE45: 014 VESPASIANO | AF45: BHZP | AG45: VESPASIANO | AH45: MG | AI45: 32236320000131 | AJ45: NTC COOLING INDUSTRIAL EIRELI | AK45: VESPASIANO | AL45: MG | AM45: BHZ | AN45: 000331020 | AO45: 126.4 | AP45: 0.0001 | AQ45: 40 | AR45: 0 | AS45: CP | AT45: LIQUIDADO | AU45: 46276 | AV45: 265.92 | AW45: 001-DIVERSOS | AX45: 001-DIVERSOS | AY45: 2106.3 | AZ45: COMBINADA | BA45: CO3809017 | BB45: 265.92 | BC45: 234.01 | BD45: 265.92 | BE45: 31.91 | BF45: 0.12 | BG45: 0 | BH45: 126.4 | BI45: 190.16 | BJ45: 0 | BK45: 18 | BL45: 0 | BM45: 0 | BN45: 3.25 | BO45: 11 | BP45: 4.23 | BQ45: 0 | BR45: 0 | BS45: 0 | BT45: 0 | BU45: 0 | BV45: 0 | BW45: 0 | BX45: 0 | BY45: 0 | BZ45: 0 | CA45: 7.37 | CB45: RSCP | CC45: BHZP | CD45: 390.31 | CE45: 0 | CF45: 0 | CG45: 0 | CH45: 0 | CI45: 0 | CJ45: 0 | CK45: 0 | CN45: 0 | CO45: 0 | CP45: 0 | CQ45: 0 | CR45: 0 | CS45: 0 | CT45: 0 | CU45: 53.18 | CV45: FATURA: 12346 | CW45: 53.18 | CX45: 012346 | CY45: 17.7 | CZ45: MAPA: 162 | DA45: 0 | DE45: 0 | DF45: A. | DG45: SC | DH45: JOINVILLE | DI45: 252895738 | DJ45: (47 ) 32052727 | DK45: 0 | DL45: JOI | DM45: 31.91
A46: 2 | B46: JOI025864-4 | C46: NORMAL | D46: JOIR | E46: JOI | F46: 46253 | G46: MMM1H28 | H46: 42260803098929000789570010000256891003747216 | I46: 61105060000163 | J46: BRASCOLA LTDA - | K46: RUA DONA FRANCISCA 8300 BLOCO D | L46: ZONA INDUSTRIAL | M46: 892 | N46: JOINVILLE | O46: SC | P46: 89219-600 | Q46: 61105060000163 | R46: BRASCOLA LTDA - | S46: JOINVILLE | T46: SC | U46: 61105060000163 | V46: BRASCOLA LTDA - | W46: RUA DONA FRANCISCA 8300 BLOCO D | X46: ZONA INDUSTRIAL | Y46: JOINVILLE | Z46: SC | AA46: (47 ) 32052727 | AC46: 18309666000272 | AD46: PAPI TEXTIL LTDA | AE46: 367 | AF46: TAMI | AG46: MIRAI | AH46: MG | AI46: 18309666000272 | AJ46: PAPI TEXTIL LTDA | AK46: MIRAI | AL46: MG | AM46: TAM | AN46: 000331196 | AO46: 51.888 | AP46: 0.0001 | AQ46: 24 | AR46: 0 | AS46: CP | AT46: LIQUIDADO | AU46: 46276 | AV46: 254.52 | AW46: 001-DIVERSOS | AX46: 001-DIVERSOS | AY46: 6233.01 | AZ46: COMBINADA | BA46: CO3809041 | BB46: 254.52 | BC46: 223.98 | BD46: 254.52 | BE46: 30.54 | BF46: 0.12 | BG46: 0 | BH46: 51.888 | BI46: 165.08 | BJ46: 0 | BK46: 18 | BL46: 0 | BM46: 0 | BN46: 9.35 | BO46: 5.5 | BP46: 4.23 | BQ46: 0 | BR46: 0 | BS46: 0 | BT46: 0 | BU46: 0 | BV46: 0 | BW46: 0 | BX46: 0 | BY46: 0 | BZ46: 0 | CA46: 21.82 | CB46: RSCP | CC46: TAMI | CD46: 450.16 | CE46: 0 | CF46: 0 | CG46: 0 | CH46: 0 | CI46: 0 | CJ46: 0 | CK46: 0 | CN46: 0 | CO46: 0 | CP46: 0 | CQ46: 0 | CR46: 0 | CS46: 0 | CT46: 0 | CU46: 50.9 | CV46: FATURA: 12346 | CW46: 50.9 | CX46: 012346 | CY46: 42 | CZ46: FATURA: 21744 | DA46: 42 | DB46: 021744 | DE46: 0 | DF46: A. | DG46: SC | DH46: JOINVILLE | DI46: 252895738 | DJ46: (47 ) 32052727 | DK46: 0 | DL46: JOI | DM46: 30.54
A47: 2 | B47: JOI025865-2 | C47: NORMAL | D47: JOIR | E47: JOI | F47: 46253 | G47: MMM1H28 | H47: 42260803098929000789570010000256901003747225 | I47: 61105060000163 | J47: BRASCOLA LTDA - | K47: RUA DONA FRANCISCA 8300 BLOCO D | L47: ZONA INDUSTRIAL | M47: 892 | N47: JOINVILLE | O47: SC | P47: 89219-600 | Q47: 61105060000163 | R47: BRASCOLA LTDA - | S47: JOINVILLE | T47: SC | U47: 61105060000163 | V47: BRASCOLA LTDA - | W47: RUA DONA FRANCISCA 8300 BLOCO D | X47: ZONA INDUSTRIAL | Y47: JOINVILLE | Z47: SC | AA47: (47 ) 32052727 | AC47: 03158506000111 | AD47: CONSTRUMAC CONSTRUCAO E VAREJO LTDA EPP | AE47: 386 | AF47: STJP | AG47: URUCUIA | AH47: MG | AI47: 03158506000111 | AJ47: CONSTRUMAC CONSTRUCAO E VAREJO LTDA EPP | AK47: URUCUIA | AL47: MG | AM47: STJ | AN47: 000331180 | AO47: 79.274 | AP47: 0.0001 | AQ47: 18 | AR47: 0 | AS47: CP | AT47: LIQUIDADO | AU47: 46276 | AV47: 321.66 | AW47: 001-DIVERSOS | AX47: 001-DIVERSOS | AY47: 2269.38 | AZ47: COMBINADA | BA47: CO3809048 | BB47: 321.66 | BC47: 283.06 | BD47: 321.66 | BE47: 38.6 | BF47: 0.12 | BG47: 0 | BH47: 79.274 | BI47: 193.99 | BJ47: 0 | BK47: 18 | BL47: 0 | BM47: 0 | BN47: 3.4 | BO47: 5.5 | BP47: 4.23 | BQ47: 50 | BR47: 0 | BS47: 0 | BT47: 0 | BU47: 0 | BV47: 0 | BW47: 0 | BX47: 0 | BY47: 0 | BZ47: 0 | CA47: 7.94 | CB47: RSCP | CC47: PANI | CD47: 392.65 | CE47: 0 | CF47: 0 | CG47: 0 | CH47: 0 | CI47: 0 | CJ47: 0 | CK47: 0 | CN47: 0 | CO47: 0 | CP47: 0 | CQ47: 0 | CR47: 0 | CS47: 0 | CT47: 0 | CU47: 64.33 | CV47: FATURA: 12346 | CW47: 64.33 | CX47: 012346 | CY47: 51 | CZ47: FATURA: 64647 | DA47: 96 | DB47: 064647 | DE47: 0 | DF47: A. | DG47: SC | DH47: JOINVILLE | DI47: 252895738 | DJ47: (47 ) 32052727 | DK47: 0 | DL47: JOI | DM47: 38.6
A48: 2 | B48: JOI025866-1 | C48: CARGA FECHADA | D48: JOIR | E48: JOI | F48: 46253 | G48: MMM1H28 | H48: 42260803098929000789570010000256911003747230 | I48: 61105060000163 | J48: BRASCOLA LTDA - | K48: RUA DONA FRANCISCA 8300 BLOCO D | L48: ZONA INDUSTRIAL | M48: 892 | N48: JOINVILLE | O48: SC | P48: 89219-600 | Q48: 61105060000163 | R48: BRASCOLA LTDA - | S48: JOINVILLE | T48: SC | U48: 61105060000163 | V48: BRASCOLA LTDA - | W48: RUA DONA FRANCISCA 8300 BLOCO D | X48: ZONA INDUSTRIAL | Y48: JOINVILLE | Z48: SC | AA48: (47 ) 32052727 | AC48: 23797376000174 | AD48: BARTOFIL DISTRIBUIDORA SA | AE48: 354 | AF48: FECI | AG48: PONTE NOVA | AH48: MG | AI48: 23797376000174 | AJ48: BARTOFIL DISTRIBUIDORA SA | AK48: PONTE NOVA | AL48: MG | AM48: FEC | AN48: 000331080 | AO48: 3982.8 | AP48: 0.0001 | AQ48: 8 | AR48: 0 | AS48: CP | AT48: LIQUIDADO | AU48: 46276 | AV48: 6998.14 | AW48: 001-DIVERSOS | AX48: 001-DIVERSOS | AY48: 82426.88 | AZ48: COMBINADA | BA48: CO3809041 | BB48: 6998.14 | BC48: 6158.36 | BD48: 6998.14 | BE48: 839.78 | BF48: 0.12 | BG48: 0 | BH48: 3982.8 | BI48: 5224 | BJ48: 0 | BK48: 18 | BL48: 0 | BM48: 0 | BN48: 123.64 | BO48: 220 | BP48: 4.23 | BQ48: 0 | BR48: 0 | BS48: 0 | BT48: 0 | BU48: 0 | BV48: 0 | BW48: 0 | BX48: 280 | BY48: 0 | BZ48: 0 | CA48: 288.49 | CB48: RSCP | CC48: TAMI | CD48: 14795.22 | CE48: 0 | CF48: 0 | CG48: 0 | CH48: 0 | CI48: 0 | CJ48: 0 | CK48: 0 | CN48: 0 | CO48: 0 | CP48: 0 | CQ48: 0 | CR48: 0 | CS48: 0 | CT48: 0 | CU48: 1399.63 | CV48: FATURA: 12346 | CW48: 1399.63 | CX48: 012346 | CY48: 0 | DA48: 0 | DE48: 0 | DF48: A. | DG48: SC | DH48: JOINVILLE | DI48: 252895738 | DJ48: (47 ) 32052727 | DK48: 0 | DL48: JOI | DM48: 839.78
A49: 2 | B49: JOI025867-9 | C49: NORMAL | D49: JOIR | E49: JOI | F49: 46253 | G49: MMM1H28 | H49: 42260803098929000789570010000256921003747246 | I49: 61105060000163 | J49: BRASCOLA LTDA - | K49: RUA DONA FRANCISCA 8300 BLOCO D | L49: ZONA INDUSTRIAL | M49: 892 | N49: JOINVILLE | O49: SC | P49: 89219-600 | Q49: 61105060000163 | R49: BRASCOLA LTDA - | S49: JOINVILLE | T49: SC | U49: 61105060000163 | V49: BRASCOLA LTDA - | W49: RUA DONA FRANCISCA 8300 BLOCO D | X49: ZONA INDUSTRIAL | Y49: JOINVILLE | Z49: SC | AA49: (47 ) 32052727 | AC49: 28837625000121 | AD49: LORRAYNE OLIVEIRA SILVA 11721084630 | AE49: 383 | AF49: TRUI | AG49: SANTA VITORIA | AH49: MG | AI49: 28837625000121 | AJ49: LORRAYNE OLIVEIRA SILVA 11721084630 | AK49: SANTA VITORIA | AL49: MG | AM49: TRU | AN49: 000331125 | AO49: 65.55 | AP49: 0.0001 | AQ49: 11 | AR49: 0 | AS49: CP | AT49: LIQUIDADO | AU49: 46276 | AV49: 247.84 | AW49: 001-DIVERSOS | AX49: 001-DIVERSOS | AY49: 1577.76 | AZ49: COMBINADA | BA49: CO3809048 | BB49: 247.84 | BC49: 218.1 | BD49: 247.84 | BE49: 29.74 | BF49: 0.12 | BG49: 0 | BH49: 65.55 | BI49: 181.6 | BJ49: 0 | BK49: 18 | BL49: 0 | BM49: 0 | BN49: 3.25 | BO49: 5.5 | BP49: 4.23 | BQ49: 0 | BR49: 0 | BS49: 0 | BT49: 0 | BU49: 0 | BV49: 0 | BW49: 0 | BX49: 0 | BY49: 0 | BZ49: 0 | CA49: 5.52 | CB49: RSCP | CC49: PANI | CD49: 383.53 | CE49: 0 | CF49: 0 | CG49: 0 | CH49: 0 | CI49: 0 | CJ49: 0 | CK49: 0 | CN49: 0 | CO49: 0 | CP49: 0 | CQ49: 0 | CR49: 0 | CS49: 0 | CT49: 0 | CU49: 49.57 | CV49: FATURA: 12346 | CW49: 49.57 | CX49: 012346 | CY49: 111.53 | CZ49: FATURA: 233142 | DA49: 94.66 | DB49: 233142 | DE49: 0 | DF49: A. | DG49: SC | DH49: JOINVILLE | DI49: 252895738 | DJ49: (47 ) 32052727 | DK49: 0 | DL49: JOI | DM49: 29.74
A50: 2 | B50: JOI025868-7 | C50: NORMAL | D50: JOIR | E50: JOI | F50: 46253 | G50: MMM1H28 | H50: 42260803098929000789570010000256931003747251 | I50: 61105060000163 | J50: BRASCOLA LTDA - | K50: RUA DONA FRANCISCA 8300 BLOCO D | L50: ZONA INDUSTRIAL | M50: 892 | N50: JOINVILLE | O50: SC | P50: 89219-600 | Q50: 61105060000163 | R50: BRASCOLA LTDA - | S50: JOINVILLE | T50: SC | U50: 61105060000163 | V50: BRASCOLA LTDA - | W50: RUA DONA FRANCISCA 8300 BLOCO D | X50: ZONA INDUSTRIAL | Y50: JOINVILLE | Z50: SC | AA50: (47 ) 32052727 | AC50: 38705406000142 | AD50: SIER MOVEIS LTDA | AE50: 365 | AF50: TAMR | AG50: UBA | AH50: MG | AI50: 38705406000142 | AJ50: SIER MOVEIS LTDA | AK50: UBA | AL50: MG | AM50: TAM | AN50: 000331201 | AO50: 35.208 | AP50: 0.0001 | AQ50: 9 | AR50: 0 | AS50: CP | AT50: LIQUIDADO | AU50: 46276 | AV50: 204.25 | AW50: 001-DIVERSOS | AX50: 001-DIVERSOS | AY50: 1560.91 | AZ50: COMBINADA | BA50: CO3809042 | BB50: 204.25 | BC50: 179.74 | BD50: 204.25 | BE50: 24.51 | BF50: 0.12 | BG50: 0 | BH50: 35.208 | BI50: 143.3 | BJ50: 0 | BK50: 18 | BL50: 0 | BM50: 0 | BN50: 3.25 | BO50: 5.5 | BP50: 4.23 | BQ50: 0 | BR50: 0 | BS50: 0 | BT50: 0 | BU50: 0 | BV50: 0 | BW50: 0 | BX50: 0 | BY50: 0 | BZ50: 0 | CA50: 5.46 | CB50: RSCP | CC50: TAMR | CD50: 383.35 | CE50: 0 | CF50: 0 | CG50: 0 | CH50: 0 | CI50: 0 | CJ50: 0 | CK50: 0 | CN50: 0 | CO50: 0 | CP50: 0 | CQ50: 0 | CR50: 0 | CS50: 0 | CT50: 0 | CU50: 40.85 | CV50: FATURA: 12346 | CW50: 40.85 | CX50: 012346 | CY50: 40 | CZ50: FATURA: 21744 | DA50: 40 | DB50: 021744 | DE50: 0 | DF50: A. | DG50: SC | DH50: JOINVILLE | DI50: 252895738 | DJ50: (47 ) 32052727 | DK50: 0 | DL50: JOI | DM50: 24.51
A51: 2 | B51: JOI025935-7 | C51: NORMAL | D51: JOIR | E51: JOI | F51: 46254 | G51: MMM1H28 | H51: 42260803098929000789570010000257601003754708 | I51: 61105060000163 | J51: BRASCOLA LTDA - | K51: RUA DONA FRANCISCA 8300 BLOCO D | L51: ZONA INDUSTRIAL | M51: 892 | N51: JOINVILLE | O51: SC | P51: 89219-600 | Q51: 61105060000163 | R51: BRASCOLA LTDA - | S51: JOINVILLE | T51: SC | U51: 61105060000163 | V51: BRASCOLA LTDA - | W51: RUA DONA FRANCISCA 8300 BLOCO D | X51: ZONA INDUSTRIAL | Y51: JOINVILLE | Z51: SC | AA51: (47 ) 32052727 | AC51: 02631261000135 | AD51: MADEIREIRA SANTA LUZIA LTDA EPP | AE51: 350 | AF51: GVRP | AG51: GOVERNADOR VALADARES | AH51: MG | AI51: 02631261000135 | AJ51: MADEIREIRA SANTA LUZIA LTDA EPP | AK51: GOVERNADOR VALADARES | AL51: MG | AM51: GVR | AN51: 000331248 | AO51: 53.712 | AP51: 0.0001 | AQ51: 18 | AR51: 0 | AS51: CP | AT51: LIQUIDADO | AU51: 46276 | AV51: 248.31 | AW51: 001-DIVERSOS | AX51: 001-DIVERSOS | AY51: 1693.81 | AZ51: COMBINADA | BA51: CO3809055 | BB51: 248.31 | BC51: 218.51 | BD51: 248.31 | BE51: 29.8 | BF51: 0.12 | BG51: 0 | BH51: 53.712 | BI51: 181.6 | BJ51: 0 | BK51: 18 | BL51: 0 | BM51: 0 | BN51: 3.25 | BO51: 5.5 | BP51: 4.23 | BQ51: 0 | BR51: 0 | BS51: 0 | BT51: 0 | BU51: 0 | BV51: 0 | BW51: 0 | BX51: 0 | BY51: 0 | BZ51: 0 | CA51: 5.93 | CB51: RSCP | CC51: RWNI | CD51: 384.68 | CE51: 0 | CF51: 0 | CG51: 0 | CH51: 0 | CI51: 0 | CJ51: 0 | CK51: 0 | CN51: 0 | CO51: 0 | CP51: 0 | CQ51: 0 | CR51: 0 | CS51: 0 | CT51: 0 | CU51: 49.66 | CV51: FATURA: 12346 | CW51: 49.66 | CX51: 012346 | CY51: 91.41 | CZ51: FATURA: 12378 | DA51: 91.41 | DB51: 012378 | DE51: 0 | DF51: A. | DG51: SC | DH51: JOINVILLE | DI51: 252895738 | DJ51: (47 ) 32052727 | DK51: 0 | DL51: JOI | DM51: 29.8
A52: 2 | B52: JOI025936-5 | C52: NORMAL | D52: JOIR | E52: JOI | F52: 46254 | G52: MMM1H28 | H52: 42260803098929000789570010000257611003754713 | I52: 61105060000163 | J52: BRASCOLA LTDA - | K52: RUA DONA FRANCISCA 8300 BLOCO D | L52: ZONA INDUSTRIAL | M52: 892 | N52: JOINVILLE | O52: SC | P52: 89219-600 | Q52: 61105060000163 | R52: BRASCOLA LTDA - | S52: JOINVILLE | T52: SC | U52: 61105060000163 | V52: BRASCOLA LTDA - | W52: RUA DONA FRANCISCA 8300 BLOCO D | X52: ZONA INDUSTRIAL | Y52: JOINVILLE | Z52: SC | AA52: (47 ) 32052727 | AC52: 02870124000153 | AD52: LENARGE TRANSPORTES E SERVICOS | AE52: 011 SABARA | AF52: BHZP | AG52: SABARA | AH52: MG | AI52: 02870124000153 | AJ52: LENARGE TRANSPORTES E SERVICOS | AK52: SABARA | AL52: MG | AM52: BHZ | AN52: 000331236 | AO52: 128.5 | AP52: 0.0001 | AQ52: 17 | AR52: 0 | AS52: CP | AT52: LIQUIDADO | AU52: 46276 | AV52: 282.58 | AW52: 001-DIVERSOS | AX52: 001-DIVERSOS | AY52: 4550 | AZ52: COMBINADA | BA52: CO3809017 | BB52: 282.58 | BC52: 248.67 | BD52: 282.58 | BE52: 33.91 | BF52: 0.12 | BG52: 0 | BH52: 128.5 | BI52: 192.68 | BJ52: 0 | BK52: 18 | BL52: 0 | BM52: 0 | BN52: 6.83 | BO52: 11 | BP52: 4.23 | BQ52: 0 | BR52: 0 | BS52: 0 | BT52: 0 | BU52: 0 | BV52: 0 | BW52: 0 | BX52: 0 | BY52: 0 | BZ52: 0 | CA52: 15.93 | CB52: RSCP | CC52: BHZP | CD52: 425.76 | CE52: 0 | CF52: 0 | CG52: 0 | CH52: 0 | CI52: 0 | CJ52: 0 | CK52: 0 | CN52: 0 | CO52: 0 | CP52: 0 | CQ52: 0 | CR52: 0 | CS52: 0 | CT52: 0 | CU52: 56.52 | CV52: FATURA: 12346 | CW52: 56.52 | CX52: 012346 | CY52: 17.99 | CZ52: MAPA: 162 | DA52: 0 | DE52: 0 | DF52: A. | DG52: SC | DH52: JOINVILLE | DI52: 252895738 | DJ52: (47 ) 32052727 | DK52: 0 | DL52: JOI | DM52: 33.91
A53: 2 | B53: JOI025937-3 | C53: NORMAL | D53: JOIR | E53: JOI | F53: 46254 | G53: MMM1H28 | H53: 42260803098929000789570010000257621003754729 | I53: 61105060000163 | J53: BRASCOLA LTDA - | K53: RUA DONA FRANCISCA 8300 BLOCO D | L53: ZONA INDUSTRIAL | M53: 892 | N53: JOINVILLE | O53: SC | P53: 89219-600 | Q53: 61105060000163 | R53: BRASCOLA LTDA - | S53: JOINVILLE | T53: SC | U53: 61105060000163 | V53: BRASCOLA LTDA - | W53: RUA DONA FRANCISCA 8300 BLOCO D | X53: ZONA INDUSTRIAL | Y53: JOINVILLE | Z53: SC | AA53: (47 ) 32052727 | AC53: 71431001000139 | AD53: MAXIBOR CASA DA BORRACHA INDUSTRIA E COMERCIO LTDA | AE53: 013 SARZEDO | AF53: BHZP | AG53: SARZEDO | AH53: MG | AI53: 71431001000139 | AJ53: MAXIBOR CASA DA BORRACHA INDUSTRIA E COMERCIO LTDA | AK53: SARZEDO | AL53: MG | AM53: BHZ | AN53: 000331259 | AO53: 89.1 | AP53: 0.0001 | AQ53: 1 | AR53: 0 | AS53: CP | AT53: LIQUIDADO | AU53: 46276 | AV53: 257.08 | AW53: 001-DIVERSOS | AX53: 001-DIVERSOS | AY53: 8004.18 | AZ53: COMBINADA | BA53: CO3809017 | BB53: 257.08 | BC53: 226.23 | BD53: 257.08 | BE53: 30.85 | BF53: 0.12 | BG53: 0 | BH53: 89.1 | BI53: 158.48 | BJ53: 0 | BK53: 18 | BL53: 0 | BM53: 0 | BN53: 12.01 | BO53: 5.5 | BP53: 4.23 | BQ53: 0 | BR53: 0 | BS53: 0 | BT53: 0 | BU53: 0 | BV53: 0 | BW53: 0 | BX53: 0 | BY53: 0 | BZ53: 0 | CA53: 28.01 | CB53: RSCP | CC53: BHZP | CD53: 475.81 | CE53: 0 | CF53: 0 | CG53: 0 | CH53: 0 | CI53: 0 | CJ53: 0 | CK53: 0 | CN53: 0 | CO53: 0 | CP53: 0 | CQ53: 0 | CR53: 0 | CS53: 0 | CT53: 0 | CU53: 51.42 | CV53: FATURA: 12346 | CW53: 51.42 | CX53: 012346 | CY53: 15 | CZ53: MAPA: 162 | DA53: 0 | DE53: 0 | DF53: A. | DG53: SC | DH53: JOINVILLE | DI53: 252895738 | DJ53: (47 ) 32052727 | DK53: 0 | DL53: JOI | DM53: 30.85
A54: 2 | B54: JOI025942-0 | C54: NORMAL | D54: JOIR | E54: JOI | F54: 46254 | G54: MMM1H28 | H54: 42260803098929000789570010000257671003758941 | I54: 61105060000163 | J54: BRASCOLA LTDA - | K54: RUA DONA FRANCISCA 8300 BLOCO D | L54: ZONA INDUSTRIAL | M54: 892 | N54: JOINVILLE | O54: SC | P54: 89219-600 | Q54: 61105060000163 | R54: BRASCOLA LTDA - | S54: JOINVILLE | T54: SC | U54: 61105060000163 | V54: BRASCOLA LTDA - | W54: RUA DONA FRANCISCA 8300 BLOCO D | X54: ZONA INDUSTRIAL | Y54: JOINVILLE | Z54: SC | AA54: (47 ) 32052727 | AC54: 39741171000107 | AD54: BARBOSA E FILHOS MATERIAIS DE CONSTRUCAO LTDA | AE54: 6 ROTA POCOS DE CALDAS | AF54: DCCR | AG54: POCOS DE CALDAS | AH54: MG | AI54: 39741171000107 | AJ54: BARBOSA E FILHOS MATERIAIS DE CONSTRUCAO LTDA | AK54: POCOS DE CALDAS | AL54: MG | AM54: DCC | AN54: 000331325 | AO54: 428 | AP54: 0.0001 | AQ54: 1 | AR54: 0 | AS54: CP | AT54: LIQUIDADO | AU54: 46276 | AV54: 795.32 | AW54: 001-DIVERSOS | AX54: 001-DIVERSOS | AY54: 9477.87 | AZ54: COMBINADA | BA54: CO3809036 | BB54: 795.32 | BC54: 699.88 | BD54: 795.32 | BE54: 95.44 | BF54: 0.12 | BG54: 0 | BH54: 428 | BI54: 602.76 | BJ54: 0 | BK54: 18 | BL54: 0 | BM54: 0 | BN54: 14.22 | BO54: 27.5 | BP54: 4.23 | BQ54: 0 | BR54: 0 | BS54: 0 | BT54: 0 | BU54: 0 | BV54: 0 | BW54: 0 | BX54: 0 | BY54: 0 | BZ54: 0 | CA54: 33.17 | CB54: RSCP | CC54: ALTR | CD54: 1295.1 | CE54: 0 | CF54: 0 | CG54: 0 | CH54: 0 | CI54: 0 | CJ54: 0 | CK54: 0 | CN54: 0 | CO54: 0 | CP54: 0 | CQ54: 0 | CR54: 0 | CS54: 0 | CT54: 0 | CU54: 159.06 | CV54: MAPA: 0 | CW54: =CU54 -> 159.06 | CY54: 278.36 | CZ54: FATURA: 153 | DA54: 278.36 | DB54: 000153 | DE54: 0 | DF54: A. | DG54: SC | DH54: JOINVILLE | DI54: 252895738 | DJ54: (47 ) 32052727 | DK54: 0 | DL54: JOI | DM54: 95.44
A55: 2 | B55: JOI025943-8 | C55: NORMAL | D55: JOIR | E55: JOI | F55: 46254 | G55: MMM1H28 | H55: 42260803098929000789570010000257681003758957 | I55: 61105060000163 | J55: BRASCOLA LTDA - | K55: RUA DONA FRANCISCA 8300 BLOCO D | L55: ZONA INDUSTRIAL | M55: 892 | N55: JOINVILLE | O55: SC | P55: 89219-600 | Q55: 61105060000163 | R55: BRASCOLA LTDA - | S55: JOINVILLE | T55: SC | U55: 61105060000163 | V55: BRASCOLA LTDA - | W55: RUA DONA FRANCISCA 8300 BLOCO D | X55: ZONA INDUSTRIAL | Y55: JOINVILLE | Z55: SC | AA55: (47 ) 32052727 | AC55: 05568526000196 | AD55: TELECIMENTO ALTERNATIVO LTDA | AE55: 394 | AF55: VEAI | AG55: MONTES CLAROS | AH55: MG | AI55: 05568526000196 | AJ55: TELECIMENTO ALTERNATIVO LTDA | AK55: MONTES CLAROS | AL55: MG | AM55: VEA | AN55: 000331348 | AO55: 68.348 | AP55: 0.0001 | AQ55: 25 | AR55: 0 | AS55: CP | AT55: LIQUIDADO | AU55: 46276 | AV55: 249.84 | AW55: 001-DIVERSOS | AX55: 001-DIVERSOS | AY55: 2080.94 | AZ55: COMBINADA | BA55: CO3809060 | BB55: 249.84 | BC55: 219.86 | BD55: 249.84 | BE55: 29.98 | BF55: 0.12 | BG55: 0 | BH55: 68.348 | BI55: 181.6 | BJ55: 0 | BK55: 18 | BL55: 0 | BM55: 0 | BN55: 3.25 | BO55: 5.5 | BP55: 4.23 | BQ55: 0 | BR55: 0 | BS55: 0 | BT55: 0 | BU55: 0 | BV55: 0 | BW55: 0 | BX55: 0 | BY55: 0 | BZ55: 0 | CA55: 7.28 | CB55: RSCP | CC55: VEAI | CD55: 389.95 | CE55: 0 | CF55: 0 | CG55: 0 | CH55: 0 | CI55: 0 | CJ55: 0 | CK55: 0 | CN55: 0 | CO55: 0 | CP55: 0 | CQ55: 0 | CR55: 0 | CS55: 0 | CT55: 0 | CU55: 49.97 | CV55: MAPA: 0 | CW55: =CU55 -> 49.97 | CY55: 74.95 | CZ55: MAPA: 0 | DA55: =CY55 -> 74.95 | DE55: 0 | DF55: A. | DG55: SC | DH55: JOINVILLE | DI55: 252895738 | DJ55: (47 ) 32052727 | DK55: 0 | DL55: JOI | DM55: 29.98
A56: 2 | B56: JOI025944-6 | C56: NORMAL | D56: JOIR | E56: JOI | F56: 46254 | G56: MMM1H28 | H56: 42260803098929000789570010000257691003758962 | I56: 61105060000163 | J56: BRASCOLA LTDA - | K56: RUA DONA FRANCISCA 8300 BLOCO D | L56: ZONA INDUSTRIAL | M56: 892 | N56: JOINVILLE | O56: SC | P56: 89219-600 | Q56: 61105060000163 | R56: BRASCOLA LTDA - | S56: JOINVILLE | T56: SC | U56: 61105060000163 | V56: BRASCOLA LTDA - | W56: RUA DONA FRANCISCA 8300 BLOCO D | X56: ZONA INDUSTRIAL | Y56: JOINVILLE | Z56: SC | AA56: (47 ) 32052727 | AC56: 65134223000197 | AD56: KENNEDY CONSTRUCOES LTDA | AE56: 373 | AF56: DCCI | AG56: SAO VICENTE DE MINAS | AH56: MG | AI56: 65134223000197 | AJ56: KENNEDY CONSTRUCOES LTDA | AK56: SAO VICENTE DE MINAS | AL56: MG | AM56: DCC | AN56: 000331354 | AO56: 56.44 | AP56: 0.0001 | AQ56: 9 | AR56: 0 | AS56: CP | AT56: LIQUIDADO | AU56: 46276 | AV56: 348.18 | AW56: 001-DIVERSOS | AX56: 001-DIVERSOS | AY56: 1811.61 | AZ56: COMBINADA | BA56: CO3809041 | BB56: 348.18 | BC56: 306.4 | BD56: 348.18 | BE56: 41.78 | BF56: 0.12 | BG56: 0 | BH56: 56.44 | BI56: 165.08 | BJ56: 0 | BK56: 18 | BL56: 0 | BM56: 0 | BN56: 3.25 | BO56: 5.5 | BP56: 4.23 | BQ56: 104 | BR56: 0 | BS56: 0 | BT56: 0 | BU56: 0 | BV56: 0 | BW56: 0 | BX56: 0 | BY56: 0 | BZ56: 0 | CA56: 6.34 | CB56: RSCP | CC56: TAMI | CD56: 386.05 | CE56: 0 | CF56: 0 | CG56: 0 | CH56: 0 | CI56: 0 | CJ56: 0 | CK56: 0 | CN56: 0 | CO56: 0 | CP56: 0 | CQ56: 0 | CR56: 0 | CS56: 0 | CT56: 0 | CU56: 69.64 | CV56: MAPA: 0 | CW56: =CU56 -> 69.64 | CY56: 201.86 | CZ56: FATURA: 153 | DA56: 201.86 | DB56: 000153 | DE56: 0 | DF56: A. | DG56: SC | DH56: JOINVILLE | DI56: 252895738 | DJ56: (47 ) 32052727 | DK56: 0 | DL56: JOI | DM56: 41.78
A57: 2 | B57: JOI025945-4 | C57: NORMAL | D57: JOIR | E57: JOI | F57: 46254 | G57: MMM1H28 | H57: 42260803098929000789570010000257701003758971 | I57: 61105060000163 | J57: BRASCOLA LTDA - | K57: RUA DONA FRANCISCA 8300 BLOCO D | L57: ZONA INDUSTRIAL | M57: 892 | N57: JOINVILLE | O57: SC | P57: 89219-600 | Q57: 61105060000163 | R57: BRASCOLA LTDA - | S57: JOINVILLE | T57: SC | U57: 61105060000163 | V57: BRASCOLA LTDA - | W57: RUA DONA FRANCISCA 8300 BLOCO D | X57: ZONA INDUSTRIAL | Y57: JOINVILLE | Z57: SC | AA57: (47 ) 32052727 | AC57: 01168124000143 | AD57: COSTA E PINHEIRO MATS PARA CONST LTDA | AE57: 386 | AF57: STJP | AG57: BURITIS | AH57: MG | AI57: 01168124000143 | AJ57: COSTA E PINHEIRO MATS PARA CONST LTDA | AK57: BURITIS | AL57: MG | AM57: STJ | AN57: 000331371 | AO57: 165.056 | AP57: 0.0001 | AQ57: 29 | AR57: 0 | AS57: CP | AT57: LIQUIDADO | AU57: 46276 | AV57: 450.63 | AW57: 001-DIVERSOS | AX57: 001-DIVERSOS | AY57: 3048.18 | AZ57: COMBINADA | BA57: CO3809048 | BB57: 450.63 | BC57: 396.55 | BD57: 450.63 | BE57: 54.08 | BF57: 0.12 | BG57: 0 | BH57: 165.056 | BI57: 298.08 | BJ57: 0 | BK57: 18 | BL57: 0 | BM57: 0 | BN57: 4.57 | BO57: 11 | BP57: 4.23 | BQ57: 50 | BR57: 0 | BS57: 0 | BT57: 0 | BU57: 0 | BV57: 0 | BW57: 0 | BX57: 0 | BY57: 0 | BZ57: 0 | CA57: 10.67 | CB57: RSCP | CC57: PANI | CD57: 403.97 | CE57: 0 | CF57: 0 | CG57: 0 | CH57: 0 | CI57: 0 | CJ57: 0 | CK57: 0 | CN57: 0 | CO57: 0 | CP57: 0 | CQ57: 0 | CR57: 0 | CS57: 0 | CT57: 0 | CU57: 90.13 | CV57: MAPA: 0 | CW57: =CU57 -> 90.13 | CY57: 84.18 | CZ57: FATURA: 65166 | DA57: 129.18 | DB57: 065166 | DE57: 0 | DF57: A. | DG57: SC | DH57: JOINVILLE | DI57: 252895738 | DJ57: (47 ) 32052727 | DK57: 0 | DL57: JOI | DM57: 54.08
A58: 2 | B58: JOI026049-5 | C58: NORMAL | D58: JOIR | E58: JOI | F58: 46258 | G58: MMM1H28 | H58: 42260803098929000789570010000258731003773501 | I58: 61105060000163 | J58: BRASCOLA LTDA - | K58: RUA DONA FRANCISCA 8300 BLOCO D | L58: ZONA INDUSTRIAL | M58: 892 | N58: JOINVILLE | O58: SC | P58: 89219-600 | Q58: 61105060000163 | R58: BRASCOLA LTDA - | S58: JOINVILLE | T58: SC | U58: 61105060000163 | V58: BRASCOLA LTDA - | W58: RUA DONA FRANCISCA 8300 BLOCO D | X58: ZONA INDUSTRIAL | Y58: JOINVILLE | Z58: SC | AA58: (47 ) 32052727 | AC58: 01074966000217 | AD58: LIDERCON LTDA ME | AE58: 011 CURVELO | AF58: STJP | AG58: FELIXLANDIA | AH58: MG | AI58: 01074966000217 | AJ58: LIDERCON LTDA ME | AK58: CURVELO | AL58: MG | AM58: STJ | AN58: 000331432 | AO58: 208.756 | AP58: 0.0001 | AQ58: 53 | AR58: 0 | AS58: CP | AT58: LIQUIDADO | AU58: 46283 | AV58: 445.23 | AW58: 001-DIVERSOS | AX58: 001-DIVERSOS | AY58: 7066.5 | AZ58: COMBINADA | BA58: CO3809043 | BB58: 445.23 | BC58: 391.8 | BD58: 445.23 | BE58: 53.43 | BF58: 0.12 | BG58: 0 | BH58: 208.756 | BI58: 317.74 | BJ58: 0 | BK58: 18 | BL58: 0 | BM58: 0 | BN58: 10.6 | BO58: 16.5 | BP58: 4.23 | BQ58: 0 | BR58: 0 | BS58: 0 | BT58: 0 | BU58: 0 | BV58: 0 | BW58: 0 | BX58: 0 | BY58: 0 | BZ58: 0 | CA58: 24.73 | CB58: RSCP | CC58: TCWI | CD58: 492.89 | CE58: 0 | CF58: 0 | CG58: 0 | CH58: 0 | CI58: 0 | CJ58: 0 | CK58: 0 | CN58: 0 | CO58: 0 | CP58: 0 | CQ58: 0 | CR58: 0 | CS58: 0 | CT58: 0 | CU58: 89.05 | CV58: FATURA: 12378 | CW58: 89.05 | CX58: 012378 | CY58: 106.47 | CZ58: FATURA: 65192 | DA58: 106.48 | DB58: 065192 | DE58: 0 | DF58: A. | DG58: SC | DH58: JOINVILLE | DI58: 252895738 | DJ58: (47 ) 32052727 | DK58: 0 | DL58: JOI | DM58: 53.43
A59: 2 | B59: JOI026050-9 | C59: NORMAL | D59: JOIR | E59: JOI | F59: 46258 | G59: MMM1H28 | H59: 42260803098929000789570010000258741003773517 | I59: 61105060000163 | J59: BRASCOLA LTDA - | K59: RUA DONA FRANCISCA 8300 BLOCO D | L59: ZONA INDUSTRIAL | M59: 892 | N59: JOINVILLE | O59: SC | P59: 89219-600 | Q59: 61105060000163 | R59: BRASCOLA LTDA - | S59: JOINVILLE | T59: SC | U59: 61105060000163 | V59: BRASCOLA LTDA - | W59: RUA DONA FRANCISCA 8300 BLOCO D | X59: ZONA INDUSTRIAL | Y59: JOINVILLE | Z59: SC | AA59: (47 ) 32052727 | AC59: 22207856000175 | AD59: FERRAGENS FILGUEIRAS LTDA EPP | AE59: 366 | AF59: TAMR | AG59: BICAS | AH59: MG | AI59: 22207856000175 | AJ59: FERRAGENS FILGUEIRAS LTDA EPP | AK59: BICAS | AL59: MG | AM59: TAM | AN59: 000331422 | AO59: 101.04 | AP59: 0.0001 | AQ59: 18 | AR59: 0 | AS59: CP | AT59: LIQUIDADO | AU59: 46283 | AV59: 260.88 | AW59: 001-DIVERSOS | AX59: 001-DIVERSOS | AY59: 3726.03 | AZ59: COMBINADA | BA59: CO3809042 | BB59: 260.88 | BC59: 229.57 | BD59: 260.88 | BE59: 31.31 | BF59: 0.12 | BG59: 0 | BH59: 101.04 | BI59: 177.71 | BJ59: 0 | BK59: 18 | BL59: 0 | BM59: 0 | BN59: 5.59 | BO59: 11 | BP59: 4.23 | BQ59: 0 | BR59: 0 | BS59: 0 | BT59: 0 | BU59: 0 | BV59: 0 | BW59: 0 | BX59: 0 | BY59: 0 | BZ59: 0 | CA59: 13.04 | CB59: RSCP | CC59: TAMR | CD59: 413.77 | CE59: 0 | CF59: 0 | CG59: 0 | CH59: 0 | CI59: 0 | CJ59: 0 | CK59: 0 | CN59: 0 | CO59: 0 | CP59: 0 | CQ59: 0 | CR59: 0 | CS59: 0 | CT59: 0 | CU59: 52.18 | CV59: FATURA: 12378 | CW59: 52.18 | CX59: 012378 | CY59: 50.52 | CZ59: MAPA: 0 | DA59: 50.52 | DB59: 022026 | DE59: 0 | DF59: A. | DG59: SC | DH59: JOINVILLE | DI59: 252895738 | DJ59: (47 ) 32052727 | DK59: 0 | DL59: JOI | DM59: 31.31
A60: 2 | B60: JOI026099-1 | C60: NORMAL | D60: JOIR | E60: JOI | F60: 46259 | G60: MMM1H28 | H60: 42260803098929000789570010000259231003781079 | I60: 61105060000163 | J60: BRASCOLA LTDA - | K60: RUA DONA FRANCISCA 8300 BLOCO D | L60: ZONA INDUSTRIAL | M60: 892 | N60: JOINVILLE | O60: SC | P60: 89219-600 | Q60: 61105060000163 | R60: BRASCOLA LTDA - | S60: JOINVILLE | T60: SC | U60: 61105060000163 | V60: BRASCOLA LTDA - | W60: RUA DONA FRANCISCA 8300 BLOCO D | X60: ZONA INDUSTRIAL | Y60: JOINVILLE | Z60: SC | AA60: (47 ) 32052727 | AC60: 03893311000115 | AD60: CALCINFER MATERIAIS DE CONSTRUCAO LTDA | AE60: 363 | AF60: TAMR | AG60: SAO JOAO DEL REI | AH60: MG | AI60: 03893311000115 | AJ60: CALCINFER MATERIAIS DE CONSTRUCAO LTDA | AK60: SAO JOAO DEL REI | AL60: MG | AM60: TAM | AN60: 000331497 | AO60: 116.032 | AP60: 0.0001 | AQ60: 24 | AR60: 0 | AS60: CP | AT60: LIQUIDADO | AU60: 46283 | AV60: 279.4 | AW60: 001-DIVERSOS | AX60: 001-DIVERSOS | AY60: 3087.65 | AZ60: COMBINADA | BA60: CO3809042 | BB60: 279.4 | BC60: 245.87 | BD60: 279.4 | BE60: 33.53 | BF60: 0.12 | BG60: 0 | BH60: 116.032 | BI60: 197.2 | BJ60: 0 | BK60: 18 | BL60: 0 | BM60: 0 | BN60: 4.63 | BO60: 11 | BP60: 4.23 | BQ60: 0 | BR60: 0 | BS60: 0 | BT60: 0 | BU60: 0 | BV60: 0 | BW60: 0 | BX60: 0 | BY60: 0 | BZ60: 0 | CA60: 10.81 | CB60: RSCP | CC60: TAMR | CD60: 404.52 | CE60: 0 | CF60: 0 | CG60: 0 | CH60: 0 | CI60: 0 | CJ60: 0 | CK60: 0 | CN60: 0 | CO60: 0 | CP60: 0 | CQ60: 0 | CR60: 0 | CS60: 0 | CT60: 0 | CU60: 55.88 | CV60: FATURA: 12378 | CW60: 55.88 | CX60: 012378 | CY60: 58.02 | CZ60: MAPA: 0 | DA60: 58.02 | DB60: 022026 | DE60: 0 | DF60: A. | DG60: SC | DH60: JOINVILLE | DI60: 252895738 | DJ60: (47 ) 32052727 | DK60: 0 | DL60: JOI | DM60: 33.53
A61: 2 | B61: JOI026100-9 | C61: NORMAL | D61: JOIR | E61: JOI | F61: 46259 | G61: MMM1H28 | H61: 42260803098929000789570010000259241003781084 | I61: 61105060000163 | J61: BRASCOLA LTDA - | K61: RUA DONA FRANCISCA 8300 BLOCO D | L61: ZONA INDUSTRIAL | M61: 892 | N61: JOINVILLE | O61: SC | P61: 89219-600 | Q61: 61105060000163 | R61: BRASCOLA LTDA - | S61: JOINVILLE | T61: SC | U61: 61105060000163 | V61: BRASCOLA LTDA - | W61: RUA DONA FRANCISCA 8300 BLOCO D | X61: ZONA INDUSTRIAL | Y61: JOINVILLE | Z61: SC | AA61: (47 ) 32052727 | AC61: 51023567000114 | AD61: CESARIO TINTAS E PECAS LTDA | AE61: 359 | AF61: EJMP | AG61: JOAO MONLEVADE | AH61: MG | AI61: 51023567000114 | AJ61: CESARIO TINTAS E PECAS LTDA | AK61: JOAO MONLEVADE | AL61: MG | AM61: EJM | AN61: 000331474 | AO61: 374.36 | AP61: 0.0001 | AQ61: 66 | AR61: 0 | AS61: CP | AT61: LIQUIDADO | AU61: 46283 | AV61: 793.39 | AW61: 001-DIVERSOS | AX61: 001-DIVERSOS | AY61: 4196.51 | AZ61: COMBINADA | BA61: CO3809055 | BB61: 793.39 | BC61: 698.18 | BD61: 793.39 | BE61: 95.21 | BF61: 0.12 | BG61: 0 | BH61: 374.36 | BI61: 632.97 | BJ61: 0 | BK61: 18 | BL61: 0 | BM61: 0 | BN61: 6.29 | BO61: 22 | BP61: 4.23 | BQ61: 0 | BR61: 0 | BS61: 0 | BT61: 0 | BU61: 0 | BV61: 0 | BW61: 0 | BX61: 0 | BY61: 0 | BZ61: 0 | CA61: 14.69 | CB61: RSCP | CC61: RWNI | CD61: 1030.91 | CE61: 0 | CF61: 0 | CG61: 0 | CH61: 0 | CI61: 0 | CJ61: 0 | CK61: 0 | CN61: 0 | CO61: 0 | CP61: 0 | CQ61: 0 | CR61: 0 | CS61: 0 | CT61: 0 | CU61: 158.68 | CV61: FATURA: 12378 | CW61: 158.68 | CX61: 012378 | CY61: 317.36 | CZ61: MAPA: 162 | DA61: =CY61 -> 317.36 | DE61: 0 | DF61: A. | DG61: SC | DH61: JOINVILLE | DI61: 252895738 | DJ61: (47 ) 32052727 | DK61: 0 | DL61: JOI | DM61: 95.21
A62: 2 | B62: JOI026101-7 | C62: NORMAL | D62: JOIR | E62: JOI | F62: 46259 | G62: MMM1H28 | H62: 42260803098929000789570010000259251003781090 | I62: 61105060000163 | J62: BRASCOLA LTDA - | K62: RUA DONA FRANCISCA 8300 BLOCO D | L62: ZONA INDUSTRIAL | M62: 892 | N62: JOINVILLE | O62: SC | P62: 89219-600 | Q62: 61105060000163 | R62: BRASCOLA LTDA - | S62: JOINVILLE | T62: SC | U62: 61105060000163 | V62: BRASCOLA LTDA - | W62: RUA DONA FRANCISCA 8300 BLOCO D | X62: ZONA INDUSTRIAL | Y62: JOINVILLE | Z62: SC | AA62: (47 ) 32052727 | AC62: 02235305000108 | AD62: GLOBAL COMPANY INDUSTRIA LTDA | AE62: 5 ROTA EXTREMA | AF62: DCCR | AG62: EXTREMA | AH62: MG | AI62: 02235305000108 | AJ62: GLOBAL COMPANY INDUSTRIA LTDA | AK62: EXTREMA | AL62: MG | AM62: DCC | AN62: 000331465 | AO62: 246 | AP62: 0.0001 | AQ62: 12 | AR62: 0 | AS62: CP | AT62: LIQUIDADO | AU62: 46283 | AV62: 479.19 | AW62: 001-DIVERSOS | AX62: 001-DIVERSOS | AY62: 3360 | AZ62: COMBINADA | BA62: CO3809036 | BB62: 479.19 | BC62: 421.69 | BD62: 479.19 | BE62: 57.5 | BF62: 0.12 | BG62: 0 | BH62: 246 | BI62: 366.16 | BJ62: 0 | BK62: 18 | BL62: 0 | BM62: 0 | BN62: 5.04 | BO62: 16.5 | BP62: 4.23 | BQ62: 0 | BR62: 0 | BS62: 0 | BT62: 0 | BU62: 0 | BV62: 0 | BW62: 0 | BX62: 0 | BY62: 0 | BZ62: 0 | CA62: 11.76 | CB62: RSCP | CC62: ALTR | CD62: 569.45 | CE62: 0 | CF62: 0 | CG62: 0 | CH62: 0 | CI62: 0 | CJ62: 0 | CK62: 0 | CN62: 0 | CO62: 0 | CP62: 0 | CQ62: 0 | CR62: 0 | CS62: 0 | CT62: 0 | CU62: 95.84 | CV62: FATURA: 12378 | CW62: 95.84 | CX62: 012378 | CY62: 167.72 | CZ62: FATURA: 153 | DA62: 167.72 | DB62: 000153 | DE62: 0 | DF62: A. | DG62: SC | DH62: JOINVILLE | DI62: 252895738 | DJ62: (47 ) 32052727 | DK62: 0 | DL62: JOI | DM62: 57.5
A63: 2 | B63: JOI026104-1 | C63: COMPLEMENTAR FRETE | D63: JOIR | E63: JOI | F63: 46259 | G63: MMM1H28 | H63: 42260803098929000789570010000259281003784910 | I63: 61105060000163 | J63: BRASCOLA LTDA - | K63: RUA DONA FRANCISCA 8300 BLOCO D | L63: ZONA INDUSTRIAL | M63: 892 | N63: JOINVILLE | O63: SC | P63: 89219-600 | Q63: 61105060000163 | R63: BRASCOLA LTDA - | S63: JOINVILLE | T63: SC | U63: 61105060000163 | V63: BRASCOLA LTDA - | W63: RUA DONA FRANCISCA 8300 BLOCO D | X63: ZONA INDUSTRIAL | Y63: JOINVILLE | Z63: SC | AA63: (47 ) 32052727 | AC63: 21765695000172 | AD63: CHAPADACO FERRAGENS LTDA EPP | AE63: 393 | AF63: STJI | AG63: CHAPADA GAUCHA | AH63: MG | AI63: 21765695000172 | AJ63: CHAPADACO FERRAGENS LTDA EPP | AK63: SAO FRANCISCO | AL63: MG | AM63: STJ | AN63: 000330540 | AO63: 39.12 | AP63: 0.0001 | AQ63: 10 | AR63: 0 | AS63: CP | AT63: LIQUIDADO | AU63: 46283 | AV63: 57 | AW63: 001-DIVERSOS | AX63: 001-DIVERSOS | AY63: 1734.34 | AZ63: COMPLEMENTAR DE FRETE | BB63: 57 | BC63: 50.16 | BD63: 57 | BE63: 6.84 | BF63: 0.12 | BG63: 0 | BH63: 39.12 | BI63: 0 | BJ63: 50.16 | BK63: 0 | BL63: 0 | BM63: 0 | BN63: 0 | BO63: 0 | BP63: 0 | BQ63: 0 | BR63: 0 | BS63: 0 | BT63: 0 | BU63: 0 | BV63: 0 | BW63: 0 | BX63: 0 | BY63: 0 | BZ63: 0 | CA63: 0 | CB63: RSCP | CC63: RMCP | CD63: 385.14 | CE63: 0 | CF63: 0 | CG63: 0 | CH63: 0 | CI63: 0 | CJ63: 0 | CK63: 0 | CN63: 0 | CO63: 0 | CP63: 0 | CQ63: 0 | CR63: 0 | CS63: 0 | CT63: 0 | CU63: 0 | CV63: MAPA: 0 | CW63: 0 | CY63: 0 | CZ63: MAPA: 0 | DA63: 0 | DE63: 0 | DF63: A. | DG63: SC | DH63: JOINVILLE | DI63: 252895738 | DJ63: (47 ) 32052727 | DK63: 0 | DL63: JOI | DM63: 6.84
A64: 2 | B64: JOI026118-1 | C64: NORMAL | D64: JOIR | E64: JOI | F64: 46259 | G64: MMM1H28 | H64: 42260803098929000789570010000259421003785630 | I64: 61105060000163 | J64: BRASCOLA LTDA - | K64: RUA DONA FRANCISCA 8300 BLOCO D | L64: ZONA INDUSTRIAL | M64: 892 | N64: JOINVILLE | O64: SC | P64: 89219-600 | Q64: 61105060000163 | R64: BRASCOLA LTDA - | S64: JOINVILLE | T64: SC | U64: 61105060000163 | V64: BRASCOLA LTDA - | W64: RUA DONA FRANCISCA 8300 BLOCO D | X64: ZONA INDUSTRIAL | Y64: JOINVILLE | Z64: SC | AA64: (47 ) 32052727 | AC64: 65851796000131 | AD64: 65.851.796 CLARISSA DE QUEIROZ DRUMOND | AE64: 002 BELO HORIZONTE | AF64: BHZP | AG64: BELO HORIZONTE | AH64: MG | AI64: 65851796000131 | AJ64: 65.851.796 CLARISSA DE QUEIROZ DRUMOND | AK64: BELO HORIZONTE | AL64: MG | AM64: BHZ | AN64: 000331532 | AO64: 26.6 | AP64: 0.312 | AQ64: 26 | AR64: 0 | AS64: CP | AT64: LIQUIDADO | AU64: 46283 | AV64: 221.33 | AW64: 001-DIVERSOS | AX64: 001-DIVERSOS | AY64: 1516.97 | AZ64: COMBINADA | BA64: CO3809017 | BB64: 221.33 | BC64: 194.77 | BD64: 221.33 | BE64: 26.56 | BF64: 0.12 | BG64: 0 | BH64: 78 | BI64: 158.48 | BJ64: 0 | BK64: 18 | BL64: 0 | BM64: 0 | BN64: 3.25 | BO64: 5.5 | BP64: 4.23 | BQ64: 0 | BR64: 0 | BS64: 0 | BT64: 0 | BU64: 0 | BV64: 0 | BW64: 0 | BX64: 0 | BY64: 0 | BZ64: 0 | CA64: 5.31 | CB64: RSCP | CC64: BHZP | CD64: 382.92 | CE64: 0 | CF64: 0 | CG64: 0 | CH64: 0 | CI64: 0 | CJ64: 0 | CK64: 0 | CN64: 0 | CO64: 0 | CP64: 0 | CQ64: 0 | CR64: 0 | CS64: 0 | CT64: 0 | CU64: 44.27 | CV64: FATURA: 12378 | CW64: 44.27 | CX64: 012378 | CY64: 15 | CZ64: MAPA: 163 | DA64: 0 | DE64: 0 | DF64: A. | DG64: SC | DH64: JOINVILLE | DI64: 252895738 | DJ64: (47 ) 32052727 | DK64: 0 | DL64: JOI | DM64: 26.56
A65: 2 | B65: JOI026119-0 | C65: NORMAL | D65: JOIR | E65: JOI | F65: 46259 | G65: MMM1H28 | H65: 42260803098929000789570010000259431003785646 | I65: 61105060000163 | J65: BRASCOLA LTDA - | K65: RUA DONA FRANCISCA 8300 BLOCO D | L65: ZONA INDUSTRIAL | M65: 892 | N65: JOINVILLE | O65: SC | P65: 89219-600 | Q65: 61105060000163 | R65: BRASCOLA LTDA - | S65: JOINVILLE | T65: SC | U65: 61105060000163 | V65: BRASCOLA LTDA - | W65: RUA DONA FRANCISCA 8300 BLOCO D | X65: ZONA INDUSTRIAL | Y65: JOINVILLE | Z65: SC | AA65: (47 ) 32052727 | AC65: 18925438000146 | AD65: PRADOLUX INDUSTRIA E COMERCIO | AE65: 6 ROTA POCOS DE CALDAS | AF65: DCCR | AG65: POCOS DE CALDAS | AH65: MG | AI65: 18925438000146 | AJ65: PRADOLUX INDUSTRIA E COMERCIO | AK65: POCOS DE CALDAS | AL65: MG | AM65: DCC | AN65: 000331549 | AO65: 41.52 | AP65: 0.12 | AQ65: 10 | AR65: 0 | AS65: CP | AT65: LIQUIDADO | AU65: 46283 | AV65: 204.99 | AW65: 001-DIVERSOS | AX65: 001-DIVERSOS | AY65: 1745.09 | AZ65: COMBINADA | BA65: CO3809036 | BB65: 204.99 | BC65: 180.39 | BD65: 204.99 | BE65: 24.6 | BF65: 0.12 | BG65: 0 | BH65: 41.52 | BI65: 143.3 | BJ65: 0 | BK65: 18 | BL65: 0 | BM65: 0 | BN65: 3.25 | BO65: 5.5 | BP65: 4.23 | BQ65: 0 | BR65: 0 | BS65: 0 | BT65: 0 | BU65: 0 | BV65: 0 | BW65: 0 | BX65: 0 | BY65: 0 | BZ65: 0 | CA65: 6.11 | CB65: RSCP | CC65: ALTR | CD65: 385.17 | CE65: 0 | CF65: 0 | CG65: 0 | CH65: 0 | CI65: 0 | CJ65: 0 | CK65: 0 | CN65: 0 | CO65: 0 | CP65: 0 | CQ65: 0 | CR65: 0 | CS65: 0 | CT65: 0 | CU65: 41 | CV65: FATURA: 12378 | CW65: 41 | CX65: 012378 | CY65: 71.75 | CZ65: FATURA: 153 | DA65: 71.75 | DB65: 000153 | DE65: 0 | DF65: A. | DG65: SC | DH65: JOINVILLE | DI65: 252895738 | DJ65: (47 ) 32052727 | DK65: 0 | DL65: JOI | DM65: 24.6
A66: 2 | B66: JOI026120-3 | C66: NORMAL | D66: JOIR | E66: JOI | F66: 46259 | G66: MMM1H28 | H66: 42260803098929000789570010000259441003785651 | I66: 61105060000163 | J66: BRASCOLA LTDA - | K66: RUA DONA FRANCISCA 8300 BLOCO D | L66: ZONA INDUSTRIAL | M66: 892 | N66: JOINVILLE | O66: SC | P66: 89219-600 | Q66: 61105060000163 | R66: BRASCOLA LTDA - | S66: JOINVILLE | T66: SC | U66: 61105060000163 | V66: BRASCOLA LTDA - | W66: RUA DONA FRANCISCA 8300 BLOCO D | X66: ZONA INDUSTRIAL | Y66: JOINVILLE | Z66: SC | AA66: (47 ) 32052727 | AC66: 63792748000194 | AD66: 63.792.748 GABRIEL GUIMARAES DE MATOS | AE66: 332 | AF66: BHZP | AG66: LAGOA SANTA | AH66: MG | AI66: 63792748000194 | AJ66: 63.792.748 GABRIEL GUIMARAES DE MATOS | AK66: LAGOA SANTA | AL66: MG | AM66: BHZ | AN66: 000331552 | AO66: 25.08 | AP66: 0.264 | AQ66: 22 | AR66: 0 | AS66: CP | AT66: LIQUIDADO | AU66: 46283 | AV66: 191.38 | AW66: 001-DIVERSOS | AX66: 001-DIVERSOS | AY66: 1528.53 | AZ66: COMBINADA | BA66: CO3809017 | BB66: 191.38 | BC66: 168.41 | BD66: 191.38 | BE66: 22.97 | BF66: 0.12 | BG66: 0 | BH66: 66 | BI66: 132.08 | BJ66: 0 | BK66: 18 | BL66: 0 | BM66: 0 | BN66: 3.25 | BO66: 5.5 | BP66: 4.23 | BQ66: 0 | BR66: 0 | BS66: 0 | BT66: 0 | BU66: 0 | BV66: 0 | BW66: 0 | BX66: 0 | BY66: 0 | BZ66: 0 | CA66: 5.35 | CB66: RSCP | CC66: BHZP | CD66: 383.07 | CE66: 0 | CF66: 0 | CG66: 0 | CH66: 0 | CI66: 0 | CJ66: 0 | CK66: 0 | CN66: 0 | CO66: 0 | CP66: 0 | CQ66: 0 | CR66: 0 | CS66: 0 | CT66: 0 | CU66: 38.28 | CV66: FATURA: 12378 | CW66: 38.28 | CX66: 012378 | CY66: 15 | CZ66: MAPA: 162 | DA66: 0 | DE66: 0 | DF66: A. | DG66: SC | DH66: JOINVILLE | DI66: 252895738 | DJ66: (47 ) 32052727 | DK66: 0 | DL66: JOI | DM66: 22.97
A67: 2 | B67: JOI026121-1 | C67: NORMAL | D67: JOIR | E67: JOI | F67: 46259 | G67: MMM1H28 | H67: 42260803098929000789570010000259451003785667 | I67: 61105060000163 | J67: BRASCOLA LTDA - | K67: RUA DONA FRANCISCA 8300 BLOCO D | L67: ZONA INDUSTRIAL | M67: 892 | N67: JOINVILLE | O67: SC | P67: 89219-600 | Q67: 61105060000163 | R67: BRASCOLA LTDA - | S67: JOINVILLE | T67: SC | U67: 61105060000163 | V67: BRASCOLA LTDA - | W67: RUA DONA FRANCISCA 8300 BLOCO D | X67: ZONA INDUSTRIAL | Y67: JOINVILLE | Z67: SC | AA67: (47 ) 32052727 | AC67: 07773599000145 | AD67: AUTO PENA TINTAS E PECAS LTDA | AE67: 369 | AF67: GVRP | AG67: MANHUACU | AH67: MG | AI67: 07773599000145 | AJ67: AUTO PENA TINTAS E PECAS LTDA | AK67: MANHUACU | AL67: MG | AM67: GVR | AN67: 000331594 | AO67: 51.72 | AP67: 0.156 | AQ67: 13 | AR67: 0 | AS67: CP | AT67: LIQUIDADO | AU67: 46283 | AV67: 248.39 | AW67: 001-DIVERSOS | AX67: 001-DIVERSOS | AY67: 1715.12 | AZ67: COMBINADA | BA67: CO3809055 | BB67: 248.39 | BC67: 218.58 | BD67: 248.39 | BE67: 29.81 | BF67: 0.12 | BG67: 0 | BH67: 51.72 | BI67: 181.6 | BJ67: 0 | BK67: 18 | BL67: 0 | BM67: 0 | BN67: 3.25 | BO67: 5.5 | BP67: 4.23 | BQ67: 0 | BR67: 0 | BS67: 0 | BT67: 0 | BU67: 0 | BV67: 0 | BW67: 0 | BX67: 0 | BY67: 0 | BZ67: 0 | CA67: 6 | CB67: RSCP | CC67: RWNI | CD67: 384.92 | CE67: 0 | CF67: 0 | CG67: 0 | CH67: 0 | CI67: 0 | CJ67: 0 | CK67: 0 | CN67: 0 | CO67: 0 | CP67: 0 | CQ67: 0 | CR67: 0 | CS67: 0 | CT67: 0 | CU67: 49.68 | CV67: FATURA: 12378 | CW67: 49.68 | CX67: 012378 | CY67: 91.44 | CZ67: MAPA: 0 | DA67: 91.44 | DE67: 0 | DF67: A. | DG67: SC | DH67: JOINVILLE | DI67: 252895738 | DJ67: (47 ) 32052727 | DK67: 0 | DL67: JOI | DM67: 29.81
A68: 2 | B68: JOI026122-0 | C68: NORMAL | D68: JOIR | E68: JOI | F68: 46259 | G68: MMM1H28 | H68: 42260803098929000789570010000259461003785672 | I68: 61105060000163 | J68: BRASCOLA LTDA - | K68: RUA DONA FRANCISCA 8300 BLOCO D | L68: ZONA INDUSTRIAL | M68: 892 | N68: JOINVILLE | O68: SC | P68: 89219-600 | Q68: 61105060000163 | R68: BRASCOLA LTDA - | S68: JOINVILLE | T68: SC | U68: 61105060000163 | V68: BRASCOLA LTDA - | W68: RUA DONA FRANCISCA 8300 BLOCO D | X68: ZONA INDUSTRIAL | Y68: JOINVILLE | Z68: SC | AA68: (47 ) 32052727 | AC68: 09287742000114 | AD68: KALUEMA MATERIAIS DE CONSTRUCAO LTDA ME | AE68: 10 ROTA CIRCUITO DAS AGUAS | AF68: DCCR | AG68: SAO LOURENCO | AH68: MG | AI68: 09287742000114 | AJ68: KALUEMA MATERIAIS DE CONSTRUCAO LTDA ME | AK68: SAO LOURENCO | AL68: MG | AM68: DCC | AN68: 000331603 | AO68: 43.24 | AP68: 0.156 | AQ68: 13 | AR68: 0 | AS68: CP | AT68: LIQUIDADO | AU68: 46283 | AV68: 204.03 | AW68: 001-DIVERSOS | AX68: 001-DIVERSOS | AY68: 1505.54 | AZ68: COMBINADA | BA68: CO3809036 | BB68: 204.03 | BC68: 179.55 | BD68: 204.03 | BE68: 24.48 | BF68: 0.12 | BG68: 0 | BH68: 43.24 | BI68: 143.3 | BJ68: 0 | BK68: 18 | BL68: 0 | BM68: 0 | BN68: 3.25 | BO68: 5.5 | BP68: 4.23 | BQ68: 0 | BR68: 0 | BS68: 0 | BT68: 0 | BU68: 0 | BV68: 0 | BW68: 0 | BX68: 0 | BY68: 0 | BZ68: 0 | CA68: 5.27 | CB68: RSCP | CC68: ALTR | CD68: 382.8 | CE68: 0 | CF68: 0 | CG68: 0 | CH68: 0 | CI68: 0 | CJ68: 0 | CK68: 0 | CN68: 0 | CO68: 0 | CP68: 0 | CQ68: 0 | CR68: 0 | CS68: 0 | CT68: 0 | CU68: 40.81 | CV68: FATURA: 12378 | CW68: 40.81 | CX68: 012378 | CY68: 71.41 | CZ68: FATURA: 153 | DA68: 71.41 | DB68: 000153 | DE68: 0 | DF68: A. | DG68: SC | DH68: JOINVILLE | DI68: 252895738 | DJ68: (47 ) 32052727 | DK68: 0 | DL68: JOI | DM68: 24.48
A69: 2 | B69: JOI026123-8 | C69: NORMAL | D69: JOIR | E69: JOI | F69: 46259 | G69: MMM1H28 | H69: 42260803098929000789570010000259471003785688 | I69: 61105060000163 | J69: BRASCOLA LTDA - | K69: RUA DONA FRANCISCA 8300 BLOCO D | L69: ZONA INDUSTRIAL | M69: 892 | N69: JOINVILLE | O69: SC | P69: 89219-600 | Q69: 61105060000163 | R69: BRASCOLA LTDA - | S69: JOINVILLE | T69: SC | U69: 61105060000163 | V69: BRASCOLA LTDA - | W69: RUA DONA FRANCISCA 8300 BLOCO D | X69: ZONA INDUSTRIAL | Y69: JOINVILLE | Z69: SC | AA69: (47 ) 32052727 | AC69: 01001679000104 | AD69: DI MATERIAIS DE CONTRUCAO LTDA | AE69: 388 | AF69: TRUI | AG69: TIROS | AH69: MG | AI69: 01001679000104 | AJ69: DI MATERIAIS DE CONTRUCAO LTDA | AK69: TIROS | AL69: MG | AM69: TRU | AN69: 000331617 | AO69: 25.5 | AP69: 0.144 | AQ69: 12 | AR69: 0 | AS69: CP | AT69: LIQUIDADO | AU69: 46283 | AV69: 220.64 | AW69: 001-DIVERSOS | AX69: 001-DIVERSOS | AY69: 1586.76 | AZ69: COMBINADA | BA69: CO3809048 | BB69: 220.64 | BC69: 194.16 | BD69: 220.64 | BE69: 26.48 | BF69: 0.12 | BG69: 0 | BH69: 36 | BI69: 157.63 | BJ69: 0 | BK69: 18 | BL69: 0 | BM69: 0 | BN69: 3.25 | BO69: 5.5 | BP69: 4.23 | BQ69: 0 | BR69: 0 | BS69: 0 | BT69: 0 | BU69: 0 | BV69: 0 | BW69: 0 | BX69: 0 | BY69: 0 | BZ69: 0 | CA69: 5.55 | CB69: RSCP | CC69: PANI | CD69: 383.66 | CE69: 0 | CF69: 0 | CG69: 0 | CH69: 0 | CI69: 0 | CJ69: 0 | CK69: 0 | CN69: 0 | CO69: 0 | CP69: 0 | CQ69: 0 | CR69: 0 | CS69: 0 | CT69: 0 | CU69: 44.13 | CV69: FATURA: 12378 | CW69: 44.13 | CX69: 012378 | CY69: 99.29 | CZ69: FATURA: 233909 | DA69: 94.8 | DB69: 233909 | DE69: 0 | DF69: A. | DG69: SC | DH69: JOINVILLE | DI69: 252895738 | DJ69: (47 ) 32052727 | DK69: 0 | DL69: JOI | DM69: 26.48
A70: 2 | B70: JOI026189-1 | C70: NORMAL | D70: JOIR | E70: JOI | F70: 46261 | G70: MMM1H28 | H70: 42260803098929000789570010000260131003798329 | I70: 61105060000163 | J70: BRASCOLA LTDA - | K70: RUA DONA FRANCISCA 8300 BLOCO D | L70: ZONA INDUSTRIAL | M70: 892 | N70: JOINVILLE | O70: SC | P70: 89219-600 | Q70: 61105060000163 | R70: BRASCOLA LTDA - | S70: JOINVILLE | T70: SC | U70: 61105060000163 | V70: BRASCOLA LTDA - | W70: RUA DONA FRANCISCA 8300 BLOCO D | X70: ZONA INDUSTRIAL | Y70: JOINVILLE | Z70: SC | AA70: (47 ) 32052727 | AC70: 18245738000184 | AD70: CACIFE TINTAS LTDA | AE70: 4 ROTA POUSO ALEGRE | AF70: DCCR | AG70: POUSO ALEGRE | AH70: MG | AI70: 18245738000184 | AJ70: CACIFE TINTAS LTDA | AK70: POUSO ALEGRE | AL70: MG | AM70: DCC | AN70: 000331714 | AO70: 49.848 | AP70: 0.0001 | AQ70: 9 | AR70: 0 | AS70: CP | AT70: LIQUIDADO | AU70: 46283 | AV70: 220.3 | AW70: 001-DIVERSOS | AX70: 001-DIVERSOS | AY70: 1500.32 | AZ70: COMBINADA | BA70: CO3809046 | BB70: 220.3 | BC70: 193.86 | BD70: 220.3 | BE70: 26.44 | BF70: 0.12 | BG70: 0 | BH70: 49.848 | BI70: 157.63 | BJ70: 0 | BK70: 18 | BL70: 0 | BM70: 0 | BN70: 3.25 | BO70: 5.5 | BP70: 4.23 | BQ70: 0 | BR70: 0 | BS70: 0 | BT70: 0 | BU70: 0 | BV70: 0 | BW70: 0 | BX70: 0 | BY70: 0 | BZ70: 0 | CA70: 5.25 | CB70: RSCP | CC70: ALTP | CD70: 382.73 | CE70: 0 | CF70: 0 | CG70: 0 | CH70: 0 | CI70: 0 | CJ70: 0 | CK70: 0 | CN70: 0 | CO70: 0 | CP70: 0 | CQ70: 0 | CR70: 0 | CS70: 0 | CT70: 0 | CU70: 44.06 | CV70: FATURA: 12378 | CW70: 44.06 | CX70: 012378 | CY70: 77.11 | CZ70: FATURA: 156 | DA70: 77.11 | DB70: 000156 | DE70: 0 | DF70: A. | DG70: SC | DH70: JOINVILLE | DI70: 252895738 | DJ70: (47 ) 32052727 | DK70: 0 | DL70: JOI | DM70: 26.44
A71: 2 | B71: JOI026190-4 | C71: NORMAL | D71: JOIR | E71: JOI | F71: 46261 | G71: MMM1H28 | H71: 42260803098929000789570010000260141003798334 | I71: 61105060000163 | J71: BRASCOLA LTDA - | K71: RUA DONA FRANCISCA 8300 BLOCO D | L71: ZONA INDUSTRIAL | M71: 892 | N71: JOINVILLE | O71: SC | P71: 89219-600 | Q71: 61105060000163 | R71: BRASCOLA LTDA - | S71: JOINVILLE | T71: SC | U71: 61105060000163 | V71: BRASCOLA LTDA - | W71: RUA DONA FRANCISCA 8300 BLOCO D | X71: ZONA INDUSTRIAL | Y71: JOINVILLE | Z71: SC | AA71: (47 ) 32052727 | AC71: 22661482000678 | AD71: FREIOPECAS LTDA | AE71: 394 | AF71: VEAI | AG71: MONTES CLAROS | AH71: MG | AI71: 22661482000678 | AJ71: FREIOPECAS LTDA | AK71: MONTES CLAROS | AL71: MG | AM71: VEA | AN71: 000331690 | AO71: 135.42 | AP71: 0.0001 | AQ71: 27 | AR71: 0 | AS71: CP | AT71: LIQUIDADO | AU71: 46283 | AV71: 341.58 | AW71: 001-DIVERSOS | AX71: 001-DIVERSOS | AY71: 3339.87 | AZ71: COMBINADA | BA71: CO3809060 | BB71: 341.58 | BC71: 300.59 | BD71: 341.58 | BE71: 40.99 | BF71: 0.12 | BG71: 0 | BH71: 135.42 | BI71: 250.66 | BJ71: 0 | BK71: 18 | BL71: 0 | BM71: 0 | BN71: 5.01 | BO71: 11 | BP71: 4.23 | BQ71: 0 | BR71: 0 | BS71: 0 | BT71: 0 | BU71: 0 | BV71: 0 | BW71: 0 | BX71: 0 | BY71: 0 | BZ71: 0 | CA71: 11.69 | CB71: RSCP | CC71: VEAI | CD71: 408.2 | CE71: 0 | CF71: 0 | CG71: 0 | CH71: 0 | CI71: 0 | CJ71: 0 | CK71: 0 | CN71: 0 | CO71: 0 | CP71: 0 | CQ71: 0 | CR71: 0 | CS71: 0 | CT71: 0 | CU71: 68.32 | CV71: FATURA: 12378 | CW71: 68.32 | CX71: 012378 | CY71: 102.47 | CZ71: MAPA: 0 | DA71: =CY71 -> 102.47 | DE71: 0 | DF71: A. | DG71: SC | DH71: JOINVILLE | DI71: 252895738 | DJ71: (47 ) 32052727 | DK71: 0 | DL71: JOI | DM71: 40.99
A72: 2 | B72: JOI026235-8 | C72: NORMAL | D72: JOIR | E72: JOI | F72: 46262 | G72: MMM1H28 | H72: 42260803098929000789570010000260591003805820 | I72: 61105060000163 | J72: BRASCOLA LTDA - | K72: RUA DONA FRANCISCA 8300 BLOCO D | L72: ZONA INDUSTRIAL | M72: 892 | N72: JOINVILLE | O72: SC | P72: 89219-600 | Q72: 61105060000163 | R72: BRASCOLA LTDA - | S72: JOINVILLE | T72: SC | U72: 61105060000163 | V72: BRASCOLA LTDA - | W72: RUA DONA FRANCISCA 8300 BLOCO D | X72: ZONA INDUSTRIAL | Y72: JOINVILLE | Z72: SC | AA72: (47 ) 32052727 | AC72: 22661482000244 | AD72: FREIOPECAS LTDA | AE72: 394 | AF72: VEAI | AG72: MONTES CLAROS | AH72: MG | AI72: 22661482000244 | AJ72: FREIOPECAS LTDA | AK72: MONTES CLAROS | AL72: MG | AM72: VEA | AN72: 000331805 | AO72: 56.064 | AP72: 0.0001 | AQ72: 14 | AR72: 0 | AS72: CP | AT72: LIQUIDADO | AU72: 46283 | AV72: 248.17 | AW72: 001-DIVERSOS | AX72: 001-DIVERSOS | AY72: 1659.49 | AZ72: COMBINADA | BA72: CO3809060 | BB72: 248.17 | BC72: 218.39 | BD72: 248.17 | BE72: 29.78 | BF72: 0.12 | BG72: 0 | BH72: 56.064 | BI72: 181.6 | BJ72: 0 | BK72: 18 | BL72: 0 | BM72: 0 | BN72: 3.25 | BO72: 5.5 | BP72: 4.23 | BQ72: 0 | BR72: 0 | BS72: 0 | BT72: 0 | BU72: 0 | BV72: 0 | BW72: 0 | BX72: 0 | BY72: 0 | BZ72: 0 | CA72: 5.81 | CB72: RSCP | CC72: VEAI | CD72: 384.34 | CE72: 0 | CF72: 0 | CG72: 0 | CH72: 0 | CI72: 0 | CJ72: 0 | CK72: 0 | CN72: 0 | CO72: 0 | CP72: 0 | CQ72: 0 | CR72: 0 | CS72: 0 | CT72: 0 | CU72: 49.63 | CV72: FATURA: 12378 | CW72: 49.63 | CX72: 012378 | CY72: 74.45 | CZ72: MAPA: 0 | DA72: =CY72 -> 74.45 | DE72: 0 | DF72: A. | DG72: SC | DH72: JOINVILLE | DI72: 252895738 | DJ72: (47 ) 32052727 | DK72: 0 | DL72: JOI | DM72: 29.78
A73: 2 | B73: JOI026236-6 | C73: NORMAL | D73: JOIR | E73: JOI | F73: 46262 | G73: MMM1H28 | H73: 42260803098929000789570010000260601003805830 | I73: 61105060000163 | J73: BRASCOLA LTDA - | K73: RUA DONA FRANCISCA 8300 BLOCO D | L73: ZONA INDUSTRIAL | M73: 892 | N73: JOINVILLE | O73: SC | P73: 89219-600 | Q73: 61105060000163 | R73: BRASCOLA LTDA - | S73: JOINVILLE | T73: SC | U73: 61105060000163 | V73: BRASCOLA LTDA - | W73: RUA DONA FRANCISCA 8300 BLOCO D | X73: ZONA INDUSTRIAL | Y73: JOINVILLE | Z73: SC | AA73: (47 ) 32052727 | AC73: 26223056000107 | AD73: ART CALHAS MATERIAL DE CONSTRUCAO LTDA ME | AE73: 363 | AF73: TAMR | AG73: SAO JOAO DEL REI | AH73: MG | AI73: 26223056000107 | AJ73: ART CALHAS MATERIAL DE CONSTRUCAO LTDA ME | AK73: SAO JOAO DEL REI | AL73: MG | AM73: TAM | AN73: 000331790 | AO73: 362.62 | AP73: 0.0001 | AQ73: 1 | AR73: 0 | AS73: CP | AT73: LIQUIDADO | AU73: 46283 | AV73: 699.24 | AW73: 001-DIVERSOS | AX73: 001-DIVERSOS | AY73: 10666.9 | AZ73: COMBINADA | BA73: CO3809042 | BB73: 699.24 | BC73: 615.33 | BD73: 699.24 | BE73: 83.91 | BF73: 0.12 | BG73: 0 | BH73: 362.62 | BI73: 517.77 | BJ73: 0 | BK73: 18 | BL73: 0 | BM73: 0 | BN73: 16 | BO73: 22 | BP73: 4.23 | BQ73: 0 | BR73: 0 | BS73: 0 | BT73: 0 | BU73: 0 | BV73: 0 | BW73: 0 | BX73: 0 | BY73: 0 | BZ73: 0 | CA73: 37.33 | CB73: RSCP | CC73: TAMR | CD73: 1083.59 | CE73: 0 | CF73: 0 | CG73: 0 | CH73: 0 | CI73: 0 | CJ73: 0 | CK73: 0 | CN73: 0 | CO73: 0 | CP73: 0 | CQ73: 0 | CR73: 0 | CS73: 0 | CT73: 0 | CU73: 139.85 | CV73: FATURA: 12378 | CW73: 139.85 | CX73: 012378 | CY73: 181.31 | CZ73: MAPA: 0 | DA73: 181.31 | DB73: 022026 | DE73: 0 | DF73: A. | DG73: SC | DH73: JOINVILLE | DI73: 252895738 | DJ73: (47 ) 32052727 | DK73: 0 | DL73: JOI | DM73: 83.91
A74: 2 | B74: JOI026237-4 | C74: NORMAL | D74: JOIR | E74: JOI | F74: 46262 | G74: MMM1H28 | H74: 42260803098929000789570010000260611003805845 | I74: 61105060000163 | J74: BRASCOLA LTDA - | K74: RUA DONA FRANCISCA 8300 BLOCO D | L74: ZONA INDUSTRIAL | M74: 892 | N74: JOINVILLE | O74: SC | P74: 89219-600 | Q74: 61105060000163 | R74: BRASCOLA LTDA - | S74: JOINVILLE | T74: SC | U74: 61105060000163 | V74: BRASCOLA LTDA - | W74: RUA DONA FRANCISCA 8300 BLOCO D | X74: ZONA INDUSTRIAL | Y74: JOINVILLE | Z74: SC | AA74: (47 ) 32052727 | AC74: 04322102000184 | AD74: ELETROMARIO LTDA EPP | AE74: 352 | AF74: GRFI | AG74: CONSELHEIRO PENA | AH74: MG | AI74: 04322102000184 | AJ74: ELETROMARIO LTDA EPP | AK74: CONSELHEIRO PENA | AL74: MG | AM74: GRF | AN74: 000331780 | AO74: 171.576 | AP74: 0.0001 | AQ74: 35 | AR74: 0 | AS74: CP | AT74: LIQUIDADO | AU74: 46283 | AV74: 411.83 | AW74: 001-DIVERSOS | AX74: 001-DIVERSOS | AY74: 4132.93 | AZ74: COMBINADA | BA74: CO3809065 | BB74: 411.83 | BC74: 362.41 | BD74: 411.83 | BE74: 49.42 | BF74: 0.12 | BG74: 0 | BH74: 171.576 | BI74: 308.51 | BJ74: 0 | BK74: 18 | BL74: 0 | BM74: 0 | BN74: 6.2 | BO74: 11 | BP74: 4.23 | BQ74: 0 | BR74: 0 | BS74: 0 | BT74: 0 | BU74: 0 | BV74: 0 | BW74: 0 | BX74: 0 | BY74: 0 | BZ74: 0 | CA74: 14.47 | CB74: RSCP | CC74: LTOI | CD74: 419.68 | CE74: 0 | CF74: 0 | CG74: 0 | CH74: 0 | CI74: 0 | CJ74: 0 | CK74: 0 | CN74: 0 | CO74: 0 | CP74: 0 | CQ74: 0 | CR74: 0 | CS74: 0 | CT74: 0 | CU74: 82.37 | CV74: FATURA: 12378 | CW74: 82.37 | CX74: 012378 | CY74: 190.93 | CZ74: MAPA: 0 | DA74: 209.13 | DB74: 133435 | DE74: 0 | DF74: A. | DG74: SC | DH74: JOINVILLE | DI74: 252895738 | DJ74: (47 ) 32052727 | DK74: 0 | DL74: JOI | DM74: 49.42
A75: 2 | B75: JOI026289-7 | C75: NORMAL | D75: JOIR | E75: JOI | F75: 46265 | G75: MMM1H28 | H75: 42260803098929000789570010000261121003814934 | I75: 61105060000163 | J75: BRASCOLA LTDA - | K75: RUA DONA FRANCISCA 8300 BLOCO D | L75: ZONA INDUSTRIAL | M75: 892 | N75: JOINVILLE | O75: SC | P75: 89219-600 | Q75: 61105060000163 | R75: BRASCOLA LTDA - | S75: JOINVILLE | T75: SC | U75: 61105060000163 | V75: BRASCOLA LTDA - | W75: RUA DONA FRANCISCA 8300 BLOCO D | X75: ZONA INDUSTRIAL | Y75: JOINVILLE | Z75: SC | AA75: (47 ) 32052727 | AC75: 44709242000124 | AD75: WEIQUER DELCIO GUEDES 28070534672 | AE75: 360 | AF75: TAMP | AG75: JUIZ DE FORA | AH75: MG | AI75: 44709242000124 | AJ75: WEIQUER DELCIO GUEDES 28070534672 | AK75: JUIZ DE FORA | AL75: MG | AM75: TAM | AN75: 000331845 | AO75: 73.122 | AP75: 0.0001 | AQ75: 15 | AR75: 0 | AS75: CP | AT75: FATURADO | AV75: 0 | AW75: 001-DIVERSOS | AX75: 001-DIVERSOS | AY75: 1561.55 | AZ75: COMBINADA | BA75: CO3809041 | BB75: 241.83 | BC75: 212.81 | BD75: 241.83 | BE75: 29.02 | BF75: 0.12 | BG75: 0 | BH75: 73.122 | BI75: 176.36 | BJ75: 0 | BK75: 18 | BL75: 0 | BM75: 0 | BN75: 3.25 | BO75: 5.5 | BP75: 4.23 | BQ75: 0 | BR75: 0 | BS75: 0 | BT75: 0 | BU75: 0 | BV75: 0 | BW75: 0 | BX75: 0 | BY75: 0 | BZ75: 0 | CA75: 5.47 | CB75: RSCP | CC75: TAMI | CD75: 383.37 | CE75: 0 | CF75: 0 | CG75: 0 | CH75: 0 | CI75: 0 | CJ75: 0 | CK75: 0 | CN75: 0 | CO75: 0 | CP75: 0 | CQ75: 0 | CR75: 0 | CS75: 0 | CT75: 0 | CU75: 48.37 | CV75: FATURA: 12378 | CW75: 48.37 | CX75: 012378 | CY75: 29.98 | CZ75: MAPA: 0 | DA75: 29.98 | DB75: 022026 | DE75: 0 | DF75: A. | DG75: SC | DH75: JOINVILLE | DI75: 252895738 | DJ75: (47 ) 32052727 | DK75: 0 | DL75: JOI | DM75: 29.02
A76: 2 | B76: JOI026290-1 | C76: NORMAL | D76: JOIR | E76: JOI | F76: 46265 | G76: MMM1H28 | H76: 42260803098929000789570010000261131003814940 | I76: 61105060000163 | J76: BRASCOLA LTDA - | K76: RUA DONA FRANCISCA 8300 BLOCO D | L76: ZONA INDUSTRIAL | M76: 892 | N76: JOINVILLE | O76: SC | P76: 89219-600 | Q76: 61105060000163 | R76: BRASCOLA LTDA - | S76: JOINVILLE | T76: SC | U76: 61105060000163 | V76: BRASCOLA LTDA - | W76: RUA DONA FRANCISCA 8300 BLOCO D | X76: ZONA INDUSTRIAL | Y76: JOINVILLE | Z76: SC | AA76: (47 ) 32052727 | AC76: 17732545000195 | AD76: AGROCP INDUSTRIA E COMERCIO DE | AE76: 12 ROTA CAMPOS GERAIS | AF76: DCCR | AG76: TRES PONTAS | AH76: MG | AI76: 17732545000195 | AJ76: AGROCP INDUSTRIA E COMERCIO DE | AK76: TRES PONTAS | AL76: MG | AM76: DCC | AN76: 000331838 | AO76: 48.204 | AP76: 0.0001 | AQ76: 9 | AR76: 0 | AS76: CP | AT76: FATURADO | AV76: 0 | AW76: 001-DIVERSOS | AX76: 001-DIVERSOS | AY76: 1584 | AZ76: COMBINADA | BA76: CO3809037 | BB76: 220.63 | BC76: 194.15 | BD76: 220.63 | BE76: 26.48 | BF76: 0.12 | BG76: 0 | BH76: 48.204 | BI76: 157.63 | BJ76: 0 | BK76: 18 | BL76: 0 | BM76: 0 | BN76: 3.25 | BO76: 5.5 | BP76: 4.23 | BQ76: 0 | BR76: 0 | BS76: 0 | BT76: 0 | BU76: 0 | BV76: 0 | BW76: 0 | BX76: 0 | BY76: 0 | BZ76: 0 | CA76: 5.54 | CB76: RSCP | CC76: ALTI | CD76: 383.57 | CE76: 0 | CF76: 0 | CG76: 0 | CH76: 0 | CI76: 0 | CJ76: 0 | CK76: 0 | CN76: 0 | CO76: 0 | CP76: 0 | CQ76: 0 | CR76: 0 | CS76: 0 | CT76: 0 | CU76: 44.13 | CV76: FATURA: 12378 | CW76: 44.13 | CX76: 012378 | CY76: 77.22 | CZ76: FATURA: 156 | DA76: 77.22 | DB76: 000156 | DE76: 0 | DF76: A. | DG76: SC | DH76: JOINVILLE | DI76: 252895738 | DJ76: (47 ) 32052727 | DK76: 0 | DL76: JOI | DM76: 26.48
A77: 2 | B77: JOI026291-9 | C77: NORMAL | D77: JOIR | E77: JOI | F77: 46265 | G77: MMM1H28 | H77: 42260803098929000789570010000261141003814955 | I77: 61105060000163 | J77: BRASCOLA LTDA - | K77: RUA DONA FRANCISCA 8300 BLOCO D | L77: ZONA INDUSTRIAL | M77: 892 | N77: JOINVILLE | O77: SC | P77: 89219-600 | Q77: 61105060000163 | R77: BRASCOLA LTDA - | S77: JOINVILLE | T77: SC | U77: 61105060000163 | V77: BRASCOLA LTDA - | W77: RUA DONA FRANCISCA 8300 BLOCO D | X77: ZONA INDUSTRIAL | Y77: JOINVILLE | Z77: SC | AA77: (47 ) 32052727 | AC77: 23524952000100 | AD77: SMURFIT KAPPA DO BRASIL INDUSTRIA DE EMBALAGENS S.A. | AE77: 367 | AF77: TAMI | AG77: PIRAPETINGA | AH77: MG | AI77: 23524952000100 | AJ77: SMURFIT KAPPA DO BRASIL INDUSTRIA DE EMBALAGENS S.A. | AK77: PIRAPETINGA | AL77: MG | AM77: TAM | AN77: 000331817 | AO77: 60 | AP77: 0.0001 | AQ77: 4 | AR77: 0 | AS77: CP | AT77: FATURADO | AV77: 0 | AW77: 001-DIVERSOS | AX77: 001-DIVERSOS | AY77: 1697.81 | AZ77: COMBINADA | BA77: CO3809041 | BB77: 547.73 | BC77: 482 | BD77: 547.73 | BE77: 65.73 | BF77: 0.12 | BG77: 0 | BH77: 60 | BI77: 165.08 | BJ77: 0 | BK77: 18 | BL77: 0 | BM77: 0 | BN77: 3.25 | BO77: 5.5 | BP77: 4.23 | BQ77: 0 | BR77: 0 | BS77: 0 | BT77: 0 | BU77: 0 | BV77: 0 | BW77: 0 | BX77: 280 | BY77: 0 | BZ77: 0 | CA77: 5.94 | CB77: RSCP | CC77: TAMI | CD77: 384.75 | CE77: 0 | CF77: 0 | CG77: 0 | CH77: 0 | CI77: 0 | CJ77: 0 | CK77: 0 | CN77: 0 | CO77: 0 | CP77: 0 | CQ77: 0 | CR77: 0 | CS77: 0 | CT77: 0 | CU77: 109.55 | CV77: FATURA: 12378 | CW77: 109.55 | CX77: 012378 | CY77: 242 | CZ77: MAPA: 0 | DA77: 242 | DB77: sem fatura | DE77: 0 | DF77: A. | DG77: SC | DH77: JOINVILLE | DI77: 252895738 | DJ77: (47 ) 32052727 | DK77: 0 | DL77: JOI | DM77: 65.73
A78: 2 | B78: JOI026292-7 | C78: NORMAL | D78: JOIR | E78: JOI | F78: 46265 | G78: MMM1H28 | H78: 42260803098929000789570010000261151003814960 | I78: 61105060000163 | J78: BRASCOLA LTDA - | K78: RUA DONA FRANCISCA 8300 BLOCO D | L78: ZONA INDUSTRIAL | M78: 892 | N78: JOINVILLE | O78: SC | P78: 89219-600 | Q78: 61105060000163 | R78: BRASCOLA LTDA - | S78: JOINVILLE | T78: SC | U78: 61105060000163 | V78: BRASCOLA LTDA - | W78: RUA DONA FRANCISCA 8300 BLOCO D | X78: ZONA INDUSTRIAL | Y78: JOINVILLE | Z78: SC | AA78: (47 ) 32052727 | AC78: 33965363000110 | AD78: LUIZ F PEREIRA E CIA LTDA | AE78: 352 | AF78: GRFI | AG78: CONSELHEIRO PENA | AH78: MG | AI78: 33965363000110 | AJ78: LUIZ F PEREIRA E CIA LTDA | AK78: CONSELHEIRO PENA | AL78: MG | AM78: GRF | AN78: 000331855 | AO78: 83.23 | AP78: 0.0001 | AQ78: 20 | AR78: 0 | AS78: CP | AT78: FATURADO | AV78: 0 | AW78: 001-DIVERSOS | AX78: 001-DIVERSOS | AY78: 2600.23 | AZ78: COMBINADA | BA78: CO3809065 | BB78: 266.73 | BC78: 234.72 | BD78: 266.73 | BE78: 32.01 | BF78: 0.12 | BG78: 0 | BH78: 83.23 | BI78: 193.99 | BJ78: 0 | BK78: 18 | BL78: 0 | BM78: 0 | BN78: 3.9 | BO78: 5.5 | BP78: 4.23 | BQ78: 0 | BR78: 0 | BS78: 0 | BT78: 0 | BU78: 0 | BV78: 0 | BW78: 0 | BX78: 0 | BY78: 0 | BZ78: 0 | CA78: 9.1 | CB78: RSCP | CC78: LTOI | CD78: 397.45 | CE78: 0 | CF78: 0 | CG78: 0 | CH78: 0 | CI78: 0 | CJ78: 0 | CK78: 0 | CN78: 0 | CO78: 0 | CP78: 0 | CQ78: 0 | CR78: 0 | CS78: 0 | CT78: 0 | CU78: 53.35 | CV78: FATURA: 12378 | CW78: 53.35 | CX78: 012378 | CY78: 123.78 | CZ78: MAPA: 0 | DA78: 138.93 | DB78: 133435 | DE78: 0 | DF78: A. | DG78: SC | DH78: JOINVILLE | DI78: 252895738 | DJ78: (47 ) 32052727 | DK78: 0 | DL78: JOI | DM78: 32.01
A79: 2 | B79: JOI026293-5 | C79: NORMAL | D79: JOIR | E79: JOI | F79: 46265 | G79: MMM1H28 | H79: 42260803098929000789570010000261161003814976 | I79: 61105060000163 | J79: BRASCOLA LTDA - | K79: RUA DONA FRANCISCA 8300 BLOCO D | L79: ZONA INDUSTRIAL | M79: 892 | N79: JOINVILLE | O79: SC | P79: 89219-600 | Q79: 61105060000163 | R79: BRASCOLA LTDA - | S79: JOINVILLE | T79: SC | U79: 61105060000163 | V79: BRASCOLA LTDA - | W79: RUA DONA FRANCISCA 8300 BLOCO D | X79: ZONA INDUSTRIAL | Y79: JOINVILLE | Z79: SC | AA79: (47 ) 32052727 | AC79: 38620670000183 | AD79: H.R. AUTO PECAS LTDA - ME | AE79: 382 | AF79: TRUR | AG79: FRUTAL | AH79: MG | AI79: 38620670000183 | AJ79: H.R. AUTO PECAS LTDA - ME | AK79: FRUTAL | AL79: MG | AM79: TRU | AN79: 000331830 | AO79: 124.6 | AP79: 0.0001 | AQ79: 18 | AR79: 0 | AS79: CP | AT79: FATURADO | AV79: 0 | AW79: 001-DIVERSOS | AX79: 001-DIVERSOS | AY79: 3012.52 | AZ79: COMBINADA | BA79: CO3809048 | BB79: 320.05 | BC79: 281.64 | BD79: 320.05 | BE79: 38.41 | BF79: 0.12 | BG79: 0 | BH79: 124.6 | BI79: 233.35 | BJ79: 0 | BK79: 18 | BL79: 0 | BM79: 0 | BN79: 4.52 | BO79: 11 | BP79: 4.23 | BQ79: 0 | BR79: 0 | BS79: 0 | BT79: 0 | BU79: 0 | BV79: 0 | BW79: 0 | BX79: 0 | BY79: 0 | BZ79: 0 | CA79: 10.54 | CB79: RSCP | CC79: PANI | CD79: 403.44 | CE79: 0 | CF79: 0 | CG79: 0 | CH79: 0 | CI79: 0 | CJ79: 0 | CK79: 0 | CN79: 0 | CO79: 0 | CP79: 0 | CQ79: 0 | CR79: 0 | CS79: 0 | CT79: 0 | CU79: 64.01 | CV79: FATURA: 12378 | CW79: 64.01 | CX79: 012378 | CY79: 128.02 | CZ79: FATURA: 233909 | DA79: 122.24 | DB79: 233909 | DE79: 0 | DF79: A. | DG79: SC | DH79: JOINVILLE | DI79: 252895738 | DJ79: (47 ) 32052727 | DK79: 0 | DL79: JOI | DM79: 38.41
A80: 2 | B80: JOI026294-3 | C80: NORMAL | D80: JOIR | E80: JOI | F80: 46265 | G80: MMM1H28 | H80: 42260803098929000789570010000261171003814981 | I80: 61105060000163 | J80: BRASCOLA LTDA - | K80: RUA DONA FRANCISCA 8300 BLOCO D | L80: ZONA INDUSTRIAL | M80: 892 | N80: JOINVILLE | O80: SC | P80: 89219-600 | Q80: 61105060000163 | R80: BRASCOLA LTDA - | S80: JOINVILLE | T80: SC | U80: 61105060000163 | V80: BRASCOLA LTDA - | W80: RUA DONA FRANCISCA 8300 BLOCO D | X80: ZONA INDUSTRIAL | Y80: JOINVILLE | Z80: SC | AA80: (47 ) 32052727 | AC80: 03170007000140 | AD80: ORGANIZACAO FERRAZ DE ITAOBIM LTDA | AE80: 396 | AF80: GRFI | AG80: ITAOBIM | AH80: MG | AI80: 03170007000140 | AJ80: ORGANIZACAO FERRAZ DE ITAOBIM LTDA | AK80: ITAOBIM | AL80: MG | AM80: GRF | AN80: 000331910 | AO80: 82.362 | AP80: 0.0001 | AQ80: 27 | AR80: 0 | AS80: CP | AT80: FATURADO | AV80: 0 | AW80: 001-DIVERSOS | AX80: 001-DIVERSOS | AY80: 2981.45 | AZ80: COMBINADA | BA80: CO3809065 | BB80: 268.9 | BC80: 236.63 | BD80: 268.9 | BE80: 32.27 | BF80: 0.12 | BG80: 0 | BH80: 82.362 | BI80: 193.99 | BJ80: 0 | BK80: 18 | BL80: 0 | BM80: 0 | BN80: 4.47 | BO80: 5.5 | BP80: 4.23 | BQ80: 0 | BR80: 0 | BS80: 0 | BT80: 0 | BU80: 0 | BV80: 0 | BW80: 0 | BX80: 0 | BY80: 0 | BZ80: 0 | CA80: 10.44 | CB80: RSCP | CC80: LTOI | CD80: 402.97 | CE80: 0 | CF80: 0 | CG80: 0 | CH80: 0 | CI80: 0 | CJ80: 0 | CK80: 0 | CN80: 0 | CO80: 0 | CP80: 0 | CQ80: 0 | CR80: 0 | CS80: 0 | CT80: 0 | CU80: 53.78 | CV80: FATURA: 12378 | CW80: 53.78 | CX80: 012378 | CY80: 123.78 | CZ80: MAPA: 0 | DA80: 138.93 | DB80: 133435 | DE80: 0 | DF80: A. | DG80: SC | DH80: JOINVILLE | DI80: 252895738 | DJ80: (47 ) 32052727 | DK80: 0 | DL80: JOI | DM80: 32.27
A81: 2 | B81: JOI026295-1 | C81: NORMAL | D81: JOIR | E81: JOI | F81: 46265 | G81: MMM1H28 | H81: 42260803098929000789570010000261181003814997 | I81: 61105060000163 | J81: BRASCOLA LTDA - | K81: RUA DONA FRANCISCA 8300 BLOCO D | L81: ZONA INDUSTRIAL | M81: 892 | N81: JOINVILLE | O81: SC | P81: 89219-600 | Q81: 61105060000163 | R81: BRASCOLA LTDA - | S81: JOINVILLE | T81: SC | U81: 61105060000163 | V81: BRASCOLA LTDA - | W81: RUA DONA FRANCISCA 8300 BLOCO D | X81: ZONA INDUSTRIAL | Y81: JOINVILLE | Z81: SC | AA81: (47 ) 32052727 | AC81: 51044848000153 | AD81: MARVADO S CASA E CONSTRUCAO LTDA | AE81: 6 ROTA POCOS DE CALDAS | AF81: DCCR | AG81: POCOS DE CALDAS | AH81: MG | AI81: 51044848000153 | AJ81: MARVADO S CASA E CONSTRUCAO LTDA | AK81: POCOS DE CALDAS | AL81: MG | AM81: DCC | AN81: 000331877 | AO81: 115.937 | AP81: 0.0001 | AQ81: 43 | AR81: 0 | AS81: CP | AT81: FATURADO | AV81: 0 | AW81: 001-DIVERSOS | AX81: 001-DIVERSOS | AY81: 3319.45 | AZ81: COMBINADA | BA81: CO3809036 | BB81: 280.58 | BC81: 246.91 | BD81: 280.58 | BE81: 33.67 | BF81: 0.12 | BG81: 0 | BH81: 115.937 | BI81: 197.08 | BJ81: 0 | BK81: 18 | BL81: 0 | BM81: 0 | BN81: 4.98 | BO81: 11 | BP81: 4.23 | BQ81: 0 | BR81: 0 | BS81: 0 | BT81: 0 | BU81: 0 | BV81: 0 | BW81: 0 | BX81: 0 | BY81: 0 | BZ81: 0 | CA81: 11.62 | CB81: RSCP | CC81: ALTR | CD81: 407.88 | CE81: 0 | CF81: 0 | CG81: 0 | CH81: 0 | CI81: 0 | CJ81: 0 | CK81: 0 | CN81: 0 | CO81: 0 | CP81: 0 | CQ81: 0 | CR81: 0 | CS81: 0 | CT81: 0 | CU81: 56.12 | CV81: FATURA: 12378 | CW81: 56.12 | CX81: 012378 | CY81: 98.2 | CZ81: FATURA: 156 | DA81: 98.2 | DB81: 000156 | DE81: 0 | DF81: A. | DG81: SC | DH81: JOINVILLE | DI81: 252895738 | DJ81: (47 ) 32052727 | DK81: 0 | DL81: JOI | DM81: 33.67
A82: 2 | B82: JOI026296-0 | C82: NORMAL | D82: JOIR | E82: JOI | F82: 46265 | G82: MMM1H28 | H82: 42260803098929000789570010000261191003815001 | I82: 61105060000163 | J82: BRASCOLA LTDA - | K82: RUA DONA FRANCISCA 8300 BLOCO D | L82: ZONA INDUSTRIAL | M82: 892 | N82: JOINVILLE | O82: SC | P82: 89219-600 | Q82: 61105060000163 | R82: BRASCOLA LTDA - | S82: JOINVILLE | T82: SC | U82: 61105060000163 | V82: BRASCOLA LTDA - | W82: RUA DONA FRANCISCA 8300 BLOCO D | X82: ZONA INDUSTRIAL | Y82: JOINVILLE | Z82: SC | AA82: (47 ) 32052727 | AC82: 18925438000146 | AD82: PRADOLUX INDUSTRIA E COMERCIO | AE82: 6 ROTA POCOS DE CALDAS | AF82: DCCR | AG82: POCOS DE CALDAS | AH82: MG | AI82: 18925438000146 | AJ82: PRADOLUX INDUSTRIA E COMERCIO | AK82: POCOS DE CALDAS | AL82: MG | AM82: DCC | AN82: 000331880 | AO82: 1 | AP82: 0.0001 | AQ82: 1 | AR82: 0 | AS82: CP | AT82: FATURADO | AV82: 0 | AW82: 001-DIVERSOS | AX82: 001-DIVERSOS | AY82: 17.01 | AZ82: COMBINADA | BA82: CO3809036 | BB82: 165.55 | BC82: 145.68 | BD82: 165.55 | BE82: 19.87 | BF82: 0.12 | BG82: 0 | BH82: 1 | BI82: 114.64 | BJ82: 0 | BK82: 18 | BL82: 0 | BM82: 0 | BN82: 3.25 | BO82: 5.5 | BP82: 4.23 | BQ82: 0 | BR82: 0 | BS82: 0 | BT82: 0 | BU82: 0 | BV82: 0 | BW82: 0 | BX82: 0 | BY82: 0 | BZ82: 0 | CA82: 0.06 | CB82: RSCP | CC82: ALTR | CD82: 367.97 | CE82: 0 | CF82: 0 | CG82: 0 | CH82: 0 | CI82: 0 | CJ82: 0 | CK82: 0 | CN82: 0 | CO82: 0 | CP82: 0 | CQ82: 0 | CR82: 0 | CS82: 0 | CT82: 0 | CU82: 33.11 | CV82: FATURA: 12378 | CW82: 33.11 | CX82: 012378 | CY82: 57.94 | CZ82: FATURA: 156 | DA82: 57.94 | DB82: 000156 | DE82: 0 | DF82: A. | DG82: SC | DH82: JOINVILLE | DI82: 252895738 | DJ82: (47 ) 32052727 | DK82: 0 | DL82: JOI | DM82: 19.87
A83: 9

Sheet CUSTO TRANSFERENCIA
F1: Como fazer cálculo: Retirar relatório opção 200, informando o periodo mensal por unidade origem. Retirar os manifestos "Cancelados". Analisar por rota. Peso Calculo e R$ CTRB. Rota SET x BHZ e BHZ x SET calcular somente uma vez. Valor CTRB e Peso calculo.
AQ2: Filial Distribuição
C3: SPO | O3: BHZ | X3: RJO | AD3: SET | AG3: CTB | AM3: BNU/BSQ | AQ3: MESES | AR3: SPO | AS3: BHZ | AT3: SET | AU3: RJO | AV3: CTB
B4: ROTA | C4: SPO-BHZ | F4: SPO-RJO | I4: SPO-SET | L4: SPO-CTB | O4: BHZ-SPO | R4: BHZ-SET/SET-BHZ | U4: BHZ-RJO | X4: RJO-BHZ | AA4: RJO-SPO | AD4: SET-SPO | AG4: CTB-SPO | AJ4: CTB-BHZ | AM4: BNU/BSQ-SPO | AQ4: JAN | AR4: 0.17 | AS4: 0.11 | AT4: 0.055 | AU4: 0.2 | AV4: 0.09
B5: MESES | C5: PESO | D5: R$ CTRB | E5: R$ MÉDIO | F5: PESO | G5: R$ CTRB | H5: R$ MÉDIO | I5: PESO | J5: R$ CTRB | K5: R$ MÉDIO | L5: PESO | M5: R$ CTRB | N5: R$ MÉDIO | O5: PESO | P5: R$ CTRB | Q5: R$ MÉDIO | R5: PESO | S5: R$ CTRB | T5: R$ MÉDIO | U5: PESO | V5: R$ CTRB | W5: R$ MÉDIO | X5: PESO | Y5: R$ CTRB | Z5: R$ MÉDIO | AA5: PESO | AB5: R$ CTRB | AC5: R$ MÉDIO | AD5: PESO | AE5: R$ CTRB | AF5: R$ MÉDIO | AG5: PESO | AH5: R$ CTRB | AI5: R$ MÉDIO | AJ5: PESO | AK5: R$ CTRB | AL5: R$ MÉDIO | AM5: PESO | AN5: R$ CTRB | AO5: R$ MÉDIO | AQ5: FEV | AR5: 0.16 | AS5: 0.14 | AT5: 0.055 | AU5: 0.23 | AV5: 0.08
B6: JAN | C6: 943041.57 | D6: 165597.64 | E6: =IF(C6="","",D6/C6) -> 0.17559951 | F6: 260795.93 | G6: 49443.62 | H6: =IF(F6="","",G6/F6) -> 0.18958739 | I6: 904113.01 | J6: 152229.76 | K6: =IF(I6="","",J6/I6) -> 0.1683747 | L6: 121714.08 | M6: 32829.5 | N6: =IF(L6="","",M6/L6) -> 0.26972639 | O6: 256231.97 | P6: 61074.06 | Q6: 0.2 | T6: =IF(R6="","",S6/R6) | U6: 315160.69 | V6: 55389.65 | W6: 0.2 | X6: 90195.27 | Y6: 28889.88 | Z6: =IF(X6="","",Y6/X6) -> 0.32030371 | AA6: 269194.81 | AB6: 67310.36 | AC6: =IF(AA6="","",AB6/AA6) -> 0.25004331 | AD6: 239413.79 | AE6: 60648.36 | AF6: =IF(AD6="","",AE6/AD6) -> 0.25332025 | AG6: 323868 | AH6: 48990.32 | AI6: =IF(AG6="","",AH6/AG6) -> 0.15126632 | AJ6: 0 | AK6: 0 | AL6: =IF(AJ6="","",AK6/AJ6) -> #DIV/0! | AM6: 351216 | AN6: 100603 | AO6: =IF(AM6="","",AN6/AM6) -> 0.28644196 | AQ6: MAR | AR6: 0.19 | AS6: 0.13 | AT6: 0.06 | AU6: 0.23 | AV6: 0.09
B7: FEV | C7: 958064.79 | D7: 185546.49 | E7: =IF(C7="","",D7/C7) -> 0.193668 | F7: 401190.58 | G7: 71129.59 | H7: =IF(F7="","",G7/F7) -> 0.17729626 | I7: 973715.19 | J7: 153837.17 | K7: =IF(I7="","",J7/I7) -> 0.1579899 | L7: 97902.15 | M7: 28065.2 | N7: =IF(L7="","",M7/L7) -> 0.28666582 | O7: 223433 | P7: 41479.91 | Q7: 0.18 | T7: =IF(R7="","",S7/R7) | U7: 262321 | V7: 48135.61 | W7: =IF(U7="","",V7/U7) -> 0.18349888 | X7: 74697.19 | Y7: 25496.58 | Z7: =IF(X7="","",Y7/X7) -> 0.34133252 | AA7: 281103.51 | AB7: 63667.34 | AC7: =IF(AA7="","",AB7/AA7) -> 0.22649073 | AD7: 240728.88 | AE7: 59760.59 | AF7: =IF(AD7="","",AE7/AD7) -> 0.24824853 | AG7: 384684 | AH7: 50080.64 | AI7: =IF(AG7="","",AH7/AG7) -> 0.13018644 | AJ7: 0 | AK7: 0 | AL7: =IF(AJ7="","",AK7/AJ7) -> #DIV/0! | AM7: 268179 | AN7: 87200 | AO7: =IF(AM7="","",AN7/AM7) -> 0.32515596 | AQ7: ABR | AR7: 0.15 | AS7: 0.13 | AT7: 0.06 | AU7: 0.26 | AV7: 0
B8: MAR | E8: 0.17 | H8: 0.19 | K8: 0.18 | N8: 0.3 | Q8: 0.17 | W8: 0.18 | Z8: 0.29 | AC8: 0.22 | AF8: 0.24 | AI8: 0 | AL8: 0 | AQ8: MAI | AR8: 0.2 | AS8: 0.12 | AT8: 0.05 | AU8: 0.25 | AV8: 0.11
B9: ABR | E9: 0.19 | H9: 0.2 | K9: 0.18 | N9: 0.24 | Q9: 0.21 | W9: 0.2 | Z9: 0.29 | AC9: 0.23 | AF9: 0.25 | AI9: 0 | AL9: 0 | AQ9: JUN | AR9: 0 | AS9: 0.14 | AT9: 0.055 | AU9: 0.28 | AV9: 0.09
B10: MAI | E10: 0.18 | H10: 0.18 | K10: 0.18 | N10: 0.28 | Q10: 0.18 | W10: 0.19 | Z10: 0.28 | AC10: 0.19 | AF10: 0.23 | AI10: 0 | AL10: 0 | AQ10: JUL | AR10: 0.19 | AS10: 0 | AT10: 0.06 | AU10: 0.22 | AV10: 0.09
B11: JUN | E11: 0.18 | H11: 0.19 | K11: 0.18 | N11: 0.31 | Q11: 0.25 | W11: 0.22 | Z11: 0.21 | AC11: 0.18 | AF11: 0.25 | AI11: 0 | AL11: 0 | AQ11: AGO
B12: JUL | E12: 0.18 | H12: 0.18 | K12: 0.18 | N12: 0.34 | Q12: 0.22 | W12: 0.21 | Z12: 0.28 | AC12: 0.19 | AF12: 0.22 | AI12: 0 | AL12: 0 | AQ12: SET
B13: AGO | E13: =IF(C13="","",D13/C13) | H13: =IF(F13="","",G13/F13) | K13: =IF(I13="","",J13/I13) | N13: =IF(L13="","",M13/L13) | Q13: =IF(O13="","",P13/O13) | T13: =IF(R13="","",S13/R13) | Z13: =IF(X13="","",Y13/X13) | AC13: =IF(AA13="","",AB13/AA13) | AF13: =IF(AD13="","",AE13/AD13) | AI13: =IF(AG13="","",AH13/AG13) | AL13: 0 | AO13: =IF(AM13="","",AN13/AM13) | AQ13: OUT
B14: SET | E14: =IF(C14="","",D14/C14) | H14: =IF(F14="","",G14/F14) | K14: =IF(I14="","",J14/I14) | N14: =IF(L14="","",M14/L14) | Q14: =IF(O14="","",P14/O14) | T14: =IF(R14="","",S14/R14) | Z14: =IF(X14="","",Y14/X14) | AC14: =IF(AA14="","",AB14/AA14) | AF14: =IF(AD14="","",AE14/AD14) | AI14: =IF(AG14="","",AH14/AG14) | AL14: =IF(AJ14="","",AK14/AJ14) | AO14: =IF(AM14="","",AN14/AM14) | AQ14: NOV
B15: OUT | E15: =IF(C15="","",D15/C15) | H15: =IF(F15="","",G15/F15) | K15: =IF(I15="","",J15/I15) | N15: =IF(L15="","",M15/L15) | Q15: =IF(O15="","",P15/O15) | T15: =IF(R15="","",S15/R15) | Z15: =IF(X15="","",Y15/X15) | AC15: =IF(AA15="","",AB15/AA15) | AF15: =IF(AD15="","",AE15/AD15) | AI15: =IF(AG15="","",AH15/AG15) | AL15: =IF(AJ15="","",AK15/AJ15) | AO15: =IF(AM15="","",AN15/AM15) | AQ15: DEZ
B16: NOV | E16: =IF(C16="","",D16/C16) | H16: =IF(F16="","",G16/F16) | K16: =IF(I16="","",J16/I16) | N16: =IF(L16="","",M16/L16) | Q16: =IF(O16="","",P16/O16) | T16: =IF(R16="","",S16/R16) | W16: =IF(U16="","",V16/U16) | Z16: =IF(X16="","",Y16/X16) | AC16: =IF(AA16="","",AB16/AA16) | AF16: =IF(AD16="","",AE16/AD16) | AI16: =IF(AG16="","",AH16/AG16) | AL16: =IF(AJ16="","",AK16/AJ16) | AO16: =IF(AM16="","",AN16/AM16) | AQ16: TOTAL | AR16: =AVERAGE(AR4:AR15) -> 0.15142857 | AS16: =AVERAGE(AS4:AS15) -> 0.11 | AT16: =AVERAGE(AT4:AT15) -> 0.056428571 | AU16: =AVERAGE(AU4:AU15) -> 0.23857143 | AV16: =AVERAGE(AV4:AV15) -> 0.078571429
B17: DEZ | E17: =IF(C17="","",D17/C17) | H17: =IF(F17="","",G17/F17) | K17: =IF(I17="","",J17/I17) | N17: =IF(L17="","",M17/L17) | Q17: =IF(O17="","",P17/O17) | T17: =IF(R17="","",S17/R17) | W17: =IF(U17="","",V17/U17) | Z17: =IF(X17="","",Y17/X17) | AC17: =IF(AA17="","",AB17/AA17) | AF17: =IF(AD17="","",AE17/AD17) | AI17: =IF(AG17="","",AH17/AG17) | AL17: =IF(AJ17="","",AK17/AJ17) | AO17: =IF(AM17="","",AN17/AM17)
B18: TOTAL | C18: =SUM(C6:C17) -> 1901106.4 | D18: =SUM(D6:D17) -> 351144.13 | E18: =IF(C18="","",D18/C18) -> 0.18470515 | F18: =SUM(F6:F17) -> 661986.51 | G18: =SUM(G6:G17) -> 120573.21 | H18: =IF(F18="","",G18/F18) -> 0.18213847 | I18: =SUM(I6:I17) -> 1877828.2 | J18: =SUM(J6:J17) -> 306066.93 | K18: =IF(I18="","",J18/I18) -> 0.16298985 | L18: =SUM(L6:L17) -> 219616.23 | M18: =SUM(M6:M17) -> 60894.7 | N18: =IF(L18="","",M18/L18) -> 0.27727778 | O18: =SUM(O6:O17) -> 479664.97 | P18: =SUM(P6:P17) -> 102553.97 | Q18: =IF(O18="","",P18/O18) -> 0.21380333 | R18: =SUM(R6:R17) -> 0 | S18: =SUM(S6:S17) -> 0 | T18: =IF(R18="","",S18/R18) -> #DIV/0! | U18: =SUM(U6:U17) -> 577481.69 | V18: =SUM(V6:V17) -> 103525.26 | W18: =IF(U18="","",V18/U18) -> 0.1792702 | X18: =SUM(X6:X17) -> 164892.46 | Y18: =SUM(Y6:Y17) -> 54386.46 | Z18: =IF(X18="","",Y18/X18) -> 0.32982988 | AA18: =SUM(AA6:AA17) -> 550298.32 | AB18: =SUM(AB6:AB17) -> 130977.7 | AC18: =IF(AA18="","",AB18/AA18) -> 0.23801217 | AD18: =SUM(AD6:AD17) -> 480142.67 | AE18: =SUM(AE6:AE17) -> 120408.95 | AF18: =IF(AD18="","",AE18/AD18) -> 0.25077744 | AG18: =SUM(AG6:AG17) -> 708552 | AH18: =SUM(AH6:AH17) -> 99070.96 | AI18: =IF(AG18="","",AH18/AG18) -> 0.13982172 | AJ18: =SUM(AJ6:AJ17) -> 0 | AK18: =SUM(AK6:AK17) -> 0 | AL18: =IF(AJ18="","",AK18/AJ18) -> #DIV/0! | AM18: =SUM(AM6:AM17) -> 619395 | AN18: =SUM(AN6:AN17) -> 187803 | AO18: =IF(AM18="","",AN18/AM18) -> 0.30320393
N19: -0.3
B22: RETIRA BH = EJM/ROP/SES/STJ
B23: RETIRA SL = DDB/SSO
O27: CTB
O28: 0.09
O29: 0.08
O30: 0.09

Sheet CUSTO NOVA
A1: DATA EMISSÃO | B1: TIPO DE DOCUMENTO | C1: PLACA DE COLETA | D1: EMISSORA | E1: UF | F1: RECEPTORA | G1: UF | H1: CLIENTE PAGADOR | I1: NF | J1: R$ MERCADORIA | K1: VOLUMES | L1: PESO | M1: FRETE | N1: % ICMS | O1: R$ COLETA | P1: CUSTO TRANSF 1 | Q1: CUSTO TRANSF 2 | R1: R$ DISTRIBUIÇÃO | S1: COMISSÃO UNIDADE | T1: R$ REDESPACHO | U1: PARCEIRO % / FRETE | V1: CUSTO OP. | W1: % | X1: RATEIO DESP. ADMINIST./apoio op | Y1: % / FRETE | Z1: RATEIO DESP. CLT operacional | AA1: % / FRETE | AB1: Seguro Acidente (0,010%) com iof | AC1: Seguro Roubo (0,010%) com iof | AD1: TOTAL CUSTOS OP. | AE1: %FRETE | AF1: ICMS | AG1: INSS DESON | AH1: PIS/COFINS/IRPJ/CSLL 5,2% | AI1: TOTAL R$ TRIBUTOS | AJ1: CUSTO GERAL | AK1: %FRETE | AL1: R$ LÍQUIDO | AM1: RESULTADO | AN1: CUSTO R$/KG
A2: {='BASE DADOS'!F2:F82} -> 46237 | B2: {='BASE DADOS'!C2:C82} -> NORMAL | C2: {='BASE DADOS'!G2:G82} -> MMM1H28 | D2: {='BASE DADOS'!E2:E82} -> JOI | E2: {='BASE DADOS'!O2:O82} -> SC | F2: {='BASE DADOS'!AM2:AM82} -> DCC | G2: {='BASE DADOS'!AL2:AL82} -> MG | H2: {='BASE DADOS'!V2:V82} -> BRASCOLA LTDA - | I2: {='BASE DADOS'!AN2:AN82} -> 000330234 | J2: {='BASE DADOS'!AY2:AY82} -> 1536.74 | K2: {='BASE DADOS'!AQ2:AQ82} -> 10 | L2: {='BASE DADOS'!BH2:BH82} -> 55.36 | M2: {='BASE DADOS'!BB2:BB82} -> 247.68 | N2: {='BASE DADOS'!BF2:BF82} -> 0.12 | O2: {='BASE DADOS'!CW2:CW82} -> 49.54 | P2: =L2*0.34 -> 18.8224 | Q2: =L2*0.18 -> 9.9648 | T2: {='BASE DADOS'!DA2:DA82} -> 86.69 | U2: =T2/M2 -> 0.35000807 | V2: =O2+P2+Q2+R2+S2+T2 -> 165.0172 | W2: =V2/M2 -> 0.66625161 | X2: =(L2*'RESULTADO DIRETO'!N$27)/6*3 -> 5.7868254 | Y2: =X2/M2 -> 0.023364121 | Z2: =(L2*'RESULTADO DIRETO'!N$15)/6*3 -> 5.2710197 | AA2: =Z2/M2 -> 0.021281572 | AB2: =(J2*0.01%)*7.38%+(J2*0.01%) -> 0.16501514 | AC2: =(J2*0.01%)*7.38%+(J2*0.01%) -> 0.16501514 | AD2: =V2+X2+Z2+AB2+AC2 -> 176.40508 | AE2: =AD2/M2 -> 0.71222979 | AF2: =M2*N2 -> 29.7216 | AH2: =M2*0.052 -> 12.87936 | AI2: =AF2+AG2+AH2 -> 42.60096 | AJ2: =AD2+AI2 -> 219.00604 | AK2: =AJ2/M2 -> 0.88422979 | AL2: =M2-AJ2 -> 28.673965 | AM2: =AL2/M2 -> 0.11577021 | AN2: =M2/L2 -> 4.4739884
A3: 46237 | B3: NORMAL | C3: MMM1H28 | D3: JOI | E3: SC | F3: DCC | G3: MG | H3: BRASCOLA LTDA - | I3: 000330250 | J3: 1596.25 | K3: 13 | L3: 44.036 | M3: 204.4 | N3: 0.12 | O3: 40.88 | P3: =L3*0.34 -> 14.97224 | Q3: =L3*0.18 -> 7.92648 | T3: 71.54 | U3: =T3/M3 -> 0.35 | V3: =O3+P3+Q3+R3+S3+T3 -> 135.31872 | W3: =V3/M3 -> 0.66202896 | X3: =(L3*'RESULTADO DIRETO'!N$27)/6*3 -> 4.6031186 | Y3: =X3/M3 -> 0.022520149 | Z3: =(L3*'RESULTADO DIRETO'!N$15)/6*3 -> 4.192822 | AA3: =Z3/M3 -> 0.020512828 | AB3: =(J3*0.01%)*7.38%+(J3*0.01%) -> 0.17140532 | AC3: =(J3*0.01%)*7.38%+(J3*0.01%) -> 0.17140532 | AD3: =V3+X3+Z3+AB3+AC3 -> 144.45747 | AE3: =AD3/M3 -> 0.7067391 | AF3: =M3*N3 -> 24.528 | AH3: =M3*0.052 -> 10.6288 | AI3: =AF3+AG3+AH3 -> 35.1568 | AJ3: =AD3+AI3 -> 179.61427 | AK3: =AJ3/M3 -> 0.8787391 | AL3: =M3-AJ3 -> 24.785729 | AM3: =AL3/M3 -> 0.1212609 | AN3: =M3/L3 -> 4.6416568
A4: 46237 | B4: NORMAL | C4: MMM1H28 | D4: JOI | E4: SC | F4: STJ | G4: MG | H4: BRASCOLA LTDA - | I4: 000330273 | J4: 2369.18 | K4: 18 | L4: 64.212 | M4: 251.33 | N4: 0.12 | O4: 50.27 | P4: =L4*0.34 -> 21.83208 | Q4: =L4*0.18 -> 11.55816 | R4: 0 | T4: 51 | U4: =T4/M4 -> 0.20292046 | V4: =O4+P4+Q4+R4+S4+T4 -> 134.66024 | W4: =V4/M4 -> 0.53579055 | X4: =(L4*'RESULTADO DIRETO'!N$27)/6*4 -> 8.9495094 | Y4: =X4/M4 -> 0.0356086 | Z4: =(L4*'RESULTADO DIRETO'!N$15)/6*4 -> 8.1517995 | AA4: =Z4/M4 -> 0.032434646 | AB4: =(J4*0.01%)*7.38%+(J4*0.01%) -> 0.25440255 | AC4: =(J4*0.01%)*7.38%+(J4*0.01%) -> 0.25440255 | AD4: =V4+X4+Z4+AB4+AC4 -> 152.27035 | AE4: =AD4/M4 -> 0.60585825 | AF4: =M4*N4 -> 30.1596 | AH4: =M4*0.052 -> 13.06916 | AI4: =AF4+AG4+AH4 -> 43.22876 | AJ4: =AD4+AI4 -> 195.49911 | AK4: =AJ4/M4 -> 0.77785825 | AL4: =M4-AJ4 -> 55.830886 | AM4: =AL4/M4 -> 0.22214175 | AN4: =M4/L4 -> 3.9140659
A5: 46237 | B5: NORMAL | C5: MMM1H28 | D5: JOI | E5: SC | F5: BHZ | G5: MG | H5: BRASCOLA LTDA - | I5: 000330178 | J5: 4577.16 | K5: 28 | L5: 205.52 | M5: 394 | N5: 0.12 | O5: 78.8 | P5: =L5*0.34 -> 69.8768 | Q5: =L5*0.18 -> 36.9936 | R5: =L5*0.14 -> 28.7728 | T5: 0 | U5: =T5/M5 -> 0 | V5: =O5+P5+Q5+R5+S5+T5 -> 214.4432 | W5: =V5/M5 -> 0.54427208 | X5: =(L5*'RESULTADO DIRETO'!N$27)/6*4 -> 28.644228 | Y5: =X5/M5 -> 0.072701087 | Z5: =(L5*'RESULTADO DIRETO'!N$15)/6*4 -> 26.09104 | AA5: =Z5/M5 -> 0.066220913 | AB5: =(J5*0.01%)*7.38%+(J5*0.01%) -> 0.49149544 | AC5: =(J5*0.01%)*7.38%+(J5*0.01%) -> 0.49149544 | AD5: =V5+X5+Z5+AB5+AC5 -> 270.16146 | AE5: =AD5/M5 -> 0.68568898 | AF5: =M5*N5 -> 47.28 | AH5: =M5*0.052 -> 20.488 | AI5: =AF5+AG5+AH5 -> 67.768 | AJ5: =AD5+AI5 -> 337.92946 | AK5: =AJ5/M5 -> 0.85768898 | AL5: =M5-AJ5 -> 56.070541 | AM5: =AL5/M5 -> 0.14231102 | AN5: =M5/L5 -> 1.9170884
A6: 46237 | B6: NORMAL | C6: MMM1H28 | D6: JOI | E6: SC | F6: SET | G6: MG | H6: BRASCOLA LTDA - | I6: 000330177 | J6: 1699.8 | K6: 9 | L6: 65.852 | M6: 192.06 | N6: 0.12 | O6: 38.41 | P6: =L6*0.34 -> 22.38968 | Q6: =L6*0.18 -> 11.85336 | R6: =L6*0.06 -> 3.95112 | T6: 0 | U6: =T6/M6 -> 0 | V6: =O6+P6+Q6+R6+S6+T6 -> 76.60416 | W6: =V6/M6 -> 0.39885536 | X6: =(L6*'RESULTADO DIRETO'!N$27)/6*4 -> 9.1780835 | Y6: =X6/M6 -> 0.047787584 | Z6: =(L6*'RESULTADO DIRETO'!N$15)/6*4 -> 8.3599997 | AA6: =Z6/M6 -> 0.043528063 | AB6: =(J6*0.01%)*7.38%+(J6*0.01%) -> 0.18252452 | AC6: =(J6*0.01%)*7.38%+(J6*0.01%) -> 0.18252452 | AD6: =V6+X6+Z6+AB6+AC6 -> 94.507292 | AE6: =AD6/M6 -> 0.49207171 | AF6: =M6*N6 -> 23.0472 | AH6: =M6*0.052 -> 9.98712 | AI6: =AF6+AG6+AH6 -> 33.03432 | AJ6: =AD6+AI6 -> 127.54161 | AK6: =AJ6/M6 -> 0.66407171 | AL6: =M6-AJ6 -> 64.518388 | AM6: =AL6/M6 -> 0.33592829 | AN6: =M6/L6 -> 2.9165401
A7: 46237 | B7: NORMAL | C7: MMM1H28 | D7: JOI | E7: SC | F7: DCC | G7: MG | H7: BRASCOLA LTDA - | I7: 000330175 | J7: 2951.4 | K7: 21 | L7: 107.628 | M7: 288.84 | N7: 0.12 | O7: 57.77 | P7: =L7*0.34 -> 36.59352 | Q7: =L7*0.18 -> 19.37304 | T7: 101.09 | U7: =T7/M7 -> 0.34998615 | V7: =O7+P7+Q7+R7+S7+T7 -> 214.82656 | W7: =V7/M7 -> 0.74375627 | X7: =(L7*'RESULTADO DIRETO'!N$27)/6*3 -> 11.250442 | Y7: =X7/M7 -> 0.038950428 | Z7: =(L7*'RESULTADO DIRETO'!N$15)/6*3 -> 10.247639 | AA7: =Z7/M7 -> 0.035478601 | AB7: =(J7*0.01%)*7.38%+(J7*0.01%) -> 0.31692133 | AC7: =(J7*0.01%)*7.38%+(J7*0.01%) -> 0.31692133 | AD7: =V7+X7+Z7+AB7+AC7 -> 236.95848 | AE7: =AD7/M7 -> 0.82037974 | AF7: =M7*N7 -> 34.6608 | AH7: =M7*0.052 -> 15.01968 | AI7: =AF7+AG7+AH7 -> 49.68048 | AJ7: =AD7+AI7 -> 286.63896 | AK7: =AJ7/M7 -> 0.99237974 | AL7: =M7-AJ7 -> 2.2010366 | AM7: =AL7/M7 -> 0.0076202623 | AN7: =M7/L7 -> 2.6836883
A8: 46237 | B8: NORMAL | C8: MMM1H28 | D8: JOI | E8: SC | F8: DCC | G8: MG | H8: BRASCOLA LTDA - | I8: 000330170 | J8: 7938.11 | K8: 48 | L8: 327.948 | M8: 632.51 | N8: 0.12 | O8: 126.5 | P8: =L8*0.34 -> 111.50232 | Q8: =L8*0.18 -> 59.03064 | T8: 221.38 | U8: =T8/M8 -> 0.35000237 | V8: =O8+P8+Q8+R8+S8+T8 -> 518.41296 | W8: =V8/M8 -> 0.81961227 | X8: =(L8*'RESULTADO DIRETO'!N$27)/6*3 -> 34.280669 | Y8: =X8/M8 -> 0.054197829 | Z8: =(L8*'RESULTADO DIRETO'!N$15)/6*3 -> 31.225079 | AA8: =Z8/M8 -> 0.049366933 | AB8: =(J8*0.01%)*7.38%+(J8*0.01%) -> 0.85239425 | AC8: =(J8*0.01%)*7.38%+(J8*0.01%) -> 0.85239425 | AD8: =V8+X8+Z8+AB8+AC8 -> 585.6235 | AE8: =AD8/M8 -> 0.92587231 | AF8: =M8*N8 -> 75.9012 | AH8: =M8*0.052 -> 32.89052 | AI8: =AF8+AG8+AH8 -> 108.79172 | AJ8: =AD8+AI8 -> 694.41522 | AK8: =AJ8/M8 -> 1.0978723 | AL8: =M8-AJ8 -> -61.905216 | AM8: =AL8/M8 -> -0.097872312 | AN8: =M8/L8 -> 1.9286899
A9: 46237 | B9: NORMAL | C9: MMM1H28 | D9: JOI | E9: SC | F9: DDB | G9: MG | H9: BRASCOLA LTDA - | I9: 000330186 | J9: 59.58 | K9: 1 | L9: 1 | M9: 178.75 | N9: 0.12 | O9: 35.75 | P9: =L9*0.34 -> 0.34 | Q9: =L9*0.18 -> 0.18 | R9: =L9*0.06 -> 0.06 | T9: 54 | U9: =T9/M9 -> 0.3020979 | V9: =O9+P9+Q9+R9+S9+T9 -> 90.33 | W9: =V9/M9 -> 0.50534266 | X9: =(L9*'RESULTADO DIRETO'!N$27)/6*4 -> 0.13937441 | Y9: =X9/M9 -> 0.00077971696 | Z9: =(L9*'RESULTADO DIRETO'!N$15)/6*4 -> 0.12695134 | AA9: =Z9/M9 -> 0.00071021729 | AB9: =(J9*0.01%)*7.38%+(J9*0.01%) -> 0.0063977004 | AC9: =(J9*0.01%)*7.38%+(J9*0.01%) -> 0.0063977004 | AD9: =V9+X9+Z9+AB9+AC9 -> 90.609121 | AE9: =AD9/M9 -> 0.50690417 | AF9: =M9*N9 -> 21.45 | AH9: =M9*0.052 -> 9.295 | AI9: =AF9+AG9+AH9 -> 30.745 | AJ9: =AD9+AI9 -> 121.35412 | AK9: =AJ9/M9 -> 0.67890417 | AL9: =M9-AJ9 -> 57.395879 | AM9: =AL9/M9 -> 0.32109583 | AN9: =M9/L9 -> 178.75
A10: 46237 | B10: NORMAL | C10: MMM1H28 | D10: JOI | E10: SC | F10: GVR | G10: MG | H10: BRASCOLA LTDA - | I10: 000330185 | J10: 59.58 | K10: 1 | L10: 1 | M10: 178.75 | N10: 0.12 | O10: 35.75 | P10: =L10*0.34 -> 0.34 | Q10: =L10*0.18 -> 0.18 | R10: =L10*0.14 -> 0.14 | T10: 67.06 | U10: =T10/M10 -> 0.37516084 | V10: =O10+P10+Q10+R10+S10+T10 -> 103.47 | W10: =V10/M10 -> 0.57885315 | X10: =(L10*'RESULTADO DIRETO'!N$27)/6*4 -> 0.13937441 | Y10: =X10/M10 -> 0.00077971696 | Z10: =(L10*'RESULTADO DIRETO'!N$15)/6*4 -> 0.12695134 | AA10: =Z10/M10 -> 0.00071021729 | AB10: =(J10*0.01%)*7.38%+(J10*0.01%) -> 0.0063977004 | AC10: =(J10*0.01%)*7.38%+(J10*0.01%) -> 0.0063977004 | AD10: =V10+X10+Z10+AB10+AC10 -> 103.74912 | AE10: =AD10/M10 -> 0.58041466 | AF10: =M10*N10 -> 21.45 | AH10: =M10*0.052 -> 9.295 | AI10: =AF10+AG10+AH10 -> 30.745 | AJ10: =AD10+AI10 -> 134.49412 | AK10: =AJ10/M10 -> 0.75241466 | AL10: =M10-AJ10 -> 44.255879 | AM10: =AL10/M10 -> 0.24758534 | AN10: =M10/L10 -> 178.75
A11: 46237 | B11: NORMAL | C11: MMM1H28 | D11: JOI | E11: SC | F11: STJ | G11: MG | H11: BRASCOLA LTDA - | I11: 000330223 | J11: 1842.97 | K11: 11 | L11: 65.694 | M11: 248.9 | N11: 0.12 | O11: 49.78 | P11: =L11*0.34 -> 22.33596 | Q11: =L11*0.18 -> 11.82492 | R11: 0 | T11: 51 | U11: =T11/M11 -> 0.20490157 | V11: =O11+P11+Q11+R11+S11+T11 -> 134.94088 | W11: =V11/M11 -> 0.54214898 | X11: =(L11*'RESULTADO DIRETO'!N$27)/6*4 -> 9.1560623 | Y11: =X11/M11 -> 0.036786108 | Z11: =(L11*'RESULTADO DIRETO'!N$15)/6*4 -> 8.3399414 | AA11: =Z11/M11 -> 0.033507197 | AB11: =(J11*0.01%)*7.38%+(J11*0.01%) -> 0.19789812 | AC11: =(J11*0.01%)*7.38%+(J11*0.01%) -> 0.19789812 | AD11: =V11+X11+Z11+AB11+AC11 -> 152.83268 | AE11: =AD11/M11 -> 0.61403246 | AF11: =M11*N11 -> 29.868 | AH11: =M11*0.052 -> 12.9428 | AI11: =AF11+AG11+AH11 -> 42.8108 | AJ11: =AD11+AI11 -> 195.64348 | AK11: =AJ11/M11 -> 0.78603246 | AL11: =M11-AJ11 -> 53.25652 | AM11: =AL11/M11 -> 0.21396754 | AN11: =M11/L11 -> 3.7887783
A12: 46239 | B12: NORMAL | C12: MMM1H28 | D12: JOI | E12: SC | F12: GVR | G12: MG | H12: BRASCOLA LTDA - | I12: 000330285 | J12: 4515.09 | K12: 30 | L12: 146.24 | M12: 332.13 | N12: 0.12 | O12: 66.43 | P12: =L12*0.34 -> 49.7216 | Q12: =L12*0.18 -> 26.3232 | R12: =L12*0.14 -> 20.4736 | T12: 125.25 | U12: =T12/M12 -> 0.37711137 | V12: =O12+P12+Q12+R12+S12+T12 -> 288.1984 | W12: =V12/M12 -> 0.8677277 | X12: =(L12*'RESULTADO DIRETO'!N$27)/6*4 -> 20.382113 | Y12: =X12/M12 -> 0.061367878 | Z12: =(L12*'RESULTADO DIRETO'!N$15)/6*4 -> 18.565364 | AA12: =Z12/M12 -> 0.055897884 | AB12: =(J12*0.01%)*7.38%+(J12*0.01%) -> 0.48483036 | AC12: =(J12*0.01%)*7.38%+(J12*0.01%) -> 0.48483036 | AD12: =V12+X12+Z12+AB12+AC12 -> 328.11554 | AE12: =AD12/M12 -> 0.98791298 | AF12: =M12*N12 -> 39.8556 | AH12: =M12*0.052 -> 17.27076 | AI12: =AF12+AG12+AH12 -> 57.12636 | AJ12: =AD12+AI12 -> 385.2419 | AK12: =AJ12/M12 -> 1.159913 | AL12: =M12-AJ12 -> -53.111898 | AM12: =AL12/M12 -> -0.15991298 | AN12: =M12/L12 -> 2.2711296
A13: 46239 | B13: NORMAL | C13: MMM1H28 | D13: JOI | E13: SC | F13: DCC | G13: MG | H13: BRASCOLA LTDA - | I13: 000330315 | J13: 1624.49 | K13: 7 | L13: 29.08 | M13: 171.94 | N13: 0.12 | O13: 34.39 | P13: =L13*0.34 -> 9.8872 | Q13: =L13*0.18 -> 5.2344 | T13: 60.18 | U13: =T13/M13 -> 0.35000582 | V13: =O13+P13+Q13+R13+S13+T13 -> 109.6916 | W13: =V13/M13 -> 0.63796441 | X13: =(L13*'RESULTADO DIRETO'!N$27)/6*3 -> 3.0397558 | Y13: =X13/M13 -> 0.017679166 | Z13: =(L13*'RESULTADO DIRETO'!N$15)/6*3 -> 2.7688088 | AA13: =Z13/M13 -> 0.016103343 | AB13: =(J13*0.01%)*7.38%+(J13*0.01%) -> 0.17443774 | AC13: =(J13*0.01%)*7.38%+(J13*0.01%) -> 0.17443774 | AD13: =V13+X13+Z13+AB13+AC13 -> 115.84904 | AE13: =AD13/M13 -> 0.67377597 | AF13: =M13*N13 -> 20.6328 | AH13: =M13*0.052 -> 8.94088 | AI13: =AF13+AG13+AH13 -> 29.57368 | AJ13: =AD13+AI13 -> 145.42272 | AK13: =AJ13/M13 -> 0.84577597 | AL13: =M13-AJ13 -> 26.51728 | AM13: =AL13/M13 -> 0.15422403 | AN13: =M13/L13 -> 5.9126547
A14: 46239 | B14: NORMAL | C14: MMM1H28 | D14: JOI | E14: SC | F14: VEA | G14: MG | H14: BRASCOLA LTDA - | I14: 000330246 | J14: 3238.98 | K14: 20 | L14: 146.8 | M14: 361.7 | N14: 0.12 | O14: 72.34 | P14: =L14*0.34 -> 49.912 | Q14: =L14*0.18 -> 26.424 | R14: =L14*0.06 -> 8.808 | T14: 108.51 | U14: =T14/M14 -> 0.3 | V14: =O14+P14+Q14+R14+S14+T14 -> 265.994 | W14: =V14/M14 -> 0.7353995 | X14: =(L14*'RESULTADO DIRETO'!N$27)/6*4 -> 20.460163 | Y14: =X14/M14 -> 0.056566666 | Z14: =(L14*'RESULTADO DIRETO'!N$15)/6*4 -> 18.636457 | AA14: =Z14/M14 -> 0.051524625 | AB14: =(J14*0.01%)*7.38%+(J14*0.01%) -> 0.34780167 | AC14: =(J14*0.01%)*7.38%+(J14*0.01%) -> 0.34780167 | AD14: =V14+X14+Z14+AB14+AC14 -> 305.78622 | AE14: =AD14/M14 -> 0.84541394 | AF14: =M14*N14 -> 43.404 | AH14: =M14*0.052 -> 18.8084 | AI14: =AF14+AG14+AH14 -> 62.2124 | AJ14: =AD14+AI14 -> 367.99862 | AK14: =AJ14/M14 -> 1.0174139 | AL14: =M14-AJ14 -> -6.2986233 | AM14: =AL14/M14 -> -0.017413943 | AN14: =M14/L14 -> 2.4638965
A15: 46239 | B15: NORMAL | C15: MMM1H28 | D15: JOI | E15: SC | F15: EJM | G15: MG | H15: BRASCOLA LTDA - | I15: 000330237 | J15: 9522.96 | K15: 1 | L15: 449.876 | M15: 967.19 | N15: 0.12 | O15: 193.44 | P15: =L15*0.34 -> 152.95784 | Q15: =L15*0.18 -> 80.97768 | R15: 0 | T15: 386.88 | U15: =T15/M15 -> 0.40000414 | V15: =O15+P15+Q15+R15+S15+T15 -> 814.25552 | W15: =V15/M15 -> 0.84187752 | X15: =(L15*'RESULTADO DIRETO'!N$27)/6*4 -> 62.701201 | Y15: =X15/M15 -> 0.064828215 | Z15: =(L15*'RESULTADO DIRETO'!N$15)/6*4 -> 57.112362 | AA15: =Z15/M15 -> 0.059049785 | AB15: =(J15*0.01%)*7.38%+(J15*0.01%) -> 1.0225754 | AC15: =(J15*0.01%)*7.38%+(J15*0.01%) -> 1.0225754 | AD15: =V15+X15+Z15+AB15+AC15 -> 936.11423 | AE15: =AD15/M15 -> 0.96787005 | AF15: =M15*N15 -> 116.0628 | AH15: =M15*0.052 -> 50.29388 | AI15: =AF15+AG15+AH15 -> 166.35668 | AJ15: =AD15+AI15 -> 1102.4709 | AK15: =AJ15/M15 -> 1.13987 | AL15: =M15-AJ15 -> -135.28091 | AM15: =AL15/M15 -> -0.13987005 | AN15: =M15/L15 -> 2.1499035
A16: 46240 | B16: NORMAL | C16: MMM1H28 | D16: JOI | E16: SC | F16: DCC | G16: MG | H16: BRASCOLA LTDA - | I16: 000330385 | J16: 3084.36 | K16: 31 | L16: 70.43 | M16: 249.45 | N16: 0.12 | O16: 49.89 | P16: =L16*0.34 -> 23.9462 | Q16: =L16*0.18 -> 12.6774 | T16: 87.31 | U16: =T16/M16 -> 0.35001002 | V16: =O16+P16+Q16+R16+S16+T16 -> 173.8236 | W16: =V16/M16 -> 0.69682742 | X16: =(L16*'RESULTADO DIRETO'!N$27)/6*3 -> 7.3621046 | Y16: =X16/M16 -> 0.029513348 | Z16: =(L16*'RESULTADO DIRETO'!N$15)/6*3 -> 6.7058872 | AA16: =Z16/M16 -> 0.026882691 | AB16: =(J16*0.01%)*7.38%+(J16*0.01%) -> 0.33119858 | AC16: =(J16*0.01%)*7.38%+(J16*0.01%) -> 0.33119858 | AD16: =V16+X16+Z16+AB16+AC16 -> 188.55399 | AE16: =AD16/M16 -> 0.75587889 | AF16: =M16*N16 -> 29.934 | AH16: =M16*0.052 -> 12.9714 | AI16: =AF16+AG16+AH16 -> 42.9054 | AJ16: =AD16+AI16 -> 231.45939 | AK16: =AJ16/M16 -> 0.92787889 | AL16: =M16-AJ16 -> 17.990611 | AM16: =AL16/M16 -> 0.07212111 | AN16: =M16/L16 -> 3.5418146
A17: 46240 | B17: NORMAL | C17: MMM1H28 | D17: JOI | E17: SC | F17: DCC | G17: MG | H17: BRASCOLA LTDA - | I17: 000330394 | J17: 1911.24 | K17: 4 | L17: 64 | M17: 230.4 | N17: 0.12 | O17: 46.08 | P17: =L17*0.34 -> 21.76 | Q17: =L17*0.18 -> 11.52 | T17: 80.64 | U17: =T17/M17 -> 0.35 | V17: =O17+P17+Q17+R17+S17+T17 -> 160 | W17: =V17/M17 -> 0.69444444 | X17: =(L17*'RESULTADO DIRETO'!N$27)/6*3 -> 6.6899716 | Y17: =X17/M17 -> 0.029036335 | Z17: =(L17*'RESULTADO DIRETO'!N$15)/6*3 -> 6.0936644 | AA17: =Z17/M17 -> 0.026448196 | AB17: =(J17*0.01%)*7.38%+(J17*0.01%) -> 0.20522895 | AC17: =(J17*0.01%)*7.38%+(J17*0.01%) -> 0.20522895 | AD17: =V17+X17+Z17+AB17+AC17 -> 173.19409 | AE17: =AD17/M17 -> 0.75171048 | AF17: =M17*N17 -> 27.648 | AH17: =M17*0.052 -> 11.9808 | AI17: =AF17+AG17+AH17 -> 39.6288 | AJ17: =AD17+AI17 -> 212.82289 | AK17: =AJ17/M17 -> 0.92371048 | AL17: =M17-AJ17 -> 17.577106 | AM17: =AL17/M17 -> 0.076289523 | AN17: =M17/L17 -> 3.6
A18: 46240 | B18: NORMAL | C18: MMM1H28 | D18: JOI | E18: SC | F18: TAM | G18: MG | H18: BRASCOLA LTDA - | I18: 000330404 | J18: 1520 | K18: 10 | L18: 73.4 | M18: 241.66 | N18: 0.12 | O18: 48.33 | P18: =L18*0.34 -> 24.956 | Q18: =L18*0.18 -> 13.212 | R18: =L18*0.14 -> 10.276 | T18: 30.09 | U18: =T18/M18 -> 0.12451378 | V18: =O18+P18+Q18+R18+S18+T18 -> 126.864 | W18: =V18/M18 -> 0.52496896 | X18: =(L18*'RESULTADO DIRETO'!N$27)/6*4 -> 10.230082 | Y18: =X18/M18 -> 0.04233254 | Z18: =(L18*'RESULTADO DIRETO'!N$15)/6*4 -> 9.3182285 | AA18: =Z18/M18 -> 0.03855925 | AB18: =(J18*0.01%)*7.38%+(J18*0.01%) -> 0.1632176 | AC18: =(J18*0.01%)*7.38%+(J18*0.01%) -> 0.1632176 | AD18: =V18+X18+Z18+AB18+AC18 -> 146.73875 | AE18: =AD18/M18 -> 0.60721156 | AF18: =M18*N18 -> 28.9992 | AH18: =M18*0.052 -> 12.56632 | AI18: =AF18+AG18+AH18 -> 41.56552 | AJ18: =AD18+AI18 -> 188.30427 | AK18: =AJ18/M18 -> 0.77921156 | AL18: =M18-AJ18 -> 53.355735 | AM18: =AL18/M18 -> 0.22078844 | AN18: =M18/L18 -> 3.2923706
A19: 46240 | B19: NORMAL | C19: MMM1H28 | D19: JOI | E19: SC | F19: STJ | G19: MG | H19: BRASCOLA LTDA - | I19: 000330407 | J19: 1680.29 | K19: 9 | L19: 54.66 | M19: 248.25 | N19: 0.12 | O19: 49.65 | P19: =L19*0.34 -> 18.5844 | Q19: =L19*0.18 -> 9.8388 | R19: 0 | T19: 51 | U19: =T19/M19 -> 0.20543807 | V19: =O19+P19+Q19+R19+S19+T19 -> 129.0732 | W19: =V19/M19 -> 0.51993233 | X19: =(L19*'RESULTADO DIRETO'!N$27)/6*4 -> 7.6182051 | Y19: =X19/M19 -> 0.030687634 | Z19: =(L19*'RESULTADO DIRETO'!N$15)/6*4 -> 6.9391603 | AA19: =Z19/M19 -> 0.027952307 | AB19: =(J19*0.01%)*7.38%+(J19*0.01%) -> 0.18042954 | AC19: =(J19*0.01%)*7.38%+(J19*0.01%) -> 0.18042954 | AD19: =V19+X19+Z19+AB19+AC19 -> 143.99142 | AE19: =AD19/M19 -> 0.58002588 | AF19: =M19*N19 -> 29.79 | AH19: =M19*0.052 -> 12.909 | AI19: =AF19+AG19+AH19 -> 42.699 | AJ19: =AD19+AI19 -> 186.69042 | AK19: =AJ19/M19 -> 0.75202588 | AL19: =M19-AJ19 -> 61.559575 | AM19: =AL19/M19 -> 0.24797412 | AN19: =M19/L19 -> 4.5417124
A20: 46240 | B20: NORMAL | C20: MMM1H28 | D20: JOI | E20: SC | F20: DCC | G20: MG | H20: BRASCOLA LTDA - | I20: 000330443 | J20: 4935.52 | K20: 52 | L20: 161.47 | M20: 357.01 | N20: 0.12 | O20: 71.4 | P20: =L20*0.34 -> 54.8998 | Q20: =L20*0.18 -> 29.0646 | T20: 324.95 | U20: =T20/M20 -> 0.91019859 | V20: =O20+P20+Q20+R20+S20+T20 -> 480.3144 | W20: =V20/M20 -> 1.3453808 | X20: =(L20*'RESULTADO DIRETO'!N$27)/6*3 -> 16.878589 | Y20: =X20/M20 -> 0.047277637 | Z20: =(L20*'RESULTADO DIRETO'!N$15)/6*3 -> 15.374125 | AA20: =Z20/M20 -> 0.043063569 | AB20: =(J20*0.01%)*7.38%+(J20*0.01%) -> 0.52997614 | AC20: =(J20*0.01%)*7.38%+(J20*0.01%) -> 0.52997614 | AD20: =V20+X20+Z20+AB20+AC20 -> 513.62707 | AE20: =AD20/M20 -> 1.438691 | AF20: =M20*N20 -> 42.8412 | AH20: =M20*0.052 -> 18.56452 | AI20: =AF20+AG20+AH20 -> 61.40572 | AJ20: =AD20+AI20 -> 575.03279 | AK20: =AJ20/M20 -> 1.610691 | AL20: =M20-AJ20 -> -218.02279 | AM20: =AL20/M20 -> -0.61069098 | AN20: =M20/L20 -> 2.2109989
A21: 46241 | B21: NORMAL | C21: MMM1H28 | D21: JOI | E21: SC | F21: GVR | G21: MG | H21: BRASCOLA LTDA - | I21: 000330493 | J21: 1631.71 | K21: 9 | L21: 40.984 | M21: 220.82 | N21: 0.12 | O21: 44.16 | P21: =L21*0.34 -> 13.93456 | Q21: =L21*0.18 -> 7.37712 | R21: =L21*0.14 -> 5.73776 | T21: 81.79 | U21: =T21/M21 -> 0.37039217 | V21: =O21+P21+Q21+R21+S21+T21 -> 152.99944 | W21: =V21/M21 -> 0.69286949 | X21: =(L21*'RESULTADO DIRETO'!N$27)/6*4 -> 5.7121207 | Y21: =X21/M21 -> 0.025867769 | Z21: =(L21*'RESULTADO DIRETO'!N$15)/6*4 -> 5.2029738 | AA21: =Z21/M21 -> 0.023562059 | AB21: =(J21*0.01%)*7.38%+(J21*0.01%) -> 0.17521302 | AC21: =(J21*0.01%)*7.38%+(J21*0.01%) -> 0.17521302 | AD21: =V21+X21+Z21+AB21+AC21 -> 164.26496 | AE21: =AD21/M21 -> 0.74388624 | AF21: =M21*N21 -> 26.4984 | AH21: =M21*0.052 -> 11.48264 | AI21: =AF21+AG21+AH21 -> 37.98104 | AJ21: =AD21+AI21 -> 202.246 | AK21: =AJ21/M21 -> 0.91588624 | AL21: =M21-AJ21 -> 18.573999 | AM21: =AL21/M21 -> 0.084113755 | AN21: =M21/L21 -> 5.3879563
A22: 46241 | B22: NORMAL | C22: MMM1H28 | D22: JOI | E22: SC | F22: GRF | G22: MG | H22: BRASCOLA LTDA - | I22: 000330483 | J22: 3051.01 | K22: 19 | L22: 74.328 | M22: 269.3 | N22: 0.12 | O22: 53.86 | P22: =L22*0.34 -> 25.27152 | Q22: 0 | R22: =L22*0.09 -> 6.68952 | T22: 138.93 | U22: =T22/M22 -> 0.51589306 | V22: =O22+P22+Q22+R22+S22+T22 -> 224.75104 | W22: =V22/M22 -> 0.83457497 | X22: =(L22*'RESULTADO DIRETO'!N$27)/6*3 -> 7.7695657 | Y22: =X22/M22 -> 0.028850968 | Z22: =(L22*'RESULTADO DIRETO'!N$15)/6*3 -> 7.0770295 | AA22: =Z22/M22 -> 0.026279352 | AB22: =(J22*0.01%)*7.38%+(J22*0.01%) -> 0.32761745 | AC22: =(J22*0.01%)*7.38%+(J22*0.01%) -> 0.32761745 | AD22: =V22+X22+Z22+AB22+AC22 -> 240.25287 | AE22: =AD22/M22 -> 0.8921384 | AF22: =M22*N22 -> 32.316 | AH22: =M22*0.052 -> 14.0036 | AI22: =AF22+AG22+AH22 -> 46.3196 | AJ22: =AD22+AI22 -> 286.57247 | AK22: =AJ22/M22 -> 1.0641384 | AL22: =M22-AJ22 -> -17.27247 | AM22: =AL22/M22 -> -0.064138396 | AN22: =M22/L22 -> 3.6231299
A23: 46241 | B23: NORMAL | C23: MMM1H28 | D23: JOI | E23: SC | F23: GVR | G23: MG | H23: BRASCOLA LTDA - | I23: 000330524 | J23: 2766.4 | K23: 25 | L23: 121.068 | M23: 312.23 | N23: 0.12 | O23: 62.45 | P23: =L23*0.34 -> 41.16312 | Q23: =L23*0.18 -> 21.79224 | R23: =L23*0.14 -> 16.94952 | T23: 118.28 | U23: =T23/M23 -> 0.3788233 | V23: =O23+P23+Q23+R23+S23+T23 -> 260.63488 | W23: =V23/M23 -> 0.83475284 | X23: =(L23*'RESULTADO DIRETO'!N$27)/6*4 -> 16.873781 | Y23: =X23/M23 -> 0.054042791 | Z23: =(L23*'RESULTADO DIRETO'!N$15)/6*4 -> 15.369745 | AA23: =Z23/M23 -> 0.049225715 | AB23: =(J23*0.01%)*7.38%+(J23*0.01%) -> 0.29705603 | AC23: =(J23*0.01%)*7.38%+(J23*0.01%) -> 0.29705603 | AD23: =V23+X23+Z23+AB23+AC23 -> 293.47252 | AE23: =AD23/M23 -> 0.93992415 | AF23: =M23*N23 -> 37.4676 | AH23: =M23*0.052 -> 16.23596 | AI23: =AF23+AG23+AH23 -> 53.70356 | AJ23: =AD23+AI23 -> 347.17608 | AK23: =AJ23/M23 -> 1.1119242 | AL23: =M23-AJ23 -> -34.946078 | AM23: =AL23/M23 -> -0.11192415 | AN23: =M23/L23 -> 2.5789639
A24: 46244 | B24: NORMAL | C24: MMM1H28 | D24: JOI | E24: SC | F24: BHZ | G24: MG | H24: BRASCOLA LTDA - | I24: 000330610 | J24: 5078.78 | K24: 1 | L24: 286 | M24: 506.6 | N24: 0.12 | O24: 101.32 | P24: =L24*0.34 -> 97.24 | Q24: =L24*0.18 -> 51.48 | R24: =L24*0.14 -> 40.04 | T24: 0 | U24: =T24/M24 -> 0 | V24: =O24+P24+Q24+R24+S24+T24 -> 290.08 | W24: =V24/M24 -> 0.57260166 | X24: =(L24*'RESULTADO DIRETO'!N$27)/6*4 -> 39.861081 | Y24: =X24/M24 -> 0.078683538 | Z24: =(L24*'RESULTADO DIRETO'!N$15)/6*4 -> 36.308084 | AA24: =Z24/M24 -> 0.071670122 | AB24: =(J24*0.01%)*7.38%+(J24*0.01%) -> 0.5453594 | AC24: =(J24*0.01%)*7.38%+(J24*0.01%) -> 0.5453594 | AD24: =V24+X24+Z24+AB24+AC24 -> 367.33988 | AE24: =AD24/M24 -> 0.72510834 | AF24: =M24*N24 -> 60.792 | AH24: =M24*0.052 -> 26.3432 | AI24: =AF24+AG24+AH24 -> 87.1352 | AJ24: =AD24+AI24 -> 454.47508 | AK24: =AJ24/M24 -> 0.89710834 | AL24: =M24-AJ24 -> 52.124917 | AM24: =AL24/M24 -> 0.10289166 | AN24: =M24/L24 -> 1.7713287
A25: 46244 | B25: NORMAL | C25: MMM1H28 | D25: JOI | E25: SC | F25: STJ | G25: MG | H25: BRASCOLA LTDA - | I25: 000330540 | J25: 1734.34 | K25: 10 | L25: 39.12 | M25: 221.23 | N25: 0.12 | O25: 44.25 | P25: =L25*0.34 -> 13.3008 | Q25: =L25*0.18 -> 7.0416 | R25: 0 | T25: 51 | U25: =T25/M25 -> 0.23052931 | V25: =O25+P25+Q25+R25+S25+T25 -> 115.5924 | W25: =V25/M25 -> 0.52249876 | X25: =(L25*'RESULTADO DIRETO'!N$27)/6*4 -> 5.4523268 | Y25: =X25/M25 -> 0.024645513 | Z25: =(L25*'RESULTADO DIRETO'!N$15)/6*4 -> 4.9663365 | AA25: =Z25/M25 -> 0.022448748 | AB25: =(J25*0.01%)*7.38%+(J25*0.01%) -> 0.18623343 | AC25: =(J25*0.01%)*7.38%+(J25*0.01%) -> 0.18623343 | AD25: =V25+X25+Z25+AB25+AC25 -> 126.38353 | AE25: =AD25/M25 -> 0.57127664 | AF25: =M25*N25 -> 26.5476 | AH25: =M25*0.052 -> 11.50396 | AI25: =AF25+AG25+AH25 -> 38.05156 | AJ25: =AD25+AI25 -> 164.43509 | AK25: =AJ25/M25 -> 0.74327664 | AL25: =M25-AJ25 -> 56.79491 | AM25: =AL25/M25 -> 0.25672336 | AN25: =M25/L25 -> 5.6551636
A26: 46244 | B26: NORMAL | C26: MMM1H28 | D26: JOI | E26: SC | F26: VEA | G26: MG | H26: BRASCOLA LTDA - | I26: 000330541 | J26: 3337.82 | K26: 19 | L26: 90.212 | M26: 270.92 | N26: 0.12 | O26: 54.18 | P26: =L26*0.34 -> 30.67208 | Q26: =L26*0.18 -> 16.23816 | R26: =L26*0.06 -> 5.41272 | T26: 81.28 | U26: =T26/M26 -> 0.30001476 | V26: =O26+P26+Q26+R26+S26+T26 -> 187.78296 | W26: =V26/M26 -> 0.69313067 | X26: =(L26*'RESULTADO DIRETO'!N$27)/6*4 -> 12.573244 | Y26: =X26/M26 -> 0.046409435 | Z26: =(L26*'RESULTADO DIRETO'!N$15)/6*4 -> 11.452534 | AA26: =Z26/M26 -> 0.042272754 | AB26: =(J26*0.01%)*7.38%+(J26*0.01%) -> 0.35841511 | AC26: =(J26*0.01%)*7.38%+(J26*0.01%) -> 0.35841511 | AD26: =V26+X26+Z26+AB26+AC26 -> 212.52557 | AE26: =AD26/M26 -> 0.78445877 | AF26: =M26*N26 -> 32.5104 | AH26: =M26*0.052 -> 14.08784 | AI26: =AF26+AG26+AH26 -> 46.59824 | AJ26: =AD26+AI26 -> 259.12381 | AK26: =AJ26/M26 -> 0.95645877 | AL26: =M26-AJ26 -> 11.796191 | AM26: =AL26/M26 -> 0.043541235 | AN26: =M26/L26 -> 3.0031481
A27: 46244 | B27: NORMAL | C27: MMM1H28 | D27: JOI | E27: SC | F27: GRF | G27: MG | H27: BRASCOLA LTDA - | I27: 000330547 | J27: 1907.49 | K27: 25 | L27: 45 | M27: 221.92 | N27: 0.12 | O27: 44.38 | P27: =L27*0.34 -> 15.3 | Q27: 0 | R27: =L27*0.09 -> 4.05 | T27: 115.34 | U27: =T27/M27 -> 0.51973684 | V27: =O27+P27+Q27+R27+S27+T27 -> 179.07 | W27: =V27/M27 -> 0.8069124 | X27: =(L27*'RESULTADO DIRETO'!N$27)/6*3 -> 4.7038862 | Y27: =X27/M27 -> 0.021196315 | Z27: =(L27*'RESULTADO DIRETO'!N$15)/6*3 -> 4.2846078 | AA27: =Z27/M27 -> 0.019306992 | AB27: =(J27*0.01%)*7.38%+(J27*0.01%) -> 0.20482628 | AC27: =(J27*0.01%)*7.38%+(J27*0.01%) -> 0.20482628 | AD27: =V27+X27+Z27+AB27+AC27 -> 188.46815 | AE27: =AD27/M27 -> 0.84926166 | AF27: =M27*N27 -> 26.6304 | AH27: =M27*0.052 -> 11.53984 | AI27: =AF27+AG27+AH27 -> 38.17024 | AJ27: =AD27+AI27 -> 226.63839 | AK27: =AJ27/M27 -> 1.0212617 | AL27: =M27-AJ27 -> -4.7183866 | AM27: =AL27/M27 -> -0.021261655 | AN27: =M27/L27 -> 4.9315556
A28: 46244 | B28: NORMAL | C28: MMM1H28 | D28: JOI | E28: SC | F28: BHZ | G28: MG | H28: BRASCOLA LTDA - | I28: 000330550 | J28: 3046.21 | K28: 39 | L28: 69.12 | M28: 198.91 | N28: 0.12 | O28: 39.78 | P28: =L28*0.34 -> 23.5008 | Q28: =L28*0.18 -> 12.4416 | R28: =L28*0.14 -> 9.6768 | T28: 0 | U28: =T28/M28 -> 0 | V28: =O28+P28+Q28+R28+S28+T28 -> 85.3992 | W28: =V28/M28 -> 0.42933588 | X28: =(L28*'RESULTADO DIRETO'!N$27)/6*4 -> 9.633559 | Y28: =X28/M28 -> 0.048431748 | Z28: =(L28*'RESULTADO DIRETO'!N$15)/6*4 -> 8.7748767 | AA28: =Z28/M28 -> 0.044114809 | AB28: =(J28*0.01%)*7.38%+(J28*0.01%) -> 0.32710203 | AC28: =(J28*0.01%)*7.38%+(J28*0.01%) -> 0.32710203 | AD28: =V28+X28+Z28+AB28+AC28 -> 104.46184 | AE28: =AD28/M28 -> 0.52517138 | AF28: =M28*N28 -> 23.8692 | AH28: =M28*0.052 -> 10.34332 | AI28: =AF28+AG28+AH28 -> 34.21252 | AJ28: =AD28+AI28 -> 138.67436 | AK28: =AJ28/M28 -> 0.69717138 | AL28: =M28-AJ28 -> 60.23564 | AM28: =AL28/M28 -> 0.30282862 | AN28: =M28/L28 -> 2.8777488
A29: 46244 | B29: NORMAL | C29: MMM1H28 | D29: JOI | E29: SC | F29: TAM | G29: MG | H29: BRASCOLA LTDA - | I29: 000330554 | J29: 3165.42 | K29: 23 | L29: 103.632 | M29: 261.52 | N29: 0.12 | O29: 52.3 | P29: =L29*0.34 -> 35.23488 | Q29: =L29*0.18 -> 18.65376 | R29: =L29*0.14 -> 14.50848 | T29: 51.82 | U29: =T29/M29 -> 0.19814928 | V29: =O29+P29+Q29+R29+S29+T29 -> 172.51712 | W29: =V29/M29 -> 0.65967085 | X29: =(L29*'RESULTADO DIRETO'!N$27)/6*4 -> 14.443649 | Y29: =X29/M29 -> 0.055229614 | Z29: =(L29*'RESULTADO DIRETO'!N$15)/6*4 -> 13.156221 | AA29: =Z29/M29 -> 0.050306751 | AB29: =(J29*0.01%)*7.38%+(J29*0.01%) -> 0.3399028 | AC29: =(J29*0.01%)*7.38%+(J29*0.01%) -> 0.3399028 | AD29: =V29+X29+Z29+AB29+AC29 -> 200.7968 | AE29: =AD29/M29 -> 0.76780665 | AF29: =M29*N29 -> 31.3824 | AH29: =M29*0.052 -> 13.59904 | AI29: =AF29+AG29+AH29 -> 44.98144 | AJ29: =AD29+AI29 -> 245.77824 | AK29: =AJ29/M29 -> 0.93980665 | AL29: =M29-AJ29 -> 15.741764 | AM29: =AL29/M29 -> 0.060193348 | AN29: =M29/L29 -> 2.5235449
A30: 46244 | B30: NORMAL | C30: MMM1H28 | D30: JOI | E30: SC | F30: DCC | G30: MG | H30: BRASCOLA LTDA - | I30: 000330569 | J30: 8021.33 | K30: 1 | L30: 361.88 | M30: 683.1 | N30: 0.12 | O30: 136.62 | P30: =L30*0.34 -> 123.0392 | Q30: =L30*0.18 -> 65.1384 | T30: 239.09 | U30: =T30/M30 -> 0.35000732 | V30: =O30+P30+Q30+R30+S30+T30 -> 563.8876 | W30: =V30/M30 -> 0.82548324 | X30: =(L30*'RESULTADO DIRETO'!N$27)/6*3 -> 37.827608 | Y30: =X30/M30 -> 0.055376384 | Z30: =(L30*'RESULTADO DIRETO'!N$15)/6*3 -> 34.455864 | AA30: =Z30/M30 -> 0.050440439 | AB30: =(J30*0.01%)*7.38%+(J30*0.01%) -> 0.86133042 | AC30: =(J30*0.01%)*7.38%+(J30*0.01%) -> 0.86133042 | AD30: =V30+X30+Z30+AB30+AC30 -> 637.89373 | AE30: =AD30/M30 -> 0.93382189 | AF30: =M30*N30 -> 81.972 | AH30: =M30*0.052 -> 35.5212 | AI30: =AF30+AG30+AH30 -> 117.4932 | AJ30: =AD30+AI30 -> 755.38693 | AK30: =AJ30/M30 -> 1.1058219 | AL30: =M30-AJ30 -> -72.286932 | AM30: =AL30/M30 -> -0.10582189 | AN30: =M30/L30 -> 1.8876423
A31: 46244 | B31: NORMAL | C31: MMM1H28 | D31: JOI | E31: SC | F31: DCC | G31: MG | H31: BRASCOLA LTDA - | I31: 000330578 | J31: 1534.86 | K31: 8 | L31: 55.376 | M31: 228.9 | N31: 0.12 | O31: 45.78 | P31: =L31*0.34 -> 18.82784 | Q31: =L31*0.18 -> 9.96768 | T31: 80.12 | U31: =T31/M31 -> 0.35002184 | V31: =O31+P31+Q31+R31+S31+T31 -> 154.69552 | W31: =V31/M31 -> 0.67582141 | X31: =(L31*'RESULTADO DIRETO'!N$27)/6*3 -> 5.7884979 | Y31: =X31/M31 -> 0.025288326 | Z31: =(L31*'RESULTADO DIRETO'!N$15)/6*3 -> 5.2725431 | AA31: =Z31/M31 -> 0.023034264 | AB31: =(J31*0.01%)*7.38%+(J31*0.01%) -> 0.16481327 | AC31: =(J31*0.01%)*7.38%+(J31*0.01%) -> 0.16481327 | AD31: =V31+X31+Z31+AB31+AC31 -> 166.08619 | AE31: =AD31/M31 -> 0.72558404 | AF31: =M31*N31 -> 27.468 | AH31: =M31*0.052 -> 11.9028 | AI31: =AF31+AG31+AH31 -> 39.3708 | AJ31: =AD31+AI31 -> 205.45699 | AK31: =AJ31/M31 -> 0.89758404 | AL31: =M31-AJ31 -> 23.443012 | AM31: =AL31/M31 -> 0.10241596 | AN31: =M31/L31 -> 4.1335597
A32: 46244 | B32: NORMAL | C32: MMM1H28 | D32: JOI | E32: SC | F32: BHZ | G32: MG | H32: BRASCOLA LTDA - | I32: 000330638 | J32: 2198.63 | K32: 18 | L32: 103.176 | M32: 234.68 | N32: 0.12 | O32: 46.94 | P32: =L32*0.34 -> 35.07984 | Q32: =L32*0.18 -> 18.57168 | R32: =L32*0.14 -> 14.44464 | T32: 0 | U32: =T32/M32 -> 0 | V32: =O32+P32+Q32+R32+S32+T32 -> 115.03616 | W32: =V32/M32 -> 0.49018306 | X32: =(L32*'RESULTADO DIRETO'!N$27)/6*4 -> 14.380094 | Y32: =X32/M32 -> 0.061275327 | Z32: =(L32*'RESULTADO DIRETO'!N$15)/6*4 -> 13.098332 | AA32: =Z32/M32 -> 0.055813583 | AB32: =(J32*0.01%)*7.38%+(J32*0.01%) -> 0.23608889 | AC32: =(J32*0.01%)*7.38%+(J32*0.01%) -> 0.23608889 | AD32: =V32+X32+Z32+AB32+AC32 -> 142.98676 | AE32: =AD32/M32 -> 0.60928397 | AF32: =M32*N32 -> 28.1616 | AH32: =M32*0.052 -> 12.20336 | AI32: =AF32+AG32+AH32 -> 40.36496 | AJ32: =AD32+AI32 -> 183.35172 | AK32: =AJ32/M32 -> 0.78128397 | AL32: =M32-AJ32 -> 51.328277 | AM32: =AL32/M32 -> 0.21871603 | AN32: =M32/L32 -> 2.27456
A33: 46245 | B33: NORMAL | C33: MMM1H28 | D33: JOI | E33: SC | F33: VEA | G33: MG | H33: BRASCOLA LTDA - | I33: 000330671 | J33: 8285.41 | K33: 1 | L33: 411.044 | M33: 889.57 | N33: 0.12 | O33: 177.91 | P33: =L33*0.34 -> 139.75496 | Q33: =L33*0.18 -> 73.98792 | R33: =L33*0.06 -> 24.66264 | T33: 266.87 | U33: =T33/M33 -> 0.29999888 | V33: =O33+P33+Q33+R33+S33+T33 -> 683.18552 | W33: =V33/M33 -> 0.76799523 | X33: =(L33*'RESULTADO DIRETO'!N$27)/6*4 -> 57.289014 | Y33: =X33/M33 -> 0.064400794 | Z33: =(L33*'RESULTADO DIRETO'!N$15)/6*4 -> 52.182587 | AA33: =Z33/M33 -> 0.058660462 | AB33: =(J33*0.01%)*7.38%+(J33*0.01%) -> 0.88968733 | AC33: =(J33*0.01%)*7.38%+(J33*0.01%) -> 0.88968733 | AD33: =V33+X33+Z33+AB33+AC33 -> 794.4365 | AE33: =AD33/M33 -> 0.89305675 | AF33: =M33*N33 -> 106.7484 | AH33: =M33*0.052 -> 46.25764 | AI33: =AF33+AG33+AH33 -> 153.00604 | AJ33: =AD33+AI33 -> 947.44254 | AK33: =AJ33/M33 -> 1.0650568 | AL33: =M33-AJ33 -> -57.872536 | AM33: =AL33/M33 -> -0.065056753 | AN33: =M33/L33 -> 2.1641722
A34: 46245 | B34: NORMAL | C34: MMM1H28 | D34: JOI | E34: SC | F34: SET | G34: MG | H34: BRASCOLA LTDA - | I34: 000330687 | J34: 15746.58 | K34: 2 | L34: 829 | M34: 1345.16 | N34: 0.12 | O34: 269.03 | P34: =L34*0.34 -> 281.86 | Q34: =L34*0.18 -> 149.22 | R34: =L34*0.06 -> 49.74 | T34: 0 | U34: =T34/M34 -> 0 | V34: =O34+P34+Q34+R34+S34+T34 -> 749.85 | W34: =V34/M34 -> 0.55744298 | X34: =(L34*'RESULTADO DIRETO'!N$27)/6*4 -> 115.54138 | Y34: =X34/M34 -> 0.085894157 | Z34: =(L34*'RESULTADO DIRETO'!N$15)/6*4 -> 105.24266 | AA34: =Z34/M34 -> 0.078238025 | AB34: =(J34*0.01%)*7.38%+(J34*0.01%) -> 1.6908678 | AC34: =(J34*0.01%)*7.38%+(J34*0.01%) -> 1.6908678 | AD34: =V34+X34+Z34+AB34+AC34 -> 974.01578 | AE34: =AD34/M34 -> 0.72408917 | AF34: =M34*N34 -> 161.4192 | AH34: =M34*0.052 -> 69.94832 | AI34: =AF34+AG34+AH34 -> 231.36752 | AJ34: =AD34+AI34 -> 1205.3833 | AK34: =AJ34/M34 -> 0.89608917 | AL34: =M34-AJ34 -> 139.7767 | AM34: =AL34/M34 -> 0.10391083 | AN34: =M34/L34 -> 1.6226297
A35: 46245 | B35: NORMAL | C35: MMM1H28 | D35: JOI | E35: SC | F35: DCC | G35: MG | H35: BRASCOLA LTDA - | I35: 000330688 | J35: 3360 | K35: 12 | L35: 246 | M35: 479.19 | N35: 0.12 | O35: 95.84 | P35: =L35*0.34 -> 83.64 | Q35: =L35*0.18 -> 44.28 | T35: 167.72 | U35: =T35/M35 -> 0.3500073 | V35: =O35+P35+Q35+R35+S35+T35 -> 391.48 | W35: =V35/M35 -> 0.81696196 | X35: =(L35*'RESULTADO DIRETO'!N$27)/6*3 -> 25.714578 | Y35: =X35/M35 -> 0.053662593 | Z35: =(L35*'RESULTADO DIRETO'!N$15)/6*3 -> 23.422522 | AA35: =Z35/M35 -> 0.048879406 | AB35: =(J35*0.01%)*7.38%+(J35*0.01%) -> 0.3607968 | AC35: =(J35*0.01%)*7.38%+(J35*0.01%) -> 0.3607968 | AD35: =V35+X35+Z35+AB35+AC35 -> 441.33869 | AE35: =AD35/M35 -> 0.92100982 | AF35: =M35*N35 -> 57.5028 | AH35: =M35*0.052 -> 24.91788 | AI35: =AF35+AG35+AH35 -> 82.42068 | AJ35: =AD35+AI35 -> 523.75937 | AK35: =AJ35/M35 -> 1.0930098 | AL35: =M35-AJ35 -> -44.569374 | AM35: =AL35/M35 -> -0.093009817 | AN35: =M35/L35 -> 1.9479268
A36: 46245 | B36: NORMAL | C36: MMM1H28 | D36: JOI | E36: SC | F36: TRU | G36: MG | H36: BRASCOLA LTDA - | I36: 000330709 | J36: 1624.13 | K36: 15 | L36: 43.3 | M36: 220.78 | N36: 0.12 | O36: 44.16 | P36: =L36*0.34 -> 14.722 | R36: =L36*0.09 -> 3.897 | T36: 84.33 | U36: =T36/M36 -> 0.38196395 | V36: =O36+P36+Q36+R36+S36+T36 -> 147.109 | W36: =V36/M36 -> 0.66631488 | X36: =(L36*'RESULTADO DIRETO'!N$27)/6*3 -> 4.5261839 | Y36: =X36/M36 -> 0.020500878 | Z36: =(L36*'RESULTADO DIRETO'!N$15)/6*3 -> 4.1227448 | AA36: =Z36/M36 -> 0.018673543 | AB36: =(J36*0.01%)*7.38%+(J36*0.01%) -> 0.17439908 | AC36: =(J36*0.01%)*7.38%+(J36*0.01%) -> 0.17439908 | AD36: =V36+X36+Z36+AB36+AC36 -> 156.10673 | AE36: =AD36/M36 -> 0.70706915 | AF36: =M36*N36 -> 26.4936 | AH36: =M36*0.052 -> 11.48056 | AI36: =AF36+AG36+AH36 -> 37.97416 | AJ36: =AD36+AI36 -> 194.08089 | AK36: =AJ36/M36 -> 0.87906915 | AL36: =M36-AJ36 -> 26.699113 | AM36: =AL36/M36 -> 0.12093085 | AN36: =M36/L36 -> 5.0988453
A37: 46245 | B37: NORMAL | C37: MMM1H28 | D37: JOI | E37: SC | F37: BHZ | G37: MG | H37: BRASCOLA LTDA - | I37: 000330713 | J37: 3029.58 | K37: 40 | L37: 72 | M37: 228.81 | N37: 0.12 | O37: 45.76 | P37: =L37*0.34 -> 24.48 | Q37: =L37*0.18 -> 12.96 | R37: =L37*0.14 -> 10.08 | T37: 0 | U37: =T37/M37 -> 0 | V37: =O37+P37+Q37+R37+S37+T37 -> 93.28 | W37: =V37/M37 -> 0.40767449 | X37: =(L37*'RESULTADO DIRETO'!N$27)/6*4 -> 10.034957 | Y37: =X37/M37 -> 0.043857162 | Z37: =(L37*'RESULTADO DIRETO'!N$15)/6*4 -> 9.1404966 | AA37: =Z37/M37 -> 0.039947977 | AB37: =(J37*0.01%)*7.38%+(J37*0.01%) -> 0.3253163 | AC37: =(J37*0.01%)*7.38%+(J37*0.01%) -> 0.3253163 | AD37: =V37+X37+Z37+AB37+AC37 -> 113.10609 | AE37: =AD37/M37 -> 0.49432318 | AF37: =M37*N37 -> 27.4572 | AH37: =M37*0.052 -> 11.89812 | AI37: =AF37+AG37+AH37 -> 39.35532 | AJ37: =AD37+AI37 -> 152.46141 | AK37: =AJ37/M37 -> 0.66632318 | AL37: =M37-AJ37 -> 76.348593 | AM37: =AL37/M37 -> 0.33367682 | AN37: =M37/L37 -> 3.1779167
A38: 46246 | B38: NORMAL | C38: MMM1H28 | D38: JOI | E38: SC | F38: GRF | G38: MG | H38: BRASCOLA LTDA - | I38: 000330841 | J38: 2891.44 | K38: 20 | L38: 90.28 | M38: 268.39 | N38: 0.12 | O38: 53.68 | P38: =L38*0.34 -> 30.6952 | Q38: 0 | R38: =L38*0.09 -> 8.1252 | T38: 138.93 | U38: =T38/M38 -> 0.51764224 | V38: =O38+P38+Q38+R38+S38+T38 -> 231.4304 | W38: =V38/M38 -> 0.86229144 | X38: =(L38*'RESULTADO DIRETO'!N$27)/6*3 -> 9.4370411 | Y38: =X38/M38 -> 0.035161672 | Z38: =(L38*'RESULTADO DIRETO'!N$15)/6*3 -> 8.5958753 | AA38: =Z38/M38 -> 0.032027554 | AB38: =(J38*0.01%)*7.38%+(J38*0.01%) -> 0.31048283 | AC38: =(J38*0.01%)*7.38%+(J38*0.01%) -> 0.31048283 | AD38: =V38+X38+Z38+AB38+AC38 -> 250.08428 | AE38: =AD38/M38 -> 0.93179434 | AF38: =M38*N38 -> 32.2068 | AH38: =M38*0.052 -> 13.95628 | AI38: =AF38+AG38+AH38 -> 46.16308 | AJ38: =AD38+AI38 -> 296.24736 | AK38: =AJ38/M38 -> 1.1037943 | AL38: =M38-AJ38 -> -27.857362 | AM38: =AL38/M38 -> -0.10379434 | AN38: =M38/L38 -> 2.9728622
A39: 46246 | B39: NORMAL | C39: MMM1H28 | D39: JOI | E39: SC | F39: BHZ | G39: MG | H39: BRASCOLA LTDA - | I39: 000330818 | J39: 165.44 | K39: 1 | L39: 4.5 | M39: 128.5 | N39: 0.12 | O39: 25.7 | P39: =L39*0.34 -> 1.53 | Q39: =L39*0.18 -> 0.81 | R39: =L39*0.14 -> 0.63 | T39: 0 | U39: =T39/M39 -> 0 | V39: =O39+P39+Q39+R39+S39+T39 -> 28.67 | W39: =V39/M39 -> 0.22311284 | X39: =(L39*'RESULTADO DIRETO'!N$27)/6*4 -> 0.62718483 | Y39: =X39/M39 -> 0.0048808158 | Z39: =(L39*'RESULTADO DIRETO'!N$15)/6*4 -> 0.57128104 | AA39: =Z39/M39 -> 0.0044457668 | AB39: =(J39*0.01%)*7.38%+(J39*0.01%) -> 0.017764947 | AC39: =(J39*0.01%)*7.38%+(J39*0.01%) -> 0.017764947 | AD39: =V39+X39+Z39+AB39+AC39 -> 29.903996 | AE39: =AD39/M39 -> 0.23271592 | AF39: =M39*N39 -> 15.42 | AH39: =M39*0.052 -> 6.682 | AI39: =AF39+AG39+AH39 -> 22.102 | AJ39: =AD39+AI39 -> 52.005996 | AK39: =AJ39/M39 -> 0.40471592 | AL39: =M39-AJ39 -> 76.494004 | AM39: =AL39/M39 -> 0.59528408 | AN39: =M39/L39 -> 28.555556
A40: 46247 | B40: CORTESIA | C40: ARMAZEM | D40: JOI | E40: SC | F40: GRF | G40: MG | H40: BRASCOLA LTDA - | I40: 000329459 | J40: 0.01 | K40: 1 | L40: 5 | M40: 0.01 | N40: 0.12 | O40: 0.01 | P40: =L40*0.34 -> 1.7 | Q40: 0 | R40: =L40*0.09 -> 0.45 | T40: 20 | U40: =T40/M40 -> 2000 | V40: =O40+P40+Q40+R40+S40+T40 -> 22.16 | W40: =V40/M40 -> 2216 | X40: =(L40*'RESULTADO DIRETO'!N$27)/6*3 -> 0.52265403 | Y40: =X40/M40 -> 52.265403 | Z40: =(L40*'RESULTADO DIRETO'!N$15)/6*3 -> 0.47606753 | AA40: =Z40/M40 -> 47.606753 | AB40: =(J40*0.01%)*7.38%+(J40*0.01%) -> 1.0738e-06 | AC40: =(J40*0.01%)*7.38%+(J40*0.01%) -> 1.0738e-06 | AD40: =V40+X40+Z40+AB40+AC40 -> 23.158724 | AE40: =AD40/M40 -> 2315.8724 | AF40: =M40*N40 -> 0.0012 | AH40: =M40*0.052 -> 0.00052 | AI40: =AF40+AG40+AH40 -> 0.00172 | AJ40: =AD40+AI40 -> 23.160444 | AK40: =AJ40/M40 -> 2316.0444 | AL40: =M40-AJ40 -> -23.150444 | AM40: =AL40/M40 -> -2315.0444 | AN40: =M40/L40 -> 0.002
A41: 46247 | B41: NORMAL | C41: MMM1H28 | D41: JOI | E41: SC | F41: GVR | G41: MG | H41: BRASCOLA LTDA - | I41: 000330958 | J41: 2212.44 | K41: 6 | L41: 90 | M41: 582.7 | N41: 0.12 | O41: 116.54 | P41: =L41*0.34 -> 30.6 | Q41: =L41*0.18 -> 16.2 | R41: =L41*0.14 -> 12.6 | T41: 508.45 | U41: =T41/M41 -> 0.87257594 | V41: =O41+P41+Q41+R41+S41+T41 -> 684.39 | W41: =V41/M41 -> 1.1745152 | X41: =(L41*'RESULTADO DIRETO'!N$27)/6*4 -> 12.543697 | Y41: =X41/M41 -> 0.021526852 | Z41: =(L41*'RESULTADO DIRETO'!N$15)/6*4 -> 11.425621 | AA41: =Z41/M41 -> 0.019608067 | AB41: =(J41*0.01%)*7.38%+(J41*0.01%) -> 0.23757181 | AC41: =(J41*0.01%)*7.38%+(J41*0.01%) -> 0.23757181 | AD41: =V41+X41+Z41+AB41+AC41 -> 708.83446 | AE41: =AD41/M41 -> 1.2164655 | AF41: =M41*N41 -> 69.924 | AH41: =M41*0.052 -> 30.3004 | AI41: =AF41+AG41+AH41 -> 100.2244 | AJ41: =AD41+AI41 -> 809.05886 | AK41: =AJ41/M41 -> 1.3884655 | AL41: =M41-AJ41 -> -226.35886 | AM41: =AL41/M41 -> -0.38846552 | AN41: =M41/L41 -> 6.4744444
A42: 46251 | B42: NORMAL | C42: MMM1H28 | D42: JOI | E42: SC | F42: DCC | G42: MG | H42: BRASCOLA LTDA - | I42: 000331060 | J42: 5891.09 | K42: 1 | L42: 207.77 | M42: 437.1 | N42: 0.12 | O42: 87.42 | P42: =L42*0.34 -> 70.6418 | Q42: =L42*0.18 -> 37.3986 | T42: 152.99 | U42: =T42/M42 -> 0.35001144 | V42: =O42+P42+Q42+R42+S42+T42 -> 348.4504 | W42: =V42/M42 -> 0.79718691 | X42: =(L42*'RESULTADO DIRETO'!N$27)/6*3 -> 21.718365 | Y42: =X42/M42 -> 0.049687407 | Z42: =(L42*'RESULTADO DIRETO'!N$15)/6*3 -> 19.78251 | AA42: =Z42/M42 -> 0.045258545 | AB42: =(J42*0.01%)*7.38%+(J42*0.01%) -> 0.63258524 | AC42: =(J42*0.01%)*7.38%+(J42*0.01%) -> 0.63258524 | AD42: =V42+X42+Z42+AB42+AC42 -> 391.21645 | AE42: =AD42/M42 -> 0.89502733 | AF42: =M42*N42 -> 52.452 | AH42: =M42*0.052 -> 22.7292 | AI42: =AF42+AG42+AH42 -> 75.1812 | AJ42: =AD42+AI42 -> 466.39765 | AK42: =AJ42/M42 -> 1.0670273 | AL42: =M42-AJ42 -> -29.297646 | AM42: =AL42/M42 -> -0.06702733 | AN42: =M42/L42 -> 2.1037686
A43: 46251 | B43: NORMAL | C43: MMM1H28 | D43: JOI | E43: SC | F43: VEA | G43: MG | H43: BRASCOLA LTDA - | I43: 000331042 | J43: 2053.74 | K43: 18 | L43: 64.202 | M43: 249.74 | N43: 0.12 | O43: 49.95 | P43: =L43*0.34 -> 21.82868 | Q43: =L43*0.18 -> 11.55636 | R43: =L43*0.06 -> 3.85212 | T43: 74.92 | U43: =T43/M43 -> 0.29999199 | V43: =O43+P43+Q43+R43+S43+T43 -> 162.10716 | W43: =V43/M43 -> 0.64910371 | X43: =(L43*'RESULTADO DIRETO'!N$27)/6*4 -> 8.9481157 | Y43: =X43/M43 -> 0.035829726 | Z43: =(L43*'RESULTADO DIRETO'!N$15)/6*4 -> 8.15053 | AA43: =Z43/M43 -> 0.032636062 | AB43: =(J43*0.01%)*7.38%+(J43*0.01%) -> 0.2205306 | AC43: =(J43*0.01%)*7.38%+(J43*0.01%) -> 0.2205306 | AD43: =V43+X43+Z43+AB43+AC43 -> 179.64687 | AE43: =AD43/M43 -> 0.71933558 | AF43: =M43*N43 -> 29.9688 | AH43: =M43*0.052 -> 12.98648 | AI43: =AF43+AG43+AH43 -> 42.95528 | AJ43: =AD43+AI43 -> 222.60215 | AK43: =AJ43/M43 -> 0.89133558 | AL43: =M43-AJ43 -> 27.137853 | AM43: =AL43/M43 -> 0.10866442 | AN43: =M43/L43 -> 3.88991
A44: 46251 | B44: NORMAL | C44: MMM1H28 | D44: JOI | E44: SC | F44: GVR | G44: MG | H44: BRASCOLA LTDA - | I44: 000331000 | J44: 2266.61 | K44: 21 | L44: 78.454 | M44: 264.83 | N44: 0.12 | O44: 52.97 | P44: =L44*0.34 -> 26.67436 | Q44: =L44*0.18 -> 14.12172 | R44: =L44*0.14 -> 10.98356 | T44: 97.19 | U44: =T44/M44 -> 0.36699014 | V44: =O44+P44+Q44+R44+S44+T44 -> 201.93964 | W44: =V44/M44 -> 0.76252554 | X44: =(L44*'RESULTADO DIRETO'!N$27)/6*4 -> 10.93448 | Y44: =X44/M44 -> 0.041288675 | Z44: =(L44*'RESULTADO DIRETO'!N$15)/6*4 -> 9.9598405 | AA44: =Z44/M44 -> 0.03760843 | AB44: =(J44*0.01%)*7.38%+(J44*0.01%) -> 0.24338858 | AC44: =(J44*0.01%)*7.38%+(J44*0.01%) -> 0.24338858 | AD44: =V44+X44+Z44+AB44+AC44 -> 223.32074 | AE44: =AD44/M44 -> 0.84326072 | AF44: =M44*N44 -> 31.7796 | AH44: =M44*0.052 -> 13.77116 | AI44: =AF44+AG44+AH44 -> 45.55076 | AJ44: =AD44+AI44 -> 268.8715 | AK44: =AJ44/M44 -> 1.0152607 | AL44: =M44-AJ44 -> -4.0414975 | AM44: =AL44/M44 -> -0.015260724 | AN44: =M44/L44 -> 3.3756086
A45: 46251 | B45: NORMAL | C45: MMM1H28 | D45: JOI | E45: SC | F45: BHZ | G45: MG | H45: BRASCOLA LTDA - | I45: 000331020 | J45: 2106.3 | K45: 40 | L45: 126.4 | M45: 265.92 | N45: 0.12 | O45: 53.18 | P45: =L45*0.34 -> 42.976 | Q45: =L45*0.18 -> 22.752 | R45: =L45*0.14 -> 17.696 | T45: 0 | U45: =T45/M45 -> 0 | V45: =O45+P45+Q45+R45+S45+T45 -> 136.604 | W45: =V45/M45 -> 0.51370337 | X45: =(L45*'RESULTADO DIRETO'!N$27)/6*4 -> 17.616925 | Y45: =X45/M45 -> 0.066248966 | Z45: =(L45*'RESULTADO DIRETO'!N$15)/6*4 -> 16.04665 | AA45: =Z45/M45 -> 0.060343899 | AB45: =(J45*0.01%)*7.38%+(J45*0.01%) -> 0.22617449 | AC45: =(J45*0.01%)*7.38%+(J45*0.01%) -> 0.22617449 | AD45: =V45+X45+Z45+AB45+AC45 -> 170.71992 | AE45: =AD45/M45 -> 0.64199731 | AF45: =M45*N45 -> 31.9104 | AH45: =M45*0.052 -> 13.82784 | AI45: =AF45+AG45+AH45 -> 45.73824 | AJ45: =AD45+AI45 -> 216.45816 | AK45: =AJ45/M45 -> 0.81399731 | AL45: =M45-AJ45 -> 49.461836 | AM45: =AL45/M45 -> 0.18600269 | AN45: =M45/L45 -> 2.1037975
A46: 46253 | B46: NORMAL | C46: MMM1H28 | D46: JOI | E46: SC | F46: TAM | G46: MG | H46: BRASCOLA LTDA - | I46: 000331196 | J46: 6233.01 | K46: 24 | L46: 51.888 | M46: 254.52 | N46: 0.12 | O46: 50.9 | P46: =L46*0.34 -> 17.64192 | Q46: =L46*0.18 -> 9.33984 | R46: =L46*0.14 -> 7.26432 | T46: 42 | U46: =T46/M46 -> 0.1650165 | V46: =O46+P46+Q46+R46+S46+T46 -> 127.14608 | W46: =V46/M46 -> 0.49955241 | X46: =(L46*'RESULTADO DIRETO'!N$27)/6*4 -> 7.2318592 | Y46: =X46/M46 -> 0.028413717 | Z46: =(L46*'RESULTADO DIRETO'!N$15)/6*4 -> 6.5872512 | AA46: =Z46/M46 -> 0.025881075 | AB46: =(J46*0.01%)*7.38%+(J46*0.01%) -> 0.66930061 | AC46: =(J46*0.01%)*7.38%+(J46*0.01%) -> 0.66930061 | AD46: =V46+X46+Z46+AB46+AC46 -> 142.30379 | AE46: =AD46/M46 -> 0.55910652 | AF46: =M46*N46 -> 30.5424 | AH46: =M46*0.052 -> 13.23504 | AI46: =AF46+AG46+AH46 -> 43.77744 | AJ46: =AD46+AI46 -> 186.08123 | AK46: =AJ46/M46 -> 0.73110652 | AL46: =M46-AJ46 -> 68.438768 | AM46: =AL46/M46 -> 0.26889348 | AN46: =M46/L46 -> 4.9051804
A47: 46253 | B47: NORMAL | C47: MMM1H28 | D47: JOI | E47: SC | F47: STJ | G47: MG | H47: BRASCOLA LTDA - | I47: 000331180 | J47: 2269.38 | K47: 18 | L47: 79.274 | M47: 321.66 | N47: 0.12 | O47: 64.33 | P47: =L47*0.34 -> 26.95316 | Q47: =L47*0.18 -> 14.26932 | R47: 0 | T47: 96 | U47: =T47/M47 -> 0.29845178 | V47: =O47+P47+Q47+R47+S47+T47 -> 201.55248 | W47: =V47/M47 -> 0.62660101 | X47: =(L47*'RESULTADO DIRETO'!N$27)/6*4 -> 11.048767 | Y47: =X47/M47 -> 0.03434921 | Z47: =(L47*'RESULTADO DIRETO'!N$15)/6*4 -> 10.063941 | AA47: =Z47/M47 -> 0.031287511 | AB47: =(J47*0.01%)*7.38%+(J47*0.01%) -> 0.24368602 | AC47: =(J47*0.01%)*7.38%+(J47*0.01%) -> 0.24368602 | AD47: =V47+X47+Z47+AB47+AC47 -> 223.15256 | AE47: =AD47/M47 -> 0.69375291 | AF47: =M47*N47 -> 38.5992 | AH47: =M47*0.052 -> 16.72632 | AI47: =AF47+AG47+AH47 -> 55.32552 | AJ47: =AD47+AI47 -> 278.47808 | AK47: =AJ47/M47 -> 0.86575291 | AL47: =M47-AJ47 -> 43.181921 | AM47: =AL47/M47 -> 0.13424709 | AN47: =M47/L47 -> 4.0575725
A48: 46253 | B48: CARGA FECHADA | C48: MMM1H28 | D48: JOI | E48: SC | F48: FEC | G48: MG | H48: BRASCOLA LTDA - | I48: 000331080 | J48: 82426.88 | K48: 8 | L48: 3982.8 | M48: 6998.14 | N48: 0.12 | O48: 1399.63 | P48: =L48*0.34 -> 1354.152 | Q48: =L48*0.18 -> 716.904 | R48: =L48*0.14 -> 557.592 | T48: 0 | U48: =T48/M48 -> 0 | V48: =O48+P48+Q48+R48+S48+T48 -> 4028.278 | W48: =V48/M48 -> 0.57562124 | X48: =(L48*'RESULTADO DIRETO'!N$27)/6*4 -> 555.10039 | Y48: =X48/M48 -> 0.079321132 | Z48: =(L48*'RESULTADO DIRETO'!N$15)/6*4 -> 505.6218 | AA48: =Z48/M48 -> 0.072250884 | AB48: =(J48*0.01%)*7.38%+(J48*0.01%) -> 8.8509984 | AC48: =(J48*0.01%)*7.38%+(J48*0.01%) -> 8.8509984 | AD48: =V48+X48+Z48+AB48+AC48 -> 5106.7022 | AE48: =AD48/M48 -> 0.72972278 | AF48: =M48*N48 -> 839.7768 | AH48: =M48*0.052 -> 363.90328 | AI48: =AF48+AG48+AH48 -> 1203.6801 | AJ48: =AD48+AI48 -> 6310.3823 | AK48: =AJ48/M48 -> 0.90172278 | AL48: =M48-AJ48 -> 687.75773 | AM48: =AL48/M48 -> 0.098277218 | AN48: =M48/L48 -> 1.7570905
