Workbook

Sheet BASE
B19: CLIENTE: | C19: Central do Frete
B20: CNPJ: | C20: 05855974000170
B21: LOCAL REMETENTE: | C21: São Paulo
B22: TIPO DE FRETE: | C22: CIF

Sheet RESULTADO DIRETO
B3: COMPETENCIA | D3: TOTAL GERAL | L3: CUSTOS | P3: PESO 2024 | S3: 70449976
B4: FRETE | G4: CUSTOS | L4: Desp. Operacional | N4: 10313790 | P4: DESPESA ADMINISTRATIVA 2024 | S4: 15734290
B5: VALOR | D5: =VLOOKUP('RESULTADO DIRETO'!D3,FONTES!B5:I15,5,) -> 77673.43 | G5: Custo Operacional | I5: =VLOOKUP(D3,FONTES!B5:I15,8,) -> 37010.735 | L5: Carga e Descarga | N5: 4671731 | P5: RATEIO | S5: =S4/S3 -> 0.22333989
B6: Receita por kg | D6: =D5/D24 -> 2.3926233 | G6: Focal (agendamento) | L6: Motorista | N6: -2454302.6
B7: Tem Subst.Trib.? | G7: Seguro Acidente (0,014%) com iof | I7: =($D$25*0.01%)*7.38%+($D$25*0.01%) -> 122.27045 | L7: TOTAL | N7: =SUM(N4:N6) -> 12531218 | P7: FATURAMENTO | S7: 85634757
B8: Aliq. | C8: 0.12 | D8: =VLOOKUP('RESULTADO DIRETO'!D3,FONTES!B5:I15,3,) -> 9075.3001 | E8: =IF(D7=$A$2,D5*C8,$A$11) -> 9320.8116 | G8: Seguro Roubo (0,014%) com iof | I8: =($D$25*0.01%)*7.38%+($D$25*0.01%) -> 122.27045 | L8: Desp. Frota | N8: 1301293 | P8: Avarias S/ | S8: 600078
G9: Custo Indenizações | L9: Diárias | N9: -306752 | P9: FATURAMENTO | S9: =S8/S7 -> 0.0070074117
B10: IMPOSTOS | G10: Custo Ajudantes extras/entregas | L10: Lavação | N10: -54194
B11: TRIBUTO | C11: ALÍQUOTA | D11: VALOR | G11: Comissão Comercial/Freelancer | L11: Sinistro | N11: -37032
B12: ICMS | D12: =VLOOKUP(D3,FONTES!B5:I15,3,) -> 9075.3001 | F12: =N27 -> 0.20906161 | G12: RATEIO DESP. ADMINIST./apoio op | I12: ='CUSTO NOVA'!X214 -> 4052.9692 | J12: =I12/D5 -> 0.052179609 | L12: Reboque | N12: -16900
B13: INSS DESON. 1,2 | F13: =N15 -> 0.19042701 | G13: RATEIO DESP. CLT operacional | I13: ='CUSTO NOVA'!Z214 -> 2820.1539 | J13: =I13/D5 -> 0.036307833 | L13: Gerenciamento de Risco | N13: -2055
B14: ISS | C14: 0 | D14: =IF(D5="","",(D5*C14)) -> 0 | G14: TOTAL CUSTOS | I14: =SUM(I5:I13) -> 44128.399 | J14: =SUM(J12:J13) -> 0.088487442 | L14: TOTAL | N14: =SUM(N8:N13) -> 884360
B15: PIS | C15: 0.052 | D15: =D5*C15 -> 4039.0184 | L15: RATEIO | N15: =(N7+N14)/S3 -> 0.19042701
B16: COFINS | G16: APURAÇÃO DO RESULTADO
B17: IRPJ | G17: VALOR BRUTO | I17: =D5 -> 77673.43
B18: CSLL | G18: ( - ) IMPOSTOS | I18: =D19*-1 -> -13114.318
B19: TOTAL TRIBITOS | D19: =SUM(D12:D18) -> 13114.318 | G19: ( - ) CUSTOS | I19: =I14*-1 -> -44128.399
L20: CUSTOS
B21: VALOR RECEITA LIQUIDA: | D21: =D5-D19 -> 64559.112 | L21: Despesa Adminstrativa | N21: 15734290
G22: VALOR LIQUIDO | I22: =SUM(I17:I21) -> 20430.712 | L22: Boletos | N22: 76586
B23: INFORMAÇÕES EXTRAS | G23: % | I23: =I22*100%/I17 -> 0.26303348 | L23: Target | N23: 12917
B24: Tonelada | D24: =VLOOKUP(D3,FONTES!B5:I15,4,) -> 32463.71 | L24: Multa Processo RJ | N24: -306546.52
B25: Valor de NF | D25: =VLOOKUP(D3,FONTES!B5:I15,7,) -> 1138670.6 | G25: QTD CTRC | H25: 82 | I25: =SUM(I26:I27) -> 1 | L25: Manutenções/Instalações Predial/Balanço Patrimonial | N25: -788861
B26: Redespacho | D26: =VLOOKUP(D3,FONTES!B5:I15,6,) -> 16765.91 | E26: =D26/D5 -> 0.21585128 | G26: Bases | H26: 16 | I26: =H26/H25 -> 0.19512195 | L26: TOTAL | N26: =SUM(N21:N25) -> 14728385
G27: Redespachos | H27: 66 | I27: =H27/H25 -> 0.80487805 | L27: RATEIO | N27: =N26/S3 -> 0.20906161
B28: Fat. cte Redespacho | D28: 21962.954 | E28: =D26/D28 -> 0.76337225
B29: Excluído por estar inclusa no Rateio Desp. ADM/OP
B30: Tonelada

Sheet FONTES
B5: COMPETENCIA | C5: TOTAL CTRC | D5: IMPOSTOS | E5: TONELADA | F5: FRETE | G5: REDESPACHO | H5: VALOR MERCADORIA | I5: TOTAL
B6: jan | C6: ='CUSTO NOVA'!I214 -> 82 | D6: ='CUSTO NOVA'!AF214 -> 9075.3001 | E6: ='CUSTO NOVA'!L214 -> 32463.71 | F6: ='CUSTO NOVA'!M214 -> 77673.43 | G6: ='CUSTO NOVA'!T214 -> 16765.91 | H6: ='CUSTO NOVA'!J214 -> 1138670.6 | I6: ='CUSTO NOVA'!V214 -> 37010.735
B7: feb
B8: mar
B9: apr
B10: may
B11: jun
B12: jul
B13: aug
B14: sep
B15: Total Geral | C15: =SUM(C6:C14) -> 82 | D15: =SUM(D6:D14) -> 9075.3001 | E15: =SUM(E6:E14) -> 32463.71 | F15: =SUM(F6:F14) -> 77673.43 | G15: =SUM(G6:G14) -> 16765.91 | H15: =SUM(H6:H14) -> 1138670.6 | I15: =SUM(I6:I14) -> 37010.735

Sheet RESULTADO REDESPACHO

Sheet BASE DADOS
A1: 1 | B1: Serie/Numero CTRC | C1: Tipo do Documento | D1: Praca Expedidora | E1: Unidade Emissora | F1: Data de Emissao | G1: Placa de Coleta | H1: Chave CT-e | I1: CNPJ Remetente | J1: Cliente Remetente | K1: Endereco do Remetente | L1: Bairro do Remetente | M1: Setor de Coleta | N1: Cidade do Remetente | O1: UF do Remetente | P1: CEP do Remetente | Q1: CNPJ Expedidor | R1: Cliente Expedidor | S1: Cidade do Expedidor | T1: UF do Expedidor | U1: CNPJ Pagador | V1: Cliente Pagador | W1: Endereco do Pagador | X1: Bairro do Pagador | Y1: Cidade do Pagador | Z1: UF do Pagador | AA1: Fone do Pagador | AB1: Segmento do Pagador | AC1: CNPJ Destinatario | AD1: Cliente Destinatario | AE1: Setor de Destino | AF1: Praca de Destino | AG1: Cidade do Destinatario | AH1: UF do Destinatario | AI1: CNPJ Recebedor | AJ1: Cliente Recebedor | AK1: Cidade de Entrega | AL1: UF de Entrega | AM1: Unidade Receptora | AN1: Numero da Nota Fiscal | AO1: Peso Real em Kg | AP1: Cubagem em m3 | AQ1: Quantidade de Volumes | AR1: Quantidade de Pares | AS1: Tipo do Frete | AT1: Tipo de Baixa | AU1: Data da Liquidacao | AV1: Valor Liquidado | AW1: Mercadoria | AX1: Especie | AY1: Valor da Mercadoria | AZ1: Tipo de Calculo | BA1: Tabela de Calculo | BB1: Valor do Frete | BC1: Valor do Frete sem ICMS | BD1: Base Calculo ICMS/ISS | BE1: Valor do ICMS | BF1: Aliquota | BG1: Valor do ISS | BH1: Peso Calculado em Kg | BI1: Frete Peso | BJ1: Frete Valor | BK1: Despacho | BL1: CAT | BM1: ITR | BN1: GRIS | BO1: Pedagio | BP1: TAS | BQ1: TDA | BR1: Suframa | BS1: Dev Canhoto NF | BT1: Reembolso | BU1: Outros | BV1: Coleta | BW1: TDC | BX1: TDE | BY1: TAR | BZ1: TRT | CA1: POS | CB1: Praca Comercial Origem | CC1: Praca Comercial Destino | CD1: Frete NTC | CE1: Frete Entrega | CF1: Separacao | CG1: Capatazia | CH1: Veiculo Dedicado | CI1: Paletizacao | CJ1: CO2 | CK1: RDC | CL1: CTRC Origem | CM1: CTe Origem | CN1: Valor do Frete do CTRC Origem | CO1: TDC CTRC Origem | CP1: TDE CTRC Origem | CQ1: TAR CTRC Origem | CR1: TRT CTRC Origem | CS1: TDA CTRC Origem | CT1: Valor do ICMS origem | CU1: Valor da Comissao de Expedicao | CV1: Rel de Comissao de Expedicao | CW1: Valor da Comissao Exp Creditada | CX1: Fatura do Subcon Exp Conferida Opcao 607 | CY1: Valor da Comissao de Recepcao | CZ1: Rel de Comissao de Recepcao | DA1: Valor da Comissao Rec Creditada | DB1: Fatura do Subcon Rec Conferida Opcao 607 | DE1: Adicional de Frete | DF1: ABC Pagador | DG1: UF origem da prestacao | DH1: Cidade origem da prestacao | DI1: IE cliente remetente | DJ1: Fone Remetente | DK1: Agendamento | DL1: Unidade Responsavel Pagador | DM1: Imposto Repassado
A2: 2 | B2: BHZ267694-0 | C2: NORMAL | D2: BHZP | E2: BHZ | F2: 46255 | G2: DJB4058 | H2: 31260803098929000355570010003892621003772782 | I2: 21260419000152 | J2: ESFERA ESTAMPARIA DE FERRO E A | K2: RODOVIA MG 431 S/N KM 45,177 | L2: SANTA MONICA | M2: 001 | N2: ITAUNA | O2: MG | P2: 35681-247 | Q2: 21260419000152 | R2: ESFERA ESTAMPARIA DE FERRO E A | S2: ITAUNA | T2: MG | U2: 05094003000155 | V2: COLSON DO BRASIL LTDA | W2: RUA DAS PALMEIRAS 350 | X2: CAPELA VELHA | Y2: ARAUCARIA | Z2: PR | AA2: (41 ) 38887555 | AC2: 05094003000155 | AD2: COLSON DO BRASIL LTDA | AE2: 002 SETOR I- FROTA | AF2: CTBP | AG2: ARAUCARIA | AH2: PR | AI2: 05094003000155 | AJ2: COLSON DO BRASIL LTDA | AK2: ARAUCARIA | AL2: PR | AM2: CTB | AN2: 000147931 | AO2: 47 | AP2: 0 | AQ2: 3 | AR2: 0 | AS2: FP | AT2: LIQUIDADO | AU2: 46267 | AV2: 172.2 | AW2: 001-DIVERSOS | AX2: 054-PNEUS E CAMARAS DE AR | AY2: 1057.88 | AZ2: COMBINADA | BA2: CO3365294 | BB2: 172.2 | BC2: 151.54 | BD2: 172.2 | BE2: 20.66 | BF2: 0.12 | BG2: 0 | BH2: 47 | BI2: 110.1 | BJ2: 0 | BK2: 17 | BL2: 0 | BM2: 9.76 | BN2: 2.25 | BO2: 5.5 | BP2: 3.23 | BQ2: 0 | BR2: 0 | BS2: 0 | BT2: 0 | BU2: 0 | BV2: 0 | BW2: 0 | BX2: 0 | BY2: 0 | BZ2: 0 | CA2: 3.7 | CB2: RWNI | CC2: CTBP | CD2: 378.38 | CE2: 0 | CF2: 0 | CG2: 0 | CH2: 0 | CI2: 0 | CJ2: 0 | CK2: 0 | CN2: 0 | CO2: 0 | CP2: 0 | CQ2: 0 | CR2: 0 | CS2: 0 | CT2: 0 | CU2: 15 | CV2: MAPA: 162 | CW2: 0 | CY2: 12 | CZ2: MAPA: 162 | DA2: 0 | DE2: 0 | DF2: A. | DG2: MG | DH2: ITAUNA | DI2: 3380715350028 | DJ2: (37 ) 32494800 | DK2: 0 | DL2: CTB | DM2: 20.66
A3: 2 | B3: CTB070615-9 | C3: NORMAL | D3: CTBP | E3: CTB | F3: 46237 | G3: DQB8989 | H3: 41260803098929000606570010000715071003657121 | I3: 05094003000155 | J3: COLSON DO BRASIL LTDA | K3: RUA DAS PALMEIRAS 350 | L3: CAPELA VELHA | M3: 002 | N3: ARAUCARIA | O3: PR | P3: 83705-500 | Q3: 05094003000155 | R3: COLSON DO BRASIL LTDA | S3: ARAUCARIA | T3: PR | U3: 05094003000155 | V3: COLSON DO BRASIL LTDA | W3: RUA DAS PALMEIRAS 350 | X3: CAPELA VELHA | Y3: ARAUCARIA | Z3: PR | AA3: (41 ) 38887555 | AC3: 23476033000884 | AD3: BMB MATERIAL DE CONSTRUCAO S.A. | AE3: RIO RIO DE JANEIRO | AF3: RJOP | AG3: RIO DE JANEIRO | AH3: RJ | AI3: 23476033000884 | AJ3: BMB MATERIAL DE CONSTRUCAO S.A. | AK3: RIO DE JANEIRO | AL3: RJ | AM3: RJO | AN3: 000188725 | AO3: 93.93 | AP3: 0 | AQ3: 8 | AR3: 0 | AS3: CP | AT3: LIQUIDADO | AU3: 46253 | AV3: 460.4 | AW3: 001-DIVERSOS | AX3: 001-DIVERSOS | AY3: 3892.48 | AZ3: COMBINADA | BA3: CO3365267 | BB3: 460.4 | BC3: 405.15 | BD3: 460.4 | BE3: 55.25 | BF3: 0.12 | BG3: 0 | BH3: 93.93 | BI3: 100.2 | BJ3: 0 | BK3: 17 | BL3: 0 | BM3: 9.76 | BN3: 5.84 | BO3: 5.5 | BP3: 3.23 | BQ3: 0 | BR3: 0 | BS3: 0 | BT3: 0 | BU3: 0 | BV3: 0 | BW3: 0 | BX3: 250 | BY3: 0 | BZ3: 0 | CA3: 13.62 | CB3: CTBP | CC3: RJOP | CD3: 400.59 | CE3: 0 | CF3: 0 | CG3: 0 | CH3: 0 | CI3: 0 | CJ3: 0 | CK3: 0 | CN3: 0 | CO3: 0 | CP3: 0 | CQ3: 0 | CR3: 0 | CS3: 0 | CT3: 0 | CU3: 14.09 | CV3: MAPA: 161 | CW3: 0 | CY3: 18 | CZ3: MAPA: 161 | DA3: 0 | DE3: 0 | DF3: A. | DG3: PR | DH3: ARAUCARIA | DI3: 9026067267 | DJ3: (41 ) 38887555 | DK3: 0 | DL3: CTB | DM3: 55.25
A4: 2 | B4: CTB070616-7 | C4: NORMAL | D4: CTBP | E4: CTB | F4: 46237 | G4: DQB8989 | H4: 41260803098929000606570010000715081003657137 | I4: 05094003000155 | J4: COLSON DO BRASIL LTDA | K4: RUA DAS PALMEIRAS 350 | L4: CAPELA VELHA | M4: 002 | N4: ARAUCARIA | O4: PR | P4: 83705-500 | Q4: 05094003000155 | R4: COLSON DO BRASIL LTDA | S4: ARAUCARIA | T4: PR | U4: 05094003000155 | V4: COLSON DO BRASIL LTDA | W4: RUA DAS PALMEIRAS 350 | X4: CAPELA VELHA | Y4: ARAUCARIA | Z4: PR | AA4: (41 ) 38887555 | AC4: 23476033000701 | AD4: BMB MATERIAL DE CONSTRUCAO S.A | AE4: SGN SAO GONACALO | AF4: RJOP | AG4: SAO GONCALO | AH4: RJ | AI4: 23476033000701 | AJ4: BMB MATERIAL DE CONSTRUCAO S.A | AK4: SAO GONCALO | AL4: RJ | AM4: RJO | AN4: 000188531 | AO4: 85.965 | AP4: 0 | AQ4: 7 | AR4: 0 | AS4: CP | AT4: LIQUIDADO | AU4: 46253 | AV4: 452.75 | AW4: 001-DIVERSOS | AX4: 054-PNEUS E CAMARAS DE AR | AY4: 2546.66 | AZ4: COMBINADA | BA4: CO3365267 | BB4: 452.75 | BC4: 398.42 | BD4: 452.75 | BE4: 54.33 | BF4: 0.12 | BG4: 0 | BH4: 85.965 | BI4: 100.2 | BJ4: 0 | BK4: 17 | BL4: 0 | BM4: 9.76 | BN4: 3.82 | BO4: 5.5 | BP4: 3.23 | BQ4: 0 | BR4: 0 | BS4: 0 | BT4: 0 | BU4: 0 | BV4: 0 | BW4: 0 | BX4: 250 | BY4: 0 | BZ4: 0 | CA4: 8.91 | CB4: CTBP | CC4: RJOP | CD4: 383.46 | CE4: 0 | CF4: 0 | CG4: 0 | CH4: 0 | CI4: 0 | CJ4: 0 | CK4: 0 | CN4: 0 | CO4: 0 | CP4: 0 | CQ4: 0 | CR4: 0 | CS4: 0 | CT4: 0 | CU4: 12.89 | CV4: MAPA: 161 | CW4: 0 | CY4: 18 | CZ4: MAPA: 161 | DA4: 0 | DE4: 0 | DF4: A. | DG4: PR | DH4: ARAUCARIA | DI4: 9026067267 | DJ4: (41 ) 38887555 | DK4: 0 | DL4: CTB | DM4: 54.33
A5: 2 | B5: CTB070617-5 | C5: NORMAL | D5: CTBP | E5: CTB | F5: 46237 | G5: DQB8989 | H5: 41260803098929000606570010000715101003657151 | I5: 05094003000155 | J5: COLSON DO BRASIL LTDA | K5: RUA DAS PALMEIRAS 350 | L5: CAPELA VELHA | M5: 002 | N5: ARAUCARIA | O5: PR | P5: 83705-500 | Q5: 05094003000155 | R5: COLSON DO BRASIL LTDA | S5: ARAUCARIA | T5: PR | U5: 05094003000155 | V5: COLSON DO BRASIL LTDA | W5: RUA DAS PALMEIRAS 350 | X5: CAPELA VELHA | Y5: ARAUCARIA | Z5: PR | AA5: (41 ) 38887555 | AC5: 25197980000195 | AD5: TRIUNFO SERVICOS PARA CONSTRUCAO CI | AE5: RIO RIO DE JANEIRO | AF5: RJOP | AG5: RIO DE JANEIRO | AH5: RJ | AI5: 25197980000195 | AJ5: TRIUNFO SERVICOS PARA CONSTRUCAO CI | AK5: RIO DE JANEIRO | AL5: RJ | AM5: RJO | AN5: 000188697 | AO5: 249 | AP5: 0 | AQ5: 15 | AR5: 0 | AS5: CP | AT5: LIQUIDADO | AU5: 46253 | AV5: 334.93 | AW5: 001-DIVERSOS | AX5: 001-DIVERSOS | AY5: 4824.67 | AZ5: COMBINADA | BA5: CO3365267 | BB5: 334.93 | BC5: 294.74 | BD5: 334.93 | BE5: 40.19 | BF5: 0.12 | BG5: 0 | BH5: 249 | BI5: 224.12 | BJ5: 0 | BK5: 17 | BL5: 0 | BM5: 9.76 | BN5: 7.24 | BO5: 16.5 | BP5: 3.23 | BQ5: 0 | BR5: 0 | BS5: 0 | BT5: 0 | BU5: 0 | BV5: 0 | BW5: 0 | BX5: 0 | BY5: 0 | BZ5: 0 | CA5: 16.89 | CB5: CTBP | CC5: RJOP | CD5: 535.2 | CE5: 0 | CF5: 0 | CG5: 0 | CH5: 0 | CI5: 0 | CJ5: 0 | CK5: 0 | CN5: 0 | CO5: 0 | CP5: 0 | CQ5: 0 | CR5: 0 | CS5: 0 | CT5: 0 | CU5: 37.35 | CV5: MAPA: 161 | CW5: 0 | CY5: 44.82 | CZ5: MAPA: 161 | DA5: 0 | DE5: 0 | DF5: A. | DG5: PR | DH5: ARAUCARIA | DI5: 9026067267 | DJ5: (41 ) 38887555 | DK5: 0 | DL5: CTB | DM5: 40.19
A6: 2 | B6: CTB070618-3 | C6: NORMAL | D6: CTBP | E6: CTB | F6: 46237 | G6: DQB8989 | H6: 41260803098929000606570010000715121003657172 | I6: 05094003000155 | J6: COLSON DO BRASIL LTDA | K6: RUA DAS PALMEIRAS 350 | L6: CAPELA VELHA | M6: 002 | N6: ARAUCARIA | O6: PR | P6: 83705-500 | Q6: 05094003000155 | R6: COLSON DO BRASIL LTDA | S6: ARAUCARIA | T6: PR | U6: 05094003000155 | V6: COLSON DO BRASIL LTDA | W6: RUA DAS PALMEIRAS 350 | X6: CAPELA VELHA | Y6: ARAUCARIA | Z6: PR | AA6: (41 ) 38887555 | AC6: 41675052000226 | AD6: NOVA VIANA ALUGUEL DE EQUIPAMENTOS LTDA | AE6: 293 | AF6: EPSI | AG6: VENDA NOVA DO IMIGRANTE | AH6: ES | AI6: 41675052000226 | AJ6: NOVA VIANA ALUGUEL DE EQUIPAMENTOS LTDA | AK6: VENDA NOVA DO IMIGRANTE | AL6: ES | AM6: EPS | AN6: 000188765 | AO6: 106.816 | AP6: 0 | AQ6: 11 | AR6: 0 | AS6: CP | AT6: LIQUIDADO | AU6: 46253 | AV6: 192.94 | AW6: 001-DIVERSOS | AX6: 001-DIVERSOS | AY6: 5881.78 | AZ6: COMBINADA | BA6: CO3365268 | BB6: 192.94 | BC6: 179.43 | BD6: 192.94 | BE6: 13.51 | BF6: 0.07 | BG6: 0 | BH6: 106.816 | BI6: 109.03 | BJ6: 0 | BK6: 17 | BL6: 0 | BM6: 9.76 | BN6: 8.82 | BO6: 11 | BP6: 3.23 | BQ6: 0 | BR6: 0 | BS6: 0 | BT6: 0 | BU6: 0 | BV6: 0 | BW6: 0 | BX6: 0 | BY6: 0 | BZ6: 0 | CA6: 20.59 | CB6: CTBP | CC6: EPSP | CD6: 426.48 | CE6: 0 | CF6: 0 | CG6: 0 | CH6: 0 | CI6: 0 | CJ6: 0 | CK6: 0 | CN6: 0 | CO6: 0 | CP6: 0 | CQ6: 0 | CR6: 0 | CS6: 0 | CT6: 0 | CU6: 16.02 | CV6: MAPA: 161 | CW6: 0 | CY6: 86.13 | CZ6: FATURA: 55156 | DA6: 92.61 | DB6: 055156 | DE6: 0 | DF6: A. | DG6: PR | DH6: ARAUCARIA | DI6: 9026067267 | DJ6: (41 ) 38887555 | DK6: 0 | DL6: CTB | DM6: 13.51
A7: 2 | B7: CTB070619-1 | C7: NORMAL | D7: CTBP | E7: CTB | F7: 46237 | G7: DQB8989 | H7: 41260803098929000606570010000715161003657210 | I7: 05094003000155 | J7: COLSON DO BRASIL LTDA | K7: RUA DAS PALMEIRAS 350 | L7: CAPELA VELHA | M7: 002 | N7: ARAUCARIA | O7: PR | P7: 83705-500 | Q7: 05094003000155 | R7: COLSON DO BRASIL LTDA | S7: ARAUCARIA | T7: PR | U7: 05094003000155 | V7: COLSON DO BRASIL LTDA | W7: RUA DAS PALMEIRAS 350 | X7: CAPELA VELHA | Y7: ARAUCARIA | Z7: PR | AA7: (41 ) 38887555 | AC7: 08696745000149 | AD7: JP COMERCIO DE FERRAGENS PARA MOVEIS LTDA | AE7: 365 | AF7: TAMR | AG7: UBA | AH7: MG | AI7: 08696745000149 | AJ7: JP COMERCIO DE FERRAGENS PARA MOVEIS LTDA | AK7: UBA | AL7: MG | AM7: TAM | AN7: 000188760 | AO7: 7.945 | AP7: 0.4856 | AQ7: 1 | AR7: 0 | AS7: CP | AT7: LIQUIDADO | AU7: 46253 | AV7: 219.59 | AW7: 001-DIVERSOS | AX7: 001-DIVERSOS | AY7: 303.14 | AZ7: COMBINADA | BA7: CO3365280 | BB7: 219.59 | BC7: 193.24 | BD7: 219.59 | BE7: 26.35 | BF7: 0.12 | BG7: 0 | BH7: 145.68 | BI7: 148.94 | BJ7: 0 | BK7: 17 | BL7: 0 | BM7: 9.76 | BN7: 2.25 | BO7: 11 | BP7: 3.23 | BQ7: 0 | BR7: 0 | BS7: 0 | BT7: 0 | BU7: 0 | BV7: 0 | BW7: 0 | BX7: 0 | BY7: 0 | BZ7: 0 | CA7: 1.06 | CB7: CTBP | CC7: TAMR | CD7: 361.05 | CE7: 0 | CF7: 0 | CG7: 0 | CH7: 0 | CI7: 0 | CJ7: 0 | CK7: 0 | CN7: 0 | CO7: 0 | CP7: 0 | CQ7: 0 | CR7: 0 | CS7: 0 | CT7: 0 | CU7: 12 | CV7: MAPA: 161 | CW7: 0 | CY7: 72.84 | CZ7: MAPA: 0 | DA7: =CY7 -> 72.84 | DE7: 0 | DF7: A. | DG7: PR | DH7: ARAUCARIA | DI7: 9026067267 | DJ7: (41 ) 38887555 | DK7: 0 | DL7: CTB | DM7: 26.35
A8: 2 | B8: CTB070620-5 | C8: NORMAL | D8: CTBP | E8: CTB | F8: 46237 | G8: DQB8989 | H8: 41260803098929000606570010000715181003657230 | I8: 05094003000155 | J8: COLSON DO BRASIL LTDA | K8: RUA DAS PALMEIRAS 350 | L8: CAPELA VELHA | M8: 002 | N8: ARAUCARIA | O8: PR | P8: 83705-500 | Q8: 05094003000155 | R8: COLSON DO BRASIL LTDA | S8: ARAUCARIA | T8: PR | U8: 05094003000155 | V8: COLSON DO BRASIL LTDA | W8: RUA DAS PALMEIRAS 350 | X8: CAPELA VELHA | Y8: ARAUCARIA | Z8: PR | AA8: (41 ) 38887555 | AC8: 55171639000121 | AD8: TS LASER LOCACAO DE EQUIPAMENTOS LT | AE8: 06 ZONA SUL | AF8: SPOP | AG8: SAO PAULO | AH8: SP | AI8: 55171639000121 | AJ8: TS LASER LOCACAO DE EQUIPAMENTOS LT | AK8: SAO PAULO | AL8: SP | AM8: SPO | AN8: 000188767 | AO8: 11.35 | AP8: 0 | AQ8: 2 | AR8: 0 | AS8: CP | AT8: LIQUIDADO | AU8: 46253 | AV8: 95.18 | AW8: 001-DIVERSOS | AX8: 001-DIVERSOS | AY8: 1713.74 | AZ8: COMBINADA | BA8: CO3365274 | BB8: 95.18 | BC8: 83.76 | BD8: 95.18 | BE8: 11.42 | BF8: 0.12 | BG8: 0 | BH8: 11.35 | BI8: 39.7 | BJ8: 0 | BK8: 17 | BL8: 0 | BM8: 9.76 | BN8: 2.57 | BO8: 5.5 | BP8: 3.23 | BQ8: 0 | BR8: 0 | BS8: 0 | BT8: 0 | BU8: 0 | BV8: 0 | BW8: 0 | BX8: 0 | BY8: 0 | BZ8: 0 | CA8: 6 | CB8: CTBP | CC8: SPOP | CD8: 375.17 | CE8: 0 | CF8: 0 | CG8: 0 | CH8: 0 | CI8: 0 | CJ8: 0 | CK8: 0 | CN8: 0 | CO8: 0 | CP8: 0 | CQ8: 0 | CR8: 0 | CS8: 0 | CT8: 0 | CU8: 12 | CV8: MAPA: 161 | CW8: 0 | CY8: 18 | CZ8: MAPA: 161 | DA8: 0 | DE8: 0 | DF8: A. | DG8: PR | DH8: ARAUCARIA | DI8: 9026067267 | DJ8: (41 ) 38887555 | DK8: 0 | DL8: CTB | DM8: 11.42
A9: 2 | B9: CTB070621-3 | C9: NORMAL | D9: CTBP | E9: CTB | F9: 46237 | G9: DQB8989 | H9: 41260803098929000606570010000715091003657142 | I9: 05094003000155 | J9: COLSON DO BRASIL LTDA | K9: RUA DAS PALMEIRAS 350 | L9: CAPELA VELHA | M9: 002 | N9: ARAUCARIA | O9: PR | P9: 83705-500 | Q9: 05094003000155 | R9: COLSON DO BRASIL LTDA | S9: ARAUCARIA | T9: PR | U9: 05094003000155 | V9: COLSON DO BRASIL LTDA | W9: RUA DAS PALMEIRAS 350 | X9: CAPELA VELHA | Y9: ARAUCARIA | Z9: PR | AA9: (41 ) 38887555 | AC9: 04956134000131 | AD9: RODAS E RODIZIOS LTDA | AE9: 005 CONTAGEM | AF9: BHZP | AG9: CONTAGEM | AH9: MG | AI9: 04956134000131 | AJ9: RODAS E RODIZIOS LTDA | AK9: CONTAGEM | AL9: MG | AM9: BHZ | AN9: 000188705 | AO9: 83.37 | AP9: 0 | AQ9: 7 | AR9: 0 | AS9: CP | AT9: LIQUIDADO | AU9: 46253 | AV9: 177.52 | AW9: 001-DIVERSOS | AX9: 001-DIVERSOS | AY9: 3905.33 | AZ9: COMBINADA | BA9: CO3365271 | BB9: 177.52 | BC9: 156.22 | BD9: 177.52 | BE9: 21.3 | BF9: 0.12 | BG9: 0 | BH9: 83.37 | BI9: 101.2 | BJ9: 0 | BK9: 17 | BL9: 0 | BM9: 9.76 | BN9: 5.86 | BO9: 5.5 | BP9: 3.23 | BQ9: 0 | BR9: 0 | BS9: 0 | BT9: 0 | BU9: 0 | BV9: 0 | BW9: 0 | BX9: 0 | BY9: 0 | BZ9: 0 | CA9: 13.67 | CB9: CTBP | CC9: BHZP | CD9: 400.72 | CE9: 0 | CF9: 0 | CG9: 0 | CH9: 0 | CI9: 0 | CJ9: 0 | CK9: 0 | CN9: 0 | CO9: 0 | CP9: 0 | CQ9: 0 | CR9: 0 | CS9: 0 | CT9: 0 | CU9: 12.51 | CV9: MAPA: 161 | CW9: 0 | CY9: 15 | CZ9: MAPA: 161 | DA9: 0 | DE9: 0 | DF9: A. | DG9: PR | DH9: ARAUCARIA | DI9: 9026067267 | DJ9: (41 ) 38887555 | DK9: 0 | DL9: CTB | DM9: 21.3
A10: 2 | B10: CTB070622-1 | C10: NORMAL | D10: CTBP | E10: CTB | F10: 46237 | G10: DQB8989 | H10: 41260803098929000606570010000715201003657255 | I10: 05094003000155 | J10: COLSON DO BRASIL LTDA | K10: RUA DAS PALMEIRAS 350 | L10: CAPELA VELHA | M10: 002 | N10: ARAUCARIA | O10: PR | P10: 83705-500 | Q10: 05094003000155 | R10: COLSON DO BRASIL LTDA | S10: ARAUCARIA | T10: PR | U10: 05094003000155 | V10: COLSON DO BRASIL LTDA | W10: RUA DAS PALMEIRAS 350 | X10: CAPELA VELHA | Y10: ARAUCARIA | Z10: PR | AA10: (41 ) 38887555 | AC10: 23476033001260 | AD10: BMB MATERIAL DE CONSTRUCAO S.A. | AE10: 09 GR2 | AF10: SPOP | AG10: SUZANO | AH10: SP | AI10: 23476033001260 | AJ10: BMB MATERIAL DE CONSTRUCAO S.A. | AK10: SUZANO | AL10: SP | AM10: SPO | AN10: 000187858 | AO10: 39.4 | AP10: 0 | AQ10: 4 | AR10: 0 | AS10: CP | AT10: LIQUIDADO | AU10: 46253 | AV10: 397 | AW10: 001-DIVERSOS | AX10: 001-DIVERSOS | AY10: 1375.97 | AZ10: COMBINADA | BA10: CO3365274 | BB10: 397 | BC10: 349.36 | BD10: 397 | BE10: 47.64 | BF10: 0.12 | BG10: 0 | BH10: 39.4 | BI10: 56.8 | BJ10: 0 | BK10: 17 | BL10: 0 | BM10: 9.76 | BN10: 2.25 | BO10: 5.5 | BP10: 3.23 | BQ10: 0 | BR10: 0 | BS10: 0 | BT10: 0 | BU10: 0 | BV10: 0 | BW10: 0 | BX10: 250 | BY10: 0 | BZ10: 0 | CA10: 4.82 | CB10: CTBP | CC10: SPOP | CD10: 371.76 | CE10: 0 | CF10: 0 | CG10: 0 | CH10: 0 | CI10: 0 | CJ10: 0 | CK10: 0 | CN10: 0 | CO10: 0 | CP10: 0 | CQ10: 0 | CR10: 0 | CS10: 0 | CT10: 0 | CU10: 12 | CV10: MAPA: 161 | CW10: 0 | CY10: 18 | CZ10: MAPA: 161 | DA10: 0 | DE10: 0 | DF10: A. | DG10: PR | DH10: ARAUCARIA | DI10: 9026067267 | DJ10: (41 ) 38887555 | DK10: 0 | DL10: CTB | DM10: 47.64
A11: 2 | B11: CTB070623-0 | C11: NORMAL | D11: CTBP | E11: CTB | F11: 46237 | G11: DQB8989 | H11: 41260803098929000606570010000715111003657167 | I11: 05094003000155 | J11: COLSON DO BRASIL LTDA | K11: RUA DAS PALMEIRAS 350 | L11: CAPELA VELHA | M11: 002 | N11: ARAUCARIA | O11: PR | P11: 83705-500 | Q11: 05094003000155 | R11: COLSON DO BRASIL LTDA | S11: ARAUCARIA | T11: PR | U11: 05094003000155 | V11: COLSON DO BRASIL LTDA | W11: RUA DAS PALMEIRAS 350 | X11: CAPELA VELHA | Y11: ARAUCARIA | Z11: PR | AA11: (41 ) 38887555 | AC11: 23476033001856 | AD11: BMB MATERIAL DE CONSTRUCAO S.A. 0018-56 | AE11: CAX DUQUE DE CAXIAS | AF11: RJOP | AG11: DUQUE DE CAXIAS | AH11: RJ | AI11: 23476033001856 | AJ11: BMB MATERIAL DE CONSTRUCAO S.A. 0018-56 | AK11: DUQUE DE CAXIAS | AL11: RJ | AM11: RJO | AN11: 000188526 | AO11: 55.6 | AP11: 0 | AQ11: 9 | AR11: 0 | AS11: CP | AT11: LIQUIDADO | AU11: 46253 | AV11: 429.09 | AW11: 001-DIVERSOS | AX11: 001-DIVERSOS | AY11: 1903.24 | AZ11: COMBINADA | BA11: CO3365267 | BB11: 429.09 | BC11: 377.6 | BD11: 429.09 | BE11: 51.49 | BF11: 0.12 | BG11: 0 | BH11: 55.6 | BI11: 82.6 | BJ11: 0 | BK11: 17 | BL11: 0 | BM11: 9.76 | BN11: 2.85 | BO11: 5.5 | BP11: 3.23 | BQ11: 0 | BR11: 0 | BS11: 0 | BT11: 0 | BU11: 0 | BV11: 0 | BW11: 0 | BX11: 250 | BY11: 0 | BZ11: 0 | CA11: 6.66 | CB11: CTBP | CC11: RJOP | CD11: 377.02 | CE11: 0 | CF11: 0 | CG11: 0 | CH11: 0 | CI11: 0 | CJ11: 0 | CK11: 0 | CN11: 0 | CO11: 0 | CP11: 0 | CQ11: 0 | CR11: 0 | CS11: 0 | CT11: 0 | CU11: 12 | CV11: MAPA: 161 | CW11: 0 | CY11: 18 | CZ11: MAPA: 161 | DA11: 0 | DE11: 0 | DF11: A. | DG11: PR | DH11: ARAUCARIA | DI11: 9026067267 | DJ11: (41 ) 38887555 | DK11: 0 | DL11: CTB | DM11: 51.49
A12: 2 | B12: CTB070708-2 | C12: NORMAL | D12: CTBP | E12: CTB | F12: 46238 | G12: DQB8989 | H12: 41260803098929000606570010000716041003663389 | I12: 05094003000155 | J12: COLSON DO BRASIL LTDA | K12: RUA DAS PALMEIRAS 350 | L12: CAPELA VELHA | M12: 002 | N12: ARAUCARIA | O12: PR | P12: 83705-500 | Q12: 05094003000155 | R12: COLSON DO BRASIL LTDA | S12: ARAUCARIA | T12: PR | U12: 05094003000155 | V12: COLSON DO BRASIL LTDA | W12: RUA DAS PALMEIRAS 350 | X12: CAPELA VELHA | Y12: ARAUCARIA | Z12: PR | AA12: (41 ) 38887555 | AC12: 10918072000176 | AD12: LUZ MAR MADEIRAS LTDA 12007391 | AE12: RIO RIO DE JANEIRO | AF12: RJOP | AG12: RIO DE JANEIRO | AH12: RJ | AI12: 10918072000176 | AJ12: LUZ MAR MADEIRAS LTDA 12007391 | AK12: RIO DE JANEIRO | AL12: RJ | AM12: RJO | AN12: 000188840 | AO12: 125.756 | AP12: 0 | AQ12: 13 | AR12: 0 | AS12: CP | AT12: LIQUIDADO | AU12: 46253 | AV12: 196.3 | AW12: 001-DIVERSOS | AX12: 001-DIVERSOS | AY12: 3711.94 | AZ12: COMBINADA | BA12: CO3365267 | BB12: 196.3 | BC12: 172.74 | BD12: 196.3 | BE12: 23.56 | BF12: 0.12 | BG12: 0 | BH12: 125.756 | BI12: 113.19 | BJ12: 0 | BK12: 17 | BL12: 0 | BM12: 9.76 | BN12: 5.57 | BO12: 11 | BP12: 3.23 | BQ12: 0 | BR12: 0 | BS12: 0 | BT12: 0 | BU12: 0 | BV12: 0 | BW12: 0 | BX12: 0 | BY12: 0 | BZ12: 0 | CA12: 12.99 | CB12: CTBP | CC12: RJOP | CD12: 398.26 | CE12: 0 | CF12: 0 | CG12: 0 | CH12: 0 | CI12: 0 | CJ12: 0 | CK12: 0 | CN12: 0 | CO12: 0 | CP12: 0 | CQ12: 0 | CR12: 0 | CS12: 0 | CT12: 0 | CU12: 18.86 | CV12: MAPA: 161 | CW12: 0 | CY12: 22.64 | CZ12: MAPA: 161 | DA12: 0 | DE12: 0 | DF12: A. | DG12: PR | DH12: ARAUCARIA | DI12: 9026067267 | DJ12: (41 ) 38887555 | DK12: 0 | DL12: CTB | DM12: 23.56
A13: 2 | B13: CTB070709-1 | C13: NORMAL | D13: CTBP | E13: CTB | F13: 46238 | G13: DQB8989 | H13: 41260803098929000606570010000716051003663408 | I13: 05094003000155 | J13: COLSON DO BRASIL LTDA | K13: RUA DAS PALMEIRAS 350 | L13: CAPELA VELHA | M13: 002 | N13: ARAUCARIA | O13: PR | P13: 83705-500 | Q13: 05094003000155 | R13: COLSON DO BRASIL LTDA | S13: ARAUCARIA | T13: PR | U13: 05094003000155 | V13: COLSON DO BRASIL LTDA | W13: RUA DAS PALMEIRAS 350 | X13: CAPELA VELHA | Y13: ARAUCARIA | Z13: PR | AA13: (41 ) 38887555 | AC13: 66294976000122 | AD13: JD COM DE DERIVADOS DE BORRACH | AE13: 384 | AF13: TRUP | AG13: UBERLANDIA | AH13: MG | AI13: 66294976000122 | AJ13: JD COM DE DERIVADOS DE BORRACH | AK13: UBERLANDIA | AL13: MG | AM13: TRU | AN13: 000188806 | AO13: 235.713 | AP13: 0 | AQ13: 19 | AR13: 0 | AS13: CP | AT13: LIQUIDADO | AU13: 46253 | AV13: 422.6 | AW13: 001-DIVERSOS | AX13: 054-PNEUS E CAMARAS DE AR | AY13: 8494.14 | AZ13: COMBINADA | BA13: CO3365284 | BB13: 422.6 | BC13: 371.89 | BD13: 422.6 | BE13: 50.71 | BF13: 0.12 | BG13: 0 | BH13: 235.713 | BI13: 282.93 | BJ13: 0 | BK13: 17 | BL13: 0 | BM13: 9.76 | BN13: 12.74 | BO13: 16.5 | BP13: 3.23 | BQ13: 0 | BR13: 0 | BS13: 0 | BT13: 0 | BU13: 0 | BV13: 0 | BW13: 0 | BX13: 0 | BY13: 0 | BZ13: 0 | CA13: 29.73 | CB13: CTBP | CC13: PANI | CD13: 549.69 | CE13: 0 | CF13: 0 | CG13: 0 | CH13: 0 | CI13: 0 | CJ13: 0 | CK13: 0 | CN13: 0 | CO13: 0 | CP13: 0 | CQ13: 0 | CR13: 0 | CS13: 0 | CT13: 0 | CU13: 35.36 | CV13: MAPA: 161 | CW13: 0 | CY13: 169.04 | CZ13: FATURA: 232309 | DA13: 161.4 | DB13: 232309 | DE13: 0 | DF13: A. | DG13: PR | DH13: ARAUCARIA | DI13: 9026067267 | DJ13: (41 ) 38887555 | DK13: 0 | DL13: CTB | DM13: 50.71
A14: 2 | B14: CTB070710-4 | C14: NORMAL | D14: CTBP | E14: CTB | F14: 46238 | G14: DQB8989 | H14: 41260803098929000606570010000716061003663421 | I14: 05094003000155 | J14: COLSON DO BRASIL LTDA | K14: RUA DAS PALMEIRAS 350 | L14: CAPELA VELHA | M14: 002 | N14: ARAUCARIA | O14: PR | P14: 83705-500 | Q14: 05094003000155 | R14: COLSON DO BRASIL LTDA | S14: ARAUCARIA | T14: PR | U14: 05094003000155 | V14: COLSON DO BRASIL LTDA | W14: RUA DAS PALMEIRAS 350 | X14: CAPELA VELHA | Y14: ARAUCARIA | Z14: PR | AA14: (41 ) 38887555 | AC14: 22860350000160 | AD14: LEONILDO DA CRUZ SANTANA 11590235657 | AE14: 395 | AF14: VEAI | AG14: RIO PARDO DE MINAS | AH14: MG | AI14: 22860350000160 | AJ14: LEONILDO DA CRUZ SANTANA 11590235657 | AK14: RIO PARDO DE MINAS | AL14: MG | AM14: VEA | AN14: 000188808 | AO14: 210.65 | AP14: 0 | AQ14: 17 | AR14: 0 | AS14: CP | AT14: LIQUIDADO | AU14: 46253 | AV14: 375.43 | AW14: 001-DIVERSOS | AX14: 001-DIVERSOS | AY14: 6209.05 | AZ14: COMBINADA | BA14: CO3365293 | BB14: 375.43 | BC14: 330.38 | BD14: 375.43 | BE14: 45.05 | BF14: 0.12 | BG14: 0 | BH14: 210.65 | BI14: 252.85 | BJ14: 0 | BK14: 17 | BL14: 0 | BM14: 9.76 | BN14: 9.31 | BO14: 16.5 | BP14: 3.23 | BQ14: 0 | BR14: 0 | BS14: 0 | BT14: 0 | BU14: 0 | BV14: 0 | BW14: 0 | BX14: 0 | BY14: 0 | BZ14: 0 | CA14: 21.73 | CB14: CTBP | CC14: RMCP | CD14: 457.34 | CE14: 0 | CF14: 0 | CG14: 0 | CH14: 0 | CI14: 0 | CJ14: 0 | CK14: 0 | CN14: 0 | CO14: 0 | CP14: 0 | CQ14: 0 | CR14: 0 | CS14: 0 | CT14: 0 | CU14: 31.6 | CV14: MAPA: 161 | CW14: 0 | CY14: 112.63 | CZ14: MAPA: 0 | DA14: =CY14 -> 112.63 | DE14: 0 | DF14: A. | DG14: PR | DH14: ARAUCARIA | DI14: 9026067267 | DJ14: (41 ) 38887555 | DK14: 0 | DL14: CTB | DM14: 45.05
A15: 2 | B15: CTB070711-2 | C15: NORMAL | D15: CTBP | E15: CTB | F15: 46238 | G15: DQB8989 | H15: 41260803098929000606570010000716071003663445 | I15: 05094003000155 | J15: COLSON DO BRASIL LTDA | K15: RUA DAS PALMEIRAS 350 | L15: CAPELA VELHA | M15: 002 | N15: ARAUCARIA | O15: PR | P15: 83705-500 | Q15: 05094003000155 | R15: COLSON DO BRASIL LTDA | S15: ARAUCARIA | T15: PR | U15: 05094003000155 | V15: COLSON DO BRASIL LTDA | W15: RUA DAS PALMEIRAS 350 | X15: CAPELA VELHA | Y15: ARAUCARIA | Z15: PR | AA15: (41 ) 38887555 | AC15: 03047584000149 | AD15: IMPERIO DOS ROLAMENTOS E PECAS | AE15: 256 | AF15: MVGP | AG15: PETROPOLIS | AH15: RJ | AI15: 03047584000149 | AJ15: IMPERIO DOS ROLAMENTOS E PECAS | AK15: PETROPOLIS | AL15: RJ | AM15: MVG | AN15: 000188845 | AO15: 80.92 | AP15: 0 | AQ15: 10 | AR15: 0 | AS15: CP | AT15: LIQUIDADO | AU15: 46253 | AV15: 210.13 | AW15: 001-DIVERSOS | AX15: 001-DIVERSOS | AY15: 3835.45 | AZ15: COMBINADA | BA15: CO3365270 | BB15: 210.13 | BC15: 184.91 | BD15: 210.13 | BE15: 25.22 | BF15: 0.12 | BG15: 0 | BH15: 80.92 | BI15: 130.25 | BJ15: 0 | BK15: 17 | BL15: 0 | BM15: 9.76 | BN15: 5.75 | BO15: 5.5 | BP15: 3.23 | BQ15: 0 | BR15: 0 | BS15: 0 | BT15: 0 | BU15: 0 | BV15: 0 | BW15: 0 | BX15: 0 | BY15: 0 | BZ15: 0 | CA15: 13.42 | CB15: CTBP | CC15: ITAI | CD15: 399.87 | CE15: 0 | CF15: 0 | CG15: 0 | CH15: 0 | CI15: 0 | CJ15: 0 | CK15: 0 | CN15: 0 | CO15: 0 | CP15: 0 | CQ15: 0 | CR15: 0 | CS15: 0 | CT15: 0 | CU15: 12.14 | CV15: MAPA: 161 | CW15: 0 | CY15: 68.82 | CZ15: FATURA: 17774 | DA15: 68.82 | DB15: 017774 | DE15: 0 | DF15: A. | DG15: PR | DH15: ARAUCARIA | DI15: 9026067267 | DJ15: (41 ) 38887555 | DK15: 0 | DL15: CTB | DM15: 25.22
A16: 2 | B16: CTB070712-1 | C16: NORMAL | D16: CTBP | E16: CTB | F16: 46238 | G16: DQB8989 | H16: 41260803098929000606570010000716081003663469 | I16: 05094003000155 | J16: COLSON DO BRASIL LTDA | K16: RUA DAS PALMEIRAS 350 | L16: CAPELA VELHA | M16: 002 | N16: ARAUCARIA | O16: PR | P16: 83705-500 | Q16: 05094003000155 | R16: COLSON DO BRASIL LTDA | S16: ARAUCARIA | T16: PR | U16: 05094003000155 | V16: COLSON DO BRASIL LTDA | W16: RUA DAS PALMEIRAS 350 | X16: CAPELA VELHA | Y16: ARAUCARIA | Z16: PR | AA16: (41 ) 38887555 | AC16: 08949409000160 | AD16: CONCERPLAN COMERCIO DE ALIMENTOS EI | AE16: 133 | AF16: PSPP | AG16: INDAIATUBA | AH16: SP | AI16: 08949409000160 | AJ16: CONCERPLAN COMERCIO DE ALIMENTOS EI | AK16: INDAIATUBA | AL16: SP | AM16: PSP | AN16: 000188788 | AO16: 29.48 | AP16: 0 | AQ16: 5 | AR16: 0 | AS16: CP | AT16: LIQUIDADO | AU16: 46253 | AV16: 166.34 | AW16: 001-DIVERSOS | AX16: 001-DIVERSOS | AY16: 5585.62 | AZ16: COMBINADA | BA16: CO3365266 | BB16: 166.34 | BC16: 146.38 | BD16: 166.34 | BE16: 19.96 | BF16: 0.12 | BG16: 0 | BH16: 29.48 | BI16: 82.96 | BJ16: 0 | BK16: 17 | BL16: 0 | BM16: 9.76 | BN16: 8.38 | BO16: 5.5 | BP16: 3.23 | BQ16: 0 | BR16: 0 | BS16: 0 | BT16: 0 | BU16: 0 | BV16: 0 | BW16: 0 | BX16: 0 | BY16: 0 | BZ16: 0 | CA16: 19.55 | CB16: CTBP | CC16: SPOR | CD16: 422.61 | CE16: 0 | CF16: 0 | CG16: 0 | CH16: 0 | CI16: 0 | CJ16: 0 | CK16: 0 | CN16: 0 | CO16: 0 | CP16: 0 | CQ16: 0 | CR16: 0 | CS16: 0 | CT16: 0 | CU16: 12 | CV16: MAPA: 161 | CW16: 0 | CY16: 49.5 | CZ16: MAPA: 161 | DA16: =CY16 -> 49.5 | DE16: 0 | DF16: A. | DG16: PR | DH16: ARAUCARIA | DI16: 9026067267 | DJ16: (41 ) 38887555 | DK16: 0 | DL16: CTB | DM16: 19.96
A17: 2 | B17: CTB070713-9 | C17: NORMAL | D17: CTBP | E17: CTB | F17: 46238 | G17: DQB8989 | H17: 41260803098929000606570010000716091003663474 | I17: 05094003000155 | J17: COLSON DO BRASIL LTDA | K17: RUA DAS PALMEIRAS 350 | L17: CAPELA VELHA | M17: 002 | N17: ARAUCARIA | O17: PR | P17: 83705-500 | Q17: 05094003000155 | R17: COLSON DO BRASIL LTDA | S17: ARAUCARIA | T17: PR | U17: 05094003000155 | V17: COLSON DO BRASIL LTDA | W17: RUA DAS PALMEIRAS 350 | X17: CAPELA VELHA | Y17: ARAUCARIA | Z17: PR | AA17: (41 ) 38887555 | AC17: 01093975000174 | AD17: OMNITEK TECNOLOGIA LTDA. | AE17: 07 ZONA OESTE | AF17: SPOP | AG17: SAO PAULO | AH17: SP | AI17: 01093975000174 | AJ17: OMNITEK TECNOLOGIA LTDA. | AK17: SAO PAULO | AL17: SP | AM17: SPO | AN17: 000188778 | AO17: 35 | AP17: 0 | AQ17: 3 | AR17: 0 | AS17: CP | AT17: LIQUIDADO | AU17: 46253 | AV17: 396.82 | AW17: 001-DIVERSOS | AX17: 001-DIVERSOS | AY17: 1332.17 | AZ17: COMBINADA | BA17: CO3365274 | BB17: 396.82 | BC17: 349.2 | BD17: 396.82 | BE17: 47.62 | BF17: 0.12 | BG17: 0 | BH17: 35 | BI17: 56.8 | BJ17: 0 | BK17: 17 | BL17: 0 | BM17: 9.76 | BN17: 2.25 | BO17: 5.5 | BP17: 3.23 | BQ17: 0 | BR17: 0 | BS17: 0 | BT17: 0 | BU17: 0 | BV17: 0 | BW17: 0 | BX17: 250 | BY17: 0 | BZ17: 0 | CA17: 4.66 | CB17: CTBP | CC17: SPOP | CD17: 371.31 | CE17: 0 | CF17: 0 | CG17: 0 | CH17: 0 | CI17: 0 | CJ17: 0 | CK17: 0 | CN17: 0 | CO17: 0 | CP17: 0 | CQ17: 0 | CR17: 0 | CS17: 0 | CT17: 0 | CU17: 12 | CV17: MAPA: 161 | CW17: 0 | CY17: 18 | CZ17: MAPA: 161 | DA17: 0 | DE17: 0 | DF17: A. | DG17: PR | DH17: ARAUCARIA | DI17: 9026067267 | DJ17: (41 ) 38887555 | DK17: 0 | DL17: CTB | DM17: 47.62
A18: 2 | B18: CTB070714-7 | C18: NORMAL | D18: CTBP | E18: CTB | F18: 46238 | G18: DQB8989 | H18: 41260803098929000606570010000716101003663491 | I18: 05094003000155 | J18: COLSON DO BRASIL LTDA | K18: RUA DAS PALMEIRAS 350 | L18: CAPELA VELHA | M18: 002 | N18: ARAUCARIA | O18: PR | P18: 83705-500 | Q18: 05094003000155 | R18: COLSON DO BRASIL LTDA | S18: ARAUCARIA | T18: PR | U18: 05094003000155 | V18: COLSON DO BRASIL LTDA | W18: RUA DAS PALMEIRAS 350 | X18: CAPELA VELHA | Y18: ARAUCARIA | Z18: PR | AA18: (41 ) 38887555 | AC18: 31555733000116 | AD18: SARGENTO FERRAGENS LTDA | AE18: CAX DUQUE DE CAXIAS | AF18: RJOP | AG18: DUQUE DE CAXIAS | AH18: RJ | AI18: 31555733000116 | AJ18: SARGENTO FERRAGENS LTDA | AK18: DUQUE DE CAXIAS | AL18: RJ | AM18: RJO | AN18: 000188799 | AO18: 148.6 | AP18: 0 | AQ18: 15 | AR18: 0 | AS18: CP | AT18: LIQUIDADO | AU18: 46253 | AV18: 513.05 | AW18: 001-DIVERSOS | AX18: 001-DIVERSOS | AY18: 5349.3 | AZ18: COMBINADA | BA18: CO3365267 | BB18: 513.05 | BC18: 451.48 | BD18: 513.05 | BE18: 61.57 | BF18: 0.12 | BG18: 0 | BH18: 148.6 | BI18: 133.75 | BJ18: 0 | BK18: 17 | BL18: 0 | BM18: 9.76 | BN18: 8.02 | BO18: 11 | BP18: 3.23 | BQ18: 0 | BR18: 0 | BS18: 0 | BT18: 0 | BU18: 0 | BV18: 0 | BW18: 0 | BX18: 250 | BY18: 0 | BZ18: 0 | CA18: 18.72 | CB18: CTBP | CC18: RJOP | CD18: 419.54 | CE18: 0 | CF18: 0 | CG18: 0 | CH18: 0 | CI18: 0 | CJ18: 0 | CK18: 0 | CN18: 0 | CO18: 0 | CP18: 0 | CQ18: 0 | CR18: 0 | CS18: 0 | CT18: 0 | CU18: 22.29 | CV18: MAPA: 161 | CW18: 0 | CY18: 26.75 | CZ18: MAPA: 161 | DA18: 0 | DE18: 0 | DF18: A. | DG18: PR | DH18: ARAUCARIA | DI18: 9026067267 | DJ18: (41 ) 38887555 | DK18: 0 | DL18: CTB | DM18: 61.57
A19: 2 | B19: CTB070715-5 | C19: NORMAL | D19: CTBP | E19: CTB | F19: 46238 | G19: DQB8989 | H19: 41260803098929000606570010000716111003663510 | I19: 05094003000155 | J19: COLSON DO BRASIL LTDA | K19: RUA DAS PALMEIRAS 350 | L19: CAPELA VELHA | M19: 002 | N19: ARAUCARIA | O19: PR | P19: 83705-500 | Q19: 05094003000155 | R19: COLSON DO BRASIL LTDA | S19: ARAUCARIA | T19: PR | U19: 05094003000155 | V19: COLSON DO BRASIL LTDA | W19: RUA DAS PALMEIRAS 350 | X19: CAPELA VELHA | Y19: ARAUCARIA | Z19: PR | AA19: (41 ) 38887555 | AC19: 00373798000117 | AD19: OPCAO PARAFUSOS E FERRAMENTAS LTDA - EPP | AE19: 299 | AF19: EPSI | AG19: SAO MATEUS | AH19: ES | AI19: 00373798000117 | AJ19: OPCAO PARAFUSOS E FERRAMENTAS LTDA - EPP | AK19: SAO MATEUS | AL19: ES | AM19: EPS | AN19: 000188844 | AO19: 315.27 | AP19: 0 | AQ19: 39 | AR19: 0 | AS19: CP | AT19: LIQUIDADO | AU19: 46253 | AV19: 463.4 | AW19: 001-DIVERSOS | AX19: 001-DIVERSOS | AY19: 11435.48 | AZ19: COMBINADA | BA19: CO3365268 | BB19: 463.4 | BC19: 430.96 | BD19: 463.4 | BE19: 32.44 | BF19: 0.07 | BG19: 0 | BH19: 315.27 | BI19: 321.8 | BJ19: 0 | BK19: 17 | BL19: 0 | BM19: 9.76 | BN19: 17.15 | BO19: 22 | BP19: 3.23 | BQ19: 0 | BR19: 0 | BS19: 0 | BT19: 0 | BU19: 0 | BV19: 0 | BW19: 0 | BX19: 0 | BY19: 0 | BZ19: 0 | CA19: 40.02 | CB19: CTBP | CC19: EPSP | CD19: 786.89 | CE19: 0 | CF19: 0 | CG19: 0 | CH19: 0 | CI19: 0 | CJ19: 0 | CK19: 0 | CN19: 0 | CO19: 0 | CP19: 0 | CQ19: 0 | CR19: 0 | CS19: 0 | CT19: 0 | CU19: 47.29 | CV19: MAPA: 161 | CW19: 0 | CY19: 206.86 | CZ19: FATURA: 55181 | DA19: 222.43 | DB19: 055181 | DE19: 0 | DF19: A. | DG19: PR | DH19: ARAUCARIA | DI19: 9026067267 | DJ19: (41 ) 38887555 | DK19: 0 | DL19: CTB | DM19: 32.44
A20: 2 | B20: CTB070716-3 | C20: NORMAL | D20: CTBP | E20: CTB | F20: 46238 | G20: DQB8989 | H20: 41260803098929000606570010000716121003663534 | I20: 05094003000155 | J20: COLSON DO BRASIL LTDA | K20: RUA DAS PALMEIRAS 350 | L20: CAPELA VELHA | M20: 002 | N20: ARAUCARIA | O20: PR | P20: 83705-500 | Q20: 05094003000155 | R20: COLSON DO BRASIL LTDA | S20: ARAUCARIA | T20: PR | U20: 05094003000155 | V20: COLSON DO BRASIL LTDA | W20: RUA DAS PALMEIRAS 350 | X20: CAPELA VELHA | Y20: ARAUCARIA | Z20: PR | AA20: (41 ) 38887555 | AC20: 23476033000531 | AD20: BMB MATERIAL DE CONSTRUCAO S.A | AE20: RIO RIO DE JANEIRO | AF20: RJOP | AG20: RIO DE JANEIRO | AH20: RJ | AI20: 23476033000531 | AJ20: BMB MATERIAL DE CONSTRUCAO S.A | AK20: RIO DE JANEIRO | AL20: RJ | AM20: RJO | AN20: 000188726 | AO20: 84.03 | AP20: 0 | AQ20: 9 | AR20: 0 | AS20: CP | AT20: LIQUIDADO | AU20: 46253 | AV20: 452.1 | AW20: 001-DIVERSOS | AX20: 001-DIVERSOS | AY20: 2430.21 | AZ20: COMBINADA | BA20: CO3365267 | BB20: 452.1 | BC20: 397.85 | BD20: 452.1 | BE20: 54.25 | BF20: 0.12 | BG20: 0 | BH20: 84.03 | BI20: 100.2 | BJ20: 0 | BK20: 17 | BL20: 0 | BM20: 9.76 | BN20: 3.65 | BO20: 5.5 | BP20: 3.23 | BQ20: 0 | BR20: 0 | BS20: 0 | BT20: 0 | BU20: 0 | BV20: 0 | BW20: 0 | BX20: 250 | BY20: 0 | BZ20: 0 | CA20: 8.51 | CB20: CTBP | CC20: RJOP | CD20: 382.29 | CE20: 0 | CF20: 0 | CG20: 0 | CH20: 0 | CI20: 0 | CJ20: 0 | CK20: 0 | CN20: 0 | CO20: 0 | CP20: 0 | CQ20: 0 | CR20: 0 | CS20: 0 | CT20: 0 | CU20: 12.6 | CV20: MAPA: 161 | CW20: 0 | CY20: 18 | CZ20: MAPA: 162 | DA20: 0 | DE20: 0 | DF20: A. | DG20: PR | DH20: ARAUCARIA | DI20: 9026067267 | DJ20: (41 ) 38887555 | DK20: 0 | DL20: CTB | DM20: 54.25
A21: 2 | B21: CTB070717-1 | C21: NORMAL | D21: CTBP | E21: CTB | F21: 46238 | G21: DQB8989 | H21: 41260803098929000606570010000716131003663540 | I21: 05094003000155 | J21: COLSON DO BRASIL LTDA | K21: RUA DAS PALMEIRAS 350 | L21: CAPELA VELHA | M21: 002 | N21: ARAUCARIA | O21: PR | P21: 83705-500 | Q21: 05094003000155 | R21: COLSON DO BRASIL LTDA | S21: ARAUCARIA | T21: PR | U21: 05094003000155 | V21: COLSON DO BRASIL LTDA | W21: RUA DAS PALMEIRAS 350 | X21: CAPELA VELHA | Y21: ARAUCARIA | Z21: PR | AA21: (41 ) 38887555 | AC21: 09552066000169 | AD21: PIN PINHEIROS COMERCIO DE UTEN | AE21: 02 ZONA NORTE | AF21: SPOP | AG21: SAO PAULO | AH21: SP | AI21: 09552066000169 | AJ21: PIN PINHEIROS COMERCIO DE UTEN | AK21: SAO PAULO | AL21: SP | AM21: SPO | AN21: 000188793 | AO21: 41.67 | AP21: 0 | AQ21: 3 | AR21: 0 | AS21: CP | AT21: LIQUIDADO | AU21: 46253 | AV21: 397.86 | AW21: 001-DIVERSOS | AX21: 001-DIVERSOS | AY21: 1565.23 | AZ21: COMBINADA | BA21: CO3365274 | BB21: 397.86 | BC21: 350.12 | BD21: 397.86 | BE21: 47.74 | BF21: 0.12 | BG21: 0 | BH21: 41.67 | BI21: 56.8 | BJ21: 0 | BK21: 17 | BL21: 0 | BM21: 9.76 | BN21: 2.35 | BO21: 5.5 | BP21: 3.23 | BQ21: 0 | BR21: 0 | BS21: 0 | BT21: 0 | BU21: 0 | BV21: 0 | BW21: 0 | BX21: 250 | BY21: 0 | BZ21: 0 | CA21: 5.48 | CB21: CTBP | CC21: SPOP | CD21: 373.65 | CE21: 0 | CF21: 0 | CG21: 0 | CH21: 0 | CI21: 0 | CJ21: 0 | CK21: 0 | CN21: 0 | CO21: 0 | CP21: 0 | CQ21: 0 | CR21: 0 | CS21: 0 | CT21: 0 | CU21: 12 | CV21: MAPA: 161 | CW21: 0 | CY21: 18 | CZ21: MAPA: 161 | DA21: 0 | DE21: 0 | DF21: A. | DG21: PR | DH21: ARAUCARIA | DI21: 9026067267 | DJ21: (41 ) 38887555 | DK21: 0 | DL21: CTB | DM21: 47.74
A22: 2 | B22: CTB070718-0 | C22: NORMAL | D22: CTBP | E22: CTB | F22: 46238 | G22: DQB8989 | H22: 41260803098929000606570010000716141003663555 | I22: 05094003000155 | J22: COLSON DO BRASIL LTDA | K22: RUA DAS PALMEIRAS 350 | L22: CAPELA VELHA | M22: 002 | N22: ARAUCARIA | O22: PR | P22: 83705-500 | Q22: 05094003000155 | R22: COLSON DO BRASIL LTDA | S22: ARAUCARIA | T22: PR | U22: 05094003000155 | V22: COLSON DO BRASIL LTDA | W22: RUA DAS PALMEIRAS 350 | X22: CAPELA VELHA | Y22: ARAUCARIA | Z22: PR | AA22: (41 ) 38887555 | AC22: 05586184000137 | AD22: FALCARE EQUIPAMENTOS INDUSTRIAIS LTDA | AE22: 11 ABCD | AF22: SPOP | AG22: SAO CAETANO DO SUL | AH22: SP | AI22: 05586184000137 | AJ22: FALCARE EQUIPAMENTOS INDUSTRIAIS LTDA | AK22: SAO CAETANO DO SUL | AL22: SP | AM22: SPO | AN22: 000188795 | AO22: 32.8 | AP22: 0 | AQ22: 4 | AR22: 0 | AS22: CP | AT22: LIQUIDADO | AU22: 46253 | AV22: 133.48 | AW22: 001-DIVERSOS | AX22: 001-DIVERSOS | AY22: 5035.5 | AZ22: COMBINADA | BA22: CO3365274 | BB22: 133.48 | BC22: 117.46 | BD22: 133.48 | BE22: 16.02 | BF22: 0.12 | BG22: 0 | BH22: 32.8 | BI22: 56.8 | BJ22: 0 | BK22: 17 | BL22: 0 | BM22: 9.76 | BN22: 7.55 | BO22: 5.5 | BP22: 3.23 | BQ22: 0 | BR22: 0 | BS22: 0 | BT22: 0 | BU22: 0 | BV22: 0 | BW22: 0 | BX22: 0 | BY22: 0 | BZ22: 0 | CA22: 17.62 | CB22: CTBP | CC22: SPOP | CD22: 415.44 | CE22: 0 | CF22: 0 | CG22: 0 | CH22: 0 | CI22: 0 | CJ22: 0 | CK22: 0 | CN22: 0 | CO22: 0 | CP22: 0 | CQ22: 0 | CR22: 0 | CS22: 0 | CT22: 0 | CU22: 12 | CV22: MAPA: 161 | CW22: 0 | CY22: 18 | CZ22: MAPA: 161 | DA22: 0 | DE22: 0 | DF22: A. | DG22: PR | DH22: ARAUCARIA | DI22: 9026067267 | DJ22: (41 ) 38887555 | DK22: 0 | DL22: CTB | DM22: 16.02
A23: 2 | B23: CTB070719-8 | C23: NORMAL | D23: CTBP | E23: CTB | F23: 46238 | G23: DQB8989 | H23: 41260803098929000606570010000716151003663560 | I23: 05094003000155 | J23: COLSON DO BRASIL LTDA | K23: RUA DAS PALMEIRAS 350 | L23: CAPELA VELHA | M23: 002 | N23: ARAUCARIA | O23: PR | P23: 83705-500 | Q23: 05094003000155 | R23: COLSON DO BRASIL LTDA | S23: ARAUCARIA | T23: PR | U23: 05094003000155 | V23: COLSON DO BRASIL LTDA | W23: RUA DAS PALMEIRAS 350 | X23: CAPELA VELHA | Y23: ARAUCARIA | Z23: PR | AA23: (41 ) 38887555 | AC23: 48960632000123 | AD23: VARGEM PEQUENA ALUGUEL DE EQUIPAMEN | AE23: RIO RIO DE JANEIRO | AF23: RJOP | AG23: RIO DE JANEIRO | AH23: RJ | AI23: 48960632000123 | AJ23: VARGEM PEQUENA ALUGUEL DE EQUIPAMEN | AK23: RIO DE JANEIRO | AL23: RJ | AM23: RJO | AN23: 000188774 | AO23: 1600 | AP23: 0 | AQ23: 100 | AR23: 0 | AS23: CP | AT23: LIQUIDADO | AU23: 46253 | AV23: 2038.49 | AW23: 001-DIVERSOS | AX23: 001-DIVERSOS | AY23: 47143.95 | AZ23: COMBINADA | BA23: CO3365267 | BB23: 2038.49 | BC23: 1793.87 | BD23: 2038.49 | BE23: 244.62 | BF23: 0.12 | BG23: 0 | BH23: 1600 | BI23: 1440.16 | BJ23: 0 | BK23: 17 | BL23: 0 | BM23: 9.76 | BN23: 70.72 | BO23: 88 | BP23: 3.23 | BQ23: 0 | BR23: 0 | BS23: 0 | BT23: 0 | BU23: 0 | BV23: 0 | BW23: 0 | BX23: 0 | BY23: 0 | BZ23: 0 | CA23: 165 | CB23: CTBP | CC23: RJOP | CD23: 4462.54 | CE23: 0 | CF23: 0 | CG23: 0 | CH23: 0 | CI23: 0 | CJ23: 0 | CK23: 0 | CN23: 0 | CO23: 0 | CP23: 0 | CQ23: 0 | CR23: 0 | CS23: 0 | CT23: 0 | CU23: 240 | CV23: MAPA: 161 | CW23: 0 | CY23: 288 | CZ23: MAPA: 161 | DA23: 0 | DE23: 0 | DF23: A. | DG23: PR | DH23: ARAUCARIA | DI23: 9026067267 | DJ23: (41 ) 38887555 | DK23: 0 | DL23: CTB | DM23: 244.62
A24: 2 | B24: CTB070760-1 | C24: COMPLEMENTAR FRETE | D24: CTBP | E24: CTB | F24: 46239 | G24: AZS7C31 | H24: 41260803098929000606570010000716561003667992 | I24: 05094003000155 | J24: COLSON DO BRASIL LTDA | K24: RUA DAS PALMEIRAS 350 | L24: CAPELA VELHA | M24: 002 | N24: ARAUCARIA | O24: PR | P24: 83705-500 | Q24: 05094003000155 | R24: COLSON DO BRASIL LTDA | S24: ARAUCARIA | T24: PR | U24: 05094003000155 | V24: COLSON DO BRASIL LTDA | W24: RUA DAS PALMEIRAS 350 | X24: CAPELA VELHA | Y24: ARAUCARIA | Z24: PR | AA24: (41 ) 38887555 | AC24: 23476033002909 | AD24: BMB MATERIAL DE CONSTRUCAO SA | AE24: 05 ZONA LESTE | AF24: SPOP | AG24: SAO PAULO | AH24: SP | AI24: 23476033002909 | AJ24: BMB MATERIAL DE CONSTRUCAO SA | AK24: SAO PAULO | AL24: SP | AM24: SPO | AN24: 000187693 | AO24: 49.28 | AP24: 0 | AQ24: 3 | AR24: 0 | AS24: CP | AT24: LIQUIDADO | AU24: 46253 | AV24: 284.09 | AW24: 001-DIVERSOS | AX24: 001-DIVERSOS | AY24: 1473.07 | AZ24: COMPLEMENTAR DE FRETE | BB24: 284.09 | BC24: 250 | BD24: 284.09 | BE24: 34.09 | BF24: 0.12 | BG24: 0 | BH24: 49.28 | BI24: 0 | BJ24: 250 | BK24: 0 | BL24: 0 | BM24: 0 | BN24: 0 | BO24: 0 | BP24: 0 | BQ24: 0 | BR24: 0 | BS24: 0 | BT24: 0 | BU24: 0 | BV24: 0 | BW24: 0 | BX24: 0 | BY24: 0 | BZ24: 0 | CA24: 0 | CB24: CTBP | CC24: SPOP | CD24: 372.72 | CE24: 0 | CF24: 0 | CG24: 0 | CH24: 0 | CI24: 0 | CJ24: 0 | CK24: 0 | CN24: 0 | CO24: 0 | CP24: 0 | CQ24: 0 | CR24: 0 | CS24: 0 | CT24: 0 | CU24: 0 | CV24: MAPA: 0 | CW24: 0 | CY24: 0 | CZ24: MAPA: 0 | DA24: 0 | DE24: 0 | DF24: A. | DG24: PR | DH24: ARAUCARIA | DI24: 9026067267 | DJ24: (41 ) 38887555 | DK24: 0 | DL24: CTB | DM24: 34.09
A25: 2 | B25: CTB070815-1 | C25: NORMAL | D25: CTBP | E25: CTB | F25: 46239 | G25: BFE7A89 | H25: 41260803098929000606570010000717111003674151 | I25: 05094003000155 | J25: COLSON DO BRASIL LTDA | K25: RUA DAS PALMEIRAS 350 | L25: CAPELA VELHA | M25: 002 | N25: ARAUCARIA | O25: PR | P25: 83705-500 | Q25: 05094003000155 | R25: COLSON DO BRASIL LTDA | S25: ARAUCARIA | T25: PR | U25: 05094003000155 | V25: COLSON DO BRASIL LTDA | W25: RUA DAS PALMEIRAS 350 | X25: CAPELA VELHA | Y25: ARAUCARIA | Z25: PR | AA25: (41 ) 38887555 | AC25: 43011160000149 | AD25: ADELMO SILVA SANTOS EQUIPAMENTOS | AE25: 11 ABCD | AF25: SPOP | AG25: DIADEMA | AH25: SP | AI25: 43011160000149 | AJ25: ADELMO SILVA SANTOS EQUIPAMENTOS | AK25: DIADEMA | AL25: SP | AM25: SPO | AN25: 000188960 | AO25: 35.061 | AP25: 0 | AQ25: 3 | AR25: 0 | AS25: CP | AT25: LIQUIDADO | AU25: 46253 | AV25: 113.5 | AW25: 001-DIVERSOS | AX25: 001-DIVERSOS | AY25: 1517.68 | AZ25: COMBINADA | BA25: CO3365274 | BB25: 113.5 | BC25: 99.88 | BD25: 113.5 | BE25: 13.62 | BF25: 0.12 | BG25: 0 | BH25: 35.061 | BI25: 56.8 | BJ25: 0 | BK25: 17 | BL25: 0 | BM25: 9.76 | BN25: 2.28 | BO25: 5.5 | BP25: 3.23 | BQ25: 0 | BR25: 0 | BS25: 0 | BT25: 0 | BU25: 0 | BV25: 0 | BW25: 0 | BX25: 0 | BY25: 0 | BZ25: 0 | CA25: 5.31 | CB25: CTBP | CC25: SPOP | CD25: 373.23 | CE25: 0 | CF25: 0 | CG25: 0 | CH25: 0 | CI25: 0 | CJ25: 0 | CK25: 0 | CN25: 0 | CO25: 0 | CP25: 0 | CQ25: 0 | CR25: 0 | CS25: 0 | CT25: 0 | CU25: 12 | CV25: MAPA: 161 | CW25: 0 | CY25: 18 | CZ25: MAPA: 161 | DA25: 0 | DE25: 0 | DF25: A. | DG25: PR | DH25: ARAUCARIA | DI25: 9026067267 | DJ25: (41 ) 38887555 | DK25: 0 | DL25: CTB | DM25: 13.62
A26: 2 | B26: CTB070816-0 | C26: NORMAL | D26: CTBP | E26: CTB | F26: 46239 | G26: BFE7A89 | H26: 41260803098929000606570010000717121003674167 | I26: 05094003000155 | J26: COLSON DO BRASIL LTDA | K26: RUA DAS PALMEIRAS 350 | L26: CAPELA VELHA | M26: 002 | N26: ARAUCARIA | O26: PR | P26: 83705-500 | Q26: 05094003000155 | R26: COLSON DO BRASIL LTDA | S26: ARAUCARIA | T26: PR | U26: 05094003000155 | V26: COLSON DO BRASIL LTDA | W26: RUA DAS PALMEIRAS 350 | X26: CAPELA VELHA | Y26: ARAUCARIA | Z26: PR | AA26: (41 ) 38887555 | AC26: 18712769000106 | AD26: MANHUACU LOCACAO DE EQUIP LTDA | AE26: 369 | AF26: GVRP | AG26: MANHUACU | AH26: MG | AI26: 18712769000106 | AJ26: MANHUACU LOCACAO DE EQUIP LTDA | AK26: MANHUACU | AL26: MG | AM26: GVR | AN26: 000188916 | AO26: 149.4 | AP26: 0 | AQ26: 9 | AR26: 0 | AS26: CP | AT26: LIQUIDADO | AU26: 46253 | AV26: 268.61 | AW26: 001-DIVERSOS | AX26: 001-DIVERSOS | AY26: 3212.6 | AZ26: COMBINADA | BA26: CO3365294 | BB26: 268.61 | BC26: 236.38 | BD26: 268.61 | BE26: 32.23 | BF26: 0.12 | BG26: 0 | BH26: 149.4 | BI26: 179.33 | BJ26: 0 | BK26: 17 | BL26: 0 | BM26: 9.76 | BN26: 4.82 | BO26: 11 | BP26: 3.23 | BQ26: 0 | BR26: 0 | BS26: 0 | BT26: 0 | BU26: 0 | BV26: 0 | BW26: 0 | BX26: 0 | BY26: 0 | BZ26: 0 | CA26: 11.24 | CB26: CTBP | CC26: RWNI | CD26: 391.79 | CE26: 0 | CF26: 0 | CG26: 0 | CH26: 0 | CI26: 0 | CJ26: 0 | CK26: 0 | CN26: 0 | CO26: 0 | CP26: 0 | CQ26: 0 | CR26: 0 | CS26: 0 | CT26: 0 | CU26: 22.41 | CV26: MAPA: 161 | CW26: 0 | CY26: 103.01 | CZ26: FATURA: 12222 | DA26: 103.01 | DB26: 012222 | DE26: 0 | DF26: A. | DG26: PR | DH26: ARAUCARIA | DI26: 9026067267 | DJ26: (41 ) 38887555 | DK26: 0 | DL26: CTB | DM26: 32.23
A27: 2 | B27: CTB070817-8 | C27: NORMAL | D27: CTBP | E27: CTB | F27: 46239 | G27: BFE7A89 | H27: 41260803098929000606570010000717131003674172 | I27: 05094003000155 | J27: COLSON DO BRASIL LTDA | K27: RUA DAS PALMEIRAS 350 | L27: CAPELA VELHA | M27: 002 | N27: ARAUCARIA | O27: PR | P27: 83705-500 | Q27: 05094003000155 | R27: COLSON DO BRASIL LTDA | S27: ARAUCARIA | T27: PR | U27: 05094003000155 | V27: COLSON DO BRASIL LTDA | W27: RUA DAS PALMEIRAS 350 | X27: CAPELA VELHA | Y27: ARAUCARIA | Z27: PR | AA27: (41 ) 38887555 | AC27: 23151087000284 | AD27: CELIO GROSSI FERRGS LTDA | AE27: 365 | AF27: TAMR | AG27: VICOSA | AH27: MG | AI27: 23151087000284 | AJ27: CELIO GROSSI FERRGS LTDA | AK27: VICOSA | AL27: MG | AM27: TAM | AN27: 000188859 | AO27: 200.55 | AP27: 0 | AQ27: 21 | AR27: 0 | AS27: CP | AT27: LIQUIDADO | AU27: 46253 | AV27: 321.93 | AW27: 001-DIVERSOS | AX27: 001-DIVERSOS | AY27: 6353.02 | AZ27: COMBINADA | BA27: CO3365280 | BB27: 321.93 | BC27: 283.3 | BD27: 321.93 | BE27: 38.63 | BF27: 0.12 | BG27: 0 | BH27: 200.55 | BI27: 205.04 | BJ27: 0 | BK27: 17 | BL27: 0 | BM27: 9.76 | BN27: 9.53 | BO27: 16.5 | BP27: 3.23 | BQ27: 0 | BR27: 0 | BS27: 0 | BT27: 0 | BU27: 0 | BV27: 0 | BW27: 0 | BX27: 0 | BY27: 0 | BZ27: 0 | CA27: 22.24 | CB27: CTBP | CC27: TAMR | CD27: 433.98 | CE27: 0 | CF27: 0 | CG27: 0 | CH27: 0 | CI27: 0 | CJ27: 0 | CK27: 0 | CN27: 0 | CO27: 0 | CP27: 0 | CQ27: 0 | CR27: 0 | CS27: 0 | CT27: 0 | CU27: 30.08 | CV27: MAPA: 161 | CW27: 0 | CY27: 100.28 | CZ27: FATURA: 21534 | DA27: 100.28 | DB27: 021534 | DE27: 0 | DF27: A. | DG27: PR | DH27: ARAUCARIA | DI27: 9026067267 | DJ27: (41 ) 38887555 | DK27: 0 | DL27: CTB | DM27: 38.63
A28: 2 | B28: CTB070818-6 | C28: NORMAL | D28: CTBP | E28: CTB | F28: 46239 | G28: BFE7A89 | H28: 41260803098929000606570010000717141003674188 | I28: 05094003000155 | J28: COLSON DO BRASIL LTDA | K28: RUA DAS PALMEIRAS 350 | L28: CAPELA VELHA | M28: 002 | N28: ARAUCARIA | O28: PR | P28: 83705-500 | Q28: 05094003000155 | R28: COLSON DO BRASIL LTDA | S28: ARAUCARIA | T28: PR | U28: 05094003000155 | V28: COLSON DO BRASIL LTDA | W28: RUA DAS PALMEIRAS 350 | X28: CAPELA VELHA | Y28: ARAUCARIA | Z28: PR | AA28: (41 ) 38887555 | AC28: 11601412000101 | AD28: BAZAR E ARMARINHO TRES IRMAOS LTDA ME | AE28: RIO RIO DE JANEIRO | AF28: RJOP | AG28: RIO DE JANEIRO | AH28: RJ | AI28: 11601412000101 | AJ28: BAZAR E ARMARINHO TRES IRMAOS LTDA ME | AK28: RIO DE JANEIRO | AL28: RJ | AM28: RJO | AN28: 000188855 | AO28: 137.4 | AP28: 0 | AQ28: 15 | AR28: 0 | AS28: CP | AT28: LIQUIDADO | AU28: 46253 | AV28: 211.63 | AW28: 001-DIVERSOS | AX28: 054-PNEUS E CAMARAS DE AR | AY28: 4315.19 | AZ28: COMBINADA | BA28: CO3365267 | BB28: 211.63 | BC28: 186.23 | BD28: 211.63 | BE28: 25.4 | BF28: 0.12 | BG28: 0 | BH28: 137.4 | BI28: 123.67 | BJ28: 0 | BK28: 17 | BL28: 0 | BM28: 9.76 | BN28: 6.47 | BO28: 11 | BP28: 3.23 | BQ28: 0 | BR28: 0 | BS28: 0 | BT28: 0 | BU28: 0 | BV28: 0 | BW28: 0 | BX28: 0 | BY28: 0 | BZ28: 0 | CA28: 15.1 | CB28: CTBP | CC28: RJOP | CD28: 406.12 | CE28: 0 | CF28: 0 | CG28: 0 | CH28: 0 | CI28: 0 | CJ28: 0 | CK28: 0 | CN28: 0 | CO28: 0 | CP28: 0 | CQ28: 0 | CR28: 0 | CS28: 0 | CT28: 0 | CU28: 20.61 | CV28: MAPA: 161 | CW28: 0 | CY28: 24.73 | CZ28: MAPA: 161 | DA28: 0 | DE28: 0 | DF28: A. | DG28: PR | DH28: ARAUCARIA | DI28: 9026067267 | DJ28: (41 ) 38887555 | DK28: 0 | DL28: CTB | DM28: 25.4
A29: 2 | B29: CTB070819-4 | C29: NORMAL | D29: CTBP | E29: CTB | F29: 46239 | G29: BFE7A89 | H29: 41260803098929000606570010000717151003674193 | I29: 05094003000155 | J29: COLSON DO BRASIL LTDA | K29: RUA DAS PALMEIRAS 350 | L29: CAPELA VELHA | M29: 002 | N29: ARAUCARIA | O29: PR | P29: 83705-500 | Q29: 05094003000155 | R29: COLSON DO BRASIL LTDA | S29: ARAUCARIA | T29: PR | U29: 05094003000155 | V29: COLSON DO BRASIL LTDA | W29: RUA DAS PALMEIRAS 350 | X29: CAPELA VELHA | Y29: ARAUCARIA | Z29: PR | AA29: (41 ) 38887555 | AC29: 21020745000192 | AD29: SUAVIDA EPIS EIRELI 950019 | AE29: RIO RIO DE JANEIRO | AF29: RJOP | AG29: RIO DE JANEIRO | AH29: RJ | AI29: 21020745000192 | AJ29: SUAVIDA EPIS EIRELI 950019 | AK29: RIO DE JANEIRO | AL29: RJ | AM29: RJO | AN29: 000188815 | AO29: 149.23 | AP29: 0 | AQ29: 21 | AR29: 0 | AS29: CP | AT29: LIQUIDADO | AU29: 46253 | AV29: 217.86 | AW29: 001-DIVERSOS | AX29: 001-DIVERSOS | AY29: 3281.56 | AZ29: COMBINADA | BA29: CO3365267 | BB29: 217.86 | BC29: 191.72 | BD29: 217.86 | BE29: 26.14 | BF29: 0.12 | BG29: 0 | BH29: 149.23 | BI29: 134.32 | BJ29: 0 | BK29: 17 | BL29: 0 | BM29: 9.76 | BN29: 4.92 | BO29: 11 | BP29: 3.23 | BQ29: 0 | BR29: 0 | BS29: 0 | BT29: 0 | BU29: 0 | BV29: 0 | BW29: 0 | BX29: 0 | BY29: 0 | BZ29: 0 | CA29: 11.49 | CB29: CTBP | CC29: RJOP | CD29: 392.68 | CE29: 0 | CF29: 0 | CG29: 0 | CH29: 0 | CI29: 0 | CJ29: 0 | CK29: 0 | CN29: 0 | CO29: 0 | CP29: 0 | CQ29: 0 | CR29: 0 | CS29: 0 | CT29: 0 | CU29: 22.38 | CV29: MAPA: 161 | CW29: 0 | CY29: 26.86 | CZ29: MAPA: 161 | DA29: 0 | DE29: 0 | DF29: A. | DG29: PR | DH29: ARAUCARIA | DI29: 9026067267 | DJ29: (41 ) 38887555 | DK29: 0 | DL29: CTB | DM29: 26.14
A30: 2 | B30: CTB070820-8 | C30: NORMAL | D30: CTBP | E30: CTB | F30: 46239 | G30: BFE7A89 | H30: 41260803098929000606570010000717161003674204 | I30: 05094003000155 | J30: COLSON DO BRASIL LTDA | K30: RUA DAS PALMEIRAS 350 | L30: CAPELA VELHA | M30: 002 | N30: ARAUCARIA | O30: PR | P30: 83705-500 | Q30: 05094003000155 | R30: COLSON DO BRASIL LTDA | S30: ARAUCARIA | T30: PR | U30: 05094003000155 | V30: COLSON DO BRASIL LTDA | W30: RUA DAS PALMEIRAS 350 | X30: CAPELA VELHA | Y30: ARAUCARIA | Z30: PR | AA30: (41 ) 38887555 | AC30: 16691059000103 | AD30: FAMART DISTRIBUIDORA DE FERRAGENS LTDA | AE30: 257 | AF30: MVGP | AG30: PETROPOLIS | AH30: RJ | AI30: 16691059000103 | AJ30: FAMART DISTRIBUIDORA DE FERRAGENS LTDA | AK30: PETROPOLIS | AL30: RJ | AM30: MVG | AN30: 000188909 | AO30: 271.414 | AP30: 0 | AQ30: 23 | AR30: 0 | AS30: CP | AT30: LIQUIDADO | AU30: 46253 | AV30: 737.32 | AW30: 001-DIVERSOS | AX30: 054-PNEUS E CAMARAS DE AR | AY30: 6960.96 | AZ30: COMBINADA | BA30: CO3365270 | BB30: 737.32 | BC30: 648.84 | BD30: 737.32 | BE30: 88.48 | BF30: 0.12 | BG30: 0 | BH30: 271.414 | BI30: 317.55 | BJ30: 0 | BK30: 17 | BL30: 0 | BM30: 9.76 | BN30: 10.44 | BO30: 16.5 | BP30: 3.23 | BQ30: 0 | BR30: 0 | BS30: 0 | BT30: 0 | BU30: 0 | BV30: 0 | BW30: 0 | BX30: 250 | BY30: 0 | BZ30: 0 | CA30: 24.36 | CB30: CTBP | CC30: ITAI | CD30: 619.02 | CE30: 0 | CF30: 0 | CG30: 0 | CH30: 0 | CI30: 0 | CJ30: 0 | CK30: 0 | CN30: 0 | CO30: 0 | CP30: 0 | CQ30: 0 | CR30: 0 | CS30: 0 | CT30: 0 | CU30: 40.71 | CV30: MAPA: 161 | CW30: 0 | CY30: 408.52 | CZ30: FATURA: 17774 | DA30: 324.32 | DB30: 017774 | DE30: 0 | DF30: A. | DG30: PR | DH30: ARAUCARIA | DI30: 9026067267 | DJ30: (41 ) 38887555 | DK30: 0 | DL30: CTB | DM30: 88.48
A31: 2 | B31: CTB070821-6 | C31: NORMAL | D31: CTBP | E31: CTB | F31: 46239 | G31: BFE7A89 | H31: 41260803098929000606570010000717171003674210 | I31: 05094003000155 | J31: COLSON DO BRASIL LTDA | K31: RUA DAS PALMEIRAS 350 | L31: CAPELA VELHA | M31: 002 | N31: ARAUCARIA | O31: PR | P31: 83705-500 | Q31: 05094003000155 | R31: COLSON DO BRASIL LTDA | S31: ARAUCARIA | T31: PR | U31: 05094003000155 | V31: COLSON DO BRASIL LTDA | W31: RUA DAS PALMEIRAS 350 | X31: CAPELA VELHA | Y31: ARAUCARIA | Z31: PR | AA31: (41 ) 38887555 | AC31: 15096516000159 | AD31: MOUTINHO REIS SUPORTE EM EQUIPAMENT | AE31: 10 BARUERI | AF31: SPOP | AG31: BARUERI | AH31: SP | AI31: 15096516000159 | AJ31: MOUTINHO REIS SUPORTE EM EQUIPAMENT | AK31: BARUERI | AL31: SP | AM31: SPO | AN31: 000188923 | AO31: 23.8 | AP31: 0 | AQ31: 2 | AR31: 0 | AS31: CP | AT31: LIQUIDADO | AU31: 46253 | AV31: 114.75 | AW31: 001-DIVERSOS | AX31: 001-DIVERSOS | AY31: 3458.05 | AZ31: COMBINADA | BA31: CO3365274 | BB31: 114.75 | BC31: 100.98 | BD31: 114.75 | BE31: 13.77 | BF31: 0.12 | BG31: 0 | BH31: 23.8 | BI31: 48.2 | BJ31: 0 | BK31: 17 | BL31: 0 | BM31: 9.76 | BN31: 5.19 | BO31: 5.5 | BP31: 3.23 | BQ31: 0 | BR31: 0 | BS31: 0 | BT31: 0 | BU31: 0 | BV31: 0 | BW31: 0 | BX31: 0 | BY31: 0 | BZ31: 0 | CA31: 12.1 | CB31: CTBP | CC31: SPOP | CD31: 395.01 | CE31: 0 | CF31: 0 | CG31: 0 | CH31: 0 | CI31: 0 | CJ31: 0 | CK31: 0 | CN31: 0 | CO31: 0 | CP31: 0 | CQ31: 0 | CR31: 0 | CS31: 0 | CT31: 0 | CU31: 12 | CV31: MAPA: 161 | CW31: 0 | CY31: 18 | CZ31: MAPA: 161 | DA31: 0 | DE31: 0 | DF31: A. | DG31: PR | DH31: ARAUCARIA | DI31: 9026067267 | DJ31: (41 ) 38887555 | DK31: 0 | DL31: CTB | DM31: 13.77
A32: 2 | B32: CTB070822-4 | C32: NORMAL | D32: CTBP | E32: CTB | F32: 46239 | G32: BFE7A89 | H32: 41260803098929000606570010000717181003674225 | I32: 05094003000155 | J32: COLSON DO BRASIL LTDA | K32: RUA DAS PALMEIRAS 350 | L32: CAPELA VELHA | M32: 002 | N32: ARAUCARIA | O32: PR | P32: 83705-500 | Q32: 05094003000155 | R32: COLSON DO BRASIL LTDA | S32: ARAUCARIA | T32: PR | U32: 05094003000155 | V32: COLSON DO BRASIL LTDA | W32: RUA DAS PALMEIRAS 350 | X32: CAPELA VELHA | Y32: ARAUCARIA | Z32: PR | AA32: (41 ) 38887555 | AC32: 30999394000102 | AD32: TECNO PRO PARAFUSOS E FERRAMEN | AE32: 332 | AF32: BHZP | AG32: LAGOA SANTA | AH32: MG | AI32: 30999394000102 | AJ32: TECNO PRO PARAFUSOS E FERRAMEN | AK32: LAGOA SANTA | AL32: MG | AM32: BHZ | AN32: 000188913 | AO32: 79.02 | AP32: 0 | AQ32: 11 | AR32: 0 | AS32: CP | AT32: LIQUIDADO | AU32: 46253 | AV32: 171.99 | AW32: 001-DIVERSOS | AX32: 001-DIVERSOS | AY32: 2932.62 | AZ32: COMBINADA | BA32: CO3365271 | BB32: 171.99 | BC32: 151.35 | BD32: 171.99 | BE32: 20.64 | BF32: 0.12 | BG32: 0 | BH32: 79.02 | BI32: 101.2 | BJ32: 0 | BK32: 17 | BL32: 0 | BM32: 9.76 | BN32: 4.4 | BO32: 5.5 | BP32: 3.23 | BQ32: 0 | BR32: 0 | BS32: 0 | BT32: 0 | BU32: 0 | BV32: 0 | BW32: 0 | BX32: 0 | BY32: 0 | BZ32: 0 | CA32: 10.26 | CB32: CTBP | CC32: BHZP | CD32: 388.15 | CE32: 0 | CF32: 0 | CG32: 0 | CH32: 0 | CI32: 0 | CJ32: 0 | CK32: 0 | CN32: 0 | CO32: 0 | CP32: 0 | CQ32: 0 | CR32: 0 | CS32: 0 | CT32: 0 | CU32: 12 | CV32: MAPA: 161 | CW32: 0 | CY32: 15 | CZ32: MAPA: 161 | DA32: 0 | DE32: 0 | DF32: A. | DG32: PR | DH32: ARAUCARIA | DI32: 9026067267 | DJ32: (41 ) 38887555 | DK32: 0 | DL32: CTB | DM32: 20.64
A33: 2 | B33: CTB070823-2 | C33: NORMAL | D33: CTBP | E33: CTB | F33: 46239 | G33: BFE7A89 | H33: 41260803098929000606570010000717191003674230 | I33: 05094003000155 | J33: COLSON DO BRASIL LTDA | K33: RUA DAS PALMEIRAS 350 | L33: CAPELA VELHA | M33: 002 | N33: ARAUCARIA | O33: PR | P33: 83705-500 | Q33: 05094003000155 | R33: COLSON DO BRASIL LTDA | S33: ARAUCARIA | T33: PR | U33: 05094003000155 | V33: COLSON DO BRASIL LTDA | W33: RUA DAS PALMEIRAS 350 | X33: CAPELA VELHA | Y33: ARAUCARIA | Z33: PR | AA33: (41 ) 38887555 | AC33: 18565489000104 | AD33: BARROS E BEIRAL ATACADO E VAREJO LTDA | AE33: 282 | AF33: RCGR | AG33: SAO FRANCISCO DE ITABAPOANA | AH33: RJ | AI33: 18565489000104 | AJ33: BARROS E BEIRAL ATACADO E VAREJO LTDA | AK33: SAO FRANCISCO DE ITABAPOANA | AL33: RJ | AM33: RCG | AN33: 000188919 | AO33: 458.155 | AP33: 0 | AQ33: 35 | AR33: 0 | AS33: CP | AT33: LIQUIDADO | AU33: 46253 | AV33: 760.59 | AW33: 001-DIVERSOS | AX33: 054-PNEUS E CAMARAS DE AR | AY33: 15156.76 | AZ33: COMBINADA | BA33: CO3365270 | BB33: 760.59 | BC33: 669.32 | BD33: 760.59 | BE33: 91.27 | BF33: 0.12 | BG33: 0 | BH33: 458.155 | BI33: 536.04 | BJ33: 0 | BK33: 17 | BL33: 0 | BM33: 9.76 | BN33: 22.74 | BO33: 27.5 | BP33: 3.23 | BQ33: 0 | BR33: 0 | BS33: 0 | BT33: 0 | BU33: 0 | BV33: 0 | BW33: 0 | BX33: 0 | BY33: 0 | BZ33: 0 | CA33: 53.05 | CB33: CTBP | CC33: ITAI | CD33: 1192.52 | CE33: 0 | CF33: 0 | CG33: 0 | CH33: 0 | CI33: 0 | CJ33: 0 | CK33: 0 | CN33: 0 | CO33: 0 | CP33: 0 | CQ33: 0 | CR33: 0 | CS33: 0 | CT33: 0 | CU33: 68.72 | CV33: MAPA: 161 | CW33: 0 | CY33: 254.46 | CZ33: FATURA: 12167 | DA33: 286.41 | DB33: 012167 | DE33: 0 | DF33: A. | DG33: PR | DH33: ARAUCARIA | DI33: 9026067267 | DJ33: (41 ) 38887555 | DK33: 0 | DL33: CTB | DM33: 91.27
A34: 2 | B34: CTB070824-1 | C34: NORMAL | D34: CTBP | E34: CTB | F34: 46239 | G34: BFE7A89 | H34: 41260803098929000606570010000717201003674240 | I34: 05094003000155 | J34: COLSON DO BRASIL LTDA | K34: RUA DAS PALMEIRAS 350 | L34: CAPELA VELHA | M34: 002 | N34: ARAUCARIA | O34: PR | P34: 83705-500 | Q34: 05094003000155 | R34: COLSON DO BRASIL LTDA | S34: ARAUCARIA | T34: PR | U34: 05094003000155 | V34: COLSON DO BRASIL LTDA | W34: RUA DAS PALMEIRAS 350 | X34: CAPELA VELHA | Y34: ARAUCARIA | Z34: PR | AA34: (41 ) 38887555 | AC34: 27951336000196 | AD34: J.M.F COMERCIAL EIRELI | AE34: 360 | AF34: TAMP | AG34: JUIZ DE FORA | AH34: MG | AI34: 27951336000196 | AJ34: J.M.F COMERCIAL EIRELI | AK34: JUIZ DE FORA | AL34: MG | AM34: TAM | AN34: 000188945 | AO34: 129.65 | AP34: 0 | AQ34: 17 | AR34: 0 | AS34: CP | AT34: LIQUIDADO | AU34: 46253 | AV34: 225.97 | AW34: 001-DIVERSOS | AX34: 001-DIVERSOS | AY34: 5062.79 | AZ34: COMBINADA | BA34: CO3365281 | BB34: 225.97 | BC34: 198.85 | BD34: 225.97 | BE34: 27.12 | BF34: 0.12 | BG34: 0 | BH34: 129.65 | BI34: 132.55 | BJ34: 0 | BK34: 17 | BL34: 0 | BM34: 9.76 | BN34: 7.59 | BO34: 11 | BP34: 3.23 | BQ34: 0 | BR34: 0 | BS34: 0 | BT34: 0 | BU34: 0 | BV34: 0 | BW34: 0 | BX34: 0 | BY34: 0 | BZ34: 0 | CA34: 17.72 | CB34: CTBP | CC34: TAMI | CD34: 415.84 | CE34: 0 | CF34: 0 | CG34: 0 | CH34: 0 | CI34: 0 | CJ34: 0 | CK34: 0 | CN34: 0 | CO34: 0 | CP34: 0 | CQ34: 0 | CR34: 0 | CS34: 0 | CT34: 0 | CU34: 19.45 | CV34: MAPA: 161 | CW34: 0 | CY34: 53.16 | CZ34: FATURA: 21534 | DA34: 53.16 | DB34: 021534 | DE34: 0 | DF34: A. | DG34: PR | DH34: ARAUCARIA | DI34: 9026067267 | DJ34: (41 ) 38887555 | DK34: 0 | DL34: CTB | DM34: 27.12
A35: 2 | B35: CTB070847-0 | C35: NORMAL | D35: CTBP | E35: CTB | F35: 46240 | G35: DQB8989 | H35: 41260803098929000606570010000717431003680635 | I35: 05094003000155 | J35: COLSON DO BRASIL LTDA | K35: RUA DAS PALMEIRAS 350 | L35: CAPELA VELHA | M35: 002 | N35: ARAUCARIA | O35: PR | P35: 83705-500 | Q35: 05094003000155 | R35: COLSON DO BRASIL LTDA | S35: ARAUCARIA | T35: PR | U35: 05094003000155 | V35: COLSON DO BRASIL LTDA | W35: RUA DAS PALMEIRAS 350 | X35: CAPELA VELHA | Y35: ARAUCARIA | Z35: PR | AA35: (41 ) 38887555 | AC35: 11927842000100 | AD35: TIAGO DE BROI EIRELI | AE35: 17 INTERIOR CPS | AF35: PSPP | AG35: JUNDIAI | AH35: SP | AI35: 11927842000100 | AJ35: TIAGO DE BROI EIRELI | AK35: JUNDIAI | AL35: SP | AM35: PSP | AN35: 000189034 | AO35: 62.3 | AP35: 0 | AQ35: 7 | AR35: 0 | AS35: CP | AT35: LIQUIDADO | AU35: 46253 | AV35: 156.27 | AW35: 001-DIVERSOS | AX35: 001-DIVERSOS | AY35: 4546.1 | AZ35: COMBINADA | BA35: CO3365274 | BB35: 156.27 | BC35: 137.52 | BD35: 156.27 | BE35: 18.75 | BF35: 0.12 | BG35: 0 | BH35: 62.3 | BI35: 79.3 | BJ35: 0 | BK35: 17 | BL35: 0 | BM35: 9.76 | BN35: 6.82 | BO35: 5.5 | BP35: 3.23 | BQ35: 0 | BR35: 0 | BS35: 0 | BT35: 0 | BU35: 0 | BV35: 0 | BW35: 0 | BX35: 0 | BY35: 0 | BZ35: 0 | CA35: 15.91 | CB35: CTBP | CC35: SPOP | CD35: 409.08 | CE35: 0 | CF35: 0 | CG35: 0 | CH35: 0 | CI35: 0 | CJ35: 0 | CK35: 0 | CN35: 0 | CO35: 0 | CP35: 0 | CQ35: 0 | CR35: 0 | CS35: 0 | CT35: 0 | CU35: 12 | CV35: MAPA: 161 | CW35: 0 | CY35: 60.5 | CZ35: MAPA: 161 | DA35: =CY35 -> 60.5 | DE35: 0 | DF35: A. | DG35: PR | DH35: ARAUCARIA | DI35: 9026067267 | DJ35: (41 ) 38887555 | DK35: 0 | DL35: CTB | DM35: 18.75
A36: 2 | B36: CTB070848-8 | C36: NORMAL | D36: CTBP | E36: CTB | F36: 46240 | G36: DQB8989 | H36: 41260803098929000606570010000717441003680640 | I36: 05094003000155 | J36: COLSON DO BRASIL LTDA | K36: RUA DAS PALMEIRAS 350 | L36: CAPELA VELHA | M36: 002 | N36: ARAUCARIA | O36: PR | P36: 83705-500 | Q36: 05094003000155 | R36: COLSON DO BRASIL LTDA | S36: ARAUCARIA | T36: PR | U36: 05094003000155 | V36: COLSON DO BRASIL LTDA | W36: RUA DAS PALMEIRAS 350 | X36: CAPELA VELHA | Y36: ARAUCARIA | Z36: PR | AA36: (41 ) 38887555 | AC36: 18358316000115 | AD36: DX FIT PISO ARTIGOS ESPORTIVOS | AE36: 08 ZONA SUDOESTE | AF36: SPOP | AG36: TABOAO DA SERRA | AH36: SP | AI36: 18358316000115 | AJ36: DX FIT PISO ARTIGOS ESPORTIVOS | AK36: TABOAO DA SERRA | AL36: SP | AM36: SPO | AN36: 000189043 | AO36: 34.44 | AP36: 0 | AQ36: 3 | AR36: 0 | AS36: CP | AT36: LIQUIDADO | AU36: 46253 | AV36: 397.86 | AW36: 001-DIVERSOS | AX36: 001-DIVERSOS | AY36: 1565.55 | AZ36: COMBINADA | BA36: CO3365274 | BB36: 397.86 | BC36: 350.12 | BD36: 397.86 | BE36: 47.74 | BF36: 0.12 | BG36: 0 | BH36: 34.44 | BI36: 56.8 | BJ36: 0 | BK36: 17 | BL36: 0 | BM36: 9.76 | BN36: 2.35 | BO36: 5.5 | BP36: 3.23 | BQ36: 0 | BR36: 0 | BS36: 0 | BT36: 0 | BU36: 0 | BV36: 0 | BW36: 0 | BX36: 250 | BY36: 0 | BZ36: 0 | CA36: 5.48 | CB36: CTBP | CC36: SPOP | CD36: 373.65 | CE36: 0 | CF36: 0 | CG36: 0 | CH36: 0 | CI36: 0 | CJ36: 0 | CK36: 0 | CN36: 0 | CO36: 0 | CP36: 0 | CQ36: 0 | CR36: 0 | CS36: 0 | CT36: 0 | CU36: 12 | CV36: MAPA: 161 | CW36: 0 | CY36: 18 | CZ36: MAPA: 161 | DA36: 0 | DE36: 0 | DF36: A. | DG36: PR | DH36: ARAUCARIA | DI36: 9026067267 | DJ36: (41 ) 38887555 | DK36: 0 | DL36: CTB | DM36: 47.74
A37: 2 | B37: CTB070849-6 | C37: NORMAL | D37: CTBP | E37: CTB | F37: 46240 | G37: DQB8989 | H37: 41260803098929000606570010000717451003680656 | I37: 05094003000155 | J37: COLSON DO BRASIL LTDA | K37: RUA DAS PALMEIRAS 350 | L37: CAPELA VELHA | M37: 002 | N37: ARAUCARIA | O37: PR | P37: 83705-500 | Q37: 05094003000155 | R37: COLSON DO BRASIL LTDA | S37: ARAUCARIA | T37: PR | U37: 05094003000155 | V37: COLSON DO BRASIL LTDA | W37: RUA DAS PALMEIRAS 350 | X37: CAPELA VELHA | Y37: ARAUCARIA | Z37: PR | AA37: (41 ) 38887555 | AC37: 23476033001694 | AD37: BMB MATERIAL DE CONSTRUCAO S.A. 0016-94 | AE37: 291 | AF37: EPSP | AG37: CARIACICA | AH37: ES | AI37: 23476033001694 | AJ37: BMB MATERIAL DE CONSTRUCAO S.A. 0016-94 | AK37: CARIACICA | AL37: ES | AM37: EPS | AN37: 000188977 | AO37: 75.75 | AP37: 0 | AQ37: 7 | AR37: 0 | AS37: CP | AT37: LIQUIDADO | AU37: 46253 | AV37: 444.06 | AW37: 001-DIVERSOS | AX37: 001-DIVERSOS | AY37: 2337.69 | AZ37: COMBINADA | BA37: CO3365268 | BB37: 444.06 | BC37: 412.98 | BD37: 444.06 | BE37: 31.08 | BF37: 0.07 | BG37: 0 | BH37: 75.75 | BI37: 115.8 | BJ37: 0 | BK37: 17 | BL37: 0 | BM37: 9.76 | BN37: 3.51 | BO37: 5.5 | BP37: 3.23 | BQ37: 0 | BR37: 0 | BS37: 0 | BT37: 0 | BU37: 0 | BV37: 0 | BW37: 0 | BX37: 250 | BY37: 0 | BZ37: 0 | CA37: 8.18 | CB37: CTBP | CC37: EPSP | CD37: 381.36 | CE37: 0 | CF37: 0 | CG37: 0 | CH37: 0 | CI37: 0 | CJ37: 0 | CK37: 0 | CN37: 0 | CO37: 0 | CP37: 0 | CQ37: 0 | CR37: 0 | CS37: 0 | CT37: 0 | CU37: 12 | CV37: MAPA: 161 | CW37: 0 | CY37: 328.23 | CZ37: FATURA: 55301 | DA37: 213.15 | DB37: 055301 | DE37: 0 | DF37: A. | DG37: PR | DH37: ARAUCARIA | DI37: 9026067267 | DJ37: (41 ) 38887555 | DK37: 0 | DL37: CTB | DM37: 31.08
A38: 2 | B38: CTB070850-0 | C38: NORMAL | D38: CTBP | E38: CTB | F38: 46240 | G38: DQB8989 | H38: 41260803098929000606570010000717461003680661 | I38: 05094003000155 | J38: COLSON DO BRASIL LTDA | K38: RUA DAS PALMEIRAS 350 | L38: CAPELA VELHA | M38: 002 | N38: ARAUCARIA | O38: PR | P38: 83705-500 | Q38: 05094003000155 | R38: COLSON DO BRASIL LTDA | S38: ARAUCARIA | T38: PR | U38: 05094003000155 | V38: COLSON DO BRASIL LTDA | W38: RUA DAS PALMEIRAS 350 | X38: CAPELA VELHA | Y38: ARAUCARIA | Z38: PR | AA38: (41 ) 38887555 | AC38: 26393341000168 | AD38: COSAMA COMERCIO DE FERRAGENS E FERR | AE38: 133 | AF38: PSPP | AG38: INDAIATUBA | AH38: SP | AI38: 26393341000168 | AJ38: COSAMA COMERCIO DE FERRAGENS E FERR | AK38: INDAIATUBA | AL38: SP | AM38: PSP | AN38: 000188979 | AO38: 41.28 | AP38: 0 | AQ38: 8 | AR38: 0 | AS38: CP | AT38: LIQUIDADO | AU38: 46253 | AV38: 160.3 | AW38: 001-DIVERSOS | AX38: 001-DIVERSOS | AY38: 1517.69 | AZ38: COMBINADA | BA38: CO3365266 | BB38: 160.3 | BC38: 141.06 | BD38: 160.3 | BE38: 19.24 | BF38: 0.12 | BG38: 0 | BH38: 41.28 | BI38: 97.98 | BJ38: 0 | BK38: 17 | BL38: 0 | BM38: 9.76 | BN38: 2.28 | BO38: 5.5 | BP38: 3.23 | BQ38: 0 | BR38: 0 | BS38: 0 | BT38: 0 | BU38: 0 | BV38: 0 | BW38: 0 | BX38: 0 | BY38: 0 | BZ38: 0 | CA38: 5.31 | CB38: CTBP | CC38: SPOR | CD38: 373.14 | CE38: 0 | CF38: 0 | CG38: 0 | CH38: 0 | CI38: 0 | CJ38: 0 | CK38: 0 | CN38: 0 | CO38: 0 | CP38: 0 | CQ38: 0 | CR38: 0 | CS38: 0 | CT38: 0 | CU38: 12 | CV38: MAPA: 161 | CW38: 0 | CY38: 49.5 | CZ38: MAPA: 161 | DA38: =CY38 -> 49.5 | DE38: 0 | DF38: A. | DG38: PR | DH38: ARAUCARIA | DI38: 9026067267 | DJ38: (41 ) 38887555 | DK38: 0 | DL38: CTB | DM38: 19.24
A39: 2 | B39: CTB070851-8 | C39: NORMAL | D39: CTBP | E39: CTB | F39: 46240 | G39: DQB8989 | H39: 41260803098929000606570010000717471003680677 | I39: 05094003000155 | J39: COLSON DO BRASIL LTDA | K39: RUA DAS PALMEIRAS 350 | L39: CAPELA VELHA | M39: 002 | N39: ARAUCARIA | O39: PR | P39: 83705-500 | Q39: 05094003000155 | R39: COLSON DO BRASIL LTDA | S39: ARAUCARIA | T39: PR | U39: 05094003000155 | V39: COLSON DO BRASIL LTDA | W39: RUA DAS PALMEIRAS 350 | X39: CAPELA VELHA | Y39: ARAUCARIA | Z39: PR | AA39: (41 ) 38887555 | AC39: 04098996000170 | AD39: ART VIVA COMUNICACAO VISUAL LTDA | AE39: 11 ABCD | AF39: SPOP | AG39: SAO CAETANO DO SUL | AH39: SP | AI39: 04098996000170 | AJ39: ART VIVA COMUNICACAO VISUAL LTDA | AK39: SAO CAETANO DO SUL | AL39: SP | AM39: SPO | AN39: 000188958 | AO39: 12.97 | AP39: 0 | AQ39: 2 | AR39: 0 | AS39: CP | AT39: LIQUIDADO | AU39: 46253 | AV39: 96 | AW39: 001-DIVERSOS | AX39: 001-DIVERSOS | AY39: 1858.04 | AZ39: COMBINADA | BA39: CO3365274 | BB39: 96 | BC39: 84.48 | BD39: 96 | BE39: 11.52 | BF39: 0.12 | BG39: 0 | BH39: 12.97 | BI39: 39.7 | BJ39: 0 | BK39: 17 | BL39: 0 | BM39: 9.76 | BN39: 2.79 | BO39: 5.5 | BP39: 3.23 | BQ39: 0 | BR39: 0 | BS39: 0 | BT39: 0 | BU39: 0 | BV39: 0 | BW39: 0 | BX39: 0 | BY39: 0 | BZ39: 0 | CA39: 6.5 | CB39: CTBP | CC39: SPOP | CD39: 376.62 | CE39: 0 | CF39: 0 | CG39: 0 | CH39: 0 | CI39: 0 | CJ39: 0 | CK39: 0 | CN39: 0 | CO39: 0 | CP39: 0 | CQ39: 0 | CR39: 0 | CS39: 0 | CT39: 0 | CU39: 12 | CV39: MAPA: 161 | CW39: 0 | CY39: 18 | CZ39: MAPA: 161 | DA39: 0 | DE39: 0 | DF39: A. | DG39: PR | DH39: ARAUCARIA | DI39: 9026067267 | DJ39: (41 ) 38887555 | DK39: 0 | DL39: CTB | DM39: 11.52
A40: 2 | B40: CTB070852-6 | C40: NORMAL | D40: CTBP | E40: CTB | F40: 46240 | G40: DQB8989 | H40: 41260803098929000606570010000717481003680682 | I40: 05094003000155 | J40: COLSON DO BRASIL LTDA | K40: RUA DAS PALMEIRAS 350 | L40: CAPELA VELHA | M40: 002 | N40: ARAUCARIA | O40: PR | P40: 83705-500 | Q40: 05094003000155 | R40: COLSON DO BRASIL LTDA | S40: ARAUCARIA | T40: PR | U40: 05094003000155 | V40: COLSON DO BRASIL LTDA | W40: RUA DAS PALMEIRAS 350 | X40: CAPELA VELHA | Y40: ARAUCARIA | Z40: PR | AA40: (41 ) 38887555 | AC40: 50971691000149 | AD40: RH MAQUINAS E EQUIPAMENTOS LTDA | AE40: NIG NOVA IGUAACU | AF40: RJOP | AG40: NOVA IGUACU | AH40: RJ | AI40: 50971691000149 | AJ40: RH MAQUINAS E EQUIPAMENTOS LTDA | AK40: NOVA IGUACU | AL40: RJ | AM40: RJO | AN40: 000188941 | AO40: 163.856 | AP40: 0.4586 | AQ40: 21 | AR40: 0 | AS40: CP | AT40: LIQUIDADO | AU40: 46253 | AV40: 243.95 | AW40: 001-DIVERSOS | AX40: 054-PNEUS E CAMARAS DE AR | AY40: 5241 | AZ40: COMBINADA | BA40: CO3365267 | BB40: 243.95 | BC40: 214.68 | BD40: 243.95 | BE40: 29.27 | BF40: 0.12 | BG40: 0 | BH40: 163.856 | BI40: 147.49 | BJ40: 0 | BK40: 17 | BL40: 0 | BM40: 9.76 | BN40: 7.86 | BO40: 11 | BP40: 3.23 | BQ40: 0 | BR40: 0 | BS40: 0 | BT40: 0 | BU40: 0 | BV40: 0 | BW40: 0 | BX40: 0 | BY40: 0 | BZ40: 0 | CA40: 18.34 | CB40: CTBP | CC40: RJOP | CD40: 418.15 | CE40: 0 | CF40: 0 | CG40: 0 | CH40: 0 | CI40: 0 | CJ40: 0 | CK40: 0 | CN40: 0 | CO40: 0 | CP40: 0 | CQ40: 0 | CR40: 0 | CS40: 0 | CT40: 0 | CU40: 24.58 | CV40: MAPA: 161 | CW40: 0 | CY40: 29.49 | CZ40: MAPA: 161 | DA40: 0 | DE40: 0 | DF40: A. | DG40: PR | DH40: ARAUCARIA | DI40: 9026067267 | DJ40: (41 ) 38887555 | DK40: 0 | DL40: CTB | DM40: 29.27
A41: 2 | B41: CTB070853-4 | C41: NORMAL | D41: CTBP | E41: CTB | F41: 46240 | G41: DQB8989 | H41: 41260803098929000606570010000717491003680698 | I41: 05094003000155 | J41: COLSON DO BRASIL LTDA | K41: RUA DAS PALMEIRAS 350 | L41: CAPELA VELHA | M41: 002 | N41: ARAUCARIA | O41: PR | P41: 83705-500 | Q41: 05094003000155 | R41: COLSON DO BRASIL LTDA | S41: ARAUCARIA | T41: PR | U41: 05094003000155 | V41: COLSON DO BRASIL LTDA | W41: RUA DAS PALMEIRAS 350 | X41: CAPELA VELHA | Y41: ARAUCARIA | Z41: PR | AA41: (41 ) 38887555 | AC41: 51459665000107 | AD41: VALE JACARAIPE ALUGUEL DE EQUIPAMENTOS LTDA | AE41: 291 | AF41: EPSP | AG41: SERRA | AH41: ES | AI41: 51459665000107 | AJ41: VALE JACARAIPE ALUGUEL DE EQUIPAMENTOS LTDA | AK41: SERRA | AL41: ES | AM41: EPS | AN41: 000189050 | AO41: 320 | AP41: 0 | AQ41: 20 | AR41: 0 | AS41: CP | AT41: LIQUIDADO | AU41: 46253 | AV41: 457.8 | AW41: 001-DIVERSOS | AX41: 001-DIVERSOS | AY41: 9428.79 | AZ41: COMBINADA | BA41: CO3365268 | BB41: 457.8 | BC41: 425.75 | BD41: 457.8 | BE41: 32.05 | BF41: 0.07 | BG41: 0 | BH41: 320 | BI41: 326.62 | BJ41: 0 | BK41: 17 | BL41: 0 | BM41: 9.76 | BN41: 14.14 | BO41: 22 | BP41: 3.23 | BQ41: 0 | BR41: 0 | BS41: 0 | BT41: 0 | BU41: 0 | BV41: 0 | BW41: 0 | BX41: 0 | BY41: 0 | BZ41: 0 | CA41: 33 | CB41: CTBP | CC41: EPSP | CD41: 772.53 | CE41: 0 | CF41: 0 | CG41: 0 | CH41: 0 | CI41: 0 | CJ41: 0 | CK41: 0 | CN41: 0 | CO41: 0 | CP41: 0 | CQ41: 0 | CR41: 0 | CS41: 0 | CT41: 0 | CU41: 48 | CV41: MAPA: 161 | CW41: 0 | CY41: 204.36 | CZ41: FATURA: 55301 | DA41: 219.74 | DB41: 055301 | DE41: 0 | DF41: A. | DG41: PR | DH41: ARAUCARIA | DI41: 9026067267 | DJ41: (41 ) 38887555 | DK41: 0 | DL41: CTB | DM41: 32.05
A42: 2 | B42: CTB070854-2 | C42: NORMAL | D42: CTBP | E42: CTB | F42: 46240 | G42: DQB8989 | H42: 41260803098929000606570010000717501003680702 | I42: 05094003000155 | J42: COLSON DO BRASIL LTDA | K42: RUA DAS PALMEIRAS 350 | L42: CAPELA VELHA | M42: 002 | N42: ARAUCARIA | O42: PR | P42: 83705-500 | Q42: 05094003000155 | R42: COLSON DO BRASIL LTDA | S42: ARAUCARIA | T42: PR | U42: 05094003000155 | V42: COLSON DO BRASIL LTDA | W42: RUA DAS PALMEIRAS 350 | X42: CAPELA VELHA | Y42: ARAUCARIA | Z42: PR | AA42: (41 ) 38887555 | AC42: 18740409000100 | AD42: TR INDUSTRIA COMERCIO E SERVICOS DE | AE42: 11 ABCD | AF42: SPOP | AG42: DIADEMA | AH42: SP | AI42: 18740409000100 | AJ42: TR INDUSTRIA COMERCIO E SERVICOS DE | AK42: DIADEMA | AL42: SP | AM42: SPO | AN42: 000189041 | AO42: 26.88 | AP42: 0 | AQ42: 3 | AR42: 0 | AS42: CP | AT42: LIQUIDADO | AU42: 46253 | AV42: 104.43 | AW42: 001-DIVERSOS | AX42: 001-DIVERSOS | AY42: 1642.29 | AZ42: COMBINADA | BA42: CO3365274 | BB42: 104.43 | BC42: 91.9 | BD42: 104.43 | BE42: 12.53 | BF42: 0.12 | BG42: 0 | BH42: 26.88 | BI42: 48.2 | BJ42: 0 | BK42: 17 | BL42: 0 | BM42: 9.76 | BN42: 2.46 | BO42: 5.5 | BP42: 3.23 | BQ42: 0 | BR42: 0 | BS42: 0 | BT42: 0 | BU42: 0 | BV42: 0 | BW42: 0 | BX42: 0 | BY42: 0 | BZ42: 0 | CA42: 5.75 | CB42: CTBP | CC42: SPOP | CD42: 374.44 | CE42: 0 | CF42: 0 | CG42: 0 | CH42: 0 | CI42: 0 | CJ42: 0 | CK42: 0 | CN42: 0 | CO42: 0 | CP42: 0 | CQ42: 0 | CR42: 0 | CS42: 0 | CT42: 0 | CU42: 12 | CV42: MAPA: 161 | CW42: 0 | CY42: 18 | CZ42: MAPA: 161 | DA42: 0 | DE42: 0 | DF42: A. | DG42: PR | DH42: ARAUCARIA | DI42: 9026067267 | DJ42: (41 ) 38887555 | DK42: 0 | DL42: CTB | DM42: 12.53
A43: 2 | B43: CTB070855-1 | C43: NORMAL | D43: CTBP | E43: CTB | F43: 46240 | G43: DQB8989 | H43: 41260803098929000606570010000717511003680718 | I43: 05094003000155 | J43: COLSON DO BRASIL LTDA | K43: RUA DAS PALMEIRAS 350 | L43: CAPELA VELHA | M43: 002 | N43: ARAUCARIA | O43: PR | P43: 83705-500 | Q43: 05094003000155 | R43: COLSON DO BRASIL LTDA | S43: ARAUCARIA | T43: PR | U43: 05094003000155 | V43: COLSON DO BRASIL LTDA | W43: RUA DAS PALMEIRAS 350 | X43: CAPELA VELHA | Y43: ARAUCARIA | Z43: PR | AA43: (41 ) 38887555 | AC43: 54477500000148 | AD43: SYNTHESIS IND COM MOBILIARIO | AE43: 124 PRES DUTRA BONSUCESSO | AF43: SPOP | AG43: GUARULHOS | AH43: SP | AI43: 54477500000148 | AJ43: SYNTHESIS IND COM MOBILIARIO | AK43: GUARULHOS | AL43: SP | AM43: SPO | AN43: 000189029 | AO43: 34 | AP43: 0 | AQ43: 2 | AR43: 0 | AS43: CP | AT43: LIQUIDADO | AU43: 46253 | AV43: 112.55 | AW43: 001-DIVERSOS | AX43: 001-DIVERSOS | AY43: 1284.39 | AZ43: COMBINADA | BA43: CO3365274 | BB43: 112.55 | BC43: 99.04 | BD43: 112.55 | BE43: 13.51 | BF43: 0.12 | BG43: 0 | BH43: 34 | BI43: 56.8 | BJ43: 0 | BK43: 17 | BL43: 0 | BM43: 9.76 | BN43: 2.25 | BO43: 5.5 | BP43: 3.23 | BQ43: 0 | BR43: 0 | BS43: 0 | BT43: 0 | BU43: 0 | BV43: 0 | BW43: 0 | BX43: 0 | BY43: 0 | BZ43: 0 | CA43: 4.5 | CB43: CTBP | CC43: SPOP | CD43: 370.84 | CE43: 0 | CF43: 0 | CG43: 0 | CH43: 0 | CI43: 0 | CJ43: 0 | CK43: 0 | CN43: 0 | CO43: 0 | CP43: 0 | CQ43: 0 | CR43: 0 | CS43: 0 | CT43: 0 | CU43: 12 | CV43: MAPA: 161 | CW43: 0 | CY43: 18 | CZ43: MAPA: 161 | DA43: 0 | DE43: 0 | DF43: A. | DG43: PR | DH43: ARAUCARIA | DI43: 9026067267 | DJ43: (41 ) 38887555 | DK43: 0 | DL43: CTB | DM43: 13.51
A44: 2 | B44: CTB070856-9 | C44: NORMAL | D44: CTBP | E44: CTB | F44: 46240 | G44: DQB8989 | H44: 41260803098929000606570010000717521003680723 | I44: 05094003000155 | J44: COLSON DO BRASIL LTDA | K44: RUA DAS PALMEIRAS 350 | L44: CAPELA VELHA | M44: 002 | N44: ARAUCARIA | O44: PR | P44: 83705-500 | Q44: 05094003000155 | R44: COLSON DO BRASIL LTDA | S44: ARAUCARIA | T44: PR | U44: 05094003000155 | V44: COLSON DO BRASIL LTDA | W44: RUA DAS PALMEIRAS 350 | X44: CAPELA VELHA | Y44: ARAUCARIA | Z44: PR | AA44: (41 ) 38887555 | AC44: 44530855000108 | AD44: NAVAS E CIA LTDA | AE44: 164 | AF44: RSOP | AG44: LINS | AH44: SP | AI44: 44530855000108 | AJ44: NAVAS E CIA LTDA | AK44: LINS | AL44: SP | AM44: RSO | AN44: 000189033 | AO44: 288.111 | AP44: 0 | AQ44: 25 | AR44: 0 | AS44: CP | AT44: LIQUIDADO | AU44: 46253 | AV44: 705.63 | AW44: 001-DIVERSOS | AX44: 054-PNEUS E CAMARAS DE AR | AY44: 11370.45 | AZ44: COMBINADA | BA44: CO3365277 | BB44: 705.63 | BC44: 620.95 | BD44: 705.63 | BE44: 84.68 | BF44: 0.12 | BG44: 0 | BH44: 288.111 | BI44: 267.6 | BJ44: 0 | BK44: 17 | BL44: 0 | BM44: 9.76 | BN44: 17.06 | BO44: 16.5 | BP44: 3.23 | BQ44: 0 | BR44: 0 | BS44: 0 | BT44: 0 | BU44: 0 | BV44: 0 | BW44: 0 | BX44: 250 | BY44: 0 | BZ44: 0 | CA44: 39.8 | CB44: CTBP | CC44: SAOI | CD44: 718.13 | CE44: 0 | CF44: 0 | CG44: 0 | CH44: 0 | CI44: 0 | CJ44: 0 | CK44: 0 | CN44: 0 | CO44: 0 | CP44: 0 | CQ44: 0 | CR44: 0 | CS44: 0 | CT44: 0 | CU44: 43.22 | CV44: MAPA: 161 | CW44: 0 | CY44: 470.77 | CZ44: MAPA: 0 | DA44: 247.83 | DE44: 0 | DF44: A. | DG44: PR | DH44: ARAUCARIA | DI44: 9026067267 | DJ44: (41 ) 38887555 | DK44: 0 | DL44: CTB | DM44: 84.68
A45: 2 | B45: CTB070857-7 | C45: NORMAL | D45: CTBP | E45: CTB | F45: 46240 | G45: DQB8989 | H45: 41260803098929000606570010000717531003680739 | I45: 05094003000155 | J45: COLSON DO BRASIL LTDA | K45: RUA DAS PALMEIRAS 350 | L45: CAPELA VELHA | M45: 002 | N45: ARAUCARIA | O45: PR | P45: 83705-500 | Q45: 05094003000155 | R45: COLSON DO BRASIL LTDA | S45: ARAUCARIA | T45: PR | U45: 05094003000155 | V45: COLSON DO BRASIL LTDA | W45: RUA DAS PALMEIRAS 350 | X45: CAPELA VELHA | Y45: ARAUCARIA | Z45: PR | AA45: (41 ) 38887555 | AC45: 26208767000102 | AD45: ARN WORLD COMERCIO DE MATERIAL | AE45: ITB ITABORAI | AF45: FRJP | AG45: ITABORAI | AH45: RJ | AI45: 26208767000102 | AJ45: ARN WORLD COMERCIO DE MATERIAL | AK45: ITABORAI | AL45: RJ | AM45: FRJ | AN45: 000188980 | AO45: 937.882 | AP45: 0 | AQ45: 81 | AR45: 0 | AS45: CP | AT45: LIQUIDADO | AU45: 46253 | AV45: 1214.45 | AW45: 001-DIVERSOS | AX45: 054-PNEUS E CAMARAS DE AR | AY45: 27907.91 | AZ45: COMBINADA | BA45: CO3365267 | BB45: 1214.45 | BC45: 1068.72 | BD45: 1214.45 | BE45: 145.73 | BF45: 0.12 | BG45: 0 | BH45: 937.882 | BI45: 844.19 | BJ45: 0 | BK45: 17 | BL45: 0 | BM45: 9.76 | BN45: 41.86 | BO45: 55 | BP45: 3.23 | BQ45: 0 | BR45: 0 | BS45: 0 | BT45: 0 | BU45: 0 | BV45: 0 | BW45: 0 | BX45: 0 | BY45: 0 | BZ45: 0 | CA45: 97.68 | CB45: CTBP | CC45: RJOP | CD45: 2557.28 | CE45: 0 | CF45: 0 | CG45: 0 | CH45: 0 | CI45: 0 | CJ45: 0 | CK45: 0 | CN45: 0 | CO45: 0 | CP45: 0 | CQ45: 0 | CR45: 0 | CS45: 0 | CT45: 0 | CU45: 140.68 | CV45: MAPA: 161 | CW45: 0 | CY45: 426.91 | CZ45: FATURA: 14347 | DA45: 438.28 | DB45: 014347 | DE45: 0 | DF45: A. | DG45: PR | DH45: ARAUCARIA | DI45: 9026067267 | DJ45: (41 ) 38887555 | DK45: 0 | DL45: CTB | DM45: 145.73
A46: 2 | B46: CTB070929-8 | C46: NORMAL | D46: CTBP | E46: CTB | F46: 46241 | G46: DQB8989 | H46: 41260803098929000606570010000718251003687653 | I46: 05094003000155 | J46: COLSON DO BRASIL LTDA | K46: RUA DAS PALMEIRAS 350 | L46: CAPELA VELHA | M46: 002 | N46: ARAUCARIA | O46: PR | P46: 83705-500 | Q46: 05094003000155 | R46: COLSON DO BRASIL LTDA | S46: ARAUCARIA | T46: PR | U46: 05094003000155 | V46: COLSON DO BRASIL LTDA | W46: RUA DAS PALMEIRAS 350 | X46: CAPELA VELHA | Y46: ARAUCARIA | Z46: PR | AA46: (41 ) 38887555 | AC46: 10624576000183 | AD46: MERCADAO DOS PARAFUSOS LTDA | AE46: 387 | AF46: TRUR | AG46: PATROCINIO | AH46: MG | AI46: 10624576000183 | AJ46: MERCADAO DOS PARAFUSOS LTDA | AK46: PATROCINIO | AL46: MG | AM46: TRU | AN46: 000189110 | AO46: 281.765 | AP46: 0 | AQ46: 35 | AR46: 0 | AS46: CP | AT46: LIQUIDADO | AU46: 46253 | AV46: 778.44 | AW46: 001-DIVERSOS | AX46: 001-DIVERSOS | AY46: 10065.1 | AZ46: COMBINADA | BA46: CO3365284 | BB46: 778.44 | BC46: 685.03 | BD46: 778.44 | BE46: 93.41 | BF46: 0.12 | BG46: 0 | BH46: 281.765 | BI46: 338.21 | BJ46: 0 | BK46: 17 | BL46: 0 | BM46: 9.76 | BN46: 15.1 | BO46: 16.5 | BP46: 3.23 | BQ46: 0 | BR46: 0 | BS46: 0 | BT46: 0 | BU46: 0 | BV46: 0 | BW46: 0 | BX46: 250 | BY46: 0 | BZ46: 0 | CA46: 35.23 | CB46: CTBP | CC46: PANI | CD46: 767.01 | CE46: 0 | CF46: 0 | CG46: 0 | CH46: 0 | CI46: 0 | CJ46: 0 | CK46: 0 | CN46: 0 | CO46: 0 | CP46: 0 | CQ46: 0 | CR46: 0 | CS46: 0 | CT46: 0 | CU46: 42.26 | CV46: MAPA: 161 | CW46: 0 | CY46: 471.38 | CZ46: FATURA: 232784 | DA46: 329.85 | DB46: 232784 | DE46: 0 | DF46: A. | DG46: PR | DH46: ARAUCARIA | DI46: 9026067267 | DJ46: (41 ) 38887555 | DK46: 0 | DL46: CTB | DM46: 93.41
A47: 2 | B47: CTB070930-1 | C47: NORMAL | D47: CTBP | E47: CTB | F47: 46241 | G47: DQB8989 | H47: 41260803098929000606570010000718241003687648 | I47: 05094003000155 | J47: COLSON DO BRASIL LTDA | K47: RUA DAS PALMEIRAS 350 | L47: CAPELA VELHA | M47: 002 | N47: ARAUCARIA | O47: PR | P47: 83705-500 | Q47: 05094003000155 | R47: COLSON DO BRASIL LTDA | S47: ARAUCARIA | T47: PR | U47: 05094003000155 | V47: COLSON DO BRASIL LTDA | W47: RUA DAS PALMEIRAS 350 | X47: CAPELA VELHA | Y47: ARAUCARIA | Z47: PR | AA47: (41 ) 38887555 | AC47: 11136813000120 | AD47: MEC FIX COMERCIO DE PARAFUSOS E ELEMENTOS DE FIXACAO LTDA - | AE47: RIO RIO DE JANEIRO | AF47: RJOP | AG47: RIO DE JANEIRO | AH47: RJ | AI47: 11136813000120 | AJ47: MEC FIX COMERCIO DE PARAFUSOS E ELEMENTOS DE FIXACAO LTDA - | AK47: RIO DE JANEIRO | AL47: RJ | AM47: RJO | AN47: 000189072 | AO47: 311.35 | AP47: 0 | AQ47: 28 | AR47: 0 | AS47: CP | AT47: LIQUIDADO | AU47: 46253 | AV47: 426.83 | AW47: 001-DIVERSOS | AX47: 001-DIVERSOS | AY47: 8674.44 | AZ47: COMBINADA | BA47: CO3365267 | BB47: 426.83 | BC47: 375.61 | BD47: 426.83 | BE47: 51.22 | BF47: 0.12 | BG47: 0 | BH47: 311.35 | BI47: 280.25 | BJ47: 0 | BK47: 17 | BL47: 0 | BM47: 9.76 | BN47: 13.01 | BO47: 22 | BP47: 3.23 | BQ47: 0 | BR47: 0 | BS47: 0 | BT47: 0 | BU47: 0 | BV47: 0 | BW47: 0 | BX47: 0 | BY47: 0 | BZ47: 0 | CA47: 30.36 | CB47: CTBP | CC47: RJOP | CD47: 852.47 | CE47: 0 | CF47: 0 | CG47: 0 | CH47: 0 | CI47: 0 | CJ47: 0 | CK47: 0 | CN47: 0 | CO47: 0 | CP47: 0 | CQ47: 0 | CR47: 0 | CS47: 0 | CT47: 0 | CU47: 46.7 | CV47: MAPA: 161 | CW47: 0 | CY47: 56.04 | CZ47: MAPA: 161 | DA47: 0 | DE47: 0 | DF47: A. | DG47: PR | DH47: ARAUCARIA | DI47: 9026067267 | DJ47: (41 ) 38887555 | DK47: 0 | DL47: CTB | DM47: 51.22
A48: 2 | B48: CTB070931-0 | C48: NORMAL | D48: CTBP | E48: CTB | F48: 46241 | G48: DQB8989 | H48: 41260803098929000606570010000718271003687674 | I48: 05094003000155 | J48: COLSON DO BRASIL LTDA | K48: RUA DAS PALMEIRAS 350 | L48: CAPELA VELHA | M48: 002 | N48: ARAUCARIA | O48: PR | P48: 83705-500 | Q48: 05094003000155 | R48: COLSON DO BRASIL LTDA | S48: ARAUCARIA | T48: PR | U48: 05094003000155 | V48: COLSON DO BRASIL LTDA | W48: RUA DAS PALMEIRAS 350 | X48: CAPELA VELHA | Y48: ARAUCARIA | Z48: PR | AA48: (41 ) 38887555 | AC48: 23476033001260 | AD48: BMB MATERIAL DE CONSTRUCAO S.A. | AE48: 09 GR2 | AF48: SPOP | AG48: SUZANO | AH48: SP | AI48: 23476033001260 | AJ48: BMB MATERIAL DE CONSTRUCAO S.A. | AK48: SUZANO | AL48: SP | AM48: SPO | AN48: 000188134 | AO48: 75.21 | AP48: 0 | AQ48: 6 | AR48: 0 | AS48: CP | AT48: LIQUIDADO | AU48: 46253 | AV48: 450.93 | AW48: 001-DIVERSOS | AX48: 001-DIVERSOS | AY48: 2285.34 | AZ48: COMBINADA | BA48: CO3365274 | BB48: 450.93 | BC48: 396.82 | BD48: 450.93 | BE48: 54.11 | BF48: 0.12 | BG48: 0 | BH48: 75.21 | BI48: 99.9 | BJ48: 0 | BK48: 17 | BL48: 0 | BM48: 9.76 | BN48: 3.43 | BO48: 5.5 | BP48: 3.23 | BQ48: 0 | BR48: 0 | BS48: 0 | BT48: 0 | BU48: 0 | BV48: 0 | BW48: 0 | BX48: 250 | BY48: 0 | BZ48: 0 | CA48: 8 | CB48: CTBP | CC48: SPOP | CD48: 380.85 | CE48: 0 | CF48: 0 | CG48: 0 | CH48: 0 | CI48: 0 | CJ48: 0 | CK48: 0 | CN48: 0 | CO48: 0 | CP48: 0 | CQ48: 0 | CR48: 0 | CS48: 0 | CT48: 0 | CU48: 12 | CV48: MAPA: 161 | CW48: 0 | CY48: 18 | CZ48: MAPA: 161 | DA48: 0 | DE48: 0 | DF48: A. | DG48: PR | DH48: ARAUCARIA | DI48: 9026067267 | DJ48: (41 ) 38887555 | DK48: 0 | DL48: CTB | DM48: 54.11
A49: 2 | B49: CTB070932-8 | C49: NORMAL | D49: CTBP | E49: CTB | F49: 46241 | G49: DQB8989 | H49: 41260803098929000606570010000718261003687669 | I49: 05094003000155 | J49: COLSON DO BRASIL LTDA | K49: RUA DAS PALMEIRAS 350 | L49: CAPELA VELHA | M49: 002 | N49: ARAUCARIA | O49: PR | P49: 83705-500 | Q49: 05094003000155 | R49: COLSON DO BRASIL LTDA | S49: ARAUCARIA | T49: PR | U49: 05094003000155 | V49: COLSON DO BRASIL LTDA | W49: RUA DAS PALMEIRAS 350 | X49: CAPELA VELHA | Y49: ARAUCARIA | Z49: PR | AA49: (41 ) 38887555 | AC49: 23476033000370 | AD49: BMB MATERIAL DE CONSTRUCAO SA | AE49: 117 | AF49: SVPR | AG49: PRAIA GRANDE | AH49: SP | AI49: 23476033000370 | AJ49: BMB MATERIAL DE CONSTRUCAO SA | AK49: PRAIA GRANDE | AL49: SP | AM49: SVP | AN49: 000188177 | AO49: 35.05 | AP49: 0 | AQ49: 4 | AR49: 0 | AS49: CP | AT49: LIQUIDADO | AU49: 46253 | AV49: 397.08 | AW49: 001-DIVERSOS | AX49: 054-PNEUS E CAMARAS DE AR | AY49: 1396.82 | AZ49: COMBINADA | BA49: CO3365274 | BB49: 397.08 | BC49: 349.43 | BD49: 397.08 | BE49: 47.65 | BF49: 0.12 | BG49: 0 | BH49: 35.05 | BI49: 56.8 | BJ49: 0 | BK49: 17 | BL49: 0 | BM49: 9.76 | BN49: 2.25 | BO49: 5.5 | BP49: 3.23 | BQ49: 0 | BR49: 0 | BS49: 0 | BT49: 0 | BU49: 0 | BV49: 0 | BW49: 0 | BX49: 250 | BY49: 0 | BZ49: 0 | CA49: 4.89 | CB49: CTBP | CC49: SPOP | CD49: 371.97 | CE49: 0 | CF49: 0 | CG49: 0 | CH49: 0 | CI49: 0 | CJ49: 0 | CK49: 0 | CN49: 0 | CO49: 0 | CP49: 0 | CQ49: 0 | CR49: 0 | CS49: 0 | CT49: 0 | CU49: 12 | CV49: MAPA: 161 | CW49: 0 | CY49: 302.1 | CZ49: FATURA: 612 | DA49: 519 | DB49: 000612 | DE49: 0 | DF49: A. | DG49: PR | DH49: ARAUCARIA | DI49: 9026067267 | DJ49: (41 ) 38887555 | DK49: 0 | DL49: CTB | DM49: 47.65
A50: 2 | B50: CTB070933-6 | C50: NORMAL | D50: CTBP | E50: CTB | F50: 46241 | G50: DQB8989 | H50: 41260803098929000606570010000718291003687695 | I50: 05094003000155 | J50: COLSON DO BRASIL LTDA | K50: RUA DAS PALMEIRAS 350 | L50: CAPELA VELHA | M50: 002 | N50: ARAUCARIA | O50: PR | P50: 83705-500 | Q50: 05094003000155 | R50: COLSON DO BRASIL LTDA | S50: ARAUCARIA | T50: PR | U50: 05094003000155 | V50: COLSON DO BRASIL LTDA | W50: RUA DAS PALMEIRAS 350 | X50: CAPELA VELHA | Y50: ARAUCARIA | Z50: PR | AA50: (41 ) 38887555 | AC50: 05095185000260 | AD50: BIGNOTTO FERRAMENTAS LTDA | AE50: 133 | AF50: PSPP | AG50: NOVA ODESSA | AH50: SP | AI50: 05095185000260 | AJ50: BIGNOTTO FERRAMENTAS LTDA | AK50: NOVA ODESSA | AL50: SP | AM50: PSP | AN50: 000189067 | AO50: 59.91 | AP50: 0 | AQ50: 6 | AR50: 0 | AS50: CP | AT50: LIQUIDADO | AU50: 46253 | AV50: 166.92 | AW50: 001-DIVERSOS | AX50: 054-PNEUS E CAMARAS DE AR | AY50: 1860.49 | AZ50: COMBINADA | BA50: CO3365277 | BB50: 166.92 | BC50: 146.89 | BD50: 166.92 | BE50: 20.03 | BF50: 0.12 | BG50: 0 | BH50: 59.91 | BI50: 102.1 | BJ50: 0 | BK50: 17 | BL50: 0 | BM50: 9.76 | BN50: 2.79 | BO50: 5.5 | BP50: 3.23 | BQ50: 0 | BR50: 0 | BS50: 0 | BT50: 0 | BU50: 0 | BV50: 0 | BW50: 0 | BX50: 0 | BY50: 0 | BZ50: 0 | CA50: 6.51 | CB50: CTBP | CC50: SAOI | CD50: 376.62 | CE50: 0 | CF50: 0 | CG50: 0 | CH50: 0 | CI50: 0 | CJ50: 0 | CK50: 0 | CN50: 0 | CO50: 0 | CP50: 0 | CQ50: 0 | CR50: 0 | CS50: 0 | CT50: 0 | CU50: 12 | CV50: MAPA: 161 | CW50: 0 | CY50: 60.5 | CZ50: MAPA: 161 | DA50: =CY50 -> 60.5 | DE50: 0 | DF50: A. | DG50: PR | DH50: ARAUCARIA | DI50: 9026067267 | DJ50: (41 ) 38887555 | DK50: 0 | DL50: CTB | DM50: 20.03
A51: 2 | B51: CTB070934-4 | C51: NORMAL | D51: CTBP | E51: CTB | F51: 46241 | G51: DQB8989 | H51: 41260803098929000606570010000718281003687680 | I51: 05094003000155 | J51: COLSON DO BRASIL LTDA | K51: RUA DAS PALMEIRAS 350 | L51: CAPELA VELHA | M51: 002 | N51: ARAUCARIA | O51: PR | P51: 83705-500 | Q51: 05094003000155 | R51: COLSON DO BRASIL LTDA | S51: ARAUCARIA | T51: PR | U51: 05094003000155 | V51: COLSON DO BRASIL LTDA | W51: RUA DAS PALMEIRAS 350 | X51: CAPELA VELHA | Y51: ARAUCARIA | Z51: PR | AA51: (41 ) 38887555 | AC51: 10678319000124 | AD51: G R VIEIRA FERRAGENS | AE51: 150 | AF51: NSLP | AG51: SAO JOSE DO RIO PRETO | AH51: SP | AI51: 10678319000124 | AJ51: G R VIEIRA FERRAGENS | AK51: SAO JOSE DO RIO PRETO | AL51: SP | AM51: NSL | AN51: 000189108 | AO51: 80 | AP51: 0 | AQ51: 2 | AR51: 0 | AS51: CP | AT51: LIQUIDADO | AU51: 46253 | AV51: 207.67 | AW51: 001-DIVERSOS | AX51: 001-DIVERSOS | AY51: 2632.1 | AZ51: COMBINADA | BA51: CO3365277 | BB51: 207.67 | BC51: 182.75 | BD51: 207.67 | BE51: 24.92 | BF51: 0.12 | BG51: 0 | BH51: 80 | BI51: 134.1 | BJ51: 0 | BK51: 17 | BL51: 0 | BM51: 9.76 | BN51: 3.95 | BO51: 5.5 | BP51: 3.23 | BQ51: 0 | BR51: 0 | BS51: 0 | BT51: 0 | BU51: 0 | BV51: 0 | BW51: 0 | BX51: 0 | BY51: 0 | BZ51: 0 | CA51: 9.21 | CB51: CTBP | CC51: SAOI | CD51: 384.29 | CE51: 0 | CF51: 0 | CG51: 0 | CH51: 0 | CI51: 0 | CJ51: 0 | CK51: 0 | CN51: 0 | CO51: 0 | CP51: 0 | CQ51: 0 | CR51: 0 | CS51: 0 | CT51: 0 | CU51: 12 | CV51: MAPA: 161 | CW51: 0 | CY51: 67.3 | CZ51: FATURA: 160426 | DA51: 94.43 | DB51: 160426 | DE51: 0 | DF51: A. | DG51: PR | DH51: ARAUCARIA | DI51: 9026067267 | DJ51: (41 ) 38887555 | DK51: 0 | DL51: CTB | DM51: 24.92
A52: 2 | B52: CTB070935-2 | C52: NORMAL | D52: CTBP | E52: CTB | F52: 46241 | G52: DQB8989 | H52: 41260803098929000606570010000718311003687715 | I52: 05094003000155 | J52: COLSON DO BRASIL LTDA | K52: RUA DAS PALMEIRAS 350 | L52: CAPELA VELHA | M52: 002 | N52: ARAUCARIA | O52: PR | P52: 83705-500 | Q52: 05094003000155 | R52: COLSON DO BRASIL LTDA | S52: ARAUCARIA | T52: PR | U52: 05094003000155 | V52: COLSON DO BRASIL LTDA | W52: RUA DAS PALMEIRAS 350 | X52: CAPELA VELHA | Y52: ARAUCARIA | Z52: PR | AA52: (41 ) 38887555 | AC52: 42970699000162 | AD52: GG FERRAGENS COLONIAIS LTDA ME | AE52: 394 | AF52: VEAI | AG52: MONTES CLAROS | AH52: MG | AI52: 42970699000162 | AJ52: GG FERRAGENS COLONIAIS LTDA ME | AK52: MONTES CLAROS | AL52: MG | AM52: VEA | AN52: 000189116 | AO52: 89.32 | AP52: 0 | AQ52: 13 | AR52: 0 | AS52: CP | AT52: LIQUIDADO | AU52: 46253 | AV52: 252.52 | AW52: 001-DIVERSOS | AX52: 001-DIVERSOS | AY52: 2704.86 | AZ52: COMBINADA | BA52: CO3365300 | BB52: 252.52 | BC52: 222.22 | BD52: 252.52 | BE52: 30.3 | BF52: 0.12 | BG52: 0 | BH52: 89.32 | BI52: 173.2 | BJ52: 0 | BK52: 17 | BL52: 0 | BM52: 9.76 | BN52: 4.06 | BO52: 5.5 | BP52: 3.23 | BQ52: 0 | BR52: 0 | BS52: 0 | BT52: 0 | BU52: 0 | BV52: 0 | BW52: 0 | BX52: 0 | BY52: 0 | BZ52: 0 | CA52: 9.47 | CB52: CTBP | CC52: VEAI | CD52: 385.17 | CE52: 0 | CF52: 0 | CG52: 0 | CH52: 0 | CI52: 0 | CJ52: 0 | CK52: 0 | CN52: 0 | CO52: 0 | CP52: 0 | CQ52: 0 | CR52: 0 | CS52: 0 | CT52: 0 | CU52: 13.4 | CV52: MAPA: 161 | CW52: 0 | CY52: 75.76 | CZ52: MAPA: 0 | DA52: =CY52 -> 75.76 | DE52: 0 | DF52: A. | DG52: PR | DH52: ARAUCARIA | DI52: 9026067267 | DJ52: (41 ) 38887555 | DK52: 0 | DL52: CTB | DM52: 30.3
A53: 2 | B53: CTB070936-1 | C53: NORMAL | D53: CTBP | E53: CTB | F53: 46241 | G53: DQB8989 | H53: 41260803098929000606570010000718301003687700 | I53: 05094003000155 | J53: COLSON DO BRASIL LTDA | K53: RUA DAS PALMEIRAS 350 | L53: CAPELA VELHA | M53: 002 | N53: ARAUCARIA | O53: PR | P53: 83705-500 | Q53: 05094003000155 | R53: COLSON DO BRASIL LTDA | S53: ARAUCARIA | T53: PR | U53: 05094003000155 | V53: COLSON DO BRASIL LTDA | W53: RUA DAS PALMEIRAS 350 | X53: CAPELA VELHA | Y53: ARAUCARIA | Z53: PR | AA53: (41 ) 38887555 | AC53: 23072909000150 | AD53: MJ COMERCIAL ELETRICA LTDA | AE53: 11 ABCD | AF53: SPOP | AG53: SAO BERNARDO DO CAMPO | AH53: SP | AI53: 23072909000150 | AJ53: MJ COMERCIAL ELETRICA LTDA | AK53: SAO BERNARDO DO CAMPO | AL53: SP | AM53: SPO | AN53: 000189070 | AO53: 23.4 | AP53: 0 | AQ53: 3 | AR53: 0 | AS53: CP | AT53: LIQUIDADO | AU53: 46253 | AV53: 103.27 | AW53: 001-DIVERSOS | AX53: 001-DIVERSOS | AY53: 1412.09 | AZ53: COMBINADA | BA53: CO3365274 | BB53: 103.27 | BC53: 90.88 | BD53: 103.27 | BE53: 12.39 | BF53: 0.12 | BG53: 0 | BH53: 23.4 | BI53: 48.2 | BJ53: 0 | BK53: 17 | BL53: 0 | BM53: 9.76 | BN53: 2.25 | BO53: 5.5 | BP53: 3.23 | BQ53: 0 | BR53: 0 | BS53: 0 | BT53: 0 | BU53: 0 | BV53: 0 | BW53: 0 | BX53: 0 | BY53: 0 | BZ53: 0 | CA53: 4.94 | CB53: CTBP | CC53: SPOP | CD53: 372.14 | CE53: 0 | CF53: 0 | CG53: 0 | CH53: 0 | CI53: 0 | CJ53: 0 | CK53: 0 | CN53: 0 | CO53: 0 | CP53: 0 | CQ53: 0 | CR53: 0 | CS53: 0 | CT53: 0 | CU53: 12 | CV53: MAPA: 161 | CW53: 0 | CY53: 18 | CZ53: MAPA: 161 | DA53: 0 | DE53: 0 | DF53: A. | DG53: PR | DH53: ARAUCARIA | DI53: 9026067267 | DJ53: (41 ) 38887555 | DK53: 0 | DL53: CTB | DM53: 12.39
A54: 2 | B54: CTB070937-9 | C54: NORMAL | D54: CTBP | E54: CTB | F54: 46241 | G54: DQB8989 | H54: 41260803098929000606570010000718321003687720 | I54: 05094003000155 | J54: COLSON DO BRASIL LTDA | K54: RUA DAS PALMEIRAS 350 | L54: CAPELA VELHA | M54: 002 | N54: ARAUCARIA | O54: PR | P54: 83705-500 | Q54: 05094003000155 | R54: COLSON DO BRASIL LTDA | S54: ARAUCARIA | T54: PR | U54: 05094003000155 | V54: COLSON DO BRASIL LTDA | W54: RUA DAS PALMEIRAS 350 | X54: CAPELA VELHA | Y54: ARAUCARIA | Z54: PR | AA54: (41 ) 38887555 | AC54: 07390159000109 | AD54: NK TECH INDUSTRIA E COMERCIO DE ARTEFATOS DE INOX LTDA ME | AE54: 11 ABCD | AF54: SPOP | AG54: SAO BERNARDO DO CAMPO | AH54: SP | AI54: 07390159000109 | AJ54: NK TECH INDUSTRIA E COMERCIO DE ARTEFATOS DE INOX LTDA ME | AK54: SAO BERNARDO DO CAMPO | AL54: SP | AM54: SPO | AN54: 000189077 | AO54: 14.81 | AP54: 0 | AQ54: 1 | AR54: 0 | AS54: CP | AT54: LIQUIDADO | AU54: 46253 | AV54: 381.63 | AW54: 001-DIVERSOS | AX54: 001-DIVERSOS | AY54: 2127.43 | AZ54: COMBINADA | BA54: CO3365274 | BB54: 381.63 | BC54: 335.83 | BD54: 381.63 | BE54: 45.8 | BF54: 0.12 | BG54: 0 | BH54: 14.81 | BI54: 39.7 | BJ54: 0 | BK54: 17 | BL54: 0 | BM54: 9.76 | BN54: 3.19 | BO54: 5.5 | BP54: 3.23 | BQ54: 0 | BR54: 0 | BS54: 0 | BT54: 0 | BU54: 0 | BV54: 0 | BW54: 0 | BX54: 250 | BY54: 0 | BZ54: 0 | CA54: 7.45 | CB54: CTBP | CC54: SPOP | CD54: 379.28 | CE54: 0 | CF54: 0 | CG54: 0 | CH54: 0 | CI54: 0 | CJ54: 0 | CK54: 0 | CN54: 0 | CO54: 0 | CP54: 0 | CQ54: 0 | CR54: 0 | CS54: 0 | CT54: 0 | CU54: 12 | CV54: MAPA: 161 | CW54: 0 | CY54: 18 | CZ54: MAPA: 161 | DA54: 0 | DE54: 0 | DF54: A. | DG54: PR | DH54: ARAUCARIA | DI54: 9026067267 | DJ54: (41 ) 38887555 | DK54: 0 | DL54: CTB | DM54: 45.8
A55: 2 | B55: CTB070938-7 | C55: NORMAL | D55: CTBP | E55: CTB | F55: 46241 | G55: DQB8989 | H55: 41260803098929000606570010000718331003687736 | I55: 05094003000155 | J55: COLSON DO BRASIL LTDA | K55: RUA DAS PALMEIRAS 350 | L55: CAPELA VELHA | M55: 002 | N55: ARAUCARIA | O55: PR | P55: 83705-500 | Q55: 05094003000155 | R55: COLSON DO BRASIL LTDA | S55: ARAUCARIA | T55: PR | U55: 05094003000155 | V55: COLSON DO BRASIL LTDA | W55: RUA DAS PALMEIRAS 350 | X55: CAPELA VELHA | Y55: ARAUCARIA | Z55: PR | AA55: (41 ) 38887555 | AC55: 53293358000116 | AD55: VERTICE INDUSTRIA COMERCIO E SERVIC | AE55: 11 ABCD | AF55: SPOP | AG55: SAO BERNARDO DO CAMPO | AH55: SP | AI55: 53293358000116 | AJ55: VERTICE INDUSTRIA COMERCIO E SERVIC | AK55: SAO BERNARDO DO CAMPO | AL55: SP | AM55: SPO | AN55: 000189064 | AO55: 39.5 | AP55: 0 | AQ55: 6 | AR55: 0 | AS55: CP | AT55: LIQUIDADO | AU55: 46253 | AV55: 113.61 | AW55: 001-DIVERSOS | AX55: 001-DIVERSOS | AY55: 1537.29 | AZ55: COMBINADA | BA55: CO3365274 | BB55: 113.61 | BC55: 99.98 | BD55: 113.61 | BE55: 13.63 | BF55: 0.12 | BG55: 0 | BH55: 39.5 | BI55: 56.8 | BJ55: 0 | BK55: 17 | BL55: 0 | BM55: 9.76 | BN55: 2.31 | BO55: 5.5 | BP55: 3.23 | BQ55: 0 | BR55: 0 | BS55: 0 | BT55: 0 | BU55: 0 | BV55: 0 | BW55: 0 | BX55: 0 | BY55: 0 | BZ55: 0 | CA55: 5.38 | CB55: CTBP | CC55: SPOP | CD55: 373.35 | CE55: 0 | CF55: 0 | CG55: 0 | CH55: 0 | CI55: 0 | CJ55: 0 | CK55: 0 | CN55: 0 | CO55: 0 | CP55: 0 | CQ55: 0 | CR55: 0 | CS55: 0 | CT55: 0 | CU55: 12 | CV55: MAPA: 161 | CW55: 0 | CY55: 18 | CZ55: MAPA: 161 | DA55: 0 | DE55: 0 | DF55: A. | DG55: PR | DH55: ARAUCARIA | DI55: 9026067267 | DJ55: (41 ) 38887555 | DK55: 0 | DL55: CTB | DM55: 13.63
A56: 2 | B56: CTB071005-9 | C56: NORMAL | D56: CTBP | E56: CTB | F56: 46244 | G56: DQB8989 | H56: 41260803098929000606570010000719001003695644 | I56: 05094003000155 | J56: COLSON DO BRASIL LTDA | K56: RUA DAS PALMEIRAS 350 | L56: CAPELA VELHA | M56: 002 | N56: ARAUCARIA | O56: PR | P56: 83705-500 | Q56: 05094003000155 | R56: COLSON DO BRASIL LTDA | S56: ARAUCARIA | T56: PR | U56: 05094003000155 | V56: COLSON DO BRASIL LTDA | W56: RUA DAS PALMEIRAS 350 | X56: CAPELA VELHA | Y56: ARAUCARIA | Z56: PR | AA56: (41 ) 38887555 | AC56: 03138265000149 | AD56: LAB DO ALCANTARA A CASA DOS MA | AE56: SGN SAO GONACALO | AF56: RJOP | AG56: SAO GONCALO | AH56: RJ | AI56: 03138265000149 | AJ56: LAB DO ALCANTARA A CASA DOS MA | AK56: SAO GONCALO | AL56: RJ | AM56: RJO | AN56: 000189166 | AO56: 131.9 | AP56: 0 | AQ56: 16 | AR56: 0 | AS56: CP | AT56: LIQUIDADO | AU56: 46260 | AV56: 202.18 | AW56: 001-DIVERSOS | AX56: 001-DIVERSOS | AY56: 3643.03 | AZ56: COMBINADA | BA56: CO3365267 | BB56: 202.18 | BC56: 177.92 | BD56: 202.18 | BE56: 24.26 | BF56: 0.12 | BG56: 0 | BH56: 131.9 | BI56: 118.72 | BJ56: 0 | BK56: 17 | BL56: 0 | BM56: 9.76 | BN56: 5.46 | BO56: 11 | BP56: 3.23 | BQ56: 0 | BR56: 0 | BS56: 0 | BT56: 0 | BU56: 0 | BV56: 0 | BW56: 0 | BX56: 0 | BY56: 0 | BZ56: 0 | CA56: 12.75 | CB56: CTBP | CC56: RJOP | CD56: 397.37 | CE56: 0 | CF56: 0 | CG56: 0 | CH56: 0 | CI56: 0 | CJ56: 0 | CK56: 0 | CN56: 0 | CO56: 0 | CP56: 0 | CQ56: 0 | CR56: 0 | CS56: 0 | CT56: 0 | CU56: 19.79 | CV56: MAPA: 161 | CW56: 0 | CY56: 23.74 | CZ56: MAPA: 161 | DA56: 0 | DE56: 0 | DF56: A. | DG56: PR | DH56: ARAUCARIA | DI56: 9026067267 | DJ56: (41 ) 38887555 | DK56: 0 | DL56: CTB | DM56: 24.26
A57: 2 | B57: CTB071006-7 | C57: NORMAL | D57: CTBP | E57: CTB | F57: 46244 | G57: DQB8989 | H57: 41260803098929000606570010000719011003695650 | I57: 05094003000155 | J57: COLSON DO BRASIL LTDA | K57: RUA DAS PALMEIRAS 350 | L57: CAPELA VELHA | M57: 002 | N57: ARAUCARIA | O57: PR | P57: 83705-500 | Q57: 05094003000155 | R57: COLSON DO BRASIL LTDA | S57: ARAUCARIA | T57: PR | U57: 05094003000155 | V57: COLSON DO BRASIL LTDA | W57: RUA DAS PALMEIRAS 350 | X57: CAPELA VELHA | Y57: ARAUCARIA | Z57: PR | AA57: (41 ) 38887555 | AC57: 41430637000103 | AD57: FRS COMERCIO DE MOVEIS COMERCIAIS LTDA | AE57: RIO RIO DE JANEIRO | AF57: RJOP | AG57: RIO DE JANEIRO | AH57: RJ | AI57: 41430637000103 | AJ57: FRS COMERCIO DE MOVEIS COMERCIAIS LTDA | AK57: RIO DE JANEIRO | AL57: RJ | AM57: RJO | AN57: 000189131 | AO57: 146.45 | AP57: 0 | AQ57: 14 | AR57: 0 | AS57: CP | AT57: LIQUIDADO | AU57: 46260 | AV57: 223.57 | AW57: 001-DIVERSOS | AX57: 001-DIVERSOS | AY57: 4786.75 | AZ57: COMBINADA | BA57: CO3365267 | BB57: 223.57 | BC57: 196.74 | BD57: 223.57 | BE57: 26.83 | BF57: 0.12 | BG57: 0 | BH57: 146.45 | BI57: 131.82 | BJ57: 0 | BK57: 17 | BL57: 0 | BM57: 9.76 | BN57: 7.18 | BO57: 11 | BP57: 3.23 | BQ57: 0 | BR57: 0 | BS57: 0 | BT57: 0 | BU57: 0 | BV57: 0 | BW57: 0 | BX57: 0 | BY57: 0 | BZ57: 0 | CA57: 16.75 | CB57: CTBP | CC57: RJOP | CD57: 412.26 | CE57: 0 | CF57: 0 | CG57: 0 | CH57: 0 | CI57: 0 | CJ57: 0 | CK57: 0 | CN57: 0 | CO57: 0 | CP57: 0 | CQ57: 0 | CR57: 0 | CS57: 0 | CT57: 0 | CU57: 21.97 | CV57: MAPA: 161 | CW57: 0 | CY57: 26.36 | CZ57: MAPA: 161 | DA57: 0 | DE57: 0 | DF57: A. | DG57: PR | DH57: ARAUCARIA | DI57: 9026067267 | DJ57: (41 ) 38887555 | DK57: 0 | DL57: CTB | DM57: 26.83
A58: 2 | B58: CTB071007-5 | C58: NORMAL | D58: CTBP | E58: CTB | F58: 46244 | G58: DQB8989 | H58: 41260803098929000606570010000719021003695665 | I58: 05094003000155 | J58: COLSON DO BRASIL LTDA | K58: RUA DAS PALMEIRAS 350 | L58: CAPELA VELHA | M58: 002 | N58: ARAUCARIA | O58: PR | P58: 83705-500 | Q58: 05094003000155 | R58: COLSON DO BRASIL LTDA | S58: ARAUCARIA | T58: PR | U58: 05094003000155 | V58: COLSON DO BRASIL LTDA | W58: RUA DAS PALMEIRAS 350 | X58: CAPELA VELHA | Y58: ARAUCARIA | Z58: PR | AA58: (41 ) 38887555 | AC58: 23476033001007 | AD58: BMB MATERIAL DE CONSTRUCAO SA | AE58: 134 | AF58: PSPP | AG58: PIRACICABA | AH58: SP | AI58: 23476033001007 | AJ58: BMB MATERIAL DE CONSTRUCAO SA | AK58: PIRACICABA | AL58: SP | AM58: PSP | AN58: 000189164 | AO58: 55.15 | AP58: 0 | AQ58: 7 | AR58: 0 | AS58: CP | AT58: LIQUIDADO | AU58: 46260 | AV58: 451.55 | AW58: 001-DIVERSOS | AX58: 001-DIVERSOS | AY58: 1955.67 | AZ58: COMBINADA | BA58: CO3365277 | BB58: 451.55 | BC58: 397.36 | BD58: 451.55 | BE58: 54.19 | BF58: 0.12 | BG58: 0 | BH58: 55.15 | BI58: 102.1 | BJ58: 0 | BK58: 17 | BL58: 0 | BM58: 9.76 | BN58: 2.93 | BO58: 5.5 | BP58: 3.23 | BQ58: 0 | BR58: 0 | BS58: 0 | BT58: 0 | BU58: 0 | BV58: 0 | BW58: 0 | BX58: 250 | BY58: 0 | BZ58: 0 | CA58: 6.84 | CB58: CTBP | CC58: SAOI | CD58: 377.55 | CE58: 0 | CF58: 0 | CG58: 0 | CH58: 0 | CI58: 0 | CJ58: 0 | CK58: 0 | CN58: 0 | CO58: 0 | CP58: 0 | CQ58: 0 | CR58: 0 | CS58: 0 | CT58: 0 | CU58: 12 | CV58: MAPA: 161 | CW58: 0 | CY58: 225.5 | CZ58: MAPA: 162 | DA58: =CY58 -> 225.5 | DE58: 0 | DF58: A. | DG58: PR | DH58: ARAUCARIA | DI58: 9026067267 | DJ58: (41 ) 38887555 | DK58: 0 | DL58: CTB | DM58: 54.19
A59: 2 | B59: CTB071008-3 | C59: NORMAL | D59: CTBP | E59: CTB | F59: 46244 | G59: DQB8989 | H59: 41260803098929000606570010000719031003695670 | I59: 05094003000155 | J59: COLSON DO BRASIL LTDA | K59: RUA DAS PALMEIRAS 350 | L59: CAPELA VELHA | M59: 002 | N59: ARAUCARIA | O59: PR | P59: 83705-500 | Q59: 05094003000155 | R59: COLSON DO BRASIL LTDA | S59: ARAUCARIA | T59: PR | U59: 05094003000155 | V59: COLSON DO BRASIL LTDA | W59: RUA DAS PALMEIRAS 350 | X59: CAPELA VELHA | Y59: ARAUCARIA | Z59: PR | AA59: (41 ) 38887555 | AC59: 28570581000116 | AD59: NLB MOTORES E BOMBAS LTDA | AE59: 132 | AF59: PSPR | AG59: ITATIBA | AH59: SP | AI59: 28570581000116 | AJ59: NLB MOTORES E BOMBAS LTDA | AK59: ITATIBA | AL59: SP | AM59: PSP | AN59: 000189118 | AO59: 41.981 | AP59: 0 | AQ59: 6 | AR59: 0 | AS59: CP | AT59: LIQUIDADO | AU59: 46260 | AV59: 294.75 | AW59: 001-DIVERSOS | AX59: 054-PNEUS E CAMARAS DE AR | AY59: 1782 | AZ59: COMBINADA | BA59: CO3365266 | BB59: 294.75 | BC59: 259.38 | BD59: 294.75 | BE59: 35.37 | BF59: 0.12 | BG59: 0 | BH59: 41.981 | BI59: 97.98 | BJ59: 0 | BK59: 17 | BL59: 0 | BM59: 9.76 | BN59: 2.67 | BO59: 5.5 | BP59: 3.23 | BQ59: 117 | BR59: 0 | BS59: 0 | BT59: 0 | BU59: 0 | BV59: 0 | BW59: 0 | BX59: 0 | BY59: 0 | BZ59: 0 | CA59: 6.24 | CB59: CTBP | CC59: SPOR | CD59: 375.81 | CE59: 0 | CF59: 0 | CG59: 0 | CH59: 0 | CI59: 0 | CJ59: 0 | CK59: 0 | CN59: 0 | CO59: 0 | CP59: 0 | CQ59: 0 | CR59: 0 | CS59: 0 | CT59: 0 | CU59: 12 | CV59: MAPA: 161 | CW59: 0 | CY59: 49.5 | CZ59: MAPA: 161 | DA59: =CY59 -> 49.5 | DE59: 0 | DF59: A. | DG59: PR | DH59: ARAUCARIA | DI59: 9026067267 | DJ59: (41 ) 38887555 | DK59: 0 | DL59: CTB | DM59: 35.37
A60: 2 | B60: CTB071009-1 | C60: NORMAL | D60: CTBP | E60: CTB | F60: 46244 | G60: DQB8989 | H60: 41260803098929000606570010000719041003695686 | I60: 05094003000155 | J60: COLSON DO BRASIL LTDA | K60: RUA DAS PALMEIRAS 350 | L60: CAPELA VELHA | M60: 002 | N60: ARAUCARIA | O60: PR | P60: 83705-500 | Q60: 05094003000155 | R60: COLSON DO BRASIL LTDA | S60: ARAUCARIA | T60: PR | U60: 05094003000155 | V60: COLSON DO BRASIL LTDA | W60: RUA DAS PALMEIRAS 350 | X60: CAPELA VELHA | Y60: ARAUCARIA | Z60: PR | AA60: (41 ) 38887555 | AC60: 23476033001341 | AD60: BMB MATERIAL DE CONSTRUCAO S.A 2040 | AE60: MES MESQUITA | AF60: RJOP | AG60: MESQUITA | AH60: RJ | AI60: 23476033001341 | AJ60: BMB MATERIAL DE CONSTRUCAO S.A 2040 | AK60: MESQUITA | AL60: RJ | AM60: RJO | AN60: 000189081 | AO60: 69.85 | AP60: 0 | AQ60: 6 | AR60: 0 | AS60: CP | AT60: LIQUIDADO | AU60: 46260 | AV60: 432.01 | AW60: 001-DIVERSOS | AX60: 054-PNEUS E CAMARAS DE AR | AY60: 2416.6 | AZ60: COMBINADA | BA60: CO3365267 | BB60: 432.01 | BC60: 380.17 | BD60: 432.01 | BE60: 51.84 | BF60: 0.12 | BG60: 0 | BH60: 69.85 | BI60: 82.6 | BJ60: 0 | BK60: 17 | BL60: 0 | BM60: 9.76 | BN60: 3.62 | BO60: 5.5 | BP60: 3.23 | BQ60: 0 | BR60: 0 | BS60: 0 | BT60: 0 | BU60: 0 | BV60: 0 | BW60: 0 | BX60: 250 | BY60: 0 | BZ60: 0 | CA60: 8.46 | CB60: CTBP | CC60: RJOP | CD60: 382.17 | CE60: 0 | CF60: 0 | CG60: 0 | CH60: 0 | CI60: 0 | CJ60: 0 | CK60: 0 | CN60: 0 | CO60: 0 | CP60: 0 | CQ60: 0 | CR60: 0 | CS60: 0 | CT60: 0 | CU60: 12 | CV60: MAPA: 161 | CW60: 0 | CY60: 18 | CZ60: MAPA: 162 | DA60: 0 | DE60: 0 | DF60: A. | DG60: PR | DH60: ARAUCARIA | DI60: 9026067267 | DJ60: (41 ) 38887555 | DK60: 0 | DL60: CTB | DM60: 51.84
A61: 2 | B61: CTB071010-5 | C61: NORMAL | D61: CTBP | E61: CTB | F61: 46244 | G61: DQB8989 | H61: 41260803098929000606570010000719051003695691 | I61: 05094003000155 | J61: COLSON DO BRASIL LTDA | K61: RUA DAS PALMEIRAS 350 | L61: CAPELA VELHA | M61: 002 | N61: ARAUCARIA | O61: PR | P61: 83705-500 | Q61: 05094003000155 | R61: COLSON DO BRASIL LTDA | S61: ARAUCARIA | T61: PR | U61: 05094003000155 | V61: COLSON DO BRASIL LTDA | W61: RUA DAS PALMEIRAS 350 | X61: CAPELA VELHA | Y61: ARAUCARIA | Z61: PR | AA61: (41 ) 38887555 | AC61: 23476033002151 | AD61: BMB MATERIAL DE CONSTRUCAO S.A. | AE61: 384 | AF61: TRUP | AG61: UBERLANDIA | AH61: MG | AI61: 23476033002151 | AJ61: BMB MATERIAL DE CONSTRUCAO S.A. | AK61: UBERLANDIA | AL61: MG | AM61: TRU | AN61: 000188597 | AO61: 87 | AP61: 0 | AQ61: 8 | AR61: 0 | AS61: CP | AT61: LIQUIDADO | AU61: 46260 | AV61: 537.86 | AW61: 001-DIVERSOS | AX61: 001-DIVERSOS | AY61: 2926.63 | AZ61: COMBINADA | BA61: CO3365284 | BB61: 537.86 | BC61: 473.32 | BD61: 537.86 | BE61: 64.54 | BF61: 0.12 | BG61: 0 | BH61: 87 | BI61: 173.2 | BJ61: 0 | BK61: 17 | BL61: 0 | BM61: 9.76 | BN61: 4.39 | BO61: 5.5 | BP61: 3.23 | BQ61: 0 | BR61: 0 | BS61: 0 | BT61: 0 | BU61: 0 | BV61: 0 | BW61: 0 | BX61: 250 | BY61: 0 | BZ61: 0 | CA61: 10.24 | CB61: CTBP | CC61: PANI | CD61: 388.04 | CE61: 0 | CF61: 0 | CG61: 0 | CH61: 0 | CI61: 0 | CJ61: 0 | CK61: 0 | CN61: 0 | CO61: 0 | CP61: 0 | CQ61: 0 | CR61: 0 | CS61: 0 | CT61: 0 | CU61: 13.05 | CV61: MAPA: 161 | CW61: 0 | CY61: 375.14 | CZ61: FATURA: 232784 | DA61: 487.52 | DB61: 232784 | DE61: 0 | DF61: A. | DG61: PR | DH61: ARAUCARIA | DI61: 9026067267 | DJ61: (41 ) 38887555 | DK61: 0 | DL61: CTB | DM61: 64.54
A62: 2 | B62: CTB071011-3 | C62: NORMAL | D62: CTBP | E62: CTB | F62: 46244 | G62: DQB8989 | H62: 41260803098929000606570010000719061003695702 | I62: 05094003000155 | J62: COLSON DO BRASIL LTDA | K62: RUA DAS PALMEIRAS 350 | L62: CAPELA VELHA | M62: 002 | N62: ARAUCARIA | O62: PR | P62: 83705-500 | Q62: 05094003000155 | R62: COLSON DO BRASIL LTDA | S62: ARAUCARIA | T62: PR | U62: 05094003000155 | V62: COLSON DO BRASIL LTDA | W62: RUA DAS PALMEIRAS 350 | X62: CAPELA VELHA | Y62: ARAUCARIA | Z62: PR | AA62: (41 ) 38887555 | AC62: 23476033000370 | AD62: BMB MATERIAL DE CONSTRUCAO SA | AE62: 117 | AF62: SVPR | AG62: PRAIA GRANDE | AH62: SP | AI62: 23476033000370 | AJ62: BMB MATERIAL DE CONSTRUCAO SA | AK62: PRAIA GRANDE | AL62: SP | AM62: SVP | AN62: 000188727 | AO62: 95.035 | AP62: 0 | AQ62: 10 | AR62: 0 | AS62: CP | AT62: LIQUIDADO | AU62: 46260 | AV62: 456.97 | AW62: 001-DIVERSOS | AX62: 054-PNEUS E CAMARAS DE AR | AY62: 3348.91 | AZ62: COMBINADA | BA62: CO3365274 | BB62: 456.97 | BC62: 402.13 | BD62: 456.97 | BE62: 54.84 | BF62: 0.12 | BG62: 0 | BH62: 95.035 | BI62: 99.9 | BJ62: 0 | BK62: 17 | BL62: 0 | BM62: 9.76 | BN62: 5.02 | BO62: 5.5 | BP62: 3.23 | BQ62: 0 | BR62: 0 | BS62: 0 | BT62: 0 | BU62: 0 | BV62: 0 | BW62: 0 | BX62: 250 | BY62: 0 | BZ62: 0 | CA62: 11.72 | CB62: CTBP | CC62: SPOP | CD62: 393.53 | CE62: 0 | CF62: 0 | CG62: 0 | CH62: 0 | CI62: 0 | CJ62: 0 | CK62: 0 | CN62: 0 | CO62: 0 | CP62: 0 | CQ62: 0 | CR62: 0 | CS62: 0 | CT62: 0 | CU62: 14.26 | CV62: MAPA: 161 | CW62: 0 | CY62: 260.02 | CZ62: FATURA: 612 | DA62: 519 | DB62: 000612 | DE62: 0 | DF62: A. | DG62: PR | DH62: ARAUCARIA | DI62: 9026067267 | DJ62: (41 ) 38887555 | DK62: 0 | DL62: CTB | DM62: 54.84
A63: 2 | B63: CTB071012-1 | C63: NORMAL | D63: CTBP | E63: CTB | F63: 46244 | G63: DQB8989 | H63: 41260803098929000606570010000719071003695718 | I63: 05094003000155 | J63: COLSON DO BRASIL LTDA | K63: RUA DAS PALMEIRAS 350 | L63: CAPELA VELHA | M63: 002 | N63: ARAUCARIA | O63: PR | P63: 83705-500 | Q63: 05094003000155 | R63: COLSON DO BRASIL LTDA | S63: ARAUCARIA | T63: PR | U63: 05094003000155 | V63: COLSON DO BRASIL LTDA | W63: RUA DAS PALMEIRAS 350 | X63: CAPELA VELHA | Y63: ARAUCARIA | Z63: PR | AA63: (41 ) 38887555 | AC63: 23476033002151 | AD63: BMB MATERIAL DE CONSTRUCAO S.A. | AE63: 384 | AF63: TRUP | AG63: UBERLANDIA | AH63: MG | AI63: 23476033002151 | AJ63: BMB MATERIAL DE CONSTRUCAO S.A. | AK63: UBERLANDIA | AL63: MG | AM63: TRU | AN63: 000188735 | AO63: 85.185 | AP63: 0 | AQ63: 7 | AR63: 0 | AS63: CP | AT63: LIQUIDADO | AU63: 46260 | AV63: 540.25 | AW63: 001-DIVERSOS | AX63: 054-PNEUS E CAMARAS DE AR | AY63: 3345.15 | AZ63: COMBINADA | BA63: CO3365284 | BB63: 540.25 | BC63: 475.42 | BD63: 540.25 | BE63: 64.83 | BF63: 0.12 | BG63: 0 | BH63: 85.185 | BI63: 173.2 | BJ63: 0 | BK63: 17 | BL63: 0 | BM63: 9.76 | BN63: 5.02 | BO63: 5.5 | BP63: 3.23 | BQ63: 0 | BR63: 0 | BS63: 0 | BT63: 0 | BU63: 0 | BV63: 0 | BW63: 0 | BX63: 250 | BY63: 0 | BZ63: 0 | CA63: 11.71 | CB63: CTBP | CC63: PANI | CD63: 393.48 | CE63: 0 | CF63: 0 | CG63: 0 | CH63: 0 | CI63: 0 | CJ63: 0 | CK63: 0 | CN63: 0 | CO63: 0 | CP63: 0 | CQ63: 0 | CR63: 0 | CS63: 0 | CT63: 0 | CU63: 12.78 | CV63: MAPA: 161 | CW63: 0 | CY63: 376.1 | CZ63: FATURA: 232784 | DA63: 488.43 | DB63: 232784 | DE63: 0 | DF63: A. | DG63: PR | DH63: ARAUCARIA | DI63: 9026067267 | DJ63: (41 ) 38887555 | DK63: 0 | DL63: CTB | DM63: 64.83
A64: 2 | B64: CTB071013-0 | C64: NORMAL | D64: CTBP | E64: CTB | F64: 46244 | G64: DQB8989 | H64: 41260803098929000606570010000719081003695723 | I64: 05094003000155 | J64: COLSON DO BRASIL LTDA | K64: RUA DAS PALMEIRAS 350 | L64: CAPELA VELHA | M64: 002 | N64: ARAUCARIA | O64: PR | P64: 83705-500 | Q64: 05094003000155 | R64: COLSON DO BRASIL LTDA | S64: ARAUCARIA | T64: PR | U64: 05094003000155 | V64: COLSON DO BRASIL LTDA | W64: RUA DAS PALMEIRAS 350 | X64: CAPELA VELHA | Y64: ARAUCARIA | Z64: PR | AA64: (41 ) 38887555 | AC64: 23476033001694 | AD64: BMB MATERIAL DE CONSTRUCAO S.A. 0016-94 | AE64: 291 | AF64: EPSP | AG64: CARIACICA | AH64: ES | AI64: 23476033001694 | AJ64: BMB MATERIAL DE CONSTRUCAO S.A. 0016-94 | AK64: CARIACICA | AL64: ES | AM64: EPS | AN64: 000189145 | AO64: 81.265 | AP64: 0 | AQ64: 6 | AR64: 0 | AS64: CP | AT64: LIQUIDADO | AU64: 46260 | AV64: 446.61 | AW64: 001-DIVERSOS | AX64: 054-PNEUS E CAMARAS DE AR | AY64: 2812.38 | AZ64: COMBINADA | BA64: CO3365268 | BB64: 446.61 | BC64: 415.35 | BD64: 446.61 | BE64: 31.26 | BF64: 0.07 | BG64: 0 | BH64: 81.265 | BI64: 115.8 | BJ64: 0 | BK64: 17 | BL64: 0 | BM64: 9.76 | BN64: 4.22 | BO64: 5.5 | BP64: 3.23 | BQ64: 0 | BR64: 0 | BS64: 0 | BT64: 0 | BU64: 0 | BV64: 0 | BW64: 0 | BX64: 250 | BY64: 0 | BZ64: 0 | CA64: 9.84 | CB64: CTBP | CC64: EPSP | CD64: 386.54 | CE64: 0 | CF64: 0 | CG64: 0 | CH64: 0 | CI64: 0 | CJ64: 0 | CK64: 0 | CN64: 0 | CO64: 0 | CP64: 0 | CQ64: 0 | CR64: 0 | CS64: 0 | CT64: 0 | CU64: 12.19 | CV64: MAPA: 161 | CW64: 0 | CY64: 329.37 | CZ64: FATURA: 55301 | DA64: 214.37 | DB64: 055301 | DE64: 0 | DF64: A. | DG64: PR | DH64: ARAUCARIA | DI64: 9026067267 | DJ64: (41 ) 38887555 | DK64: 0 | DL64: CTB | DM64: 31.26
A65: 2 | B65: CTB071014-8 | C65: NORMAL | D65: CTBP | E65: CTB | F65: 46244 | G65: DQB8989 | H65: 41260803098929000606570010000719091003695739 | I65: 05094003000155 | J65: COLSON DO BRASIL LTDA | K65: RUA DAS PALMEIRAS 350 | L65: CAPELA VELHA | M65: 002 | N65: ARAUCARIA | O65: PR | P65: 83705-500 | Q65: 05094003000155 | R65: COLSON DO BRASIL LTDA | S65: ARAUCARIA | T65: PR | U65: 05094003000155 | V65: COLSON DO BRASIL LTDA | W65: RUA DAS PALMEIRAS 350 | X65: CAPELA VELHA | Y65: ARAUCARIA | Z65: PR | AA65: (41 ) 38887555 | AC65: 21253573000105 | AD65: FREITAS E MORAES LOCACAO DE FERRAMENTAS | AE65: 283 | AF65: RCGR | AG65: BOM JESUS DO ITABAPOANA | AH65: RJ | AI65: 21253573000105 | AJ65: FREITAS E MORAES LOCACAO DE FERRAMENTAS | AK65: BOM JESUS DO ITABAPOANA | AL65: RJ | AM65: RCG | AN65: 000189142 | AO65: 217.5 | AP65: 0 | AQ65: 15 | AR65: 0 | AS65: CP | AT65: LIQUIDADO | AU65: 46260 | AV65: 376.41 | AW65: 001-DIVERSOS | AX65: 001-DIVERSOS | AY65: 6053.16 | AZ65: COMBINADA | BA65: CO3365270 | BB65: 376.41 | BC65: 331.24 | BD65: 376.41 | BE65: 45.17 | BF65: 0.12 | BG65: 0 | BH65: 217.5 | BI65: 254.48 | BJ65: 0 | BK65: 17 | BL65: 0 | BM65: 9.76 | BN65: 9.08 | BO65: 16.5 | BP65: 3.23 | BQ65: 0 | BR65: 0 | BS65: 0 | BT65: 0 | BU65: 0 | BV65: 0 | BW65: 0 | BX65: 0 | BY65: 0 | BZ65: 0 | CA65: 21.19 | CB65: CTBP | CC65: ITAI | CD65: 489.93 | CE65: 0 | CF65: 0 | CG65: 0 | CH65: 0 | CI65: 0 | CJ65: 0 | CK65: 0 | CN65: 0 | CO65: 0 | CP65: 0 | CQ65: 0 | CR65: 0 | CS65: 0 | CT65: 0 | CU65: 32.63 | CV65: MAPA: 161 | CW65: 0 | CY65: 129.85 | CZ65: FATURA: 12167 | DA65: 145.66 | DB65: 012167 | DE65: 0 | DF65: A. | DG65: PR | DH65: ARAUCARIA | DI65: 9026067267 | DJ65: (41 ) 38887555 | DK65: 0 | DL65: CTB | DM65: 45.17
A66: 2 | B66: CTB071085-7 | C66: NORMAL | D66: CTBP | E66: CTB | F66: 46245 | G66: DQB8989 | H66: 41260803098929000606570010000719721003702895 | I66: 05094003000155 | J66: COLSON DO BRASIL LTDA | K66: RUA DAS PALMEIRAS 350 | L66: CAPELA VELHA | M66: 002 | N66: ARAUCARIA | O66: PR | P66: 83705-500 | Q66: 05094003000155 | R66: COLSON DO BRASIL LTDA | S66: ARAUCARIA | T66: PR | U66: 05094003000155 | V66: COLSON DO BRASIL LTDA | W66: RUA DAS PALMEIRAS 350 | X66: CAPELA VELHA | Y66: ARAUCARIA | Z66: PR | AA66: (41 ) 38887555 | AC66: 74469446000287 | AD66: RR PARAFUSOS FERRAGENS E FERRAMENT | AE66: 131 | AF66: PSPR | AG66: ARTUR NOGUEIRA | AH66: SP | AI66: 74469446000287 | AJ66: RR PARAFUSOS FERRAGENS E FERRAMENT | AK66: ARTUR NOGUEIRA | AL66: SP | AM66: PSP | AN66: 000189216 | AO66: 77.45 | AP66: 0 | AQ66: 7 | AR66: 0 | AS66: CP | AT66: LIQUIDADO | AU66: 46260 | AV66: 261.38 | AW66: 001-DIVERSOS | AX66: 001-DIVERSOS | AY66: 3192.9 | AZ66: COMBINADA | BA66: CO3365266 | BB66: 261.38 | BC66: 230.01 | BD66: 261.38 | BE66: 31.37 | BF66: 0.12 | BG66: 0 | BH66: 77.45 | BI66: 178.55 | BJ66: 0 | BK66: 17 | BL66: 0 | BM66: 9.76 | BN66: 4.79 | BO66: 5.5 | BP66: 3.23 | BQ66: 0 | BR66: 0 | BS66: 0 | BT66: 0 | BU66: 0 | BV66: 0 | BW66: 0 | BX66: 0 | BY66: 0 | BZ66: 0 | CA66: 11.18 | CB66: CTBP | CC66: SAOP | CD66: 391.52 | CE66: 0 | CF66: 0 | CG66: 0 | CH66: 0 | CI66: 0 | CJ66: 0 | CK66: 0 | CN66: 0 | CO66: 0 | CP66: 0 | CQ66: 0 | CR66: 0 | CS66: 0 | CT66: 0 | CU66: 12 | CV66: MAPA: 161 | CW66: 0 | CY66: 66 | CZ66: MAPA: 162 | DA66: =CY66 -> 66 | DE66: 0 | DF66: A. | DG66: PR | DH66: ARAUCARIA | DI66: 9026067267 | DJ66: (41 ) 38887555 | DK66: 0 | DL66: CTB | DM66: 28.71
A67: 2 | B67: CTB071045-8 | C67: COMPLEMENTAR FRETE | D67: CTBP | E67: CTB | F67: 46245 | G67: BFE7A89 | H67: 41260803098929000606570010000719401003699351 | I67: 05094003000155 | J67: COLSON DO BRASIL LTDA | K67: RUA DAS PALMEIRAS 350 | L67: CAPELA VELHA | M67: 002 | N67: ARAUCARIA | O67: PR | P67: 83705-500 | Q67: 05094003000155 | R67: COLSON DO BRASIL LTDA | S67: ARAUCARIA | T67: PR | U67: 05094003000155 | V67: COLSON DO BRASIL LTDA | W67: RUA DAS PALMEIRAS 350 | X67: CAPELA VELHA | Y67: ARAUCARIA | Z67: PR | AA67: (41 ) 38887555 | AC67: 43011160000149 | AD67: ADELMO SILVA SANTOS EQUIPAMENTOS | AE67: 11 ABCD | AF67: SPOP | AG67: DIADEMA | AH67: SP | AI67: 43011160000149 | AJ67: ADELMO SILVA SANTOS EQUIPAMENTOS | AK67: DIADEMA | AL67: SP | AM67: SPO | AN67: 000188960 | AO67: 35.061 | AP67: 0 | AQ67: 3 | AR67: 0 | AS67: CP | AT67: LIQUIDADO | AU67: 46260 | AV67: 284.09 | AW67: 001-DIVERSOS | AX67: 001-DIVERSOS | AY67: 1517.68 | AZ67: COMPLEMENTAR DE FRETE | BB67: 284.09 | BC67: 250 | BD67: 284.09 | BE67: 34.09 | BF67: 0.12 | BG67: 0 | BH67: 35.061 | BI67: 0 | BJ67: 250 | BK67: 0 | BL67: 0 | BM67: 0 | BN67: 0 | BO67: 0 | BP67: 0 | BQ67: 0 | BR67: 0 | BS67: 0 | BT67: 0 | BU67: 0 | BV67: 0 | BW67: 0 | BX67: 0 | BY67: 0 | BZ67: 0 | CA67: 0 | CB67: CTBP | CC67: SPOP | CD67: 373.16 | CE67: 0 | CF67: 0 | CG67: 0 | CH67: 0 | CI67: 0 | CJ67: 0 | CK67: 0 | CN67: 0 | CO67: 0 | CP67: 0 | CQ67: 0 | CR67: 0 | CS67: 0 | CT67: 0 | CU67: 0 | CV67: MAPA: 0 | CW67: 0 | CY67: 0 | CZ67: MAPA: 0 | DA67: 0 | DE67: 0 | DF67: A. | DG67: PR | DH67: ARAUCARIA | DI67: 9026067267 | DJ67: (41 ) 38887555 | DK67: 0 | DL67: CTB | DM67: 34.09
A68: 2 | B68: CTB071075-0 | C68: NORMAL | D68: CTBP | E68: CTB | F68: 46245 | G68: DQB8989 | H68: 41260803098929000606570010000719741003702911 | I68: 05094003000155 | J68: COLSON DO BRASIL LTDA | K68: RUA DAS PALMEIRAS 350 | L68: CAPELA VELHA | M68: 002 | N68: ARAUCARIA | O68: PR | P68: 83705-500 | Q68: 05094003000155 | R68: COLSON DO BRASIL LTDA | S68: ARAUCARIA | T68: PR | U68: 05094003000155 | V68: COLSON DO BRASIL LTDA | W68: RUA DAS PALMEIRAS 350 | X68: CAPELA VELHA | Y68: ARAUCARIA | Z68: PR | AA68: (41 ) 38887555 | AC68: 74200403001192 | AD68: NOVA CASA DISTRIBUIDORA DE MAT | AE68: 005 CONTAGEM | AF68: BHZP | AG68: CONTAGEM | AH68: MG | AI68: 74200403001192 | AJ68: NOVA CASA DISTRIBUIDORA DE MAT | AK68: CONTAGEM | AL68: MG | AM68: BHZ | AN68: 000189254 | AO68: 151.4 | AP68: 0 | AQ68: 11 | AR68: 0 | AS68: CP | AT68: LIQUIDADO | AU68: 46260 | AV68: 501.11 | AW68: 001-DIVERSOS | AX68: 001-DIVERSOS | AY68: 3324.17 | AZ68: COMBINADA | BA68: CO3365271 | BB68: 501.11 | BC68: 440.98 | BD68: 501.11 | BE68: 60.13 | BF68: 0.12 | BG68: 0 | BH68: 151.4 | BI68: 133.37 | BJ68: 0 | BK68: 17 | BL68: 0 | BM68: 9.76 | BN68: 4.99 | BO68: 11 | BP68: 3.23 | BQ68: 0 | BR68: 0 | BS68: 0 | BT68: 0 | BU68: 0 | BV68: 0 | BW68: 0 | BX68: 250 | BY68: 0 | BZ68: 0 | CA68: 11.63 | CB68: CTBP | CC68: BHZP | CD68: 393.21 | CE68: 0 | CF68: 0 | CG68: 0 | CH68: 0 | CI68: 0 | CJ68: 0 | CK68: 0 | CN68: 0 | CO68: 0 | CP68: 0 | CQ68: 0 | CR68: 0 | CS68: 0 | CT68: 0 | CU68: 22.71 | CV68: MAPA: 161 | CW68: 0 | CY68: 21.2 | CZ68: MAPA: 162 | DA68: 0 | DE68: 0 | DF68: A. | DG68: PR | DH68: ARAUCARIA | DI68: 9026067267 | DJ68: (41 ) 38887555 | DK68: 0 | DL68: CTB | DM68: 60.13
A69: 2 | B69: CTB071076-8 | C69: NORMAL | D69: CTBP | E69: CTB | F69: 46245 | G69: DQB8989 | H69: 41260803098929000606570010000719751003702927 | I69: 05094003000155 | J69: COLSON DO BRASIL LTDA | K69: RUA DAS PALMEIRAS 350 | L69: CAPELA VELHA | M69: 002 | N69: ARAUCARIA | O69: PR | P69: 83705-500 | Q69: 05094003000155 | R69: COLSON DO BRASIL LTDA | S69: ARAUCARIA | T69: PR | U69: 05094003000155 | V69: COLSON DO BRASIL LTDA | W69: RUA DAS PALMEIRAS 350 | X69: CAPELA VELHA | Y69: ARAUCARIA | Z69: PR | AA69: (41 ) 38887555 | AC69: 23476033001775 | AD69: BMB MATERIAL DE CONSTRUCAO S.A | AE69: RIO RIO DE JANEIRO | AF69: RJOP | AG69: RIO DE JANEIRO | AH69: RJ | AI69: 23476033001775 | AJ69: BMB MATERIAL DE CONSTRUCAO S.A | AK69: RIO DE JANEIRO | AL69: RJ | AM69: RJO | AN69: 000189146 | AO69: 83.425 | AP69: 0 | AQ69: 6 | AR69: 0 | AS69: CP | AT69: LIQUIDADO | AU69: 46260 | AV69: 453.33 | AW69: 001-DIVERSOS | AX69: 054-PNEUS E CAMARAS DE AR | AY69: 2649.85 | AZ69: COMBINADA | BA69: CO3365267 | BB69: 453.33 | BC69: 398.93 | BD69: 453.33 | BE69: 54.4 | BF69: 0.12 | BG69: 0 | BH69: 83.425 | BI69: 100.2 | BJ69: 0 | BK69: 17 | BL69: 0 | BM69: 9.76 | BN69: 3.97 | BO69: 5.5 | BP69: 3.23 | BQ69: 0 | BR69: 0 | BS69: 0 | BT69: 0 | BU69: 0 | BV69: 0 | BW69: 0 | BX69: 250 | BY69: 0 | BZ69: 0 | CA69: 9.27 | CB69: CTBP | CC69: RJOP | CD69: 384.5 | CE69: 0 | CF69: 0 | CG69: 0 | CH69: 0 | CI69: 0 | CJ69: 0 | CK69: 0 | CN69: 0 | CO69: 0 | CP69: 0 | CQ69: 0 | CR69: 0 | CS69: 0 | CT69: 0 | CU69: 12.51 | CV69: MAPA: 161 | CW69: 0 | CY69: 18 | CZ69: MAPA: 162 | DA69: 0 | DE69: 0 | DF69: A. | DG69: PR | DH69: ARAUCARIA | DI69: 9026067267 | DJ69: (41 ) 38887555 | DK69: 0 | DL69: CTB | DM69: 54.4
A70: 2 | B70: CTB071077-6 | C70: NORMAL | D70: CTBP | E70: CTB | F70: 46245 | G70: DQB8989 | H70: 41260803098929000606570010000719761003702932 | I70: 05094003000155 | J70: COLSON DO BRASIL LTDA | K70: RUA DAS PALMEIRAS 350 | L70: CAPELA VELHA | M70: 002 | N70: ARAUCARIA | O70: PR | P70: 83705-500 | Q70: 05094003000155 | R70: COLSON DO BRASIL LTDA | S70: ARAUCARIA | T70: PR | U70: 05094003000155 | V70: COLSON DO BRASIL LTDA | W70: RUA DAS PALMEIRAS 350 | X70: CAPELA VELHA | Y70: ARAUCARIA | Z70: PR | AA70: (41 ) 38887555 | AC70: 42434985000103 | AD70: PARAFUSO ALEX LTDA ME | AE70: RIO RIO DE JANEIRO | AF70: RJOP | AG70: RIO DE JANEIRO | AH70: RJ | AI70: 42434985000103 | AJ70: PARAFUSO ALEX LTDA ME | AK70: RIO DE JANEIRO | AL70: RJ | AM70: RJO | AN70: 000189184 | AO70: 606.721 | AP70: 0 | AQ70: 70 | AR70: 0 | AS70: CP | AT70: LIQUIDADO | AU70: 46260 | AV70: 795.67 | AW70: 001-DIVERSOS | AX70: 054-PNEUS E CAMARAS DE AR | AY70: 17118.02 | AZ70: COMBINADA | BA70: CO3365267 | BB70: 795.67 | BC70: 700.19 | BD70: 795.67 | BE70: 95.48 | BF70: 0.12 | BG70: 0 | BH70: 606.721 | BI70: 546.11 | BJ70: 0 | BK70: 17 | BL70: 0 | BM70: 9.76 | BN70: 25.68 | BO70: 38.5 | BP70: 3.23 | BQ70: 0 | BR70: 0 | BS70: 0 | BT70: 0 | BU70: 0 | BV70: 0 | BW70: 0 | BX70: 0 | BY70: 0 | BZ70: 0 | CA70: 59.91 | CB70: CTBP | CC70: RJOP | CD70: 1996.16 | CE70: 0 | CF70: 0 | CG70: 0 | CH70: 0 | CI70: 0 | CJ70: 0 | CK70: 0 | CN70: 0 | CO70: 0 | CP70: 0 | CQ70: 0 | CR70: 0 | CS70: 0 | CT70: 0 | CU70: 91.01 | CV70: MAPA: 161 | CW70: 0 | CY70: 109.21 | CZ70: MAPA: 161 | DA70: 0 | DE70: 0 | DF70: A. | DG70: PR | DH70: ARAUCARIA | DI70: 9026067267 | DJ70: (41 ) 38887555 | DK70: 0 | DL70: CTB | DM70: 95.48
A71: 2 | B71: CTB071078-4 | C71: NORMAL | D71: CTBP | E71: CTB | F71: 46245 | G71: DQB8989 | H71: 41260803098929000606570010000719771003702948 | I71: 05094003000155 | J71: COLSON DO BRASIL LTDA | K71: RUA DAS PALMEIRAS 350 | L71: CAPELA VELHA | M71: 002 | N71: ARAUCARIA | O71: PR | P71: 83705-500 | Q71: 05094003000155 | R71: COLSON DO BRASIL LTDA | S71: ARAUCARIA | T71: PR | U71: 05094003000155 | V71: COLSON DO BRASIL LTDA | W71: RUA DAS PALMEIRAS 350 | X71: CAPELA VELHA | Y71: ARAUCARIA | Z71: PR | AA71: (41 ) 38887555 | AC71: 39527817000158 | AD71: ACO RUBER COML. LTDA | AE71: 272 | AF71: MVGP | AG71: VOLTA REDONDA | AH71: RJ | AI71: 39527817000158 | AJ71: ACO RUBER COML. LTDA | AK71: VOLTA REDONDA | AL71: RJ | AM71: MVG | AN71: 000189206 | AO71: 158.413 | AP71: 0 | AQ71: 22 | AR71: 0 | AS71: CP | AT71: LIQUIDADO | AU71: 46260 | AV71: 289.27 | AW71: 001-DIVERSOS | AX71: 054-PNEUS E CAMARAS DE AR | AY71: 5645.07 | AZ71: COMBINADA | BA71: CO3365270 | BB71: 289.27 | BC71: 254.56 | BD71: 289.27 | BE71: 34.71 | BF71: 0.12 | BG71: 0 | BH71: 158.413 | BI71: 185.34 | BJ71: 0 | BK71: 17 | BL71: 0 | BM71: 9.76 | BN71: 8.47 | BO71: 11 | BP71: 3.23 | BQ71: 0 | BR71: 0 | BS71: 0 | BT71: 0 | BU71: 0 | BV71: 0 | BW71: 0 | BX71: 0 | BY71: 0 | BZ71: 0 | CA71: 19.76 | CB71: CTBP | CC71: ITAI | CD71: 423.4 | CE71: 0 | CF71: 0 | CG71: 0 | CH71: 0 | CI71: 0 | CJ71: 0 | CK71: 0 | CN71: 0 | CO71: 0 | CP71: 0 | CQ71: 0 | CR71: 0 | CS71: 0 | CT71: 0 | CU71: 23.76 | CV71: MAPA: 161 | CW71: 0 | CY71: 95.1 | CZ71: FATURA: 17774 | DA71: 95.1 | DB71: 017774 | DE71: 0 | DF71: A. | DG71: PR | DH71: ARAUCARIA | DI71: 9026067267 | DJ71: (41 ) 38887555 | DK71: 0 | DL71: CTB | DM71: 34.71
A72: 2 | B72: CTB071079-2 | C72: NORMAL | D72: CTBP | E72: CTB | F72: 46245 | G72: DQB8989 | H72: 41260803098929000606570010000719781003702953 | I72: 05094003000155 | J72: COLSON DO BRASIL LTDA | K72: RUA DAS PALMEIRAS 350 | L72: CAPELA VELHA | M72: 002 | N72: ARAUCARIA | O72: PR | P72: 83705-500 | Q72: 05094003000155 | R72: COLSON DO BRASIL LTDA | S72: ARAUCARIA | T72: PR | U72: 05094003000155 | V72: COLSON DO BRASIL LTDA | W72: RUA DAS PALMEIRAS 350 | X72: CAPELA VELHA | Y72: ARAUCARIA | Z72: PR | AA72: (41 ) 38887555 | AC72: 06327315000124 | AD72: URBAN LOC LOCACOES E COMERCIO LTDA | AE72: 144 | AF72: NSLR | AG72: RIFAINA | AH72: SP | AI72: 06327315000124 | AJ72: URBAN LOC LOCACOES E COMERCIO LTDA | AK72: RIFAINA | AL72: SP | AM72: NSL | AN72: 000189258 | AO72: 215.8 | AP72: 0 | AQ72: 13 | AR72: 0 | AS72: CP | AT72: LIQUIDADO | AU72: 46260 | AV72: 380.83 | AW72: 001-DIVERSOS | AX72: 001-DIVERSOS | AY72: 4640.43 | AZ72: COMBINADA | BA72: CO3365277 | BB72: 380.83 | BC72: 335.13 | BD72: 380.83 | BE72: 45.7 | BF72: 0.12 | BG72: 0 | BH72: 215.8 | BI72: 200.44 | BJ72: 0 | BK72: 17 | BL72: 0 | BM72: 9.76 | BN72: 6.96 | BO72: 16.5 | BP72: 3.23 | BQ72: 65 | BR72: 0 | BS72: 0 | BT72: 0 | BU72: 0 | BV72: 0 | BW72: 0 | BX72: 0 | BY72: 0 | BZ72: 0 | CA72: 16.24 | CB72: CTBP | CC72: SAOI | CD72: 465.62 | CE72: 0 | CF72: 0 | CG72: 0 | CH72: 0 | CI72: 0 | CJ72: 0 | CK72: 0 | CN72: 0 | CO72: 0 | CP72: 0 | CQ72: 0 | CR72: 0 | CS72: 0 | CT72: 0 | CU72: 32.37 | CV72: MAPA: 161 | CW72: 0 | CY72: 110.01 | CZ72: FATURA: 160426 | DA72: 196.1 | DB72: 160426 | DE72: 0 | DF72: A. | DG72: PR | DH72: ARAUCARIA | DI72: 9026067267 | DJ72: (41 ) 38887555 | DK72: 0 | DL72: CTB | DM72: 45.7
A73: 2 | B73: CTB071080-6 | C73: NORMAL | D73: CTBP | E73: CTB | F73: 46245 | G73: DQB8989 | H73: 41260803098929000606570010000719791003702969 | I73: 05094003000155 | J73: COLSON DO BRASIL LTDA | K73: RUA DAS PALMEIRAS 350 | L73: CAPELA VELHA | M73: 002 | N73: ARAUCARIA | O73: PR | P73: 83705-500 | Q73: 05094003000155 | R73: COLSON DO BRASIL LTDA | S73: ARAUCARIA | T73: PR | U73: 05094003000155 | V73: COLSON DO BRASIL LTDA | W73: RUA DAS PALMEIRAS 350 | X73: CAPELA VELHA | Y73: ARAUCARIA | Z73: PR | AA73: (41 ) 38887555 | AC73: 35287123000130 | AD73: HOSPITAL DAS CAMAS MANUTENCOES EM GERAL LTDA | AE73: 09 GR2 | AF73: SPOR | AG73: MOGI DAS CRUZES | AH73: SP | AI73: 35287123000130 | AJ73: HOSPITAL DAS CAMAS MANUTENCOES EM GERAL LTDA | AK73: MOGI DAS CRUZES | AL73: SP | AM73: SPO | AN73: 000189262 | AO73: 59.5 | AP73: 0 | AQ73: 4 | AR73: 0 | AS73: CP | AT73: LIQUIDADO | AU73: 46260 | AV73: 238.76 | AW73: 001-DIVERSOS | AX73: 001-DIVERSOS | AY73: 7775.76 | AZ73: COMBINADA | BA73: CO3365266 | BB73: 238.76 | BC73: 210.11 | BD73: 238.76 | BE73: 28.65 | BF73: 0.12 | BG73: 0 | BH73: 59.5 | BI73: 135.74 | BJ73: 0 | BK73: 17 | BL73: 0 | BM73: 9.76 | BN73: 11.66 | BO73: 5.5 | BP73: 3.23 | BQ73: 0 | BR73: 0 | BS73: 0 | BT73: 0 | BU73: 0 | BV73: 0 | BW73: 0 | BX73: 0 | BY73: 0 | BZ73: 0 | CA73: 27.22 | CB73: CTBP | CC73: SPOR | CD73: 451.09 | CE73: 0 | CF73: 0 | CG73: 0 | CH73: 0 | CI73: 0 | CJ73: 0 | CK73: 0 | CN73: 0 | CO73: 0 | CP73: 0 | CQ73: 0 | CR73: 0 | CS73: 0 | CT73: 0 | CU73: 12 | CV73: MAPA: 161 | CW73: 0 | CY73: 18 | CZ73: MAPA: 161 | DA73: 0 | DE73: 0 | DF73: A. | DG73: PR | DH73: ARAUCARIA | DI73: 9026067267 | DJ73: (41 ) 38887555 | DK73: 0 | DL73: CTB | DM73: 28.65
A74: 2 | B74: CTB071081-4 | C74: NORMAL | D74: CTBP | E74: CTB | F74: 46245 | G74: DQB8989 | H74: 41260803098929000606570010000719801003702978 | I74: 05094003000155 | J74: COLSON DO BRASIL LTDA | K74: RUA DAS PALMEIRAS 350 | L74: CAPELA VELHA | M74: 002 | N74: ARAUCARIA | O74: PR | P74: 83705-500 | Q74: 05094003000155 | R74: COLSON DO BRASIL LTDA | S74: ARAUCARIA | T74: PR | U74: 05094003000155 | V74: COLSON DO BRASIL LTDA | W74: RUA DAS PALMEIRAS 350 | X74: CAPELA VELHA | Y74: ARAUCARIA | Z74: PR | AA74: (41 ) 38887555 | AC74: 10313426000159 | AD74: FORM E ART IND.COM.ART.METALIC | AE74: 09 GR2 | AF74: SPOP | AG74: ITAQUAQUECETUBA | AH74: SP | AI74: 10313426000159 | AJ74: FORM E ART IND.COM.ART.METALIC | AK74: ITAQUAQUECETUBA | AL74: SP | AM74: SPO | AN74: 000189257 | AO74: 1045.2 | AP74: 0 | AQ74: 80 | AR74: 0 | AS74: CP | AT74: LIQUIDADO | AU74: 46260 | AV74: 1411.06 | AW74: 001-DIVERSOS | AX74: 001-DIVERSOS | AY74: 44224 | AZ74: COMBINADA | BA74: CO3365274 | BB74: 1411.06 | BC74: 1241.73 | BD74: 1411.06 | BE74: 169.33 | BF74: 0.12 | BG74: 0 | BH74: 1045.2 | BI74: 930.12 | BJ74: 0 | BK74: 17 | BL74: 0 | BM74: 9.76 | BN74: 66.34 | BO74: 60.5 | BP74: 3.23 | BQ74: 0 | BR74: 0 | BS74: 0 | BT74: 0 | BU74: 0 | BV74: 0 | BW74: 0 | BX74: 0 | BY74: 0 | BZ74: 0 | CA74: 154.78 | CB74: CTBP | CC74: SPOP | CD74: 3882.94 | CE74: 0 | CF74: 0 | CG74: 0 | CH74: 0 | CI74: 0 | CJ74: 0 | CK74: 0 | CN74: 0 | CO74: 0 | CP74: 0 | CQ74: 0 | CR74: 0 | CS74: 0 | CT74: 0 | CU74: 156.78 | CV74: MAPA: 161 | CW74: 0 | CY74: 188.14 | CZ74: MAPA: 161 | DA74: 0 | DE74: 0 | DF74: A. | DG74: PR | DH74: ARAUCARIA | DI74: 9026067267 | DJ74: (41 ) 38887555 | DK74: 0 | DL74: CTB | DM74: 169.33
A75: 2 | B75: CTB071082-2 | C75: NORMAL | D75: CTBP | E75: CTB | F75: 46245 | G75: DQB8989 | H75: 41260803098929000606570010000719711003702880 | I75: 05094003000155 | J75: COLSON DO BRASIL LTDA | K75: RUA DAS PALMEIRAS 350 | L75: CAPELA VELHA | M75: 002 | N75: ARAUCARIA | O75: PR | P75: 83705-500 | Q75: 05094003000155 | R75: COLSON DO BRASIL LTDA | S75: ARAUCARIA | T75: PR | U75: 05094003000155 | V75: COLSON DO BRASIL LTDA | W75: RUA DAS PALMEIRAS 350 | X75: CAPELA VELHA | Y75: ARAUCARIA | Z75: PR | AA75: (41 ) 38887555 | AC75: 10418387000154 | AD75: AERORACK EQUIPAMENTOS INDUSTRIAIS E | AE75: 09 GR2 | AF75: SPOR | AG75: MOGI DAS CRUZES | AH75: SP | AI75: 10418387000154 | AJ75: AERORACK EQUIPAMENTOS INDUSTRIAIS E | AK75: MOGI DAS CRUZES | AL75: SP | AM75: SPO | AN75: 000189269 | AO75: 130.05 | AP75: 0 | AQ75: 12 | AR75: 0 | AS75: CP | AT75: LIQUIDADO | AU75: 46260 | AV75: 279.39 | AW75: 001-DIVERSOS | AX75: 001-DIVERSOS | AY75: 10258.19 | AZ75: COMBINADA | BA75: CO3365266 | BB75: 279.39 | BC75: 245.86 | BD75: 279.39 | BE75: 33.53 | BF75: 0.12 | BG75: 0 | BH75: 130.05 | BI75: 153.58 | BJ75: 0 | BK75: 17 | BL75: 0 | BM75: 9.76 | BN75: 15.39 | BO75: 11 | BP75: 3.23 | BQ75: 0 | BR75: 0 | BS75: 0 | BT75: 0 | BU75: 0 | BV75: 0 | BW75: 0 | BX75: 0 | BY75: 0 | BZ75: 0 | CA75: 35.9 | CB75: CTBP | CC75: SPOR | CD75: 483.37 | CE75: 0 | CF75: 0 | CG75: 0 | CH75: 0 | CI75: 0 | CJ75: 0 | CK75: 0 | CN75: 0 | CO75: 0 | CP75: 0 | CQ75: 0 | CR75: 0 | CS75: 0 | CT75: 0 | CU75: 19.51 | CV75: MAPA: 161 | CW75: 0 | CY75: 23.41 | CZ75: MAPA: 161 | DA75: 0 | DE75: 0 | DF75: A. | DG75: PR | DH75: ARAUCARIA | DI75: 9026067267 | DJ75: (41 ) 38887555 | DK75: 0 | DL75: CTB | DM75: 33.53
A76: 2 | B76: CTB071083-1 | C76: NORMAL | D76: CTBP | E76: CTB | F76: 46245 | G76: DQB8989 | H76: 41260803098929000606570010000719811003702983 | I76: 05094003000155 | J76: COLSON DO BRASIL LTDA | K76: RUA DAS PALMEIRAS 350 | L76: CAPELA VELHA | M76: 002 | N76: ARAUCARIA | O76: PR | P76: 83705-500 | Q76: 05094003000155 | R76: COLSON DO BRASIL LTDA | S76: ARAUCARIA | T76: PR | U76: 05094003000155 | V76: COLSON DO BRASIL LTDA | W76: RUA DAS PALMEIRAS 350 | X76: CAPELA VELHA | Y76: ARAUCARIA | Z76: PR | AA76: (41 ) 38887555 | AC76: 07156884000117 | AD76: GERALDO MAGELA DE ALMEIDA CALCADOS | AE76: 11 ABCD | AF76: SPOP | AG76: SAO CAETANO DO SUL | AH76: SP | AI76: 07156884000117 | AJ76: GERALDO MAGELA DE ALMEIDA CALCADOS | AK76: SAO CAETANO DO SUL | AL76: SP | AM76: SPO | AN76: 000189219 | AO76: 33.62 | AP76: 0 | AQ76: 3 | AR76: 0 | AS76: CP | AT76: LIQUIDADO | AU76: 46260 | AV76: 113.56 | AW76: 001-DIVERSOS | AX76: 001-DIVERSOS | AY76: 1528.28 | AZ76: COMBINADA | BA76: CO3365274 | BB76: 113.56 | BC76: 99.93 | BD76: 113.56 | BE76: 13.63 | BF76: 0.12 | BG76: 0 | BH76: 33.62 | BI76: 56.8 | BJ76: 0 | BK76: 17 | BL76: 0 | BM76: 9.76 | BN76: 2.29 | BO76: 5.5 | BP76: 3.23 | BQ76: 0 | BR76: 0 | BS76: 0 | BT76: 0 | BU76: 0 | BV76: 0 | BW76: 0 | BX76: 0 | BY76: 0 | BZ76: 0 | CA76: 5.35 | CB76: CTBP | CC76: SPOP | CD76: 373.31 | CE76: 0 | CF76: 0 | CG76: 0 | CH76: 0 | CI76: 0 | CJ76: 0 | CK76: 0 | CN76: 0 | CO76: 0 | CP76: 0 | CQ76: 0 | CR76: 0 | CS76: 0 | CT76: 0 | CU76: 12 | CV76: MAPA: 161 | CW76: 0 | CY76: 18 | CZ76: MAPA: 161 | DA76: 0 | DE76: 0 | DF76: A. | DG76: PR | DH76: ARAUCARIA | DI76: 9026067267 | DJ76: (41 ) 38887555 | DK76: 0 | DL76: CTB | DM76: 13.63
A77: 2 | B77: CTB071084-9 | C77: NORMAL | D77: CTBP | E77: CTB | F77: 46245 | G77: DQB8989 | H77: 41260803098929000606570010000719701003702874 | I77: 05094003000155 | J77: COLSON DO BRASIL LTDA | K77: RUA DAS PALMEIRAS 350 | L77: CAPELA VELHA | M77: 002 | N77: ARAUCARIA | O77: PR | P77: 83705-500 | Q77: 05094003000155 | R77: COLSON DO BRASIL LTDA | S77: ARAUCARIA | T77: PR | U77: 05094003000155 | V77: COLSON DO BRASIL LTDA | W77: RUA DAS PALMEIRAS 350 | X77: CAPELA VELHA | Y77: ARAUCARIA | Z77: PR | AA77: (41 ) 38887555 | AC77: 49911812000188 | AD77: TEKNOVATION EQUIPAMENTOS E SERVICOS | AE77: 06 ZONA SUL | AF77: SPOP | AG77: SAO PAULO | AH77: SP | AI77: 49911812000188 | AJ77: TEKNOVATION EQUIPAMENTOS E SERVICOS | AK77: SAO PAULO | AL77: SP | AM77: SPO | AN77: 000189240 | AO77: 40.3 | AP77: 0 | AQ77: 6 | AR77: 0 | AS77: CP | AT77: LIQUIDADO | AU77: 46260 | AV77: 113.42 | AW77: 001-DIVERSOS | AX77: 001-DIVERSOS | AY77: 1503.59 | AZ77: COMBINADA | BA77: CO3365274 | BB77: 113.42 | BC77: 99.81 | BD77: 113.42 | BE77: 13.61 | BF77: 0.12 | BG77: 0 | BH77: 40.3 | BI77: 56.8 | BJ77: 0 | BK77: 17 | BL77: 0 | BM77: 9.76 | BN77: 2.26 | BO77: 5.5 | BP77: 3.23 | BQ77: 0 | BR77: 0 | BS77: 0 | BT77: 0 | BU77: 0 | BV77: 0 | BW77: 0 | BX77: 0 | BY77: 0 | BZ77: 0 | CA77: 5.26 | CB77: CTBP | CC77: SPOP | CD77: 373.09 | CE77: 0 | CF77: 0 | CG77: 0 | CH77: 0 | CI77: 0 | CJ77: 0 | CK77: 0 | CN77: 0 | CO77: 0 | CP77: 0 | CQ77: 0 | CR77: 0 | CS77: 0 | CT77: 0 | CU77: 12 | CV77: MAPA: 161 | CW77: 0 | CY77: 18 | CZ77: MAPA: 161 | DA77: 0 | DE77: 0 | DF77: A. | DG77: PR | DH77: ARAUCARIA | DI77: 9026067267 | DJ77: (41 ) 38887555 | DK77: 0 | DL77: CTB | DM77: 13.61
A78: 2 | B78: CTB071141-1 | C78: NORMAL | D78: CTBP | E78: CTB | F78: 46246 | G78: DQB8989 | H78: 41260803098929000606570010000720411003710528 | I78: 05094003000155 | J78: COLSON DO BRASIL LTDA | K78: RUA DAS PALMEIRAS 350 | L78: CAPELA VELHA | M78: 002 | N78: ARAUCARIA | O78: PR | P78: 83705-500 | Q78: 05094003000155 | R78: COLSON DO BRASIL LTDA | S78: ARAUCARIA | T78: PR | U78: 05094003000155 | V78: COLSON DO BRASIL LTDA | W78: RUA DAS PALMEIRAS 350 | X78: CAPELA VELHA | Y78: ARAUCARIA | Z78: PR | AA78: (41 ) 38887555 | AC78: 16943655000133 | AD78: STREET INOX COMERCIO DE ARTIGOS PAR | AE78: 133 | AF78: PSPP | AG78: ELIAS FAUSTO | AH78: SP | AI78: 16943655000133 | AJ78: STREET INOX COMERCIO DE ARTIGOS PAR | AK78: ELIAS FAUSTO | AL78: SP | AM78: PSP | AN78: 000189313 | AO78: 1188.4 | AP78: 0 | AQ78: 118 | AR78: 0 | AS78: CP | AT78: LIQUIDADO | AU78: 46260 | AV78: 1537.01 | AW78: 001-DIVERSOS | AX78: 001-DIVERSOS | AY78: 30557.03 | AZ78: COMBINADA | BA78: CO3365277 | BB78: 1537.01 | BC78: 1352.57 | BD78: 1537.01 | BE78: 184.44 | BF78: 0.12 | BG78: 0 | BH78: 1188.4 | BI78: 1103.79 | BJ78: 0 | BK78: 17 | BL78: 0 | BM78: 9.76 | BN78: 45.84 | BO78: 66 | BP78: 3.23 | BQ78: 0 | BR78: 0 | BS78: 0 | BT78: 0 | BU78: 0 | BV78: 0 | BW78: 0 | BX78: 0 | BY78: 0 | BZ78: 0 | CA78: 106.95 | CB78: CTBP | CC78: SAOI | CD78: 4206.38 | CE78: 0 | CF78: 0 | CG78: 0 | CH78: 0 | CI78: 0 | CJ78: 0 | CK78: 0 | CN78: 0 | CO78: 0 | CP78: 0 | CQ78: 0 | CR78: 0 | CS78: 0 | CT78: 0 | CU78: 178.26 | CV78: MAPA: 161 | CW78: 0 | CY78: 501.36 | CZ78: MAPA: 162 | DA78: =CY78 -> 501.36 | DE78: 0 | DF78: A. | DG78: PR | DH78: ARAUCARIA | DI78: 9026067267 | DJ78: (41 ) 38887555 | DK78: 0 | DL78: CTB | DM78: 31.37
A79: 2 | B79: CTB071140-3 | C79: NORMAL | D79: CTBP | E79: CTB | F79: 46246 | G79: DQB8989 | H79: 41260803098929000606570010000720391003710503 | I79: 05094003000155 | J79: COLSON DO BRASIL LTDA | K79: RUA DAS PALMEIRAS 350 | L79: CAPELA VELHA | M79: 002 | N79: ARAUCARIA | O79: PR | P79: 83705-500 | Q79: 05094003000155 | R79: COLSON DO BRASIL LTDA | S79: ARAUCARIA | T79: PR | U79: 05094003000155 | V79: COLSON DO BRASIL LTDA | W79: RUA DAS PALMEIRAS 350 | X79: CAPELA VELHA | Y79: ARAUCARIA | Z79: PR | AA79: (41 ) 38887555 | AC79: 10372459000170 | AD79: R AMICHI IND E COM DE CARRINHO | AE79: CAX DUQUE DE CAXIAS | AF79: RJOP | AG79: DUQUE DE CAXIAS | AH79: RJ | AI79: 10372459000170 | AJ79: R AMICHI IND E COM DE CARRINHO | AK79: DUQUE DE CAXIAS | AL79: RJ | AM79: RJO | AN79: 000189377 | AO79: 56.3 | AP79: 0 | AQ79: 5 | AR79: 0 | AS79: CP | AT79: LIQUIDADO | AU79: 46260 | AV79: 143.43 | AW79: 001-DIVERSOS | AX79: 001-DIVERSOS | AY79: 1625.98 | AZ79: COMBINADA | BA79: CO3365267 | BB79: 143.43 | BC79: 126.22 | BD79: 143.43 | BE79: 17.21 | BF79: 0.12 | BG79: 0 | BH79: 56.3 | BI79: 82.6 | BJ79: 0 | BK79: 17 | BL79: 0 | BM79: 9.76 | BN79: 2.44 | BO79: 5.5 | BP79: 3.23 | BQ79: 0 | BR79: 0 | BS79: 0 | BT79: 0 | BU79: 0 | BV79: 0 | BW79: 0 | BX79: 0 | BY79: 0 | BZ79: 0 | CA79: 5.69 | CB79: CTBP | CC79: RJOP | CD79: 374.3 | CE79: 0 | CF79: 0 | CG79: 0 | CH79: 0 | CI79: 0 | CJ79: 0 | CK79: 0 | CN79: 0 | CO79: 0 | CP79: 0 | CQ79: 0 | CR79: 0 | CS79: 0 | CT79: 0 | CU79: 12 | CV79: MAPA: 161 | CW79: 0 | CY79: 18 | CZ79: MAPA: 161 | DA79: 0 | DE79: 0 | DF79: A. | DG79: PR | DH79: ARAUCARIA | DI79: 9026067267 | DJ79: (41 ) 38887555 | DK79: 0 | DL79: CTB | DM79: 17.21
A80: 2 | B80: CTB071365-1 | C80: NORMAL | D80: CTBP | E80: CTB | F80: 46251 | G80: DQB8989 | H80: 41260803098929000606570010000722681003735541 | I80: 05094003000155 | J80: COLSON DO BRASIL LTDA | K80: RUA DAS PALMEIRAS 350 | L80: CAPELA VELHA | M80: 002 | N80: ARAUCARIA | O80: PR | P80: 83705-500 | Q80: 05094003000155 | R80: COLSON DO BRASIL LTDA | S80: ARAUCARIA | T80: PR | U80: 05094003000155 | V80: COLSON DO BRASIL LTDA | W80: RUA DAS PALMEIRAS 350 | X80: CAPELA VELHA | Y80: ARAUCARIA | Z80: PR | AA80: (41 ) 38887555 | AC80: 23476033001007 | AD80: BMB MATERIAL DE CONSTRUCAO SA | AE80: 134 | AF80: PSPP | AG80: PIRACICABA | AH80: SP | AI80: 23476033001007 | AJ80: BMB MATERIAL DE CONSTRUCAO SA | AK80: PIRACICABA | AL80: SP | AM80: PSP | AN80: 000189565 | AO80: 98.675 | AP80: 0 | AQ80: 8 | AR80: 0 | AS80: CP | AT80: LIQUIDADO | AU80: 46267 | AV80: 495.59 | AW80: 001-DIVERSOS | AX80: 054-PNEUS E CAMARAS DE AR | AY80: 3306.35 | AZ80: COMBINADA | BA80: CO3365277 | BB80: 495.59 | BC80: 436.12 | BD80: 495.59 | BE80: 59.47 | BF80: 0.12 | BG80: 0 | BH80: 98.675 | BI80: 134.1 | BJ80: 0 | BK80: 17 | BL80: 0 | BM80: 9.76 | BN80: 4.96 | BO80: 5.5 | BP80: 3.23 | BQ80: 0 | BR80: 0 | BS80: 0 | BT80: 0 | BU80: 0 | BV80: 0 | BW80: 0 | BX80: 250 | BY80: 0 | BZ80: 0 | CA80: 11.57 | CB80: CTBP | CC80: SAOI | CD80: 407.69 | CE80: 0 | CF80: 0 | CG80: 0 | CH80: 0 | CI80: 0 | CJ80: 0 | CK80: 0 | CN80: 0 | CO80: 0 | CP80: 0 | CQ80: 0 | CR80: 0 | CS80: 0 | CT80: 0 | CU80: 14.8 | CV80: MAPA: 162 | CW80: 0 | CY80: 231 | CZ80: MAPA: 162 | DA80: =CY80 -> 231 | DE80: 0 | DF80: A. | DG80: PR | DH80: ARAUCARIA | DI80: 9026067267 | DJ80: (41 ) 38887555 | DK80: 0 | DL80: CTB | DM80: 184.44
A81: 2 | B81: CTB071142-0 | C81: NORMAL | D81: CTBP | E81: CTB | F81: 46246 | G81: DQB8989 | H81: 41260803098929000606570010000720361003710471 | I81: 05094003000155 | J81: COLSON DO BRASIL LTDA | K81: RUA DAS PALMEIRAS 350 | L81: CAPELA VELHA | M81: 002 | N81: ARAUCARIA | O81: PR | P81: 83705-500 | Q81: 05094003000155 | R81: COLSON DO BRASIL LTDA | S81: ARAUCARIA | T81: PR | U81: 05094003000155 | V81: COLSON DO BRASIL LTDA | W81: RUA DAS PALMEIRAS 350 | X81: CAPELA VELHA | Y81: ARAUCARIA | Z81: PR | AA81: (41 ) 38887555 | AC81: 48880720000115 | AD81: MOBSTEEL EQUIPAMENTOS INOXIDAV | AE81: 05 ZONA LESTE | AF81: SPOP | AG81: SAO PAULO | AH81: SP | AI81: 48880720000115 | AJ81: MOBSTEEL EQUIPAMENTOS INOXIDAV | AK81: SAO PAULO | AL81: SP | AM81: SPO | AN81: 000189314 | AO81: 35.68 | AP81: 0 | AQ81: 4 | AR81: 0 | AS81: CP | AT81: LIQUIDADO | AU81: 46260 | AV81: 113.82 | AW81: 001-DIVERSOS | AX81: 001-DIVERSOS | AY81: 1575.11 | AZ81: COMBINADA | BA81: CO3365274 | BB81: 113.82 | BC81: 100.16 | BD81: 113.82 | BE81: 13.66 | BF81: 0.12 | BG81: 0 | BH81: 35.68 | BI81: 56.8 | BJ81: 0 | BK81: 17 | BL81: 0 | BM81: 9.76 | BN81: 2.36 | BO81: 5.5 | BP81: 3.23 | BQ81: 0 | BR81: 0 | BS81: 0 | BT81: 0 | BU81: 0 | BV81: 0 | BW81: 0 | BX81: 0 | BY81: 0 | BZ81: 0 | CA81: 5.51 | CB81: CTBP | CC81: SPOP | CD81: 373.79 | CE81: 0 | CF81: 0 | CG81: 0 | CH81: 0 | CI81: 0 | CJ81: 0 | CK81: 0 | CN81: 0 | CO81: 0 | CP81: 0 | CQ81: 0 | CR81: 0 | CS81: 0 | CT81: 0 | CU81: 12 | CV81: MAPA: 161 | CW81: 0 | CY81: 18 | CZ81: MAPA: 161 | DA81: 0 | DE81: 0 | DF81: A. | DG81: PR | DH81: ARAUCARIA | DI81: 9026067267 | DJ81: (41 ) 38887555 | DK81: 0 | DL81: CTB | DM81: 13.66
A82: 2 | B82: CTB071143-8 | C82: NORMAL | D82: CTBP | E82: CTB | F82: 46246 | G82: DQB8989 | H82: 41260803098929000606570010000720351003710466 | I82: 05094003000155 | J82: COLSON DO BRASIL LTDA | K82: RUA DAS PALMEIRAS 350 | L82: CAPELA VELHA | M82: 002 | N82: ARAUCARIA | O82: PR | P82: 83705-500 | Q82: 05094003000155 | R82: COLSON DO BRASIL LTDA | S82: ARAUCARIA | T82: PR | U82: 05094003000155 | V82: COLSON DO BRASIL LTDA | W82: RUA DAS PALMEIRAS 350 | X82: CAPELA VELHA | Y82: ARAUCARIA | Z82: PR | AA82: (41 ) 38887555 | AC82: 14458674000300 | AD82: FLUZAO ATACADAO DA CONSTRUCAO LTDA | AE82: RIO RIO DE JANEIRO | AF82: RJOP | AG82: RIO DE JANEIRO | AH82: RJ | AI82: 14458674000300 | AJ82: FLUZAO ATACADAO DA CONSTRUCAO LTDA | AK82: RIO DE JANEIRO | AL82: RJ | AM82: RJO | AN82: 000189284 | AO82: 808.331 | AP82: 0 | AQ82: 75 | AR82: 0 | AS82: CP | AT82: LIQUIDADO | AU82: 46260 | AV82: 1328.17 | AW82: 001-DIVERSOS | AX82: 054-PNEUS E CAMARAS DE AR | AY82: 22343.36 | AZ82: COMBINADA | BA82: CO3365267 | BB82: 1328.17 | BC82: 1168.79 | BD82: 1328.17 | BE82: 159.38 | BF82: 0.12 | BG82: 0 | BH82: 808.331 | BI82: 727.58 | BJ82: 0 | BK82: 17 | BL82: 0 | BM82: 9.76 | BN82: 33.52 | BO82: 49.5 | BP82: 3.23 | BQ82: 0 | BR82: 0 | BS82: 0 | BT82: 0 | BU82: 0 | BV82: 0 | BW82: 0 | BX82: 250 | BY82: 0 | BZ82: 0 | CA82: 78.2 | CB82: CTBP | CC82: RJOP | CD82: 2769.91 | CE82: 0 | CF82: 0 | CG82: 0 | CH82: 0 | CI82: 0 | CJ82: 0 | CK82: 0 | CN82: 0 | CO82: 0 | CP82: 0 | CQ82: 0 | CR82: 0 | CS82: 0 | CT82: 0 | CU82: 121.25 | CV82: MAPA: 161 | CW82: 0 | CY82: 145.5 | CZ82: MAPA: 162 | DA82: 0 | DE82: 0 | DF82: A. | DG82: PR | DH82: ARAUCARIA | DI82: 9026067267 | DJ82: (41 ) 38887555 | DK82: 0 | DL82: CTB | DM82: 159.38
A83: 2 | B83: CTB071144-6 | C83: NORMAL | D83: CTBP | E83: CTB | F83: 46246 | G83: DQB8989 | H83: 41260803098929000606570010000720381003710492 | I83: 05094003000155 | J83: COLSON DO BRASIL LTDA | K83: RUA DAS PALMEIRAS 350 | L83: CAPELA VELHA | M83: 002 | N83: ARAUCARIA | O83: PR | P83: 83705-500 | Q83: 05094003000155 | R83: COLSON DO BRASIL LTDA | S83: ARAUCARIA | T83: PR | U83: 05094003000155 | V83: COLSON DO BRASIL LTDA | W83: RUA DAS PALMEIRAS 350 | X83: CAPELA VELHA | Y83: ARAUCARIA | Z83: PR | AA83: (41 ) 38887555 | AC83: 14458674000149 | AD83: FLUZAO ATACADAO DA CONSTR LTDA | AE83: RIO RIO DE JANEIRO | AF83: RJOP | AG83: RIO DE JANEIRO | AH83: RJ | AI83: 14458674000149 | AJ83: FLUZAO ATACADAO DA CONSTR LTDA | AK83: RIO DE JANEIRO | AL83: RJ | AM83: RJO | AN83: 000189282 | AO83: 930.236 | AP83: 0 | AQ83: 80 | AR83: 0 | AS83: CP | AT83: LIQUIDADO | AU83: 46260 | AV83: 1467.95 | AW83: 001-DIVERSOS | AX83: 054-PNEUS E CAMARAS DE AR | AY83: 23899.67 | AZ83: COMBINADA | BA83: CO3365267 | BB83: 1467.95 | BC83: 1291.8 | BD83: 1467.95 | BE83: 176.15 | BF83: 0.12 | BG83: 0 | BH83: 930.236 | BI83: 837.31 | BJ83: 0 | BK83: 17 | BL83: 0 | BM83: 9.76 | BN83: 35.85 | BO83: 55 | BP83: 3.23 | BQ83: 0 | BR83: 0 | BS83: 0 | BT83: 0 | BU83: 0 | BV83: 0 | BW83: 0 | BX83: 250 | BY83: 0 | BZ83: 0 | CA83: 83.65 | CB83: CTBP | CC83: RJOP | CD83: 3216.37 | CE83: 0 | CF83: 0 | CG83: 0 | CH83: 0 | CI83: 0 | CJ83: 0 | CK83: 0 | CN83: 0 | CO83: 0 | CP83: 0 | CQ83: 0 | CR83: 0 | CS83: 0 | CT83: 0 | CU83: 139.54 | CV83: MAPA: 161 | CW83: 0 | CY83: 167.44 | CZ83: MAPA: 162 | DA83: 0 | DE83: 0 | DF83: A. | DG83: PR | DH83: ARAUCARIA | DI83: 9026067267 | DJ83: (41 ) 38887555 | DK83: 0 | DL83: CTB | DM83: 176.15
A84: 2 | B84: CTB071145-4 | C84: NORMAL | D84: CTBP | E84: CTB | F84: 46246 | G84: DQB8989 | H84: 41260803098929000606570010000720401003710512 | I84: 05094003000155 | J84: COLSON DO BRASIL LTDA | K84: RUA DAS PALMEIRAS 350 | L84: CAPELA VELHA | M84: 002 | N84: ARAUCARIA | O84: PR | P84: 83705-500 | Q84: 05094003000155 | R84: COLSON DO BRASIL LTDA | S84: ARAUCARIA | T84: PR | U84: 05094003000155 | V84: COLSON DO BRASIL LTDA | W84: RUA DAS PALMEIRAS 350 | X84: CAPELA VELHA | Y84: ARAUCARIA | Z84: PR | AA84: (41 ) 38887555 | AC84: 00783986000113 | AD84: TRIMTEC LTDA | AE84: 122 | AF84: SJKP | AG84: CACAPAVA | AH84: SP | AI84: 00783986000113 | AJ84: TRIMTEC LTDA | AK84: CACAPAVA | AL84: SP | AM84: SJK | AN84: 000189325 | AO84: 105.7 | AP84: 0 | AQ84: 8 | AR84: 0 | AS84: CP | AT84: LIQUIDADO | AU84: 46260 | AV84: 515.1 | AW84: 001-DIVERSOS | AX84: 001-DIVERSOS | AY84: 12824.89 | AZ84: COMBINADA | BA84: CO3365277 | BB84: 515.1 | BC84: 453.29 | BD84: 515.1 | BE84: 61.81 | BF84: 0.12 | BG84: 0 | BH84: 105.7 | BI84: 98.17 | BJ84: 0 | BK84: 17 | BL84: 0 | BM84: 9.76 | BN84: 19.24 | BO84: 11 | BP84: 3.23 | BQ84: 0 | BR84: 0 | BS84: 0 | BT84: 0 | BU84: 0 | BV84: 0 | BW84: 0 | BX84: 250 | BY84: 0 | BZ84: 0 | CA84: 44.89 | CB84: CTBP | CC84: SAOI | CD84: 516.7 | CE84: 0 | CF84: 0 | CG84: 0 | CH84: 0 | CI84: 0 | CJ84: 0 | CK84: 0 | CN84: 0 | CO84: 0 | CP84: 0 | CQ84: 0 | CR84: 0 | CS84: 0 | CT84: 0 | CU84: 15.86 | CV84: MAPA: 161 | CW84: 0 | CY84: 200.82 | CZ84: FATURA: 27569 | DA84: 200.82 | DB84: 027569 | DE84: 0 | DF84: A. | DG84: PR | DH84: ARAUCARIA | DI84: 9026067267 | DJ84: (41 ) 38887555 | DK84: 0 | DL84: CTB | DM84: 61.81
A85: 2 | B85: CTB071146-2 | C85: NORMAL | D85: CTBP | E85: CTB | F85: 46246 | G85: DQB8989 | H85: 41260803098929000606570010000720371003710487 | I85: 05094003000155 | J85: COLSON DO BRASIL LTDA | K85: RUA DAS PALMEIRAS 350 | L85: CAPELA VELHA | M85: 002 | N85: ARAUCARIA | O85: PR | P85: 83705-500 | Q85: 05094003000155 | R85: COLSON DO BRASIL LTDA | S85: ARAUCARIA | T85: PR | U85: 05094003000155 | V85: COLSON DO BRASIL LTDA | W85: RUA DAS PALMEIRAS 350 | X85: CAPELA VELHA | Y85: ARAUCARIA | Z85: PR | AA85: (41 ) 38887555 | AC85: 02969264000183 | AD85: KAWAMAC INDUSTRIA E COMERCIO DE MAQUINAS LTDA EPP | AE85: 123 VILA IZABEL ARACILIA | AF85: SPOP | AG85: GUARULHOS | AH85: SP | AI85: 02969264000183 | AJ85: KAWAMAC INDUSTRIA E COMERCIO DE MAQUINAS LTDA EPP | AK85: GUARULHOS | AL85: SP | AM85: SPO | AN85: 000189338 | AO85: 33.264 | AP85: 0 | AQ85: 4 | AR85: 0 | AS85: CP | AT85: LIQUIDADO | AU85: 46260 | AV85: 117.78 | AW85: 001-DIVERSOS | AX85: 001-DIVERSOS | AY85: 2271.66 | AZ85: COMBINADA | BA85: CO3365274 | BB85: 117.78 | BC85: 103.65 | BD85: 117.78 | BE85: 14.13 | BF85: 0.12 | BG85: 0 | BH85: 33.264 | BI85: 56.8 | BJ85: 0 | BK85: 17 | BL85: 0 | BM85: 9.76 | BN85: 3.41 | BO85: 5.5 | BP85: 3.23 | BQ85: 0 | BR85: 0 | BS85: 0 | BT85: 0 | BU85: 0 | BV85: 0 | BW85: 0 | BX85: 0 | BY85: 0 | BZ85: 0 | CA85: 7.95 | CB85: CTBP | CC85: SPOP | CD85: 380.67 | CE85: 0 | CF85: 0 | CG85: 0 | CH85: 0 | CI85: 0 | CJ85: 0 | CK85: 0 | CN85: 0 | CO85: 0 | CP85: 0 | CQ85: 0 | CR85: 0 | CS85: 0 | CT85: 0 | CU85: 12 | CV85: MAPA: 161 | CW85: 0 | CY85: 18 | CZ85: MAPA: 161 | DA85: 0 | DE85: 0 | DF85: A. | DG85: PR | DH85: ARAUCARIA | DI85: 9026067267 | DJ85: (41 ) 38887555 | DK85: 0 | DL85: CTB | DM85: 14.13
A86: 2 | B86: CTB071147-1 | C86: NORMAL | D86: CTBP | E86: CTB | F86: 46246 | G86: DQB8989 | H86: 41260803098929000606570010000720421003710533 | I86: 05094003000155 | J86: COLSON DO BRASIL LTDA | K86: RUA DAS PALMEIRAS 350 | L86: CAPELA VELHA | M86: 002 | N86: ARAUCARIA | O86: PR | P86: 83705-500 | Q86: 05094003000155 | R86: COLSON DO BRASIL LTDA | S86: ARAUCARIA | T86: PR | U86: 05094003000155 | V86: COLSON DO BRASIL LTDA | W86: RUA DAS PALMEIRAS 350 | X86: CAPELA VELHA | Y86: ARAUCARIA | Z86: PR | AA86: (41 ) 38887555 | AC86: 14702985000101 | AD86: TMS IMPORTADORA E COMERCIO LTDA | AE86: SJK SAO JOSE DOS CAMPOS | AF86: SJKP | AG86: SAO JOSE DOS CAMPOS | AH86: SP | AI86: 14702985000101 | AJ86: TMS IMPORTADORA E COMERCIO LTDA | AK86: SAO JOSE DOS CAMPOS | AL86: SP | AM86: SJK | AN86: 000189324 | AO86: 105.7 | AP86: 0 | AQ86: 8 | AR86: 0 | AS86: CP | AT86: LIQUIDADO | AU86: 46260 | AV86: 231.01 | AW86: 001-DIVERSOS | AX86: 001-DIVERSOS | AY86: 12824.89 | AZ86: COMBINADA | BA86: CO3365277 | BB86: 231.01 | BC86: 203.29 | BD86: 231.01 | BE86: 27.72 | BF86: 0.12 | BG86: 0 | BH86: 105.7 | BI86: 98.17 | BJ86: 0 | BK86: 17 | BL86: 0 | BM86: 9.76 | BN86: 19.24 | BO86: 11 | BP86: 3.23 | BQ86: 0 | BR86: 0 | BS86: 0 | BT86: 0 | BU86: 0 | BV86: 0 | BW86: 0 | BX86: 0 | BY86: 0 | BZ86: 0 | CA86: 44.89 | CB86: CTBP | CC86: SAOI | CD86: 516.69 | CE86: 0 | CF86: 0 | CG86: 0 | CH86: 0 | CI86: 0 | CJ86: 0 | CK86: 0 | CN86: 0 | CO86: 0 | CP86: 0 | CQ86: 0 | CR86: 0 | CS86: 0 | CT86: 0 | CU86: 15.86 | CV86: MAPA: 161 | CW86: 0 | CY86: 50.82 | CZ86: FATURA: 27569 | DA86: 50.82 | DB86: 027569 | DE86: 0 | DF86: A. | DG86: PR | DH86: ARAUCARIA | DI86: 9026067267 | DJ86: (41 ) 38887555 | DK86: 0 | DL86: CTB | DM86: 27.72
A87: 2 | B87: CTB071197-7 | C87: NORMAL | D87: CTBP | E87: CTB | F87: 46247 | G87: AFF1761 | H87: 41260803098929000606570010000721091003718799 | I87: 05094003000155 | J87: COLSON DO BRASIL LTDA | K87: RUA DAS PALMEIRAS 350 | L87: CAPELA VELHA | M87: 002 | N87: ARAUCARIA | O87: PR | P87: 83705-500 | Q87: 05094003000155 | R87: COLSON DO BRASIL LTDA | S87: ARAUCARIA | T87: PR | U87: 05094003000155 | V87: COLSON DO BRASIL LTDA | W87: RUA DAS PALMEIRAS 350 | X87: CAPELA VELHA | Y87: ARAUCARIA | Z87: PR | AA87: (41 ) 38887555 | AC87: 23476033000531 | AD87: BMB MATERIAL DE CONSTRUCAO S.A | AE87: RIO RIO DE JANEIRO | AF87: RJOP | AG87: RIO DE JANEIRO | AH87: RJ | AI87: 23476033000531 | AJ87: BMB MATERIAL DE CONSTRUCAO S.A | AK87: RIO DE JANEIRO | AL87: RJ | AM87: RJO | AN87: 000189405 | AO87: 79.925 | AP87: 0 | AQ87: 8 | AR87: 0 | AS87: CP | AT87: LIQUIDADO | AU87: 46260 | AV87: 452.25 | AW87: 001-DIVERSOS | AX87: 054-PNEUS E CAMARAS DE AR | AY87: 2457.42 | AZ87: COMBINADA | BA87: CO3365267 | BB87: 452.25 | BC87: 397.98 | BD87: 452.25 | BE87: 54.27 | BF87: 0.12 | BG87: 0 | BH87: 79.925 | BI87: 100.2 | BJ87: 0 | BK87: 17 | BL87: 0 | BM87: 9.76 | BN87: 3.69 | BO87: 5.5 | BP87: 3.23 | BQ87: 0 | BR87: 0 | BS87: 0 | BT87: 0 | BU87: 0 | BV87: 0 | BW87: 0 | BX87: 250 | BY87: 0 | BZ87: 0 | CA87: 8.6 | CB87: CTBP | CC87: RJOP | CD87: 395.39 | CE87: 0 | CF87: 0 | CG87: 0 | CH87: 0 | CI87: 0 | CJ87: 0 | CK87: 0 | CN87: 0 | CO87: 0 | CP87: 0 | CQ87: 0 | CR87: 0 | CS87: 0 | CT87: 0 | CU87: 12 | CV87: MAPA: 161 | CW87: 0 | CY87: 18 | CZ87: MAPA: 162 | DA87: 0 | DE87: 0 | DF87: A. | DG87: PR | DH87: ARAUCARIA | DI87: 9026067267 | DJ87: (41 ) 38887555 | DK87: 0 | DL87: CTB | DM87: 54.27
A88: 2 | B88: CTB071198-5 | C88: NORMAL | D88: CTBP | E88: CTB | F88: 46247 | G88: AFF1761 | H88: 41260803098929000606570010000721041003718717 | I88: 05094003000155 | J88: COLSON DO BRASIL LTDA | K88: RUA DAS PALMEIRAS 350 | L88: CAPELA VELHA | M88: 002 | N88: ARAUCARIA | O88: PR | P88: 83705-500 | Q88: 05094003000155 | R88: COLSON DO BRASIL LTDA | S88: ARAUCARIA | T88: PR | U88: 05094003000155 | V88: COLSON DO BRASIL LTDA | W88: RUA DAS PALMEIRAS 350 | X88: CAPELA VELHA | Y88: ARAUCARIA | Z88: PR | AA88: (41 ) 38887555 | AC88: 55571109000170 | AD88: RYNO LIFT SOLUCOES EM ELEVACAO E MOVIMENTACAO DE CARGAS LTDA | AE88: 148 | AF88: LFNP | AG88: JABOTICABAL | AH88: SP | AI88: 55571109000170 | AJ88: RYNO LIFT SOLUCOES EM ELEVACAO E MOVIMENTACAO DE CARGAS LTDA | AK88: JABOTICABAL | AL88: SP | AM88: LFN | AN88: 000189339 | AO88: 107.18 | AP88: 0 | AQ88: 8 | AR88: 0 | AS88: CP | AT88: LIQUIDADO | AU88: 46260 | AV88: 204.28 | AW88: 001-DIVERSOS | AX88: 001-DIVERSOS | AY88: 7846.14 | AZ88: COMBINADA | BA88: CO3365277 | BB88: 204.28 | BC88: 179.77 | BD88: 204.28 | BE88: 24.51 | BF88: 0.12 | BG88: 0 | BH88: 107.18 | BI88: 99.55 | BJ88: 0 | BK88: 17 | BL88: 0 | BM88: 9.76 | BN88: 11.77 | BO88: 11 | BP88: 3.23 | BQ88: 0 | BR88: 0 | BS88: 0 | BT88: 0 | BU88: 0 | BV88: 0 | BW88: 0 | BX88: 0 | BY88: 0 | BZ88: 0 | CA88: 27.46 | CB88: CTBP | CC88: SAOI | CD88: 473.53 | CE88: 0 | CF88: 0 | CG88: 0 | CH88: 0 | CI88: 0 | CJ88: 0 | CK88: 0 | CN88: 0 | CO88: 0 | CP88: 0 | CQ88: 0 | CR88: 0 | CS88: 0 | CT88: 0 | CU88: 16.08 | CV88: MAPA: 161 | CW88: 0 | CY88: 75.6 | CZ88: FATURA: 326288 | DA88: 99.07 | DB88: 326288 | DE88: 0 | DF88: A. | DG88: PR | DH88: ARAUCARIA | DI88: 9026067267 | DJ88: (41 ) 38887555 | DK88: 0 | DL88: CTB | DM88: 24.51
A89: 2 | B89: CTB071199-3 | C89: NORMAL | D89: CTBP | E89: CTB | F89: 46247 | G89: AFF1761 | H89: 41260803098929000606570010000721111003718819 | I89: 05094003000155 | J89: COLSON DO BRASIL LTDA | K89: RUA DAS PALMEIRAS 350 | L89: CAPELA VELHA | M89: 002 | N89: ARAUCARIA | O89: PR | P89: 83705-500 | Q89: 05094003000155 | R89: COLSON DO BRASIL LTDA | S89: ARAUCARIA | T89: PR | U89: 05094003000155 | V89: COLSON DO BRASIL LTDA | W89: RUA DAS PALMEIRAS 350 | X89: CAPELA VELHA | Y89: ARAUCARIA | Z89: PR | AA89: (41 ) 38887555 | AC89: 09580775000158 | AD89: SOLTEC RACKS LTDA | AE89: 11 ABCD | AF89: SPOP | AG89: RIBEIRAO PIRES | AH89: SP | AI89: 09580775000158 | AJ89: SOLTEC RACKS LTDA | AK89: RIBEIRAO PIRES | AL89: SP | AM89: SPO | AN89: 000189417 | AO89: 9.84 | AP89: 0 | AQ89: 1 | AR89: 0 | AS89: CP | AT89: LIQUIDADO | AU89: 46260 | AV89: 200.4 | AW89: 001-DIVERSOS | AX89: 001-DIVERSOS | AY89: 1373.89 | AZ89: COMBINADA | BA89: CO3365277 | BB89: 200.4 | BC89: 176.35 | BD89: 200.4 | BE89: 24.05 | BF89: 0.12 | BG89: 0 | BH89: 9.84 | BI89: 38.8 | BJ89: 0 | BK89: 17 | BL89: 0 | BM89: 9.76 | BN89: 2.25 | BO89: 5.5 | BP89: 3.23 | BQ89: 95 | BR89: 0 | BS89: 0 | BT89: 0 | BU89: 0 | BV89: 0 | BW89: 0 | BX89: 0 | BY89: 0 | BZ89: 0 | CA89: 4.81 | CB89: CTBP | CC89: SAOI | CD89: 381.5 | CE89: 0 | CF89: 0 | CG89: 0 | CH89: 0 | CI89: 0 | CJ89: 0 | CK89: 0 | CN89: 0 | CO89: 0 | CP89: 0 | CQ89: 0 | CR89: 0 | CS89: 0 | CT89: 0 | CU89: 12 | CV89: MAPA: 161 | CW89: 0 | CY89: 18 | CZ89: MAPA: 162 | DA89: 0 | DE89: 0 | DF89: A. | DG89: PR | DH89: ARAUCARIA | DI89: 9026067267 | DJ89: (41 ) 38887555 | DK89: 0 | DL89: CTB | DM89: 24.05
A90: 2 | B90: CTB071200-1 | C90: NORMAL | D90: CTBP | E90: CTB | F90: 46247 | G90: AFF1761 | H90: 41260803098929000606570010000721061003718746 | I90: 05094003000155 | J90: COLSON DO BRASIL LTDA | K90: RUA DAS PALMEIRAS 350 | L90: CAPELA VELHA | M90: 002 | N90: ARAUCARIA | O90: PR | P90: 83705-500 | Q90: 05094003000155 | R90: COLSON DO BRASIL LTDA | S90: ARAUCARIA | T90: PR | U90: 05094003000155 | V90: COLSON DO BRASIL LTDA | W90: RUA DAS PALMEIRAS 350 | X90: CAPELA VELHA | Y90: ARAUCARIA | Z90: PR | AA90: (41 ) 38887555 | AC90: 22571361000120 | AD90: REALMARKET COMERCIO DE MOVEIS EIREL | AE90: RIO RIO DE JANEIRO | AF90: RJOP | AG90: RIO DE JANEIRO | AH90: RJ | AI90: 22571361000120 | AJ90: REALMARKET COMERCIO DE MOVEIS EIREL | AK90: RIO DE JANEIRO | AL90: RJ | AM90: RJO | AN90: 000189387 | AO90: 131.4 | AP90: 0 | AQ90: 24 | AR90: 0 | AS90: CP | AT90: LIQUIDADO | AU90: 46260 | AV90: 207.55 | AW90: 001-DIVERSOS | AX90: 001-DIVERSOS | AY90: 4675.98 | AZ90: COMBINADA | BA90: CO3365267 | BB90: 207.55 | BC90: 182.64 | BD90: 207.55 | BE90: 24.91 | BF90: 0.12 | BG90: 0 | BH90: 131.4 | BI90: 118.27 | BJ90: 0 | BK90: 17 | BL90: 0 | BM90: 9.76 | BN90: 7.01 | BO90: 11 | BP90: 3.23 | BQ90: 0 | BR90: 0 | BS90: 0 | BT90: 0 | BU90: 0 | BV90: 0 | BW90: 0 | BX90: 0 | BY90: 0 | BZ90: 0 | CA90: 16.37 | CB90: CTBP | CC90: RJOP | CD90: 427.59 | CE90: 0 | CF90: 0 | CG90: 0 | CH90: 0 | CI90: 0 | CJ90: 0 | CK90: 0 | CN90: 0 | CO90: 0 | CP90: 0 | CQ90: 0 | CR90: 0 | CS90: 0 | CT90: 0 | CU90: 19.71 | CV90: MAPA: 161 | CW90: 0 | CY90: 23.65 | CZ90: MAPA: 162 | DA90: 0 | DE90: 0 | DF90: A. | DG90: PR | DH90: ARAUCARIA | DI90: 9026067267 | DJ90: (41 ) 38887555 | DK90: 0 | DL90: CTB | DM90: 24.91
A91: 2 | B91: CTB071369-4 | C91: NORMAL | D91: CTBP | E91: CTB | F91: 46251 | G91: DQB8989 | H91: 41260803098929000606570010000722721003735587 | I91: 05094003000155 | J91: COLSON DO BRASIL LTDA | K91: RUA DAS PALMEIRAS 350 | L91: CAPELA VELHA | M91: 002 | N91: ARAUCARIA | O91: PR | P91: 83705-500 | Q91: 05094003000155 | R91: COLSON DO BRASIL LTDA | S91: ARAUCARIA | T91: PR | U91: 05094003000155 | V91: COLSON DO BRASIL LTDA | W91: RUA DAS PALMEIRAS 350 | X91: CAPELA VELHA | Y91: ARAUCARIA | Z91: PR | AA91: (41 ) 38887555 | AC91: 26831868000127 | AD91: ELAINE APARECIDA PINHEIRO VIEIRA FE | AE91: 133 | AF91: PSPP | AG91: INDAIATUBA | AH91: SP | AI91: 26831868000127 | AJ91: ELAINE APARECIDA PINHEIRO VIEIRA FE | AK91: INDAIATUBA | AL91: SP | AM91: PSP | AN91: 000189561 | AO91: 120.25 | AP91: 0 | AQ91: 12 | AR91: 0 | AS91: CP | AT91: LIQUIDADO | AU91: 46267 | AV91: 234.68 | AW91: 001-DIVERSOS | AX91: 001-DIVERSOS | AY91: 4706.55 | AZ91: COMBINADA | BA91: CO3365266 | BB91: 234.68 | BC91: 206.52 | BD91: 234.68 | BE91: 28.16 | BF91: 0.12 | BG91: 0 | BH91: 120.25 | BI91: 142 | BJ91: 0 | BK91: 17 | BL91: 0 | BM91: 9.76 | BN91: 7.06 | BO91: 11 | BP91: 3.23 | BQ91: 0 | BR91: 0 | BS91: 0 | BT91: 0 | BU91: 0 | BV91: 0 | BW91: 0 | BX91: 0 | BY91: 0 | BZ91: 0 | CA91: 16.47 | CB91: CTBP | CC91: SPOR | CD91: 428.01 | CE91: 0 | CF91: 0 | CG91: 0 | CH91: 0 | CI91: 0 | CJ91: 0 | CK91: 0 | CN91: 0 | CO91: 0 | CP91: 0 | CQ91: 0 | CR91: 0 | CS91: 0 | CT91: 0 | CU91: 18.04 | CV91: MAPA: 162 | CW91: 0 | CY91: 74.1 | CZ91: MAPA: 162 | DA91: =CY91 -> 74.1 | DE91: 0 | DF91: A. | DG91: PR | DH91: ARAUCARIA | DI91: 9026067267 | DJ91: (41 ) 38887555 | DK91: 0 | DL91: CTB | DM91: 26.24
A92: 2 | B92: CTB071202-7 | C92: NORMAL | D92: CTBP | E92: CTB | F92: 46247 | G92: AFF1761 | H92: 41260803098929000606570010000721081003718775 | I92: 05094003000155 | J92: COLSON DO BRASIL LTDA | K92: RUA DAS PALMEIRAS 350 | L92: CAPELA VELHA | M92: 002 | N92: ARAUCARIA | O92: PR | P92: 83705-500 | Q92: 05094003000155 | R92: COLSON DO BRASIL LTDA | S92: ARAUCARIA | T92: PR | U92: 05094003000155 | V92: COLSON DO BRASIL LTDA | W92: RUA DAS PALMEIRAS 350 | X92: CAPELA VELHA | Y92: ARAUCARIA | Z92: PR | AA92: (41 ) 38887555 | AC92: 23476033000701 | AD92: BMB MATERIAL DE CONSTRUCAO S.A | AE92: SGN SAO GONACALO | AF92: RJOP | AG92: SAO GONCALO | AH92: RJ | AI92: 23476033000701 | AJ92: BMB MATERIAL DE CONSTRUCAO S.A | AK92: SAO GONCALO | AL92: RJ | AM92: RJO | AN92: 000189406 | AO92: 39.7 | AP92: 0 | AQ92: 3 | AR92: 0 | AS92: CP | AT92: LIQUIDADO | AU92: 46260 | AV92: 399.58 | AW92: 001-DIVERSOS | AX92: 001-DIVERSOS | AY92: 1426.17 | AZ92: COMBINADA | BA92: CO3365267 | BB92: 399.58 | BC92: 351.63 | BD92: 399.58 | BE92: 47.95 | BF92: 0.12 | BG92: 0 | BH92: 39.7 | BI92: 58.9 | BJ92: 0 | BK92: 17 | BL92: 0 | BM92: 9.76 | BN92: 2.25 | BO92: 5.5 | BP92: 3.23 | BQ92: 0 | BR92: 0 | BS92: 0 | BT92: 0 | BU92: 0 | BV92: 0 | BW92: 0 | BX92: 250 | BY92: 0 | BZ92: 0 | CA92: 4.99 | CB92: CTBP | CC92: RJOP | CD92: 382.01 | CE92: 0 | CF92: 0 | CG92: 0 | CH92: 0 | CI92: 0 | CJ92: 0 | CK92: 0 | CN92: 0 | CO92: 0 | CP92: 0 | CQ92: 0 | CR92: 0 | CS92: 0 | CT92: 0 | CU92: 12 | CV92: MAPA: 161 | CW92: 0 | CY92: 18 | CZ92: MAPA: 162 | DA92: 0 | DE92: 0 | DF92: A. | DG92: PR | DH92: ARAUCARIA | DI92: 9026067267 | DJ92: (41 ) 38887555 | DK92: 0 | DL92: CTB | DM92: 47.95
A93: 2 | B93: CTB071373-2 | C93: NORMAL | D93: CTBP | E93: CTB | F93: 46251 | G93: DQB8989 | H93: 41260803098929000606570010000722801003735660 | I93: 05094003000155 | J93: COLSON DO BRASIL LTDA | K93: RUA DAS PALMEIRAS 350 | L93: CAPELA VELHA | M93: 002 | N93: ARAUCARIA | O93: PR | P93: 83705-500 | Q93: 05094003000155 | R93: COLSON DO BRASIL LTDA | S93: ARAUCARIA | T93: PR | U93: 05094003000155 | V93: COLSON DO BRASIL LTDA | W93: RUA DAS PALMEIRAS 350 | X93: CAPELA VELHA | Y93: ARAUCARIA | Z93: PR | AA93: (41 ) 38887555 | AC93: 11671952000153 | AD93: FLEXMAQ COMERCIO DE EQUIPAMENTOS IN | AE93: 131 | AF93: PSPP | AG93: SUMARE | AH93: SP | AI93: 11671952000153 | AJ93: FLEXMAQ COMERCIO DE EQUIPAMENTOS IN | AK93: SUMARE | AL93: SP | AM93: PSP | AN93: 000189555 | AO93: 52.92 | AP93: 0 | AQ93: 6 | AR93: 0 | AS93: CP | AT93: LIQUIDADO | AU93: 46267 | AV93: 204.19 | AW93: 001-DIVERSOS | AX93: 001-DIVERSOS | AY93: 1690.24 | AZ93: COMBINADA | BA93: CO3365266 | BB93: 204.19 | BC93: 179.69 | BD93: 204.19 | BE93: 24.5 | BF93: 0.12 | BG93: 0 | BH93: 52.92 | BI93: 135.74 | BJ93: 0 | BK93: 17 | BL93: 0 | BM93: 9.76 | BN93: 2.54 | BO93: 5.5 | BP93: 3.23 | BQ93: 0 | BR93: 0 | BS93: 0 | BT93: 0 | BU93: 0 | BV93: 0 | BW93: 0 | BX93: 0 | BY93: 0 | BZ93: 0 | CA93: 5.92 | CB93: CTBP | CC93: SAOP | CD93: 384.68 | CE93: 0 | CF93: 0 | CG93: 0 | CH93: 0 | CI93: 0 | CJ93: 0 | CK93: 0 | CN93: 0 | CO93: 0 | CP93: 0 | CQ93: 0 | CR93: 0 | CS93: 0 | CT93: 0 | CU93: 12 | CV93: MAPA: 162 | CW93: 0 | CY93: 60.5 | CZ93: MAPA: 0 | DA93: =CY93 -> 60.5 | DE93: 0 | DF93: A. | DG93: PR | DH93: ARAUCARIA | DI93: 9026067267 | DJ93: (41 ) 38887555 | DK93: 0 | DL93: CTB | DM93: 163.95
A94: 2 | B94: CTB071204-3 | C94: NORMAL | D94: CTBP | E94: CTB | F94: 46247 | G94: AFF1761 | H94: 41260803098929000606570010000721101003718803 | I94: 05094003000155 | J94: COLSON DO BRASIL LTDA | K94: RUA DAS PALMEIRAS 350 | L94: CAPELA VELHA | M94: 002 | N94: ARAUCARIA | O94: PR | P94: 83705-500 | Q94: 05094003000155 | R94: COLSON DO BRASIL LTDA | S94: ARAUCARIA | T94: PR | U94: 05094003000155 | V94: COLSON DO BRASIL LTDA | W94: RUA DAS PALMEIRAS 350 | X94: CAPELA VELHA | Y94: ARAUCARIA | Z94: PR | AA94: (41 ) 38887555 | AC94: 41777728000101 | AD94: PRIMATEC COMERCIO E SERVICO LT | AE94: RIO RIO DE JANEIRO | AF94: RJOP | AG94: RIO DE JANEIRO | AH94: RJ | AI94: 41777728000101 | AJ94: PRIMATEC COMERCIO E SERVICO LT | AK94: RIO DE JANEIRO | AL94: RJ | AM94: RJO | AN94: 000189392 | AO94: 130.4 | AP94: 0 | AQ94: 12 | AR94: 0 | AS94: CP | AT94: LIQUIDADO | AU94: 46260 | AV94: 199.3 | AW94: 001-DIVERSOS | AX94: 001-DIVERSOS | AY94: 3403.74 | AZ94: COMBINADA | BA94: CO3365267 | BB94: 199.3 | BC94: 175.38 | BD94: 199.3 | BE94: 23.92 | BF94: 0.12 | BG94: 0 | BH94: 130.4 | BI94: 117.37 | BJ94: 0 | BK94: 17 | BL94: 0 | BM94: 9.76 | BN94: 5.11 | BO94: 11 | BP94: 3.23 | BQ94: 0 | BR94: 0 | BS94: 0 | BT94: 0 | BU94: 0 | BV94: 0 | BW94: 0 | BX94: 0 | BY94: 0 | BZ94: 0 | CA94: 11.91 | CB94: CTBP | CC94: RJOP | CD94: 409.16 | CE94: 0 | CF94: 0 | CG94: 0 | CH94: 0 | CI94: 0 | CJ94: 0 | CK94: 0 | CN94: 0 | CO94: 0 | CP94: 0 | CQ94: 0 | CR94: 0 | CS94: 0 | CT94: 0 | CU94: 19.56 | CV94: MAPA: 161 | CW94: 0 | CY94: 23.47 | CZ94: MAPA: 162 | DA94: 0 | DE94: 0 | DF94: A. | DG94: PR | DH94: ARAUCARIA | DI94: 9026067267 | DJ94: (41 ) 38887555 | DK94: 0 | DL94: CTB | DM94: 23.92
A95: 2 | B95: CTB071205-1 | C95: NORMAL | D95: CTBP | E95: CTB | F95: 46247 | G95: AFF1761 | H95: 41260803098929000606570010000721151003718877 | I95: 05094003000155 | J95: COLSON DO BRASIL LTDA | K95: RUA DAS PALMEIRAS 350 | L95: CAPELA VELHA | M95: 002 | N95: ARAUCARIA | O95: PR | P95: 83705-500 | Q95: 05094003000155 | R95: COLSON DO BRASIL LTDA | S95: ARAUCARIA | T95: PR | U95: 05094003000155 | V95: COLSON DO BRASIL LTDA | W95: RUA DAS PALMEIRAS 350 | X95: CAPELA VELHA | Y95: ARAUCARIA | Z95: PR | AA95: (41 ) 38887555 | AC95: 35240032000149 | AD95: ELETRIC ILUMINACAO E FERRAMENTAS LTDA | AE95: 07 ZONA OESTE | AF95: SPOP | AG95: SAO PAULO | AH95: SP | AI95: 35240032000149 | AJ95: ELETRIC ILUMINACAO E FERRAMENTAS LTDA | AK95: SAO PAULO | AL95: SP | AM95: SPO | AN95: 000189407 | AO95: 28.8 | AP95: 0 | AQ95: 2 | AR95: 0 | AS95: CP | AT95: LIQUIDADO | AU95: 46260 | AV95: 111.08 | AW95: 001-DIVERSOS | AX95: 001-DIVERSOS | AY95: 2810.55 | AZ95: COMBINADA | BA95: CO3365274 | BB95: 111.08 | BC95: 97.75 | BD95: 111.08 | BE95: 13.33 | BF95: 0.12 | BG95: 0 | BH95: 28.8 | BI95: 48.2 | BJ95: 0 | BK95: 17 | BL95: 0 | BM95: 9.76 | BN95: 4.22 | BO95: 5.5 | BP95: 3.23 | BQ95: 0 | BR95: 0 | BS95: 0 | BT95: 0 | BU95: 0 | BV95: 0 | BW95: 0 | BX95: 0 | BY95: 0 | BZ95: 0 | CA95: 9.84 | CB95: CTBP | CC95: SPOP | CD95: 400.58 | CE95: 0 | CF95: 0 | CG95: 0 | CH95: 0 | CI95: 0 | CJ95: 0 | CK95: 0 | CN95: 0 | CO95: 0 | CP95: 0 | CQ95: 0 | CR95: 0 | CS95: 0 | CT95: 0 | CU95: 12 | CV95: MAPA: 161 | CW95: 0 | CY95: 18 | CZ95: MAPA: 162 | DA95: 0 | DE95: 0 | DF95: A. | DG95: PR | DH95: ARAUCARIA | DI95: 9026067267 | DJ95: (41 ) 38887555 | DK95: 0 | DL95: CTB | DM95: 13.33
A96: 2 | B96: CTB071206-0 | C96: NORMAL | D96: CTBP | E96: CTB | F96: 46247 | G96: AFF1761 | H96: 41260803098929000606570010000721161003718882 | I96: 05094003000155 | J96: COLSON DO BRASIL LTDA | K96: RUA DAS PALMEIRAS 350 | L96: CAPELA VELHA | M96: 002 | N96: ARAUCARIA | O96: PR | P96: 83705-500 | Q96: 05094003000155 | R96: COLSON DO BRASIL LTDA | S96: ARAUCARIA | T96: PR | U96: 05094003000155 | V96: COLSON DO BRASIL LTDA | W96: RUA DAS PALMEIRAS 350 | X96: CAPELA VELHA | Y96: ARAUCARIA | Z96: PR | AA96: (41 ) 38887555 | AC96: 32606792000139 | AD96: CONSTRUSERRA MAT CONSTRUCAO EIRELI ME | AE96: 256 | AF96: MVGP | AG96: PETROPOLIS | AH96: RJ | AI96: 32606792000139 | AJ96: CONSTRUSERRA MAT CONSTRUCAO EIRELI ME | AK96: PETROPOLIS | AL96: RJ | AM96: MVG | AN96: 000189394 | AO96: 40.56 | AP96: 0 | AQ96: 4 | AR96: 0 | AS96: CP | AT96: LIQUIDADO | AU96: 46260 | AV96: 152.83 | AW96: 001-DIVERSOS | AX96: 001-DIVERSOS | AY96: 5219.62 | AZ96: COMBINADA | BA96: CO3365270 | BB96: 152.83 | BC96: 134.49 | BD96: 152.83 | BE96: 18.34 | BF96: 0.12 | BG96: 0 | BH96: 40.56 | BI96: 72.9 | BJ96: 0 | BK96: 17 | BL96: 0 | BM96: 9.76 | BN96: 7.83 | BO96: 5.5 | BP96: 3.23 | BQ96: 0 | BR96: 0 | BS96: 0 | BT96: 0 | BU96: 0 | BV96: 0 | BW96: 0 | BX96: 0 | BY96: 0 | BZ96: 0 | CA96: 18.27 | CB96: CTBP | CC96: ITAI | CD96: 435.41 | CE96: 0 | CF96: 0 | CG96: 0 | CH96: 0 | CI96: 0 | CJ96: 0 | CK96: 0 | CN96: 0 | CO96: 0 | CP96: 0 | CQ96: 0 | CR96: 0 | CS96: 0 | CT96: 0 | CU96: 12 | CV96: MAPA: 161 | CW96: 0 | CY96: 52.18 | CZ96: FATURA: 17893 | DA96: 52.18 | DB96: 017893 | DE96: 0 | DF96: A. | DG96: PR | DH96: ARAUCARIA | DI96: 9026067267 | DJ96: (41 ) 38887555 | DK96: 0 | DL96: CTB | DM96: 18.34
A97: 2 | B97: CTB071207-8 | C97: NORMAL | D97: CTBP | E97: CTB | F97: 46247 | G97: AFF1761 | H97: 41260803098929000606570010000721121003718832 | I97: 05094003000155 | J97: COLSON DO BRASIL LTDA | K97: RUA DAS PALMEIRAS 350 | L97: CAPELA VELHA | M97: 002 | N97: ARAUCARIA | O97: PR | P97: 83705-500 | Q97: 05094003000155 | R97: COLSON DO BRASIL LTDA | S97: ARAUCARIA | T97: PR | U97: 05094003000155 | V97: COLSON DO BRASIL LTDA | W97: RUA DAS PALMEIRAS 350 | X97: CAPELA VELHA | Y97: ARAUCARIA | Z97: PR | AA97: (41 ) 38887555 | AC97: 57224566000114 | AD97: POWER STEEL COMERCIO E SERVICOS LTDA | AE97: 070 | AF97: SPOP | AG97: GUARULHOS | AH97: SP | AI97: 57224566000114 | AJ97: POWER STEEL COMERCIO E SERVICOS LTDA | AK97: GUARULHOS | AL97: SP | AM97: SPO | AN97: 000189455 | AO97: 16.152 | AP97: 0 | AQ97: 5 | AR97: 0 | AS97: CP | AT97: LIQUIDADO | AU97: 46260 | AV97: 97.76 | AW97: 001-DIVERSOS | AX97: 001-DIVERSOS | AY97: 2167.59 | AZ97: COMBINADA | BA97: CO3365274 | BB97: 97.76 | BC97: 86.03 | BD97: 97.76 | BE97: 11.73 | BF97: 0.12 | BG97: 0 | BH97: 16.152 | BI97: 39.7 | BJ97: 0 | BK97: 17 | BL97: 0 | BM97: 9.76 | BN97: 3.25 | BO97: 5.5 | BP97: 3.23 | BQ97: 0 | BR97: 0 | BS97: 0 | BT97: 0 | BU97: 0 | BV97: 0 | BW97: 0 | BX97: 0 | BY97: 0 | BZ97: 0 | CA97: 7.59 | CB97: CTBP | CC97: SPOP | CD97: 391.2 | CE97: 0 | CF97: 0 | CG97: 0 | CH97: 0 | CI97: 0 | CJ97: 0 | CK97: 0 | CN97: 0 | CO97: 0 | CP97: 0 | CQ97: 0 | CR97: 0 | CS97: 0 | CT97: 0 | CU97: 12 | CV97: MAPA: 161 | CW97: 0 | CY97: 18 | CZ97: MAPA: 162 | DA97: 0 | DE97: 0 | DF97: A. | DG97: PR | DH97: ARAUCARIA | DI97: 9026067267 | DJ97: (41 ) 38887555 | DK97: 0 | DL97: CTB | DM97: 11.73
A98: 2 | B98: CTB071208-6 | C98: NORMAL | D98: CTBP | E98: CTB | F98: 46247 | G98: AFF1761 | H98: 41260803098929000606570010000721171003718898 | I98: 05094003000155 | J98: COLSON DO BRASIL LTDA | K98: RUA DAS PALMEIRAS 350 | L98: CAPELA VELHA | M98: 002 | N98: ARAUCARIA | O98: PR | P98: 83705-500 | Q98: 05094003000155 | R98: COLSON DO BRASIL LTDA | S98: ARAUCARIA | T98: PR | U98: 05094003000155 | V98: COLSON DO BRASIL LTDA | W98: RUA DAS PALMEIRAS 350 | X98: CAPELA VELHA | Y98: ARAUCARIA | Z98: PR | AA98: (41 ) 38887555 | AC98: 23476033001856 | AD98: BMB MATERIAL DE CONSTRUCAO S.A. 0018-56 | AE98: CAX DUQUE DE CAXIAS | AF98: RJOP | AG98: DUQUE DE CAXIAS | AH98: RJ | AI98: 23476033001856 | AJ98: BMB MATERIAL DE CONSTRUCAO S.A. 0018-56 | AK98: DUQUE DE CAXIAS | AL98: RJ | AM98: RJO | AN98: 000189374 | AO98: 92 | AP98: 0 | AQ98: 10 | AR98: 0 | AS98: CP | AT98: LIQUIDADO | AU98: 46260 | AV98: 451.89 | AW98: 001-DIVERSOS | AX98: 001-DIVERSOS | AY98: 2394.54 | AZ98: COMBINADA | BA98: CO3365267 | BB98: 451.89 | BC98: 397.66 | BD98: 451.89 | BE98: 54.23 | BF98: 0.12 | BG98: 0 | BH98: 92 | BI98: 100.2 | BJ98: 0 | BK98: 17 | BL98: 0 | BM98: 9.76 | BN98: 3.59 | BO98: 5.5 | BP98: 3.23 | BQ98: 0 | BR98: 0 | BS98: 0 | BT98: 0 | BU98: 0 | BV98: 0 | BW98: 0 | BX98: 250 | BY98: 0 | BZ98: 0 | CA98: 8.38 | CB98: CTBP | CC98: RJOP | CD98: 394.49 | CE98: 0 | CF98: 0 | CG98: 0 | CH98: 0 | CI98: 0 | CJ98: 0 | CK98: 0 | CN98: 0 | CO98: 0 | CP98: 0 | CQ98: 0 | CR98: 0 | CS98: 0 | CT98: 0 | CU98: 13.8 | CV98: MAPA: 161 | CW98: 0 | CY98: 18 | CZ98: MAPA: 162 | DA98: 0 | DE98: 0 | DF98: A. | DG98: PR | DH98: ARAUCARIA | DI98: 9026067267 | DJ98: (41 ) 38887555 | DK98: 0 | DL98: CTB | DM98: 54.23
A99: 2 | B99: CTB071209-4 | C99: NORMAL | D99: CTBP | E99: CTB | F99: 46247 | G99: AFF1761 | H99: 41260803098929000606570010000721141003718853 | I99: 05094003000155 | J99: COLSON DO BRASIL LTDA | K99: RUA DAS PALMEIRAS 350 | L99: CAPELA VELHA | M99: 002 | N99: ARAUCARIA | O99: PR | P99: 83705-500 | Q99: 05094003000155 | R99: COLSON DO BRASIL LTDA | S99: ARAUCARIA | T99: PR | U99: 05094003000155 | V99: COLSON DO BRASIL LTDA | W99: RUA DAS PALMEIRAS 350 | X99: CAPELA VELHA | Y99: ARAUCARIA | Z99: PR | AA99: (41 ) 38887555 | AC99: 21164087000102 | AD99: DISCHER MAQUINAS E FERRAMENTAS | AE99: 296 | AF99: EPSI | AG99: SANTA MARIA DE JETIBA | AH99: ES | AI99: 21164087000102 | AJ99: DISCHER MAQUINAS E FERRAMENTAS | AK99: SANTA MARIA DE JETIBA | AL99: ES | AM99: EPS | AN99: 000189364 | AO99: 160.184 | AP99: 0 | AQ99: 19 | AR99: 0 | AS99: CP | AT99: LIQUIDADO | AU99: 46260 | AV99: 253.57 | AW99: 001-DIVERSOS | AX99: 054-PNEUS E CAMARAS DE AR | AY99: 6265.4 | AZ99: COMBINADA | BA99: CO3365268 | BB99: 253.57 | BC99: 235.82 | BD99: 253.57 | BE99: 17.75 | BF99: 0.07 | BG99: 0 | BH99: 160.184 | BI99: 163.5 | BJ99: 0 | BK99: 17 | BL99: 0 | BM99: 9.76 | BN99: 9.4 | BO99: 11 | BP99: 3.23 | BQ99: 0 | BR99: 0 | BS99: 0 | BT99: 0 | BU99: 0 | BV99: 0 | BW99: 0 | BX99: 0 | BY99: 0 | BZ99: 0 | CA99: 21.93 | CB99: CTBP | CC99: EPSP | CD99: 450.63 | CE99: 0 | CF99: 0 | CG99: 0 | CH99: 0 | CI99: 0 | CJ99: 0 | CK99: 0 | CN99: 0 | CO99: 0 | CP99: 0 | CQ99: 0 | CR99: 0 | CS99: 0 | CT99: 0 | CU99: 24.03 | CV99: MAPA: 161 | CW99: 0 | CY99: 113.19 | CZ99: FATURA: 55342 | DA99: 121.71 | DB99: 055342 | DE99: 0 | DF99: A. | DG99: PR | DH99: ARAUCARIA | DI99: 9026067267 | DJ99: (41 ) 38887555 | DK99: 0 | DL99: CTB | DM99: 17.75
A100: 2 | B100: CTB071210-8 | C100: NORMAL | D100: CTBP | E100: CTB | F100: 46247 | G100: AFF1761 | H100: 41260803098929000606570010000721181003718909 | I100: 05094003000155 | J100: COLSON DO BRASIL LTDA | K100: RUA DAS PALMEIRAS 350 | L100: CAPELA VELHA | M100: 002 | N100: ARAUCARIA | O100: PR | P100: 83705-500 | Q100: 05094003000155 | R100: COLSON DO BRASIL LTDA | S100: ARAUCARIA | T100: PR | U100: 05094003000155 | V100: COLSON DO BRASIL LTDA | W100: RUA DAS PALMEIRAS 350 | X100: CAPELA VELHA | Y100: ARAUCARIA | Z100: PR | AA100: (41 ) 38887555 | AC100: 68620541000156 | AD100: PARAFUSOS SIAN LTDA | AE100: RIO RIO DE JANEIRO | AF100: RJOP | AG100: RIO DE JANEIRO | AH100: RJ | AI100: 68620541000156 | AJ100: PARAFUSOS SIAN LTDA | AK100: RIO DE JANEIRO | AL100: RJ | AM100: RJO | AN100: 000189446 | AO100: 122.45 | AP100: 0 | AQ100: 20 | AR100: 0 | AS100: CP | AT100: LIQUIDADO | AU100: 46260 | AV100: 196.16 | AW100: 001-DIVERSOS | AX100: 001-DIVERSOS | AY100: 4281.46 | AZ100: COMBINADA | BA100: CO3365267 | BB100: 196.16 | BC100: 172.62 | BD100: 196.16 | BE100: 23.54 | BF100: 0.12 | BG100: 0 | BH100: 122.45 | BI100: 110.22 | BJ100: 0 | BK100: 17 | BL100: 0 | BM100: 9.76 | BN100: 6.42 | BO100: 11 | BP100: 3.23 | BQ100: 0 | BR100: 0 | BS100: 0 | BT100: 0 | BU100: 0 | BV100: 0 | BW100: 0 | BX100: 0 | BY100: 0 | BZ100: 0 | CA100: 14.99 | CB100: CTBP | CC100: RJOP | CD100: 421.85 | CE100: 0 | CF100: 0 | CG100: 0 | CH100: 0 | CI100: 0 | CJ100: 0 | CK100: 0 | CN100: 0 | CO100: 0 | CP100: 0 | CQ100: 0 | CR100: 0 | CS100: 0 | CT100: 0 | CU100: 18.37 | CV100: MAPA: 161 | CW100: 0 | CY100: 22.04 | CZ100: MAPA: 162 | DA100: 0 | DE100: 0 | DF100: A. | DG100: PR | DH100: ARAUCARIA | DI100: 9026067267 | DJ100: (41 ) 38887555 | DK100: 0 | DL100: CTB | DM100: 23.54
...

Sheet CUSTO TRANSFERENCIA
F1: Como fazer cálculo: Retirar relatório opção 200, informando o periodo mensal por unidade origem. Retirar os manifestos "Cancelados". Analisar por rota. Peso Calculo e R$ CTRB. Rota SET x BHZ e BHZ x SET calcular somente uma vez. Valor CTRB e Peso calculo.
AQ2: Filial Distribuição
C3: SPO | O3: BHZ | X3: RJO | AD3: SET | AG3: CTB | AM3: BNU/BSQ | AQ3: MESES | AR3: SPO | AS3: BHZ | AT3: SET | AU3: RJO | AV3: CTB
B4: ROTA | C4: SPO-BHZ | F4: SPO-RJO | I4: SPO-SET | L4: SPO-CTB | O4: BHZ-SPO | R4: BHZ-SET/SET-BHZ | U4: BHZ-RJO | X4: RJO-BHZ | AA4: RJO-SPO | AD4: SET-SPO | AG4: CTB-SPO | AJ4: CTB-BHZ | AM4: BNU/BSQ-SPO | AQ4: JAN | AR4: 0.17 | AS4: 0.11 | AT4: 0.055 | AU4: 0.2 | AV4: 0.09
B5: MESES | C5: PESO | D5: R$ CTRB | E5: R$ MÉDIO | F5: PESO | G5: R$ CTRB | H5: R$ MÉDIO | I5: PESO | J5: R$ CTRB | K5: R$ MÉDIO | L5: PESO | M5: R$ CTRB | N5: R$ MÉDIO | O5: PESO | P5: R$ CTRB | Q5: R$ MÉDIO | R5: PESO | S5: R$ CTRB | T5: R$ MÉDIO | U5: PESO | V5: R$ CTRB | W5: R$ MÉDIO | X5: PESO | Y5: R$ CTRB | Z5: R$ MÉDIO | AA5: PESO | AB5: R$ CTRB | AC5: R$ MÉDIO | AD5: PESO | AE5: R$ CTRB | AF5: R$ MÉDIO | AG5: PESO | AH5: R$ CTRB | AI5: R$ MÉDIO | AJ5: PESO | AK5: R$ CTRB | AL5: R$ MÉDIO | AM5: PESO | AN5: R$ CTRB | AO5: R$ MÉDIO | AQ5: FEV | AR5: 0.16 | AS5: 0.14 | AT5: 0.055 | AU5: 0.23 | AV5: 0.08
B6: JAN | C6: 943041.57 | D6: 165597.64 | E6: =IF(C6="","",D6/C6) -> 0.17559951 | F6: 260795.93 | G6: 49443.62 | H6: =IF(F6="","",G6/F6) -> 0.18958739 | I6: 904113.01 | J6: 152229.76 | K6: =IF(I6="","",J6/I6) -> 0.1683747 | L6: 121714.08 | M6: 32829.5 | N6: =IF(L6="","",M6/L6) -> 0.26972639 | O6: 256231.97 | P6: 61074.06 | Q6: 0.2 | T6: =IF(R6="","",S6/R6) | U6: 315160.69 | V6: 55389.65 | W6: 0.2 | X6: 90195.27 | Y6: 28889.88 | Z6: =IF(X6="","",Y6/X6) -> 0.32030371 | AA6: 269194.81 | AB6: 67310.36 | AC6: =IF(AA6="","",AB6/AA6) -> 0.25004331 | AD6: 239413.79 | AE6: 60648.36 | AF6: =IF(AD6="","",AE6/AD6) -> 0.25332025 | AG6: 323868 | AH6: 48990.32 | AI6: =IF(AG6="","",AH6/AG6) -> 0.15126632 | AJ6: 0 | AK6: 0 | AL6: =IF(AJ6="","",AK6/AJ6) -> #DIV/0! | AM6: 351216 | AN6: 100603 | AO6: =IF(AM6="","",AN6/AM6) -> 0.28644196 | AQ6: MAR | AR6: 0.19 | AS6: 0.13 | AT6: 0.06 | AU6: 0.23 | AV6: 0.09
B7: FEV | C7: 958064.79 | D7: 185546.49 | E7: =IF(C7="","",D7/C7) -> 0.193668 | F7: 401190.58 | G7: 71129.59 | H7: =IF(F7="","",G7/F7) -> 0.17729626 | I7: 973715.19 | J7: 153837.17 | K7: =IF(I7="","",J7/I7) -> 0.1579899 | L7: 97902.15 | M7: 28065.2 | N7: =IF(L7="","",M7/L7) -> 0.28666582 | O7: 223433 | P7: 41479.91 | Q7: 0.18 | T7: =IF(R7="","",S7/R7) | U7: 262321 | V7: 48135.61 | W7: =IF(U7="","",V7/U7) -> 0.18349888 | X7: 74697.19 | Y7: 25496.58 | Z7: =IF(X7="","",Y7/X7) -> 0.34133252 | AA7: 281103.51 | AB7: 63667.34 | AC7: =IF(AA7="","",AB7/AA7) -> 0.22649073 | AD7: 240728.88 | AE7: 59760.59 | AF7: =IF(AD7="","",AE7/AD7) -> 0.24824853 | AG7: 384684 | AH7: 50080.64 | AI7: =IF(AG7="","",AH7/AG7) -> 0.13018644 | AJ7: 0 | AK7: 0 | AL7: =IF(AJ7="","",AK7/AJ7) -> #DIV/0! | AM7: 268179 | AN7: 87200 | AO7: =IF(AM7="","",AN7/AM7) -> 0.32515596 | AQ7: ABR | AR7: 0.15 | AS7: 0.13 | AT7: 0.06 | AU7: 0.26 | AV7: 0
B8: MAR | E8: 0.17 | H8: 0.19 | K8: 0.18 | N8: 0.3 | Q8: 0.17 | W8: 0.18 | Z8: 0.29 | AC8: 0.22 | AF8: 0.24 | AI8: 0 | AL8: 0 | AQ8: MAI | AR8: 0.2 | AS8: 0.12 | AT8: 0.05 | AU8: 0.25 | AV8: 0.11
B9: ABR | E9: 0.19 | H9: 0.2 | K9: 0.18 | N9: 0.24 | Q9: 0.21 | W9: 0.2 | Z9: 0.29 | AC9: 0.23 | AF9: 0.25 | AI9: 0 | AL9: 0 | AQ9: JUN | AR9: 0 | AS9: 0.14 | AT9: 0.055 | AU9: 0.28 | AV9: 0.09
B10: MAI | E10: 0.18 | H10: 0.18 | K10: 0.18 | N10: 0.28 | Q10: 0.18 | W10: 0.19 | Z10: 0.28 | AC10: 0.19 | AF10: 0.23 | AI10: 0 | AL10: 0 | AQ10: JUL | AR10: 0.19 | AS10: 0.15 | AT10: 0.06 | AU10: 0.22 | AV10: 0.09
B11: JUN | E11: 0.18 | H11: 0.19 | K11: 0.18 | N11: 0.31 | Q11: 0.25 | W11: 0.22 | Z11: 0.21 | AC11: 0.18 | AF11: 0.25 | AI11: 0.17 | AL11: 0 | AQ11: AGO
B12: JUL | E12: 0.18 | H12: 0.18 | K12: 0.18 | N12: 0.34 | Q12: 0.22 | W12: 0.21 | Z12: 0.28 | AC12: 0.19 | AF12: 0.22 | AI12: 0.2 | AL12: 0 | AQ12: SET
B13: AGO | E13: =IF(C13="","",D13/C13) | H13: =IF(F13="","",G13/F13) | K13: =IF(I13="","",J13/I13) | N13: =IF(L13="","",M13/L13) | Q13: =IF(O13="","",P13/O13) | T13: =IF(R13="","",S13/R13) | Z13: =IF(X13="","",Y13/X13) | AC13: =IF(AA13="","",AB13/AA13) | AF13: =IF(AD13="","",AE13/AD13) | AI13: =IF(AG13="","",AH13/AG13) | AL13: 0 | AO13: =IF(AM13="","",AN13/AM13) | AQ13: OUT
B14: SET | E14: =IF(C14="","",D14/C14) | H14: =IF(F14="","",G14/F14) | K14: =IF(I14="","",J14/I14) | N14: =IF(L14="","",M14/L14) | Q14: =IF(O14="","",P14/O14) | T14: =IF(R14="","",S14/R14) | Z14: =IF(X14="","",Y14/X14) | AC14: =IF(AA14="","",AB14/AA14) | AF14: =IF(AD14="","",AE14/AD14) | AI14: =IF(AG14="","",AH14/AG14) | AL14: =IF(AJ14="","",AK14/AJ14) | AO14: =IF(AM14="","",AN14/AM14) | AQ14: NOV
B15: OUT | E15: =IF(C15="","",D15/C15) | H15: =IF(F15="","",G15/F15) | K15: =IF(I15="","",J15/I15) | N15: =IF(L15="","",M15/L15) | Q15: =IF(O15="","",P15/O15) | T15: =IF(R15="","",S15/R15) | Z15: =IF(X15="","",Y15/X15) | AC15: =IF(AA15="","",AB15/AA15) | AF15: =IF(AD15="","",AE15/AD15) | AI15: =IF(AG15="","",AH15/AG15) | AL15: =IF(AJ15="","",AK15/AJ15) | AO15: =IF(AM15="","",AN15/AM15) | AQ15: DEZ
B16: NOV | E16: =IF(C16="","",D16/C16) | H16: =IF(F16="","",G16/F16) | K16: =IF(I16="","",J16/I16) | N16: =IF(L16="","",M16/L16) | Q16: =IF(O16="","",P16/O16) | T16: =IF(R16="","",S16/R16) | W16: =IF(U16="","",V16/U16) | Z16: =IF(X16="","",Y16/X16) | AC16: =IF(AA16="","",AB16/AA16) | AF16: =IF(AD16="","",AE16/AD16) | AI16: =IF(AG16="","",AH16/AG16) | AL16: =IF(AJ16="","",AK16/AJ16) | AO16: =IF(AM16="","",AN16/AM16) | AQ16: TOTAL | AR16: =AVERAGE(AR4:AR15) -> 0.15142857 | AS16: =AVERAGE(AS4:AS15) -> 0.13142857 | AT16: =AVERAGE(AT4:AT15) -> 0.056428571 | AU16: =AVERAGE(AU4:AU15) -> 0.23857143 | AV16: =AVERAGE(AV4:AV15) -> 0.078571429
B17: DEZ | E17: =IF(C17="","",D17/C17) | H17: =IF(F17="","",G17/F17) | K17: =IF(I17="","",J17/I17) | N17: =IF(L17="","",M17/L17) | Q17: =IF(O17="","",P17/O17) | T17: =IF(R17="","",S17/R17) | W17: =IF(U17="","",V17/U17) | Z17: =IF(X17="","",Y17/X17) | AC17: =IF(AA17="","",AB17/AA17) | AF17: =IF(AD17="","",AE17/AD17) | AI17: =IF(AG17="","",AH17/AG17) | AL17: =IF(AJ17="","",AK17/AJ17) | AO17: =IF(AM17="","",AN17/AM17)
B18: TOTAL | C18: =SUM(C6:C17) -> 1901106.4 | D18: =SUM(D6:D17) -> 351144.13 | E18: =IF(C18="","",D18/C18) -> 0.18470515 | F18: =SUM(F6:F17) -> 661986.51 | G18: =SUM(G6:G17) -> 120573.21 | H18: =IF(F18="","",G18/F18) -> 0.18213847 | I18: =SUM(I6:I17) -> 1877828.2 | J18: =SUM(J6:J17) -> 306066.93 | K18: =IF(I18="","",J18/I18) -> 0.16298985 | L18: =SUM(L6:L17) -> 219616.23 | M18: =SUM(M6:M17) -> 60894.7 | N18: =IF(L18="","",M18/L18) -> 0.27727778 | O18: =SUM(O6:O17) -> 479664.97 | P18: =SUM(P6:P17) -> 102553.97 | Q18: =IF(O18="","",P18/O18) -> 0.21380333 | R18: =SUM(R6:R17) -> 0 | S18: =SUM(S6:S17) -> 0 | T18: =IF(R18="","",S18/R18) -> #DIV/0! | U18: =SUM(U6:U17) -> 577481.69 | V18: =SUM(V6:V17) -> 103525.26 | W18: =IF(U18="","",V18/U18) -> 0.1792702 | X18: =SUM(X6:X17) -> 164892.46 | Y18: =SUM(Y6:Y17) -> 54386.46 | Z18: =IF(X18="","",Y18/X18) -> 0.32982988 | AA18: =SUM(AA6:AA17) -> 550298.32 | AB18: =SUM(AB6:AB17) -> 130977.7 | AC18: =IF(AA18="","",AB18/AA18) -> 0.23801217 | AD18: =SUM(AD6:AD17) -> 480142.67 | AE18: =SUM(AE6:AE17) -> 120408.95 | AF18: =IF(AD18="","",AE18/AD18) -> 0.25077744 | AG18: =SUM(AG6:AG17) -> 708552 | AH18: =SUM(AH6:AH17) -> 99070.96 | AI18: =IF(AG18="","",AH18/AG18) -> 0.13982172 | AJ18: =SUM(AJ6:AJ17) -> 0 | AK18: =SUM(AK6:AK17) -> 0 | AL18: =IF(AJ18="","",AK18/AJ18) -> #DIV/0! | AM18: =SUM(AM6:AM17) -> 619395 | AN18: =SUM(AN6:AN17) -> 187803 | AO18: =IF(AM18="","",AN18/AM18) -> 0.30320393
N19: -0.3
B22: RETIRA BH = EJM/ROP/SES/STJ
B23: RETIRA SL = DDB/SSO
O27: CTB
O28: 0.09
O29: 0.08
O30: 0.09

Sheet CUSTO NOVA
A1: DATA EMISSÃO | B1: TIPO DE DOCUMENTO | C1: PLACA DE COLETA | D1: EMISSORA | E1: UF | F1: RECEPTORA | G1: UF | H1: CLIENTE PAGADOR | I1: NF | J1: R$ MERCADORIA | K1: VOLUMES | L1: PESO | M1: FRETE | N1: % ICMS | O1: R$ COLETA | P1: CUSTO TRANSF 1 | Q1: CUSTO TRANSF 2 | R1: R$ DISTRIBUIÇÃO | S1: COMISSÃO UNIDADE | T1: R$ REDESPACHO | U1: PARCEIRO % / FRETE | V1: CUSTO OP. | W1: % | X1: RATEIO DESP. ADMINIST./apoio op | Y1: % / FRETE | Z1: RATEIO DESP. CLT operacional | AA1: % / FRETE | AB1: Seguro Acidente (0,010%) com iof | AC1: Seguro Roubo (0,010%) com iof | AD1: TOTAL CUSTOS OP. | AE1: %FRETE | AF1: ICMS | AG1: INSS DESON | AH1: PIS/COFINS/IRPJ/CSLL 5,2% | AI1: TOTAL R$ TRIBUTOS | AJ1: CUSTO GERAL | AK1: %FRETE | AL1: R$ LÍQUIDO | AM1: RESULTADO | AN1: CUSTO R$/KG
A2: F | B2: C | C2: G | D2: E | E2: O | F2: AM | G2: AL | H2: V | I2: AN | J2: AY | K2: AQ | L2: BH | M2: BB | N2: BF | O2: - | P2: - | Q2: - | R2: - | S2: - | T2: DJ | U2: - | V2: - | W2: - | X2: - | Y2: - | Z2: - | AA2: - | AB2: - | AC2: - | AD2: - | AE2: - | AF2: BE | AG2: - | AH2: - | AI2: - | AJ2: - | AK2: - | AL2: - | AM2: - | AN2: -
A3: {='BASE DADOS'!F2:F212} -> 46255 | B3: {='BASE DADOS'!C2:C212} -> NORMAL | C3: {='BASE DADOS'!G2:G212} -> DJB4058 | D3: {='BASE DADOS'!E2:E212} -> BHZ | E3: {='BASE DADOS'!O2:O212} -> MG | F3: {='BASE DADOS'!AM2:AM212} -> CTB | G3: {='BASE DADOS'!AL2:AL212} -> PR | H3: {='BASE DADOS'!V2:V212} -> COLSON DO BRASIL LTDA | I3: {='BASE DADOS'!AN2:AN212} -> 000147931 | J3: {='BASE DADOS'!AY2:AY212} -> 1057.88 | K3: {='BASE DADOS'!AQ2:AQ212} -> 3 | L3: {='BASE DADOS'!BH2:BH212} -> 47 | M3: {='BASE DADOS'!BB2:BB212} -> 172.2 | N3: {='BASE DADOS'!BF2:BF212} -> 0.12 | P3: =L3*0.34 -> 15.98 | Q3: =L3*0.18 -> 8.46 | T3: {='BASE DADOS'!DA2:DA212} -> 0 | U3: =T3/M3 -> 0 | V3: =O3+P3+Q3+R3+S3+T3 -> 24.44 | W3: =V3/M3 -> 0.14192799 | X3: =(L3*'RESULTADO DIRETO'!N$27)/6*3 -> 4.9129479 | Y3: =X3/M3 -> 0.028530475 | Z3: =(L3*'RESULTADO DIRETO'!N$15)/6*4 -> 5.966713 | AA3: =Z3/M3 -> 0.034649902 | AB3: =(J3*0.01%)*7.38%+(J3*0.01%) -> 0.11359515 | AC3: =(J3*0.01%)*7.38%+(J3*0.01%) -> 0.11359515 | AD3: =V3+X3+Z3+AB3+AC3 -> 35.546851 | AE3: =AD3/M3 -> 0.20642771 | AF3: =M3*N3 -> 20.664 | AH3: =M3*0.052 -> 8.9544 | AI3: =AF3+AG3+AH3 -> 29.6184 | AJ3: =AD3+AI3 -> 65.165251 | AK3: =AJ3/M3 -> 0.37842771 | AL3: =M3-AJ3 -> 107.03475 | AM3: =AL3/M3 -> 0.62157229 | AN3: =M3/L3 -> 3.6638298
A4: 46237 | B4: NORMAL | C4: DQB8989 | D4: CTB | E4: PR | F4: RJO | G4: RJ | H4: COLSON DO BRASIL LTDA | I4: 000188725 | J4: 3892.48 | K4: 8 | L4: 93.93 | M4: 460.4 | N4: 0.12 | O4: =L4*0.09 -> 8.4537 | P4: =L4*0.2 -> 18.786 | Q4: =L4*0.18 -> 16.9074 | R4: =M4*0.22 -> 101.288 | T4: 0 | U4: =T4/M4 -> 0 | V4: =O4+P4+Q4+R4+S4+T4 -> 145.4351 | W4: =V4/M4 -> 0.31588858 | X4: =(L4*'RESULTADO DIRETO'!N$27)/6*4 -> 13.091438 | Y4: =X4/M4 -> 0.028434922 | Z4: =(L4*'RESULTADO DIRETO'!N$15)/6*3 -> 8.9434046 | AA4: =Z4/M4 -> 0.019425292 | AB4: =(J4*0.01%)*7.38%+(J4*0.01%) -> 0.4179745 | AC4: =(J4*0.01%)*7.38%+(J4*0.01%) -> 0.4179745 | AD4: =V4+X4+Z4+AB4+AC4 -> 168.30589 | AE4: =AD4/M4 -> 0.36556449 | AF4: =M4*N4 -> 55.248 | AH4: =M4*0.052 -> 23.9408 | AI4: =AF4+AG4+AH4 -> 79.1888 | AJ4: =AD4+AI4 -> 247.49469 | AK4: =AJ4/M4 -> 0.53756449 | AL4: =M4-AJ4 -> 212.90531 | AM4: =AL4/M4 -> 0.46243551 | AN4: =M4/L4 -> 4.9015224
A5: 46237 | B5: NORMAL | C5: DQB8989 | D5: CTB | E5: PR | F5: RJO | G5: RJ | H5: COLSON DO BRASIL LTDA | I5: 000188531 | J5: 2546.66 | K5: 7 | L5: 85.965 | M5: 452.75 | N5: 0.12 | O5: =L5*0.09 -> 7.73685 | P5: =L5*0.2 -> 17.193 | Q5: =L5*0.18 -> 15.4737 | R5: =M5*0.22 -> 99.605 | T5: 0 | U5: =T5/M5 -> 0 | V5: =O5+P5+Q5+R5+S5+T5 -> 140.00855 | W5: =V5/M5 -> 0.30924031 | X5: =(L5*'RESULTADO DIRETO'!N$27)/6*4 -> 11.981321 | Y5: =X5/M5 -> 0.026463437 | Z5: =(L5*'RESULTADO DIRETO'!N$15)/6*3 -> 8.185029 | AA5: =Z5/M5 -> 0.018078474 | AB5: =(J5*0.01%)*7.38%+(J5*0.01%) -> 0.27346035 | AC5: =(J5*0.01%)*7.38%+(J5*0.01%) -> 0.27346035 | AD5: =V5+X5+Z5+AB5+AC5 -> 160.72182 | AE5: =AD5/M5 -> 0.35499022 | AF5: =M5*N5 -> 54.33 | AH5: =M5*0.052 -> 23.543 | AI5: =AF5+AG5+AH5 -> 77.873 | AJ5: =AD5+AI5 -> 238.59482 | AK5: =AJ5/M5 -> 0.52699022 | AL5: =M5-AJ5 -> 214.15518 | AM5: =AL5/M5 -> 0.47300978 | AN5: =M5/L5 -> 5.2666783
A6: 46237 | B6: NORMAL | C6: DQB8989 | D6: CTB | E6: PR | F6: RJO | G6: RJ | H6: COLSON DO BRASIL LTDA | I6: 000188697 | J6: 4824.67 | K6: 15 | L6: 249 | M6: 334.93 | N6: 0.12 | O6: =L6*0.09 -> 22.41 | P6: =L6*0.2 -> 49.8 | Q6: =L6*0.18 -> 44.82 | R6: =M6*0.22 -> 73.6846 | T6: 0 | U6: =T6/M6 -> 0 | V6: =O6+P6+Q6+R6+S6+T6 -> 190.7146 | W6: =V6/M6 -> 0.5694163 | X6: =(L6*'RESULTADO DIRETO'!N$27)/6*4 -> 34.704227 | Y6: =X6/M6 -> 0.10361636 | Z6: =(L6*'RESULTADO DIRETO'!N$15)/6*3 -> 23.708163 | AA6: =Z6/M6 -> 0.070785427 | AB6: =(J6*0.01%)*7.38%+(J6*0.01%) -> 0.51807306 | AC6: =(J6*0.01%)*7.38%+(J6*0.01%) -> 0.51807306 | AD6: =V6+X6+Z6+AB6+AC6 -> 250.16314 | AE6: =AD6/M6 -> 0.7469117 | AF6: =M6*N6 -> 40.1916 | AH6: =M6*0.052 -> 17.41636 | AI6: =AF6+AG6+AH6 -> 57.60796 | AJ6: =AD6+AI6 -> 307.7711 | AK6: =AJ6/M6 -> 0.9189117 | AL6: =M6-AJ6 -> 27.158903 | AM6: =AL6/M6 -> 0.081088297 | AN6: =M6/L6 -> 1.3451004
A7: 46237 | B7: NORMAL | C7: DQB8989 | D7: CTB | E7: PR | F7: EPS | G7: ES | H7: COLSON DO BRASIL LTDA | I7: 000188765 | J7: 5881.78 | K7: 11 | L7: 106.816 | M7: 192.94 | N7: 0.07 | O7: =L7*0.09 -> 9.61344 | P7: =L7*0.2 -> 21.3632 | T7: 92.61 | U7: =T7/M7 -> 0.47999378 | V7: =O7+P7+Q7+R7+S7+T7 -> 123.58664 | W7: =V7/M7 -> 0.64054442 | X7: =(L7*'RESULTADO DIRETO'!N$27)/6*3 -> 11.165563 | Y7: =X7/M7 -> 0.057870646 | Z7: =(L7*'RESULTADO DIRETO'!N$15)/6*4 -> 13.560434 | AA7: =Z7/M7 -> 0.070283168 | AB7: =(J7*0.01%)*7.38%+(J7*0.01%) -> 0.63158554 | AC7: =(J7*0.01%)*7.38%+(J7*0.01%) -> 0.63158554 | AE7: =AD7/M7 -> 0 | AF7: =M7*N7 -> 13.5058 | AH7: =M7*0.052 -> 10.03288 | AI7: =AF7+AG7+AH7 -> 23.53868 | AJ7: =AD7+AI7 -> 23.53868 | AK7: =AJ7/M7 -> 0.122 | AL7: =M7-AJ7 -> 169.40132 | AM7: =AL7/M7 -> 0.878 | AN7: =M7/L7 -> 1.8062837
A8: 46237 | B8: NORMAL | C8: DQB8989 | D8: CTB | E8: PR | F8: TAM | G8: MG | H8: COLSON DO BRASIL LTDA | I8: 000188760 | J8: 303.14 | K8: 1 | L8: 145.68 | M8: 219.59 | N8: 0.12 | O8: =L8*0.09 -> 13.1112 | P8: =L8*0.2 -> 29.136 | Q8: =L8*0.18 -> 26.2224 | R8: =L8*0.15 -> 21.852 | T8: 72.84 | U8: =T8/M8 -> 0.33170909 | V8: =O8+P8+Q8+R8+S8+T8 -> 163.1616 | W8: =V8/M8 -> 0.74302837 | X8: =(L8*'RESULTADO DIRETO'!N$27)/6*4 -> 20.304064 | Y8: =X8/M8 -> 0.092463517 | Z8: =(L8*'RESULTADO DIRETO'!N$15)/6*3 -> 13.870704 | AA8: =Z8/M8 -> 0.063166372 | AB8: =(J8*0.01%)*7.38%+(J8*0.01%) -> 0.032551173 | AC8: =(J8*0.01%)*7.38%+(J8*0.01%) -> 0.032551173 | AD8: =V8+X8+Z8+AB8+AC8 -> 197.40147 | AE8: =AD8/M8 -> 0.89895473 | AF8: =M8*N8 -> 26.3508 | AH8: =M8*0.052 -> 11.41868 | AI8: =AF8+AG8+AH8 -> 37.76948 | AJ8: =AD8+AI8 -> 235.17095 | AK8: =AJ8/M8 -> 1.0709547 | AL8: =M8-AJ8 -> -15.58095 | AM8: =AL8/M8 -> -0.070954732 | AN8: =M8/L8 -> 1.5073449
A9: 46237 | B9: NORMAL | C9: DQB8989 | D9: CTB | E9: PR | F9: SPO | G9: SP | H9: COLSON DO BRASIL LTDA | I9: 000188767 | J9: 1713.74 | K9: 2 | L9: 11.35 | M9: 95.18 | N9: 0.12 | O9: =L9*0.09 -> 1.0215 | P9: =L9*0.2 -> 2.27 | R9: =L9*0.19 -> 2.1565 | T9: 0 | U9: =T9/M9 -> 0 | V9: =O9+P9+Q9+R9+S9+T9 -> 5.448 | W9: =V9/M9 -> 0.057238916 | X9: =(L9*'RESULTADO DIRETO'!N$27)/6*3 -> 1.1864246 | Y9: =X9/M9 -> 0.012465062 | Z9: =(L9*'RESULTADO DIRETO'!N$15)/6*2 -> 0.72044886 | AA9: =Z9/M9 -> 0.0075693303 | AB9: =(J9*0.01%)*7.38%+(J9*0.01%) -> 0.1840214 | AC9: =(J9*0.01%)*7.38%+(J9*0.01%) -> 0.1840214 | AD9: =V9+X9+Z9+AB9+AC9 -> 7.7229163 | AE9: =AD9/M9 -> 0.081140117 | AF9: =M9*N9 -> 11.4216 | AH9: =M9*0.052 -> 4.94936 | AI9: =AF9+AG9+AH9 -> 16.37096 | AJ9: =AD9+AI9 -> 24.093876 | AK9: =AJ9/M9 -> 0.25314012 | AL9: =M9-AJ9 -> 71.086124 | AM9: =AL9/M9 -> 0.74685988 | AN9: =M9/L9 -> 8.3859031
A10: 46237 | B10: NORMAL | C10: DQB8989 | D10: CTB | E10: PR | F10: BHZ | G10: MG | H10: COLSON DO BRASIL LTDA | I10: 000188705 | J10: 3905.33 | K10: 7 | L10: 83.37 | M10: 177.52 | N10: 0.12 | O10: =L10*0.09 -> 7.5033 | P10: =L10*0.2 -> 16.674 | Q10: =L10*0.18 -> 15.0066 | R10: =L10*0.15 -> 12.5055 | T10: 0 | U10: =T10/M10 -> 0 | V10: =O10+P10+Q10+R10+S10+T10 -> 51.6894 | W10: =V10/M10 -> 0.29117508 | X10: =(L10*'RESULTADO DIRETO'!N$27)/6*4 -> 11.619644 | Y10: =X10/M10 -> 0.06545541 | Z10: =(L10*'RESULTADO DIRETO'!N$15)/6*3 -> 7.93795 | AA10: =Z10/M10 -> 0.044715807 | AB10: =(J10*0.01%)*7.38%+(J10*0.01%) -> 0.41935434 | AC10: =(J10*0.01%)*7.38%+(J10*0.01%) -> 0.41935434 | AD10: =V10+X10+Z10+AB10+AC10 -> 72.085703 | AE10: =AD10/M10 -> 0.40607088 | AF10: =M10*N10 -> 21.3024 | AH10: =M10*0.052 -> 9.23104 | AI10: =AF10+AG10+AH10 -> 30.53344 | AJ10: =AD10+AI10 -> 102.61914 | AK10: =AJ10/M10 -> 0.57807088 | AL10: =M10-AJ10 -> 74.900857 | AM10: =AL10/M10 -> 0.42192912 | AN10: =M10/L10 -> 2.1293031
A11: 46237 | B11: NORMAL | C11: DQB8989 | D11: CTB | E11: PR | F11: SPO | G11: SP | H11: COLSON DO BRASIL LTDA | I11: 000187858 | J11: 1375.97 | K11: 4 | L11: 39.4 | M11: 397 | N11: 0.12 | O11: =L11*0.09 -> 3.546 | P11: =L11*0.2 -> 7.88 | R11: =L11*0.19 -> 7.486 | T11: 0 | U11: =T11/M11 -> 0 | V11: =O11+P11+Q11+R11+S11+T11 -> 18.912 | W11: =V11/M11 -> 0.04763728 | X11: =(L11*'RESULTADO DIRETO'!N$27)/6*3 -> 4.1185137 | Y11: =X11/M11 -> 0.01037409 | Z11: =(L11*'RESULTADO DIRETO'!N$15)/6*2 -> 2.5009414 | AA11: =Z11/M11 -> 0.0062996006 | AB11: =(J11*0.01%)*7.38%+(J11*0.01%) -> 0.14775166 | AC11: =(J11*0.01%)*7.38%+(J11*0.01%) -> 0.14775166 | AD11: =V11+X11+Z11+AB11+AC11 -> 25.826958 | AE11: =AD11/M11 -> 0.065055311 | AF11: =M11*N11 -> 47.64 | AH11: =M11*0.052 -> 20.644 | AI11: =AF11+AG11+AH11 -> 68.284 | AJ11: =AD11+AI11 -> 94.110958 | AK11: =AJ11/M11 -> 0.23705531 | AL11: =M11-AJ11 -> 302.88904 | AM11: =AL11/M11 -> 0.76294469 | AN11: =M11/L11 -> 10.076142
A12: 46237 | B12: NORMAL | C12: DQB8989 | D12: CTB | E12: PR | F12: RJO | G12: RJ | H12: COLSON DO BRASIL LTDA | I12: 000188526 | J12: 1903.24 | K12: 9 | L12: 55.6 | M12: 429.09 | N12: 0.12 | O12: =L12*0.09 -> 5.004 | P12: =L12*0.2 -> 11.12 | Q12: =L12*0.18 -> 10.008 | R12: =M12*0.22 -> 94.3998 | T12: 0 | U12: =T12/M12 -> 0 | V12: =O12+P12+Q12+R12+S12+T12 -> 120.5318 | W12: =V12/M12 -> 0.28090098 | X12: =(L12*'RESULTADO DIRETO'!N$27)/6*4 -> 7.749217 | Y12: =X12/M12 -> 0.018059654 | Z12: =(L12*'RESULTADO DIRETO'!N$15)/6*3 -> 5.2938709 | AA12: =Z12/M12 -> 0.012337437 | AB12: =(J12*0.01%)*7.38%+(J12*0.01%) -> 0.20436991 | AC12: =(J12*0.01%)*7.38%+(J12*0.01%) -> 0.20436991 | AD12: =V12+X12+Z12+AB12+AC12 -> 133.98363 | AE12: =AD12/M12 -> 0.31225064 | AF12: =M12*N12 -> 51.4908 | AH12: =M12*0.052 -> 22.31268 | AI12: =AF12+AG12+AH12 -> 73.80348 | AJ12: =AD12+AI12 -> 207.78711 | AK12: =AJ12/M12 -> 0.48425064 | AL12: =M12-AJ12 -> 221.30289 | AM12: =AL12/M12 -> 0.51574936 | AN12: =M12/L12 -> 7.717446
A13: 46238 | B13: NORMAL | C13: DQB8989 | D13: CTB | E13: PR | F13: RJO | G13: RJ | H13: COLSON DO BRASIL LTDA | I13: 000188840 | J13: 3711.94 | K13: 13 | L13: 125.756 | M13: 196.3 | N13: 0.12 | O13: =L13*0.09 -> 11.31804 | P13: =L13*0.2 -> 25.1512 | Q13: =L13*0.18 -> 22.63608 | R13: =M13*0.22 -> 43.186 | T13: 0 | U13: =T13/M13 -> 0 | V13: =O13+P13+Q13+R13+S13+T13 -> 102.29132 | W13: =V13/M13 -> 0.52109689 | X13: =(L13*'RESULTADO DIRETO'!N$27)/6*4 -> 17.527168 | Y13: =X13/M13 -> 0.089287662 | Z13: =(L13*'RESULTADO DIRETO'!N$15)/6*3 -> 11.97367 | AA13: =Z13/M13 -> 0.060996789 | AB13: =(J13*0.01%)*7.38%+(J13*0.01%) -> 0.39858812 | AC13: =(J13*0.01%)*7.38%+(J13*0.01%) -> 0.39858812 | AD13: =V13+X13+Z13+AB13+AC13 -> 132.58933 | AE13: =AD13/M13 -> 0.67544235 | AF13: =M13*N13 -> 23.556 | AH13: =M13*0.052 -> 10.2076 | AI13: =AF13+AG13+AH13 -> 33.7636 | AJ13: =AD13+AI13 -> 166.35293 | AK13: =AJ13/M13 -> 0.84744235 | AL13: =M13-AJ13 -> 29.947066 | AM13: =AL13/M13 -> 0.15255765 | AN13: =M13/L13 -> 1.5609593
A14: 46238 | B14: NORMAL | C14: DQB8989 | D14: CTB | E14: PR | F14: TRU | G14: MG | H14: COLSON DO BRASIL LTDA | I14: 000188806 | J14: 8494.14 | K14: 19 | L14: 235.713 | M14: 422.6 | N14: 0.12 | O14: =L14*0.09 -> 21.21417 | P14: =L14*0.2 -> 47.1426 | R14: =L14*0.09 -> 21.21417 | T14: 161.4 | U14: =T14/M14 -> 0.38192144 | V14: =O14+P14+Q14+R14+S14+T14 -> 250.97094 | W14: =V14/M14 -> 0.5938735 | X14: =(L14*'RESULTADO DIRETO'!N$27)/6*3 -> 24.63927 | Y14: =X14/M14 -> 0.058303998 | Z14: =(L14*'RESULTADO DIRETO'!N$15)/6*2 -> 14.962041 | AA14: =Z14/M14 -> 0.035404734 | AB14: =(J14*0.01%)*7.38%+(J14*0.01%) -> 0.91210075 | AC14: =(J14*0.01%)*7.38%+(J14*0.01%) -> 0.91210075 | AD14: =V14+X14+Z14+AB14+AC14 -> 292.39645 | AE14: =AD14/M14 -> 0.69189885 | AF14: =M14*N14 -> 50.712 | AH14: =M14*0.052 -> 21.9752 | AI14: =AF14+AG14+AH14 -> 72.6872 | AJ14: =AD14+AI14 -> 365.08365 | AK14: =AJ14/M14 -> 0.86389885 | AL14: =M14-AJ14 -> 57.516348 | AM14: =AL14/M14 -> 0.13610115 | AN14: =M14/L14 -> 1.7928583
A15: 46238 | B15: NORMAL | C15: DQB8989 | D15: CTB | E15: PR | F15: VEA | G15: MG | H15: COLSON DO BRASIL LTDA | I15: 000188808 | J15: 6209.05 | K15: 17 | L15: 210.65 | M15: 375.43 | N15: 0.12 | O15: =L15*0.09 -> 18.9585 | P15: =L15*0.2 -> 42.13 | Q15: =L15*0.18 -> 37.917 | R15: =L15*0.06 -> 12.639 | T15: 112.63 | U15: =T15/M15 -> 0.30000266 | V15: =O15+P15+Q15+R15+S15+T15 -> 224.2745 | W15: =V15/M15 -> 0.59738034 | X15: =(L15*'RESULTADO DIRETO'!N$27)/6*4 -> 29.359219 | Y15: =X15/M15 -> 0.078201579 | Z15: =(L15*'RESULTADO DIRETO'!N$15)/6*3 -> 20.056725 | AA15: =Z15/M15 -> 0.053423341 | AB15: =(J15*0.01%)*7.38%+(J15*0.01%) -> 0.66672779 | AC15: =(J15*0.01%)*7.38%+(J15*0.01%) -> 0.66672779 | AD15: =V15+X15+Z15+AB15+AC15 -> 275.0239 | AE15: =AD15/M15 -> 0.73255707 | AF15: =M15*N15 -> 45.0516 | AH15: =M15*0.052 -> 19.52236 | AI15: =AF15+AG15+AH15 -> 64.57396 | AJ15: =AD15+AI15 -> 339.59786 | AK15: =AJ15/M15 -> 0.90455707 | AL15: =M15-AJ15 -> 35.83214 | AM15: =AL15/M15 -> 0.095442933 | AN15: =M15/L15 -> 1.7822454
A16: 46238 | B16: NORMAL | C16: DQB8989 | D16: CTB | E16: PR | F16: MVG | G16: RJ | H16: COLSON DO BRASIL LTDA | I16: 000188845 | J16: 3835.45 | K16: 10 | L16: 80.92 | M16: 210.13 | N16: 0.12 | O16: =L16*0.09 -> 7.2828 | P16: =L16*0.2 -> 16.184 | Q16: =L16*0.18 -> 14.5656 | R16: =M16*0.22 -> 46.2286 | T16: 68.82 | U16: =T16/M16 -> 0.32751154 | V16: =O16+P16+Q16+R16+S16+T16 -> 153.081 | W16: =V16/M16 -> 0.72850616 | X16: =(L16*'RESULTADO DIRETO'!N$27)/6*4 -> 11.278177 | Y16: =X16/M16 -> 0.053672379 | Z16: =(L16*'RESULTADO DIRETO'!N$15)/6*3 -> 7.7046769 | AA16: =Z16/M16 -> 0.03666624 | AB16: =(J16*0.01%)*7.38%+(J16*0.01%) -> 0.41185062 | AC16: =(J16*0.01%)*7.38%+(J16*0.01%) -> 0.41185062 | AD16: =V16+X16+Z16+AB16+AC16 -> 172.88756 | AE16: =AD16/M16 -> 0.82276474 | AF16: =M16*N16 -> 25.2156 | AH16: =M16*0.052 -> 10.92676 | AI16: =AF16+AG16+AH16 -> 36.14236 | AJ16: =AD16+AI16 -> 209.02992 | AK16: =AJ16/M16 -> 0.99476474 | AL16: =M16-AJ16 -> 1.1000848 | AM16: =AL16/M16 -> 0.0052352582 | AN16: =M16/L16 -> 2.5967622
A17: 46238 | B17: NORMAL | C17: DQB8989 | D17: CTB | E17: PR | F17: PSP | G17: SP | H17: COLSON DO BRASIL LTDA | I17: 000188788 | J17: 5585.62 | K17: 5 | L17: 29.48 | M17: 166.34 | N17: 0.12 | O17: =L17*0.09 -> 2.6532 | P17: =L17*0.2 -> 5.896 | R17: =L17*0 -> 0 | T17: 49.5 | U17: =T17/M17 -> 0.29758326 | V17: =O17+P17+Q17+R17+S17+T17 -> 58.0492 | W17: =V17/M17 -> 0.3489792 | X17: =(L17*'RESULTADO DIRETO'!N$27)/6*3 -> 3.0815681 | Y17: =X17/M17 -> 0.018525719 | Z17: =(L17*'RESULTADO DIRETO'!N$15)/6*2 -> 1.8712628 | AA17: =Z17/M17 -> 0.011249626 | AB17: =(J17*0.01%)*7.38%+(J17*0.01%) -> 0.59978388 | AC17: =(J17*0.01%)*7.38%+(J17*0.01%) -> 0.59978388 | AD17: =V17+X17+Z17+AB17+AC17 -> 64.201599 | AE17: =AD17/M17 -> 0.38596609 | AF17: =M17*N17 -> 19.9608 | AH17: =M17*0.052 -> 8.64968 | AI17: =AF17+AG17+AH17 -> 28.61048 | AJ17: =AD17+AI17 -> 92.812079 | AK17: =AJ17/M17 -> 0.55796609 | AL17: =M17-AJ17 -> 73.527921 | AM17: =AL17/M17 -> 0.44203391 | AN17: =M17/L17 -> 5.6424695
A18: 46238 | B18: NORMAL | C18: DQB8989 | D18: CTB | E18: PR | F18: SPO | G18: SP | H18: COLSON DO BRASIL LTDA | I18: 000188778 | J18: 1332.17 | K18: 3 | L18: 35 | M18: 396.82 | N18: 0.12 | O18: =L18*0.09 -> 3.15 | P18: =L18*0.2 -> 7 | R18: =L18*0.19 -> 6.65 | T18: 0 | U18: =T18/M18 -> 0 | V18: =O18+P18+Q18+R18+S18+T18 -> 16.8 | W18: =V18/M18 -> 0.042336576 | X18: =(L18*'RESULTADO DIRETO'!N$27)/6*3 -> 3.6585782 | Y18: =X18/M18 -> 0.0092197424 | Z18: =(L18*'RESULTADO DIRETO'!N$15)/6*2 -> 2.2216485 | AA18: =Z18/M18 -> 0.0055986303 | AB18: =(J18*0.01%)*7.38%+(J18*0.01%) -> 0.14304841 | AC18: =(J18*0.01%)*7.38%+(J18*0.01%) -> 0.14304841 | AD18: =V18+X18+Z18+AB18+AC18 -> 22.966323 | AE18: =AD18/M18 -> 0.057875922 | AF18: =M18*N18 -> 47.6184 | AH18: =M18*0.052 -> 20.63464 | AI18: =AF18+AG18+AH18 -> 68.25304 | AJ18: =AD18+AI18 -> 91.219363 | AK18: =AJ18/M18 -> 0.22987592 | AL18: =M18-AJ18 -> 305.60064 | AM18: =AL18/M18 -> 0.77012408 | AN18: =M18/L18 -> 11.337714
A19: 46238 | B19: NORMAL | C19: DQB8989 | D19: CTB | E19: PR | F19: RJO | G19: RJ | H19: COLSON DO BRASIL LTDA | I19: 000188799 | J19: 5349.3 | K19: 15 | L19: 148.6 | M19: 513.05 | N19: 0.12 | O19: =L19*0.09 -> 13.374 | P19: =L19*0.2 -> 29.72 | Q19: =L19*0.18 -> 26.748 | R19: =M19*0.22 -> 112.871 | T19: 0 | U19: =T19/M19 -> 0 | V19: =O19+P19+Q19+R19+S19+T19 -> 182.713 | W19: =V19/M19 -> 0.35613098 | X19: =(L19*'RESULTADO DIRETO'!N$27)/6*4 -> 20.711037 | Y19: =X19/M19 -> 0.040368457 | Z19: =(L19*'RESULTADO DIRETO'!N$15)/6*3 -> 14.148727 | AA19: =Z19/M19 -> 0.027577677 | AB19: =(J19*0.01%)*7.38%+(J19*0.01%) -> 0.57440783 | AC19: =(J19*0.01%)*7.38%+(J19*0.01%) -> 0.57440783 | AD19: =V19+X19+Z19+AB19+AC19 -> 218.72158 | AE19: =AD19/M19 -> 0.4263163 | AF19: =M19*N19 -> 61.566 | AH19: =M19*0.052 -> 26.6786 | AI19: =AF19+AG19+AH19 -> 88.2446 | AJ19: =AD19+AI19 -> 306.96618 | AK19: =AJ19/M19 -> 0.5983163 | AL19: =M19-AJ19 -> 206.08382 | AM19: =AL19/M19 -> 0.4016837 | AN19: =M19/L19 -> 3.4525572
A20: 46238 | B20: NORMAL | C20: DQB8989 | D20: CTB | E20: PR | F20: EPS | G20: ES | H20: COLSON DO BRASIL LTDA | I20: 000188844 | J20: 11435.48 | K20: 39 | L20: 315.27 | M20: 463.4 | N20: 0.07 | O20: =L20*0.09 -> 28.3743 | P20: =L20*0.2 -> 63.054 | T20: 222.43 | U20: =T20/M20 -> 0.47999568 | V20: =O20+P20+Q20+R20+S20+T20 -> 313.8583 | W20: =V20/M20 -> 0.67729456 | X20: =(L20*'RESULTADO DIRETO'!N$27)/6*3 -> 32.955427 | Y20: =X20/M20 -> 0.071116588 | Z20: =(L20*'RESULTADO DIRETO'!N$15)/6*4 -> 40.023949 | AA20: =Z20/M20 -> 0.086370197 | AB20: =(J20*0.01%)*7.38%+(J20*0.01%) -> 1.2279418 | AC20: =(J20*0.01%)*7.38%+(J20*0.01%) -> 1.2279418 | AE20: =AD20/M20 -> 0 | AF20: =M20*N20 -> 32.438 | AH20: =M20*0.052 -> 24.0968 | AI20: =AF20+AG20+AH20 -> 56.5348 | AJ20: =AD20+AI20 -> 56.5348 | AK20: =AJ20/M20 -> 0.122 | AL20: =M20-AJ20 -> 406.8652 | AM20: =AL20/M20 -> 0.878 | AN20: =M20/L20 -> 1.4698512
